Workbook

Sheet 背景
T1: 人物背景 Background | AP1: =IF(E5="","请选择背景",IF(AND(V3<>"",V4=""),"个性需两条",""))
B3: 角色 | E3: =IF(主要!D3="","",主要!D3) -> 瑞茵.戴派 | R3: 个性 | V3: 喜欢喝酒，不拘小节
B4: 玩家 | E4: =IF(主要!D4="","",主要!D4) -> 人心比痔疮更可怕 | V4: 吃苦耐劳，时常为了寻找神奇生物四处乱跑去乡下的树林
B5: 背景 | E5: 园丁 | R5: 理想 | V5: 成为纽特那样的神奇动物学家
B6: 故乡 | E6: 洞背村 | R6: 羁绊 | V6: 父母被食死徒折磨疯了，还在icu，所以是由外婆外公带大的
B7: 信仰 | R7: 缺点 | V7: 邋遢，不修边幅
R8: 背景原因
B9: 发色 | E9: 浅咖色 | R9: =IF(背景数据!F96=0,"",背景数据!F96)
B10: 瞳色 | E10: 绿色
B11: 肤色 | E11: 白 | R11: 职业原因 | V11: 很神必，一个喜欢神奇动物学的人被分到了拉文克劳
B12: 其他 | R12: =IF(背景数据!I8=0,"",背景数据!I8) | V12: 喜欢研究不同种类的神奇动物知识，还想把它们按照某个体系分类
R13: =IF(背景数据!I14=0,"",背景数据!I14)
B14: 人物 衣装 外貌 描述 | E14: 戴着大眼镜片的短头发浅咖发色少女，喜欢把头发变成小辫，留着雷霆齐刘海，校服不太喜欢好好穿，眼底有黑圆圈是因为偶尔宿醉。 | R14: =IF(背景数据!I20=0,"",背景数据!I20)
R15: =IF(背景数据!I26=0,"",背景数据!I26)
R16: =IF(背景数据!I46=0,"",背景数据!I46)
R17: =IF(背景数据!I58=0,"",背景数据!I58)
R19: 出生预兆
R20: =IF(赠礼数据!D2=0,"",赠礼数据!D2)
R21: =IF(赠礼数据!D10=0,"",赠礼数据!D10)
R22: 龙类纽带
R24: 背景故事 | V24: 同纳威，但是区别是家里确实家底十分雄厚，并且由外公外婆带大，生长于英国郊外的一个小村庄，叫做洞背村，家里是做酒厂的，酒的质量非常高，在巫师界十分出名，导致小时候瑞茵就成了半个酒鬼，酒量很好，经常喝完酒一拍脑袋即兴出门去观察动物，为此挨过不少揍，因为家里有钱，在村里算是街头一霸，孩子王，会用魔法烟花点燃乡下农户养的猪屁股，长大了之后稍微收敛了一点，但是依旧死性不改。
B45: 人物形象
B47: 语言 | E47: 英语

Sheet 主要
O1: DND 5E 人物卡 <New Edition v1.0.0> | AG1: 推荐在电脑上使用Excel2010及以后版本打开本卡
AV2: 小工具
B3: 角色 | D3: 瑞茵.戴派 | P3: 经验 | R3: 0 | Y3: =IF(R3="",1,LOOKUP($R$3,综合数据!D:D,综合数据!C:C)) -> 1 | AW3: 1级 | AY3: 2级 | BA3: 3级 | BC3: 4级 | BE3: 5级 | BG3: 6级 | BI3: 7级 | BK3: 8级 | BM3: 9级 | BO3: 10级
B4: 玩家 | D4: 人心比痔疮更可怕 | P4: 主职 | R4: 秘学士 | V4: 神奇动物 | Y4: 1 | AV4: 生命值小工具 | AW4: 8
P5: =综合数据!H2 -> 0
B6: 种族 | D6: 拉文克劳 | J6: 性别 | L6: 女 | P6: 兼职 | AW6: 11级 | AY6: 12级 | BA6: 13级 | BC6: 14级 | BE6: 15级 | BG6: 16级 | BI6: 17级 | BK6: 18级 | BM6: 19级 | BO6: 20级
B7: 亚种 | J7: 年龄 | L7: 11
B9: 身高 | D9: 145 | J9: 阵营 | L9: 混乱中立 | S9: 熟练 | U9: =IFERROR(VLOOKUP(Y3,综合数据!C:E,3,0)+Y10,2) -> 2 | Y9: 其他 | AW9: 调整值 | BA9: 角色等级 | BE9: 生命总值 | BH9: 仅需填入每级生命骰结果 自动结算各项调整值
B10: 体重 | J10: 赠礼 | X10: < | AW10: =R16+综合数据!F2 -> 1 | BA10: =COUNTA(AW4:BP4,AW7:BP7) -> 1 | BE10: =SUM(综合数据!F3:F22)+IF(COUNTIF(职业数据!AD16:AD18,职业数据!B11),职业数据!AG11,0) -> 9
M12: 属性 | U12: =IF(D6="","请选择种族",IF(种族数据!U18=1,"未选亚种",IF(种族数据!T18=0,"错误亚种",""))) | BD12: 属性分布
B13: 熟练 | F13: 总值 | I13: 初始值 | K13: 种族 | M13: 成长 | O13: 修正 | R13: 调整值 | T13: 豁免 | W13: 修正 | Y13: 临时
C14: 力量 | F14: =SUM(I14:P14) -> 8 | H14: < | I14: 8 | Q14: > | R14: =INT(F14/2-5) -> -1 | T14: =INT(F14/2-5)+IF(综合数据!J1=TRUE,$U$9,0)+SUM(W14:Z14) -> -1 | V14: <
C15: 敏捷 | F15: =SUM(I15:P15) -> 15 | H15: < | I15: 14 | K15: 1 | Q15: > | R15: =INT(F15/2-5) -> 2 | T15: =INT(F15/2-5)+IF(综合数据!K1=TRUE,$U$9,0)+SUM(W15:Z15) -> 2 | V15: <
C16: 体质 | F16: =SUM(I16:P16) -> 13 | H16: < | I16: 13 | Q16: > | R16: =INT(F16/2-5) -> 1 | T16: =INT(F16/2-5)+IF(综合数据!L1=TRUE,$U$9,0)+SUM(W16:Z16) -> 1 | V16: <
C17: 智力 | F17: =SUM(I17:P17) -> 18 | H17: < | I17: 17 | K17: 1 | Q17: > | R17: =INT(F17/2-5) -> 4 | T17: =INT(F17/2-5)+IF(综合数据!M1=TRUE,$U$9,0)+SUM(W17:Z17) -> 4 | V17: <
C18: 感知 | F18: =SUM(I18:P18) -> 17 | H18: < | I18: 16 | K18: 1 | Q18: > | R18: =INT(F18/2-5) -> 3 | T18: =INT(F18/2-5)+IF(综合数据!N1=TRUE,$U$9,0)+SUM(W18:Z18) -> 3 | V18: <
C19: 魅力 | F19: =SUM(I19:P19) -> 10 | H19: < | I19: 10 | Q19: > | R19: =INT(F19/2-5) -> 0 | T19: =INT(F19/2-5)+IF(综合数据!O1=TRUE,$U$9,0)+SUM(W19:Z19) -> 0 | V19: <
B21: 战斗
G22: 临时 | N22: Now | Q22: Max
B23: 先攻 | D23: =SUM(R15+G23)+IF(COUNTIF(专长数据!E2:E7,专长数据!A3),5,0)+IF(COUNTIF(职业数据!AD16:AD18,职业数据!D9),R18,0)+IF(COUNTIF(职业数据!AD16:AD18,职业数据!H10),R19,0)+IF(OR(COUNTIF(职业数据!AD16:AD18,职业数据!K13),COUNTIF(职业数据!AD16:AD18,职业数据!L13)),R17,0) -> -3 | F23: < | G23: -5 | J23: HP | M23: 9 | P23: / | Q23: =BE10 -> 9 | V23: 临时 HP | X23: 0
J25: =M23 -> 9
B26: AC | D26: {=IF(AB39="",0,AB39)+IF(种族数据!V3=种族数据!A34,0,IF(AND(装备数据!AO2<>"",装备数据!AO2<R15),装备数据!AO2,IF(装备数据!AO2=0,0,R15)))+G26+IF(装备数据!AS2=TRUE,IF(AP39="",0,AP39),0)+IF(AND(装备数据!AL2=装备数据!J4,装备数据!K4=10),MAX(IF(职业数据!AG2>=1,R16,0),IF(AND(职业数据!AG7>=1,装备数据!AS2=FALSE),R18,0),0),0)+IF(D6=种族数据!A25,M28R16-R15,0)} -> 11 | F26: < | G26: -1 | J26: HD | L26: 2 | N26: / | O26: =IF(Y4<=0,"",Y4) -> 1 | Q26: =职业数据!AS6 | S26: + | V26: /
D28: 持盾 | G28: 其他 | I28: 死亡豁免成功 | P28: 失败 | AB28: 画像
B29: DC | D29: =SUM(8+U9+G29+IF(F31=C14,R14,IF(F31=C15,R15,IF(F31=C16,R16,IF(F31=C17,R17,IF(F31=C18,R18,IF(F31=C19,R19,0))))))) -> 14 | F29: < | J29: 抗性 | AB29: 免疫
AV30: 技能分布
B31: DC属性 | F31: 智力
J32: 体型 | L32: 中型 | P32: 速度 | R32: 30 | AB32: 优势
B34: 被动察觉 | F34: =SUM(10+R18) -> 13 | J34: 荒野形态 | S34: 特殊能力 | AB34: 劣势
B37: 技能 | L37: =IF(AND(COUNTIF(职业数据!AC16:AC18,职业数据!A7),装备数据!AU6=0),"无法使用武僧武器",IF(OR(AND(COUNTIF(L41:N45,"专用*")>=1,装备数据!AU7=0),AND(COUNTIF(L41:N45,"剑圣*")>=1,装备数据!AU7<2),AND(COUNTIF(L41:N45,"匠师*")>=1,装备数据!AU9=0),AND(COUNTIF(L41:N45,"咒术")>=1,装备数据!AU8=0)),"无法使用职业武器",IF(装备数据!AW3=0,"护甲种类有误",IF(AND(种族数据!V3=种族数据!A34,装备数据!AW2=1),"龟人无法使用护甲",IF(装备数据!R47<=-1,"同调装备过多",""))))) -> 护甲种类有误 | S37: 装备 | W37: =IF(COUNTIF(装备数据!R30:R45,TRUE)=0,"","已同调的装备："&COUNTIF(装备数据!R30:R45,TRUE)&"/"&IF(职业数据!AG14>=18,6,IF(职业数据!AG14>=14,5,IF(职业数据!AG14>=10,4,3)))) | AD37: 快捷战斗
A38: 熟练 | C38: 力量系 | F38: 修正 | I38: 总值 | L38: 护甲 | O38: 同调 | P38: 名称 | U38: 特性 | X38: 熟练 | Y38: 重量 | AA38: 基础AC | AD38: 最大敏捷 | AH38: 劣势 | AJ38: 护盾 | AL38: 同调 | AN38: 名称 | AP38: AC | AR38: 重量 | AU38: 熟练
C39: 运动 | H39: > | I39: =$R$14+IF(综合数据!R2=TRUE,$U$9,0)+F39 -> -1 | AA39: > | AB39: =装备数据!$AM$2 -> 10 | AH39: 沉重
C40: 敏捷系 | L40: 武器 | O40: 同调 | P40: 名称 | T40: 特性 | Y40: 重量 | AB40: 熟练 | AC40: 命中骰 | AF40: 加值 | AH40: 基础伤害 | AK40: 加值 | AN40: 类型 | AQ40: 弹药 | AT40: 计重
C41: 体操 | H41: > | I41: 4 | L41: 魔杖 | S41: 凤凰羽毛、梧桐木，13.5英寸，刚硬 | Y41: 1 | AA41: > | AC41: =IF(L41="","","D20"&IF(装备数据!AR6>0,"+","")&IF(装备数据!AR6<>0,装备数据!AR6,"")) -> D20 | AF41: =IF(AG41>0,"+","") | AK41: =IF(AL41>0,"+","") | AQ41: 箭
C42: 巧手 | H42: > | I42: 4 | AA42: > | AC42: =IF(L42="","","D20"&IF(装备数据!AR7>0,"+","")&IF(装备数据!AR7<>0,装备数据!AR7,"")) | AF42: =IF(AG42>0,"+","") | AK42: =IF(AL42>0,"+","") | AQ42: 吹
C43: 隐匿 | H43: > | I43: 6 | N43: > | AA43: > | AC43: =IF(L43="","","D20"&IF(装备数据!AR8>0,"+","")&IF(装备数据!AR8<>0,装备数据!AR8,"")) | AF43: =IF(AG43>0,"+","") | AK43: =IF(AL43>0,"+","") | AQ43: 矢
C44: 智力系 | N44: > | AA44: > | AC44: =IF(L44="","","D20"&IF(装备数据!AR9>0,"+","")&IF(装备数据!AR9<>0,装备数据!AR9,"")) | AF44: =IF(AG44>0,"+","") | AK44: =IF(AL44>0,"+","") | AQ44: 投
C45: 奥秘 | H45: > | I45: =$R$17+IF(综合数据!R6=TRUE,$U$9,0)+F45 -> 4 | N45: > | AA45: > | AC45: =IF(L45="","","D20"&IF(装备数据!AR10>0,"+","")&IF(装备数据!AR10<>0,装备数据!AR10,"")) | AF45: =IF(AG45>0,"+","") | AK45: =IF(AL45>0,"+","") | AQ45: 弹
C46: 历史 | H46: > | I46: 2 | L46: 其他 | O46: 同调 | Q46: 名称 | V46: 特性 | AA46: 重量 | AV46: 异常状态及选开属性
C47: 调查 | F47: 2 | H47: > | I47: =$R$17+IF(综合数据!R8=TRUE,$U$9,0)+F47 -> 6 | L47: 身体 | N47: > | AK47: 法术 | AM47: =IF(SUMPRODUCT(--(AO52:AO60>AR52:AR60)),"法术位超上限","") | AW47: 异常
C48: 自然 | H48: > | I48: =$R$17+IF(综合数据!R9=TRUE,$U$9,0)+F48 -> 4 | L48: 双手 | N48: > | AD48: 施法关键属性 | AH48: 命中骰 | AK48: 加值 | AO48: 法术DC | AQ48: 加值 | AX48: 目盲 | BB48: 魅惑 | BF48: 耳聋 | BJ48: 恐慌 | BN48: 擒抱
C49: 宗教 | H49: > | I49: =$R$17+IF(综合数据!R10=TRUE,$U$9,0)+F49 -> 4 | L49: 左手 | N49: > | AD49: 智力 | AG49: > | AH49: =IF(AD49="","","D20"&IF(法术数据!AU8>0,"+","")&IF(法术数据!AU8<>0,法术数据!AU8,"")) -> D20+6 | AK49: =IF(AL49>0,"+","") -> + | AL49: 1 | AN49: / | AO49: =IF(AD49="","",8+法术数据!AU8) -> 14 | AQ49: =IF(AR49>0,"+","") -> + | AR49: 1 | AX49: 失能 | BB49: 隐形 | BF49: 麻痹 | BJ49: 石化 | BN49: 中毒
C50: 感知系 | L50: 身体 | N50: > | AG50: > | AH50: =IF(AD50="","","D20"&IF(法术数据!AU9>0,"+","")&IF(法术数据!AU9<>0,法术数据!AU9,"")) | AK50: =IF(AL50>0,"+","") | AN50: / | AO50: =IF(AD50="","",8+法术数据!AU9) | AQ50: =IF(AR50>0,"+","") | AX50: 倒地 | BB50: 束缚 | BF50: 震慑 | BJ50: 昏迷
C51: 驯兽 | F51: 2 | H51: > | I51: 4 | N51: > | AD51: 准备法术 | AE51: 职业 | AM51: 法术位 | AW51: 状态 | AY51: 描述
C52: 洞悉 | F52: 2 | H52: > | I52: 6 | N52: > | AE52: =IF(AI52="","",R4) | AH52: > | AI52: =IFERROR(VLOOKUP(R4,法术数据!$AU$2:$AV$6,2,0),"") | AM52: 1 | AO52: 0 | AQ52: / | AR52: =IF(职业数据!AE22>=3,4,IF(职业数据!AE22>=2,3,IF(职业数据!AE22>=1,2,0)))+IF(职业数据!AG12<=2,职业数据!AG12) -> 0 | AW52: 力竭 | AZ52: 1级 | BC52: 2级 | BF52: 3级 | BI52: 4级 | BL52: 5级 | BO52: 6级
C53: 医药 | H53: > | I53: 6 | N53: > | AH53: > | AI53: =IFERROR(VLOOKUP(R6,法术数据!$AU$2:$AV$6,2,0),"") | AM53: 2 | AN53: 0 | AO53: 0 | AP53: / | AQ53: / | AR53: =IF(职业数据!AE22>=4,3,IF(职业数据!AE22>=3,2,0))+IF(AND(职业数据!AG12>=3,职业数据!AG12<=4),2,0) -> 0 | AW53: 毒药
C54: 察觉 | H54: > | I54: 6 | N54: > | AE54: =IF(AI54="","",R7) | AH54: > | AI54: =IFERROR(VLOOKUP(R7,法术数据!$AU$2:$AV$6,2,0),"") | AM54: 3 | AN54: 0 | AO54: 0 | AP54: / | AQ54: / | AR54: =IF(职业数据!AE22>=6,3,IF(职业数据!AE22>=5,2,0))+IF(AND(职业数据!AG12>=5,职业数据!AG12<=6),2,0) -> 0 | AW54: 疯狂
C55: 求生 | F55: 2 | H55: > | I55: 4 | N55: > | AE55: 随身钱币 | AK55: 计重 | AM55: 4 | AN55: 0 | AO55: 0 | AP55: / | AQ55: / | AR55: =IF(职业数据!AE22>=9,3,IF(职业数据!AE22>=8,2,IF(职业数据!AE22>=7,1,0)))+IF(AND(职业数据!AG12>=7,职业数据!AG12<=8),2,0) -> 0 | AW55: 伤患
C56: 魅力系 | L56: 负重规则 | O56: 15 | R56: ——负重&财产—— | AE56: PP | AM56: 5 | AN56: 0 | AO56: 0 | AP56: / | AQ56: / | AR56: =IF(职业数据!AE22>=18,3,IF(职业数据!AE22>=10,2,IF(职业数据!AE22>=9,1,0)))+IF(职业数据!AG12>=17,4,IF(职业数据!AG12>=11,3,IF(职业数据!AG12>=9,2,0))) -> 0 | AY56: 总值 | BB56: 初始值 | BD56: 成长 | BG56: 豁免 | BJ56: 选开异常
C57: 欺瞒 | H57: > | I57: =$R$19+IF(综合数据!R16=TRUE,$U$9,0)+F57 -> 0 | L57: 装备 | O57: 背包1 | R57: 背包2 | U57: > | V57: 总负重 | Z57: < | AA57: 2 | AD57: < | AE57: EP | AM57: 6 | AN57: 1 | AO57: 0 | AP57: / | AQ57: / | AR57: =IF(职业数据!AE22>=19,2,IF(职业数据!AE22>=11,1,0)) -> 0 | AW57: 荣誉 | AY57: =SUM(BB57:BE57) -> 8 | BA57: < | BB57: 8 | BF57: > | BG57: =INT(AY57/2-5) -> -1 | BK57: 心慌 | BO57: 惊恐
C58: 威吓 | H58: > | I58: =$R$19+IF(综合数据!R17=TRUE,$U$9,0)+F58 -> 0 | L58: =SUM(AA47:AB55,Y41:Z45,Y39,AR39,IF(综合数据!R20=TRUE,装备数据!AD1,0)) -> 1 | O58: =背包!V3 -> 5 | R58: =背包!AS3 -> 1 | V58: =SUM(L58:T58)+AA58+AA60 -> 58.4 | AA58: =IF(综合数据!R21=TRUE,SUM(AG56:AK60)/50,0) -> 51.4 | AE58: GP | AG58: 2570 | AM58: 7 | AN58: 0 | AO58: 0 | AP58: / | AQ58: / | AR58: =IF(职业数据!AE22>=20,2,IF(职业数据!AE22>=13,1,0)) -> 0 | AW58: 理智 | AY58: =SUM(BB58:BE58) -> 8 | BA58: < | BB58: 8 | BF58: > | BG58: =INT(AY58/2-5) -> -1 | BK58: 缴械
C59: 表演 | H59: > | I59: =$R$19+IF(综合数据!R18=TRUE,$U$9,0)+F59 -> 0 | L59: 最大轻载 | P59: / | Q59: 最大重载 | V59: 状态 | AA59: 次元袋 | AE59: SP | AM59: 8 | AN59: 1 | AO59: 0 | AP59: / | AQ59: / | AR59: =IF(职业数据!AE22>=15,1,0) -> 0
C60: 游说 | H60: > | I60: =$R$19+IF(综合数据!R19=TRUE,$U$9,0)+F60 -> 0 | L60: =F14*O56*IF(OR(种族数据!V3=种族数据!A12,种族数据!V3=种族数据!A13,种族数据!V4=种族数据!B18,种族数据!V3=种族数据!A20,种族数据!V3=种族数据!A25,COUNTIF(职业数据!$BG$2:$BG$44,职业数据!B44)),2,1) -> 120 | P60: / | Q60: =L60*2 -> 240 | V60: =IF(V58>Q60,"超载",IF(V58>L60,"重载","轻载")) -> 轻载 | AA60: =IF(背包!B27="无效",0,15)+IF(背包!Y27="无效",0,5) -> 0 | AE60: CP | AM60: 9 | AN60: 0 | AO60: 0 | AP60: / | AQ60: / | AR60: =IF(职业数据!AE22>=17,1,0) -> 0 | AV60: 魔宠或宠物
B61: ——————货币换算—————— | N61: 重量 | Q61: 铜币CP | W61: 银币SP | AC61: 银金币EP | AI61: 金币GP | AO61: 铂金币PP
H62: 金币GP | M62: > | N62: =B62/50 -> 0 | Q62: =综合数据!P21*100 -> 0 | W62: =综合数据!P21*10 -> 0 | AC62: =综合数据!P21*2 -> 0 | AI62: =综合数据!P21 -> 0 | AO62: =综合数据!P21/10 -> 0 | AW62: 名字 | BG62: 种族
AW63: 体型 | BC63: 类别 | BJ63: 阵营
C64: =IF(法术数据!AO47>1,"有重复法术","") | I64: 已准备的法术 | P64: =IF(法术数据!AQ47=0,"","有"&法术数据!AQ47&"个法术需要专注") | X64: 专注 | AE64: 已准备法术的效果 | BO64: 熟练
B65: Lv | C65: 法术名称 | I65: Lv | J65: 法术名称 | P65: Lv | Q65: 法术名称 | W65: 法术名 | AE65: 等级 | AH65: 系别 | AK65: 施法距离 | AW65: AC | BB65: 速度 | BK65: 等级 | BO65: =IFERROR(LOOKUP(BM65,综合数据!#REF!,综合数据!E:E),2) -> 2
I66: =法术数据!AP17 | P66: =法术数据!AP32 | W66: 炽焰赋权 | AE66: =IF(W66="","",VLOOKUP(VLOOKUP(W66,法术数据!B:P,15,FALSE),CHOOSE({1,2},法术数据!AI2:AI11,法术数据!AH2:AH11),2,FALSE)) -> 六环 | AH66: =IF(W66="","",VLOOKUP(W66,法术数据!B:E,4,0)) -> 变化 | AK66: =IF(W66="","",(VLOOKUP(W66,法术数据!B:G,6,0))) -> 自身
B67: =法术数据!AP3 | I67: =法术数据!AP18 | P67: =法术数据!AP33 | W67: 施法时间 | AW67: HP | BB67: / | BG67: HD | BK67: /
B68: =法术数据!AP4 | I68: =法术数据!AP19 | P68: =法术数据!AP34 | W68: =IF(W66="","",VLOOKUP(W66,法术数据!B:F,5,0)&IF(VLOOKUP(W66,法术数据!B:D,3,0)=1,"（仪式）","")) -> 1动作 | AW68: 熟练 | AZ68: 总值 | BC68: 调整值 | BE68: 豁免
B69: =法术数据!AP5 | I69: =法术数据!AP20 | P69: =法术数据!AP35 | W69: 持续时间 | AD69: 法术成分 | AK69: =IF(W66="","",IF(VLOOKUP(W66,法术数据!B:H,7,0)=1," 言语 ","")&IF(VLOOKUP(W66,法术数据!B:I,8,0)=1," 姿势 ","")&IF(VLOOKUP(W66,法术数据!B:J,9,0)=1," 材料 ","")) -> 言语 姿势 | AW69: FALSE | AX69: 力量 | BB69: > | BC69: =INT(AZ69/2-5) -> -5 | BE69: =INT(AZ69/2-5)+IF(AW69=TRUE,$BO$65,0) -> -5
B70: =法术数据!AP6 | I70: =法术数据!AP21 | P70: =法术数据!AP36 | W70: =IF(W66="","",IF(VLOOKUP(W66,法术数据!B:M,12,0)=1,"专注，","")&VLOOKUP(W66,法术数据!B:N,13,0)) -> 专注，至多10分钟 | AD70: =IF(W66="","",IF(VLOOKUP(W66,法术数据!B:K,10,0)="","",VLOOKUP(W66,法术数据!B:K,10,0))&IF(VLOOKUP(W66,法术数据!B:J,9,0)=2,CHAR(10),"")&IF(VLOOKUP(W66,法术数据!B:L,11,0)="","",(VLOOKUP(W66,法术数据!B:L,11,0)))) | AW70: FALSE | AX70: 敏捷 | BB70: > | BC70: =INT(AZ70/2-5) -> -5 | BE70: =INT(AZ70/2-5)+IF(AW70=TRUE,$BO$65,0) -> -5
B71: =法术数据!AP7 | I71: =法术数据!AP22 | P71: =法术数据!AP37 | W71: 法术效果说明 | AW71: FALSE | AX71: 体质 | BB71: > | BC71: =INT(AZ71/2-5) -> -5 | BE71: =INT(AZ71/2-5)+IF(AW71=TRUE,$BO$65,0) -> -5
B72: =法术数据!AP8 | I72: =法术数据!AP23 | P72: =法术数据!AP38 | W72: =IF(W66="","",(VLOOKUP(W66,法术数据!B:O,14,0))) -> 火焰环绕着你的身体，照亮周围30尺半径的区域，并在外围30尺范围内产生微弱的亮光。这些火焰不会伤害到你。直到此法术终结，你得到如下的好处： 你免疫于火焰伤害并对冷冻伤害具有抗力。 任何在回合中第一次进入你周围5尺范围之内，或是在你周围5尺范围之内结束回合的生物受到1d10火焰伤害。 你可以使用你的动作以创造出一条以你为起始点，向由你选择的方向延伸的15尺长、5尺宽的火线。在线中的每个生物都必须进行一次敏捷豁免检定。豁免失败的生物受到4d8火焰伤害，豁免成功者受到上述伤害的一半。 | AX72: 智力 | BB72: > | BC72: =INT(AZ72/2-5) -> -5 | BE72: =INT(AZ72/2-5)+IF(AW72=TRUE,$BO$65,0) -> -5
B73: =法术数据!AP9 | I73: =法术数据!AP24 | P73: =法术数据!AP39 | AW73: FALSE | AX73: 感知 | BB73: > | BC73: =INT(AZ73/2-5) -> -5 | BE73: =INT(AZ73/2-5)+IF(AW73=TRUE,$BO$65,0) -> -5
B74: =法术数据!AP10 | I74: =法术数据!AP25 | P74: =法术数据!AP40 | AX74: 魅力 | BB74: > | BC74: =INT(AZ74/2-5) -> -5 | BE74: =INT(AZ74/2-5)+IF(AW74=TRUE,$BO$65,0) -> -5
B75: =法术数据!AP11 | I75: =法术数据!AP26 | P75: =法术数据!AP41
B76: =法术数据!AP12 | I76: =法术数据!AP27 | P76: =法术数据!AP42 | AW76: 技能
B77: =法术数据!AP13 | I77: =法术数据!AP28 | P77: =法术数据!AP43 | AW77: 抗性
B78: =法术数据!AP14 | I78: =法术数据!AP29 | P78: =法术数据!AP44 | AW78: 免疫
B79: =法术数据!AP15 | I79: =法术数据!AP30 | P79: =法术数据!AP45 | AW79: 感官 | BG79: 语言
B80: =法术数据!AP16 | I80: =法术数据!AP31 | P80: =法术数据!AP46 | AW80: 动作
B82: 德鲁伊 | K82: 职业能力 | R82: =IF(B82="","请选择职业",IF(职业数据!AC22>=1,"职业无等级",IF(职业数据!AB20>=1,"职业重复",IF(职业数据!AC20>=1,"子职错误",IF(职业数据!AC21>=1,"未选子职",IF(职业数据!BI48>1,"有重复特性",IF(职业数据!BH47>=1,"有互斥特性",IF(职业数据!BI50>=1,"可选特性未选",IF(职业数据!BI51>=1,"可选特性选多",""))))))))) -> 子职错误 | Z82: =IF(D6="","请选择种族",IF(种族数据!U18=1,"未选亚种",IF(种族数据!T18=0,"错误亚种",IF(种族数据!AC16>1,"有重复特性",IF(种族数据!AC17>=1,"有互斥特性",IF(种族数据!AD17>1,"强化错误","")))))) | AG82: 种族特性
B83: 次数 | D83: 名称 | H83: 描述 | Y83: 次数 | AA83: 名称 | AE83: 描述
C84: 生命骰 | H84: 1×D8 | Z84: 属性值加成 | AE84: 智力，感知和任选一个属性值加1
C85: 护甲熟练项 | Z85: 速度 | AE85: 基础步行速度为30尺
C86: 武器熟练项 | Z86: 体型 | AE86: 中型或小型。在你选择种族时选择体型
C87: 工具熟练项 | H87: 草药工具 | Z87: 深厚学识 | AE87: 每当你进行智力或感知相关的属性检定时，若你在该检定上拥有熟练，那么你可以将小于等于5的D20掷骰原值视为6。
C88: 豁免熟练项 | H88: 智力、敏捷 | Z88: 罗伊纳的图书馆 | AE88: 你可以通过寻求室友的帮助的同时浏览拉文克劳公共休息室内找到的书籍来研究某个难题。
C89: 技能熟练项 | H89: 神奇动物，生存 | Z89: 额外专长 | AE89: 你选择并获得一个专长。
C90: 属性值提升 | H90: 当达到第4、8、12、16、19级时，你可以选择一项属性值提升2点，或是选择两项属性各提升1点。不过你不能通过此特性让属性值超过20
C95: 施法关键属性 | H95: 智力
AW96: 特性
AW97: 飞掠Flyby。飞蛇飞出敌人的触及范围时不会引起借机攻击。
Z99: =IF(背景!E5="","请选择背景",IF(背景数据!B31>1,"有重复特性","")) | AG99: 背景特性
Y100: 次数 | AA100: 名称 | AE100: 描述
Z102: 工具熟练项 | AE102: 草药工具
Z103: 技能熟练项 | AE103: 生存，神奇动物，草药工具
Z107: =IF(专长数据!F10+专长数据!G12>=1,"未选专长",IF(专长数据!F10+专长数据!G12<=-1,"专长过多",IF(专长数据!F11>=1,"重复专长",""))) -> 专长过多 | AG107: 专长 | AN107: =IF(COUNTIF(专长数据!E2:E9,"<>0")=0,"","已选专长："&COUNTIF(专长数据!E2:E9,"<>0")&"/"&专长数据!F10+专长数据!F12) -> 已选专长：2/0
Y108: 次数 | AA108: 名称 | AE108: 描述
Z109: 变形天赋 | AE109: 以一个动作你可以随意改变自己的外表，你可以自由决定你的容姿，身高，体重，声音，发色与发长。但你的属性，体型与大体外形不会因此而改变，例如若你变形前是两足生物，那么你无法用该天赋变为四足生物。 ·你可以使你成为水生生物，并在指尖长出蹼。以一个动作，你获得等同于你步行速度的游泳速度。
Z110: 安定施法 | AE110: 你身上肩负的压力使你在危急时刻冷静无比，你总能保持专注。当你受到伤害时，你无需进行体质豁免检定也能保持专注
AV113: 版本选择
AW114: PHB | AZ114: DMG | BC114: MM | BF114: SCAG | BI114: VGM | BL114: XGE | BO114: MTF
AW115: GTR | AZ115: ERLW | BC115: EGTW | BF115: ACQ | BI115: MOT | BL115: TCE | BO115: VRGR
AW116: FTD | AZ116: SCC | BC116: MotM
BD118: 你的角色可能 | BP118: 显示
Z119: =IF(装备数据!AM21>=1,"重复熟练项","") | AG119: 工具熟练项
Y120: 次数 | AA120: 名称 | AE120: 描述 | AV120: 力量 | AZ120: =IFERROR(LOOKUP($F$14,综合数据!I:I,综合数据!J:J),"") -> 你揍人就像在给对方按摩
Z121: 草药工具 | AE121: 草药工具熟练项允许你辨认植物并安全地提取有效成分 奥秘：你对药材的性味归经和功能主治的了解，使你在对植物进行魔法研究或试图鉴定药剂时具有额外的洞察力 调查：当你调查一个长有植物的区域时，草药工具熟练项能帮助你发现那些其他人可能会忽视的细节或线索 医药：你对草药医学的掌握有助于提高你使用药用植物治疗疾病和创伤的水平 自然、求生：当你在野外旅行时，你的草药技能有助于辨认植物和找到一般人不知道的食物来源 辨认植物：仅仅通过外观和气味，你就能快速辨认出大部分植物 | AV121: 敏捷 | AZ121: =IFERROR(LOOKUP($F$15,综合数据!I:I,综合数据!K:K),"") -> 左右横跳
...

Sheet 背包
A1: 背包 Inventory
B3: 背包 | P3: =IF(AND(COUNTA(B5:H14)+COUNTA(B16:H25)>0,B3=""),"请选择容器",IF(V3-装备数据!Z11>装备数据!Y11,"容量超上限","")) | V3: =装备数据!Z11+SUMPRODUCT(S5:T25,V5:W25) -> 5 | Y3: 小包 | AM3: =IF(AND(COUNTA(Y5:AE14)+COUNTA(Y16:AE25)>0,Y3=""),"请选择容器",IF(AS3-装备数据!Z32>装备数据!Y32,"容量超上限","")) | AS3: =装备数据!Z32+SUMPRODUCT(AP5:AQ25,AS5:AT25) -> 1 | AW3: 杂物袋1 | BT3: 杂物袋2
B4: 名称 | I4: 描述 | S4: 重量 | V4: 数量 | Y4: 名称 | AF4: 描述 | AP4: 重量 | AS4: 数量
U5: × | AR5: ×
U6: × | AR6: ×
U7: × | AR7: ×
U8: × | AR8: ×
U9: × | AR9: ×
U10: × | AR10: ×
U11: × | AR11: ×
U12: × | AR12: ×
U13: × | AR13: ×
U14: × | AR14: ×
U16: × | AR16: ×
U17: × | AR17: ×
... U25: × | AR25: ×
B27: 无效 | H27: 次元袋 | P27: =IF(U27>500,"超载","") | U27: =SUMPRODUCT(S29:T82,V29:W82) -> 0 | Y27: 无效 | AE27: 霍华德的便利袋 | AM27: =IF(AR27>120,"超载","") | AR27: =SUMPRODUCT(AP29:AQ82,AS29:AT82) -> 0
B28: 名称 | I28: 描述 | S28: 重量 | V28: 数量 | Y28: 名称 | AF28: 描述 | AP28: 重量 | AS28: 数量
U29: × | AR29: ×
U30: × | AR30: ×
U31: × | AR31: ×
U32: × | AR32: ×
U33: × | AR33: ×
U34: × | AR34: ×
U35: × | AR35: ×
U36: × | AR36: ×
U37: × | AR37: ×
U38: × | AR38: ×
U40: × | AR40: ×
U41: × | AR41: ×
... U82: × | AR82: ×

Sheet 法术书
T2: 书页标签
C3: =IF(Y5<>"",Y5,V5)
T4: 法术书 | V4: 法术书1 | W4: 页码 | Y4: =101-法术数据!AV10 -> 1
U5: =IF(V5="","","Lv") | V5: =IF(V4="法术书1",VLOOKUP(101-法术数据!AV10,法术数据!AJ:AK,2,FALSE),IF(V4="法术书2",VLOOKUP(201-法术数据!AV10,法术数据!AJ:AK,2,FALSE),IF(V4="法术书3",VLOOKUP(301-法术数据!AV10,法术数据!AJ:AK,2,FALSE),"空白标签"))) | W5: 优先读取
U6: =IFERROR(VLOOKUP(V5,法术数据!B:P,15,FALSE),"")
T7: 法术书1 | Z7: 法术书2 | AF7: 法术书3
C8: =IF(C3="","",VLOOKUP(C3,法术数据!B:C,2,FALSE)) | O8: =IF(C3="","","出自："&VLOOKUP(C3,法术数据!B:Q,16,FALSE)) | T8: =IF(V8="","",法术数据!AJ2) | U8: =IFERROR(VLOOKUP(V8,法术数据!B:P,15,FALSE),"") | W8: =IF(Y8="","",法术数据!AJ52) | X8: =IFERROR(VLOOKUP(Y8,法术数据!B:P,15,FALSE),"") | Z8: =IF(AB8="","",法术数据!AJ2) | AA8: =IFERROR(VLOOKUP(AB8,法术数据!B:P,15,FALSE),"") | AC8: =IF(AE8="","",法术数据!AJ52) | AD8: =IFERROR(VLOOKUP(AE8,法术数据!B:P,15,FALSE),"") | AF8: =IF(AH8="","",法术数据!AJ2) | AG8: =IFERROR(VLOOKUP(AH8,法术数据!B:P,15,FALSE),"") | AI8: =IF(AK8="","",法术数据!AJ52) | AJ8: =IFERROR(VLOOKUP(AK8,法术数据!B:P,15,FALSE),"")
C9: =IF(C3="","","施法时间： "&VLOOKUP(C3,法术数据!B:F,5,FALSE)&IF(VLOOKUP(C3,法术数据!B:D,3,FALSE)=1,"（仪式）","")) | O9: =IF(C3="","",VLOOKUP(VLOOKUP(C3,法术数据!B:P,15,FALSE),CHOOSE({1,2},法术数据!AI2:AI11,法术数据!AH2:AH11),2,FALSE)&" / "&VLOOKUP(C3,法术数据!B:E,4,FALSE)) | T9: =IF(V9="","",法术数据!AJ3) | U9: =IFERROR(VLOOKUP(V9,法术数据!B:P,15,FALSE),"") | W9: =IF(Y9="","",法术数据!AJ53) | X9: =IFERROR(VLOOKUP(Y9,法术数据!B:P,15,FALSE),"") | Z9: =IF(AB9="","",法术数据!AJ3) | AA9: =IFERROR(VLOOKUP(AB9,法术数据!B:P,15,FALSE),"") | AC9: =IF(AE9="","",法术数据!AV53) | AD9: =IFERROR(VLOOKUP(AE9,法术数据!B:P,15,FALSE),"") | AF9: =IF(AH9="","",法术数据!AJ3) | AG9: =IFERROR(VLOOKUP(AH9,法术数据!B:P,15,FALSE),"") | AI9: =IF(AK9="","",法术数据!AT53) | AJ9: =IFERROR(VLOOKUP(AK9,法术数据!B:P,15,FALSE),"")
T10: =IF(V10="","",法术数据!AJ4) | U10: =IFERROR(VLOOKUP(V10,法术数据!B:P,15,FALSE),"") | W10: =IF(Y10="","",法术数据!AJ54) | X10: =IFERROR(VLOOKUP(Y10,法术数据!B:P,15,FALSE),"") | Z10: =IF(AB10="","",法术数据!AJ4) | AA10: =IFERROR(VLOOKUP(AB10,法术数据!B:P,15,FALSE),"") | AC10: =IF(AE10="","",法术数据!AJ54) | AD10: =IFERROR(VLOOKUP(AE10,法术数据!B:P,15,FALSE),"") | AF10: =IF(AH10="","",法术数据!AJ4) | AG10: =IFERROR(VLOOKUP(AH10,法术数据!B:P,15,FALSE),"") | AI10: =IF(AK10="","",法术数据!AJ54) | AJ10: =IFERROR(VLOOKUP(AK10,法术数据!B:P,15,FALSE),"")
C11: =IF(C3="","","法术成分："&IF(VLOOKUP(C3,法术数据!B:H,7,FALSE)=1," 言语 ","")&IF(VLOOKUP(C3,法术数据!B:I,8,FALSE)=1," 姿势 ","")&IF(VLOOKUP(C3,法术数据!B:J,9,FALSE)=1," 材料 ","")) | K11: =IF(C3="","","施法距离： "&(VLOOKUP(C3,法术数据!B:G,6,FALSE))) | T11: =IF(V11="","",法术数据!AJ5) | U11: =IFERROR(VLOOKUP(V11,法术数据!B:P,15,FALSE),"") | W11: =IF(Y11="","",法术数据!AJ55) | X11: =IFERROR(VLOOKUP(Y11,法术数据!B:P,15,FALSE),"") | Z11: =IF(AB11="","",法术数据!AJ5) | AA11: =IFERROR(VLOOKUP(AB11,法术数据!B:P,15,FALSE),"") | AC11: =IF(AE11="","",法术数据!AV55) | AD11: =IFERROR(VLOOKUP(AE11,法术数据!B:P,15,FALSE),"") | AF11: =IF(AH11="","",法术数据!AJ5) | AG11: =IFERROR(VLOOKUP(AH11,法术数据!B:P,15,FALSE),"") | AI11: =IF(AK11="","",法术数据!AT55) | AJ11: =IFERROR(VLOOKUP(AK11,法术数据!B:P,15,FALSE),"")
T12: =IF(V12="","",法术数据!AJ6) | U12: =IFERROR(VLOOKUP(V12,法术数据!B:P,15,FALSE),"") | W12: =IF(Y12="","",法术数据!AJ56) | X12: =IFERROR(VLOOKUP(Y12,法术数据!B:P,15,FALSE),"") | Z12: =IF(AB12="","",法术数据!AJ6) | AA12: =IFERROR(VLOOKUP(AB12,法术数据!B:P,15,FALSE),"") | AC12: =IF(AE12="","",法术数据!AJ56) | AD12: =IFERROR(VLOOKUP(AE12,法术数据!B:P,15,FALSE),"") | AF12: =IF(AH12="","",法术数据!AJ6) | AG12: =IFERROR(VLOOKUP(AH12,法术数据!B:P,15,FALSE),"") | AI12: =IF(AK12="","",法术数据!AJ56) | AJ12: =IFERROR(VLOOKUP(AK12,法术数据!B:P,15,FALSE),"")
C13: =IF(C3="","",IF(VLOOKUP(C3,法术数据!B:K,10,FALSE)="","","触媒： "&VLOOKUP(C3,法术数据!B:K,10,FALSE))&IF(VLOOKUP(C3,法术数据!B:J,9,FALSE)=2,CHAR(10),"")&IF(VLOOKUP(C3,法术数据!B:L,11,FALSE)="","","耗材： "&(VLOOKUP(C3,法术数据!B:L,11,FALSE)))) | T13: =IF(V13="","",法术数据!AJ7) | U13: =IFERROR(VLOOKUP(V13,法术数据!B:P,15,FALSE),"") | W13: =IF(Y13="","",法术数据!AJ57) | X13: =IFERROR(VLOOKUP(Y13,法术数据!B:P,15,FALSE),"") | Z13: =IF(AB13="","",法术数据!AJ7) | AA13: =IFERROR(VLOOKUP(AB13,法术数据!B:P,15,FALSE),"") | AC13: =IF(AE13="","",法术数据!AV57) | AD13: =IFERROR(VLOOKUP(AE13,法术数据!B:P,15,FALSE),"") | AF13: =IF(AH13="","",法术数据!AJ7) | AG13: =IFERROR(VLOOKUP(AH13,法术数据!B:P,15,FALSE),"") | AI13: =IF(AK13="","",法术数据!AT57) | AJ13: =IFERROR(VLOOKUP(AK13,法术数据!B:P,15,FALSE),"")
T14: =IF(V14="","",法术数据!AJ8) | U14: =IFERROR(VLOOKUP(V14,法术数据!B:P,15,FALSE),"") | W14: =IF(Y14="","",法术数据!AJ58) | X14: =IFERROR(VLOOKUP(Y14,法术数据!B:P,15,FALSE),"") | Z14: =IF(AB14="","",法术数据!AJ8) | AA14: =IFERROR(VLOOKUP(AB14,法术数据!B:P,15,FALSE),"") | AC14: =IF(AE14="","",法术数据!AJ58) | AD14: =IFERROR(VLOOKUP(AE14,法术数据!B:P,15,FALSE),"") | AF14: =IF(AH14="","",法术数据!AJ8) | AG14: =IFERROR(VLOOKUP(AH14,法术数据!B:P,15,FALSE),"") | AI14: =IF(AK14="","",法术数据!AJ58) | AJ14: =IFERROR(VLOOKUP(AK14,法术数据!B:P,15,FALSE),"")
T15: =IF(V15="","",法术数据!AJ9) | U15: =IFERROR(VLOOKUP(V15,法术数据!B:P,15,FALSE),"") | W15: =IF(Y15="","",法术数据!AJ59) | X15: =IFERROR(VLOOKUP(Y15,法术数据!B:P,15,FALSE),"") | Z15: =IF(AB15="","",法术数据!AJ9) | AA15: =IFERROR(VLOOKUP(AB15,法术数据!B:P,15,FALSE),"") | AC15: =IF(AE15="","",法术数据!AV59) | AD15: =IFERROR(VLOOKUP(AE15,法术数据!B:P,15,FALSE),"") | AF15: =IF(AH15="","",法术数据!AJ9) | AG15: =IFERROR(VLOOKUP(AH15,法术数据!B:P,15,FALSE),"") | AI15: =IF(AK15="","",法术数据!AT59) | AJ15: =IFERROR(VLOOKUP(AK15,法术数据!B:P,15,FALSE),"")
T16: =IF(V16="","",法术数据!AJ10) | U16: =IFERROR(VLOOKUP(V16,法术数据!B:P,15,FALSE),"") | W16: =IF(Y16="","",法术数据!AJ60) | X16: =IFERROR(VLOOKUP(Y16,法术数据!B:P,15,FALSE),"") | Z16: =IF(AB16="","",法术数据!AJ10) | AA16: =IFERROR(VLOOKUP(AB16,法术数据!B:P,15,FALSE),"") | AC16: =IF(AE16="","",法术数据!AJ60) | AD16: =IFERROR(VLOOKUP(AE16,法术数据!B:P,15,FALSE),"") | AF16: =IF(AH16="","",法术数据!AJ10) | AG16: =IFERROR(VLOOKUP(AH16,法术数据!B:P,15,FALSE),"") | AI16: =IF(AK16="","",法术数据!AJ60) | AJ16: =IFERROR(VLOOKUP(AK16,法术数据!B:P,15,FALSE),"")
T17: =IF(V17="","",法术数据!AJ11) | U17: =IFERROR(VLOOKUP(V17,法术数据!B:P,15,FALSE),"") | W17: =IF(Y17="","",法术数据!AJ61) | X17: =IFERROR(VLOOKUP(Y17,法术数据!B:P,15,FALSE),"") | Z17: =IF(AB17="","",法术数据!AJ11) | AA17: =IFERROR(VLOOKUP(AB17,法术数据!B:P,15,FALSE),"") | AC17: =IF(AE17="","",法术数据!AV61) | AD17: =IFERROR(VLOOKUP(AE17,法术数据!B:P,15,FALSE),"") | AF17: =IF(AH17="","",法术数据!AJ11) | AG17: =IFERROR(VLOOKUP(AH17,法术数据!B:P,15,FALSE),"") | AI17: =IF(AK17="","",法术数据!AT61) | AJ17: =IFERROR(VLOOKUP(AK17,法术数据!B:P,15,FALSE),"")
T18: =IF(V18="","",法术数据!AJ12) | U18: =IFERROR(VLOOKUP(V18,法术数据!B:P,15,FALSE),"") | W18: =IF(Y18="","",法术数据!AJ62) | X18: =IFERROR(VLOOKUP(Y18,法术数据!B:P,15,FALSE),"") | Z18: =IF(AB18="","",法术数据!AJ12) | AA18: =IFERROR(VLOOKUP(AB18,法术数据!B:P,15,FALSE),"") | AC18: =IF(AE18="","",法术数据!AJ62) | AD18: =IFERROR(VLOOKUP(AE18,法术数据!B:P,15,FALSE),"") | AF18: =IF(AH18="","",法术数据!AJ12) | AG18: =IFERROR(VLOOKUP(AH18,法术数据!B:P,15,FALSE),"") | AI18: =IF(AK18="","",法术数据!AJ62) | AJ18: =IFERROR(VLOOKUP(AK18,法术数据!B:P,15,FALSE),"")
C19: =IF(C3="","","持续时间： "&VLOOKUP(C3,法术数据!B:N,13,FALSE)) | O19: =IFERROR(IF(VLOOKUP(C3,法术数据!B:M,12,FALSE)=1,"需要专注",""),"") | T19: =IF(V19="","",法术数据!AJ13) | U19: =IFERROR(VLOOKUP(V19,法术数据!B:P,15,FALSE),"") | W19: =IF(Y19="","",法术数据!AJ63) | X19: =IFERROR(VLOOKUP(Y19,法术数据!B:P,15,FALSE),"") | Z19: =IF(AB19="","",法术数据!AJ13) | AA19: =IFERROR(VLOOKUP(AB19,法术数据!B:P,15,FALSE),"") | AC19: =IF(AE19="","",法术数据!AV63) | AD19: =IFERROR(VLOOKUP(AE19,法术数据!B:P,15,FALSE),"") | AF19: =IF(AH19="","",法术数据!AJ13) | AG19: =IFERROR(VLOOKUP(AH19,法术数据!B:P,15,FALSE),"") | AI19: =IF(AK19="","",法术数据!AT63) | AJ19: =IFERROR(VLOOKUP(AK19,法术数据!B:P,15,FALSE),"")
T20: =IF(V20="","",法术数据!AJ14) | U20: =IFERROR(VLOOKUP(V20,法术数据!B:P,15,FALSE),"") | W20: =IF(Y20="","",法术数据!AJ64) | X20: =IFERROR(VLOOKUP(Y20,法术数据!B:P,15,FALSE),"") | Z20: =IF(AB20="","",法术数据!AJ14) | AA20: =IFERROR(VLOOKUP(AB20,法术数据!B:P,15,FALSE),"") | AC20: =IF(AE20="","",法术数据!AJ64) | AD20: =IFERROR(VLOOKUP(AE20,法术数据!B:P,15,FALSE),"") | AF20: =IF(AH20="","",法术数据!AJ14) | AG20: =IFERROR(VLOOKUP(AH20,法术数据!B:P,15,FALSE),"") | AI20: =IF(AK20="","",法术数据!AJ64) | AJ20: =IFERROR(VLOOKUP(AK20,法术数据!B:P,15,FALSE),"")
T21: =IF(V21="","",法术数据!AJ15) | U21: =IFERROR(VLOOKUP(V21,法术数据!B:P,15,FALSE),"") | W21: =IF(Y21="","",法术数据!AJ65) | X21: =IFERROR(VLOOKUP(Y21,法术数据!B:P,15,FALSE),"") | Z21: =IF(AB21="","",法术数据!AJ15) | AA21: =IFERROR(VLOOKUP(AB21,法术数据!B:P,15,FALSE),"") | AC21: =IF(AE21="","",法术数据!AV65) | AD21: =IFERROR(VLOOKUP(AE21,法术数据!B:P,15,FALSE),"") | AF21: =IF(AH21="","",法术数据!AJ15) | AG21: =IFERROR(VLOOKUP(AH21,法术数据!B:P,15,FALSE),"") | AI21: =IF(AK21="","",法术数据!AT65) | AJ21: =IFERROR(VLOOKUP(AK21,法术数据!B:P,15,FALSE),"")
C22: =IF(C23<>"","法术说明","") | T22: =IF(V22="","",法术数据!AJ16) | U22: =IFERROR(VLOOKUP(V22,法术数据!B:P,15,FALSE),"") | W22: =IF(Y22="","",法术数据!AJ66) | X22: =IFERROR(VLOOKUP(Y22,法术数据!B:P,15,FALSE),"") | Z22: =IF(AB22="","",法术数据!AJ16) | AA22: =IFERROR(VLOOKUP(AB22,法术数据!B:P,15,FALSE),"") | AC22: =IF(AE22="","",法术数据!AJ66) | AD22: =IFERROR(VLOOKUP(AE22,法术数据!B:P,15,FALSE),"") | AF22: =IF(AH22="","",法术数据!AJ16) | AG22: =IFERROR(VLOOKUP(AH22,法术数据!B:P,15,FALSE),"") | AI22: =IF(AK22="","",法术数据!AJ66) | AJ22: =IFERROR(VLOOKUP(AK22,法术数据!B:P,15,FALSE),"")
C23: =IF(C3="","",(VLOOKUP(C3,法术数据!B:O,14,FALSE))) | T23: =IF(V23="","",法术数据!AJ17) | U23: =IFERROR(VLOOKUP(V23,法术数据!B:P,15,FALSE),"") | W23: =IF(Y23="","",法术数据!AJ67) | X23: =IFERROR(VLOOKUP(Y23,法术数据!B:P,15,FALSE),"") | Z23: =IF(AB23="","",法术数据!AJ17) | AA23: =IFERROR(VLOOKUP(AB23,法术数据!B:P,15,FALSE),"") | AC23: =IF(AE23="","",法术数据!AV67) | AD23: =IFERROR(VLOOKUP(AE23,法术数据!B:P,15,FALSE),"") | AF23: =IF(AH23="","",法术数据!AJ17) | AG23: =IFERROR(VLOOKUP(AH23,法术数据!B:P,15,FALSE),"") | AI23: =IF(AK23="","",法术数据!AT67) | AJ23: =IFERROR(VLOOKUP(AK23,法术数据!B:P,15,FALSE),"")
T24: =IF(V24="","",法术数据!AJ18) | U24: =IFERROR(VLOOKUP(V24,法术数据!B:P,15,FALSE),"") | W24: =IF(Y24="","",法术数据!AJ68) | X24: =IFERROR(VLOOKUP(Y24,法术数据!B:P,15,FALSE),"") | Z24: =IF(AB24="","",法术数据!AJ18) | AA24: =IFERROR(VLOOKUP(AB24,法术数据!B:P,15,FALSE),"") | AC24: =IF(AE24="","",法术数据!AJ68) | AD24: =IFERROR(VLOOKUP(AE24,法术数据!B:P,15,FALSE),"") | AF24: =IF(AH24="","",法术数据!AJ18) | AG24: =IFERROR(VLOOKUP(AH24,法术数据!B:P,15,FALSE),"") | AI24: =IF(AK24="","",法术数据!AJ68) | AJ24: =IFERROR(VLOOKUP(AK24,法术数据!B:P,15,FALSE),"")
T25: =IF(V25="","",法术数据!AJ19) | U25: =IFERROR(VLOOKUP(V25,法术数据!B:P,15,FALSE),"") | W25: =IF(Y25="","",法术数据!AJ69) | X25: =IFERROR(VLOOKUP(Y25,法术数据!B:P,15,FALSE),"") | Z25: =IF(AB25="","",法术数据!AJ19) | AA25: =IFERROR(VLOOKUP(AB25,法术数据!B:P,15,FALSE),"") | AC25: =IF(AE25="","",法术数据!AV69) | AD25: =IFERROR(VLOOKUP(AE25,法术数据!B:P,15,FALSE),"") | AF25: =IF(AH25="","",法术数据!AJ19) | AG25: =IFERROR(VLOOKUP(AH25,法术数据!B:P,15,FALSE),"") | AI25: =IF(AK25="","",法术数据!AT69) | AJ25: =IFERROR(VLOOKUP(AK25,法术数据!B:P,15,FALSE),"")
T26: =IF(V26="","",法术数据!AJ20) | U26: =IFERROR(VLOOKUP(V26,法术数据!B:P,15,FALSE),"") | W26: =IF(Y26="","",法术数据!AJ70) | X26: =IFERROR(VLOOKUP(Y26,法术数据!B:P,15,FALSE),"") | Z26: =IF(AB26="","",法术数据!AJ20) | AA26: =IFERROR(VLOOKUP(AB26,法术数据!B:P,15,FALSE),"") | AC26: =IF(AE26="","",法术数据!AJ70) | AD26: =IFERROR(VLOOKUP(AE26,法术数据!B:P,15,FALSE),"") | AF26: =IF(AH26="","",法术数据!AJ20) | AG26: =IFERROR(VLOOKUP(AH26,法术数据!B:P,15,FALSE),"") | AI26: =IF(AK26="","",法术数据!AJ70) | AJ26: =IFERROR(VLOOKUP(AK26,法术数据!B:P,15,FALSE),"")
T27: =IF(V27="","",法术数据!AJ21) | U27: =IFERROR(VLOOKUP(V27,法术数据!B:P,15,FALSE),"") | W27: =IF(Y27="","",法术数据!AJ71) | X27: =IFERROR(VLOOKUP(Y27,法术数据!B:P,15,FALSE),"") | Z27: =IF(AB27="","",法术数据!AJ21) | AA27: =IFERROR(VLOOKUP(AB27,法术数据!B:P,15,FALSE),"") | AC27: =IF(AE27="","",法术数据!AV71) | AD27: =IFERROR(VLOOKUP(AE27,法术数据!B:P,15,FALSE),"") | AF27: =IF(AH27="","",法术数据!AJ21) | AG27: =IFERROR(VLOOKUP(AH27,法术数据!B:P,15,FALSE),"") | AI27: =IF(AK27="","",法术数据!AT71) | AJ27: =IFERROR(VLOOKUP(AK27,法术数据!B:P,15,FALSE),"")
T28: =IF(V28="","",法术数据!AJ22) | U28: =IFERROR(VLOOKUP(V28,法术数据!B:P,15,FALSE),"") | W28: =IF(Y28="","",法术数据!AJ72) | X28: =IFERROR(VLOOKUP(Y28,法术数据!B:P,15,FALSE),"") | Z28: =IF(AB28="","",法术数据!AJ22) | AA28: =IFERROR(VLOOKUP(AB28,法术数据!B:P,15,FALSE),"") | AC28: =IF(AE28="","",法术数据!AJ72) | AD28: =IFERROR(VLOOKUP(AE28,法术数据!B:P,15,FALSE),"") | AF28: =IF(AH28="","",法术数据!AJ22) | AG28: =IFERROR(VLOOKUP(AH28,法术数据!B:P,15,FALSE),"") | AI28: =IF(AK28="","",法术数据!AJ72) | AJ28: =IFERROR(VLOOKUP(AK28,法术数据!B:P,15,FALSE),"")
T29: =IF(V29="","",法术数据!AJ23) | U29: =IFERROR(VLOOKUP(V29,法术数据!B:P,15,FALSE),"") | W29: =IF(Y29="","",法术数据!AJ73) | X29: =IFERROR(VLOOKUP(Y29,法术数据!B:P,15,FALSE),"") | Z29: =IF(AB29="","",法术数据!AJ23) | AA29: =IFERROR(VLOOKUP(AB29,法术数据!B:P,15,FALSE),"") | AC29: =IF(AE29="","",法术数据!AV73) | AD29: =IFERROR(VLOOKUP(AE29,法术数据!B:P,15,FALSE),"") | AF29: =IF(AH29="","",法术数据!AJ23) | AG29: =IFERROR(VLOOKUP(AH29,法术数据!B:P,15,FALSE),"") | AI29: =IF(AK29="","",法术数据!AT73) | AJ29: =IFERROR(VLOOKUP(AK29,法术数据!B:P,15,FALSE),"")
T30: =IF(V30="","",法术数据!AJ24) | U30: =IFERROR(VLOOKUP(V30,法术数据!B:P,15,FALSE),"") | W30: =IF(Y30="","",法术数据!AJ74) | X30: =IFERROR(VLOOKUP(Y30,法术数据!B:P,15,FALSE),"") | Z30: =IF(AB30="","",法术数据!AJ24) | AA30: =IFERROR(VLOOKUP(AB30,法术数据!B:P,15,FALSE),"") | AC30: =IF(AE30="","",法术数据!AJ74) | AD30: =IFERROR(VLOOKUP(AE30,法术数据!B:P,15,FALSE),"") | AF30: =IF(AH30="","",法术数据!AJ24) | AG30: =IFERROR(VLOOKUP(AH30,法术数据!B:P,15,FALSE),"") | AI30: =IF(AK30="","",法术数据!AJ74) | AJ30: =IFERROR(VLOOKUP(AK30,法术数据!B:P,15,FALSE),"")
T31: =IF(V31="","",法术数据!AJ25) | U31: =IFERROR(VLOOKUP(V31,法术数据!B:P,15,FALSE),"") | W31: =IF(Y31="","",法术数据!AJ75) | X31: =IFERROR(VLOOKUP(Y31,法术数据!B:P,15,FALSE),"") | Z31: =IF(AB31="","",法术数据!AJ25) | AA31: =IFERROR(VLOOKUP(AB31,法术数据!B:P,15,FALSE),"") | AC31: =IF(AE31="","",法术数据!AV75) | AD31: =IFERROR(VLOOKUP(AE31,法术数据!B:P,15,FALSE),"") | AF31: =IF(AH31="","",法术数据!AJ25) | AG31: =IFERROR(VLOOKUP(AH31,法术数据!B:P,15,FALSE),"") | AI31: =IF(AK31="","",法术数据!AT75) | AJ31: =IFERROR(VLOOKUP(AK31,法术数据!B:P,15,FALSE),"")
T32: =IF(V32="","",法术数据!AJ26) | U32: =IFERROR(VLOOKUP(V32,法术数据!B:P,15,FALSE),"") | W32: =IF(Y32="","",法术数据!AJ76) | X32: =IFERROR(VLOOKUP(Y32,法术数据!B:P,15,FALSE),"") | Z32: =IF(AB32="","",法术数据!AJ26) | AA32: =IFERROR(VLOOKUP(AB32,法术数据!B:P,15,FALSE),"") | AC32: =IF(AE32="","",法术数据!AJ76) | AD32: =IFERROR(VLOOKUP(AE32,法术数据!B:P,15,FALSE),"") | AF32: =IF(AH32="","",法术数据!AJ26) | AG32: =IFERROR(VLOOKUP(AH32,法术数据!B:P,15,FALSE),"") | AI32: =IF(AK32="","",法术数据!AJ76) | AJ32: =IFERROR(VLOOKUP(AK32,法术数据!B:P,15,FALSE),"")
T33: =IF(V33="","",法术数据!AJ27) | U33: =IFERROR(VLOOKUP(V33,法术数据!B:P,15,FALSE),"") | W33: =IF(Y33="","",法术数据!AJ77) | X33: =IFERROR(VLOOKUP(Y33,法术数据!B:P,15,FALSE),"") | Z33: =IF(AB33="","",法术数据!AJ27) | AA33: =IFERROR(VLOOKUP(AB33,法术数据!B:P,15,FALSE),"") | AC33: =IF(AE33="","",法术数据!AV77) | AD33: =IFERROR(VLOOKUP(AE33,法术数据!B:P,15,FALSE),"") | AF33: =IF(AH33="","",法术数据!AJ27) | AG33: =IFERROR(VLOOKUP(AH33,法术数据!B:P,15,FALSE),"") | AI33: =IF(AK33="","",法术数据!AT77) | AJ33: =IFERROR(VLOOKUP(AK33,法术数据!B:P,15,FALSE),"")
T34: =IF(V34="","",法术数据!AJ28) | U34: =IFERROR(VLOOKUP(V34,法术数据!B:P,15,FALSE),"") | W34: =IF(Y34="","",法术数据!AJ78) | X34: =IFERROR(VLOOKUP(Y34,法术数据!B:P,15,FALSE),"") | Z34: =IF(AB34="","",法术数据!AJ28) | AA34: =IFERROR(VLOOKUP(AB34,法术数据!B:P,15,FALSE),"") | AC34: =IF(AE34="","",法术数据!AJ78) | AD34: =IFERROR(VLOOKUP(AE34,法术数据!B:P,15,FALSE),"") | AF34: =IF(AH34="","",法术数据!AJ28) | AG34: =IFERROR(VLOOKUP(AH34,法术数据!B:P,15,FALSE),"") | AI34: =IF(AK34="","",法术数据!AJ78) | AJ34: =IFERROR(VLOOKUP(AK34,法术数据!B:P,15,FALSE),"")
T35: =IF(V35="","",法术数据!AJ29) | U35: =IFERROR(VLOOKUP(V35,法术数据!B:P,15,FALSE),"") | W35: =IF(Y35="","",法术数据!AJ79) | X35: =IFERROR(VLOOKUP(Y35,法术数据!B:P,15,FALSE),"") | Z35: =IF(AB35="","",法术数据!AJ29) | AA35: =IFERROR(VLOOKUP(AB35,法术数据!B:P,15,FALSE),"") | AC35: =IF(AE35="","",法术数据!AV79) | AD35: =IFERROR(VLOOKUP(AE35,法术数据!B:P,15,FALSE),"") | AF35: =IF(AH35="","",法术数据!AJ29) | AG35: =IFERROR(VLOOKUP(AH35,法术数据!B:P,15,FALSE),"") | AI35: =IF(AK35="","",法术数据!AT79) | AJ35: =IFERROR(VLOOKUP(AK35,法术数据!B:P,15,FALSE),"")
T36: =IF(V36="","",法术数据!AJ30) | U36: =IFERROR(VLOOKUP(V36,法术数据!B:P,15,FALSE),"") | W36: =IF(Y36="","",法术数据!AJ80) | X36: =IFERROR(VLOOKUP(Y36,法术数据!B:P,15,FALSE),"") | Z36: =IF(AB36="","",法术数据!AJ30) | AA36: =IFERROR(VLOOKUP(AB36,法术数据!B:P,15,FALSE),"") | AC36: =IF(AE36="","",法术数据!AJ80) | AD36: =IFERROR(VLOOKUP(AE36,法术数据!B:P,15,FALSE),"") | AF36: =IF(AH36="","",法术数据!AJ30) | AG36: =IFERROR(VLOOKUP(AH36,法术数据!B:P,15,FALSE),"") | AI36: =IF(AK36="","",法术数据!AJ80) | AJ36: =IFERROR(VLOOKUP(AK36,法术数据!B:P,15,FALSE),"")
T37: =IF(V37="","",法术数据!AJ31) | U37: =IFERROR(VLOOKUP(V37,法术数据!B:P,15,FALSE),"") | W37: =IF(Y37="","",法术数据!AJ81) | X37: =IFERROR(VLOOKUP(Y37,法术数据!B:P,15,FALSE),"") | Z37: =IF(AB37="","",法术数据!AJ31) | AA37: =IFERROR(VLOOKUP(AB37,法术数据!B:P,15,FALSE),"") | AC37: =IF(AE37="","",法术数据!AV81) | AD37: =IFERROR(VLOOKUP(AE37,法术数据!B:P,15,FALSE),"") | AF37: =IF(AH37="","",法术数据!AJ31) | AG37: =IFERROR(VLOOKUP(AH37,法术数据!B:P,15,FALSE),"") | AI37: =IF(AK37="","",法术数据!AT81) | AJ37: =IFERROR(VLOOKUP(AK37,法术数据!B:P,15,FALSE),"")
T38: =IF(V38="","",法术数据!AJ32) | U38: =IFERROR(VLOOKUP(V38,法术数据!B:P,15,FALSE),"") | W38: =IF(Y38="","",法术数据!AJ82) | X38: =IFERROR(VLOOKUP(Y38,法术数据!B:P,15,FALSE),"") | Z38: =IF(AB38="","",法术数据!AJ32) | AA38: =IFERROR(VLOOKUP(AB38,法术数据!B:P,15,FALSE),"") | AC38: =IF(AE38="","",法术数据!AJ82) | AD38: =IFERROR(VLOOKUP(AE38,法术数据!B:P,15,FALSE),"") | AF38: =IF(AH38="","",法术数据!AJ32) | AG38: =IFERROR(VLOOKUP(AH38,法术数据!B:P,15,FALSE),"") | AI38: =IF(AK38="","",法术数据!AJ82) | AJ38: =IFERROR(VLOOKUP(AK38,法术数据!B:P,15,FALSE),"")
T39: =IF(V39="","",法术数据!AJ33) | U39: =IFERROR(VLOOKUP(V39,法术数据!B:P,15,FALSE),"") | W39: =IF(Y39="","",法术数据!AJ83) | X39: =IFERROR(VLOOKUP(Y39,法术数据!B:P,15,FALSE),"") | Z39: =IF(AB39="","",法术数据!AJ33) | AA39: =IFERROR(VLOOKUP(AB39,法术数据!B:P,15,FALSE),"") | AC39: =IF(AE39="","",法术数据!AV83) | AD39: =IFERROR(VLOOKUP(AE39,法术数据!B:P,15,FALSE),"") | AF39: =IF(AH39="","",法术数据!AJ33) | AG39: =IFERROR(VLOOKUP(AH39,法术数据!B:P,15,FALSE),"") | AI39: =IF(AK39="","",法术数据!AT83) | AJ39: =IFERROR(VLOOKUP(AK39,法术数据!B:P,15,FALSE),"")
T40: =IF(V40="","",法术数据!AJ34) | U40: =IFERROR(VLOOKUP(V40,法术数据!B:P,15,FALSE),"") | W40: =IF(Y40="","",法术数据!AJ84) | X40: =IFERROR(VLOOKUP(Y40,法术数据!B:P,15,FALSE),"") | Z40: =IF(AB40="","",法术数据!AJ34) | AA40: =IFERROR(VLOOKUP(AB40,法术数据!B:P,15,FALSE),"") | AC40: =IF(AE40="","",法术数据!AJ84) | AD40: =IFERROR(VLOOKUP(AE40,法术数据!B:P,15,FALSE),"") | AF40: =IF(AH40="","",法术数据!AJ34) | AG40: =IFERROR(VLOOKUP(AH40,法术数据!B:P,15,FALSE),"") | AI40: =IF(AK40="","",法术数据!AJ84) | AJ40: =IFERROR(VLOOKUP(AK40,法术数据!B:P,15,FALSE),"")
T41: =IF(V41="","",法术数据!AJ35) | U41: =IFERROR(VLOOKUP(V41,法术数据!B:P,15,FALSE),"") | W41: =IF(Y41="","",法术数据!AJ85) | X41: =IFERROR(VLOOKUP(Y41,法术数据!B:P,15,FALSE),"") | Z41: =IF(AB41="","",法术数据!AJ35) | AA41: =IFERROR(VLOOKUP(AB41,法术数据!B:P,15,FALSE),"") | AC41: =IF(AE41="","",法术数据!AV85) | AD41: =IFERROR(VLOOKUP(AE41,法术数据!B:P,15,FALSE),"") | AF41: =IF(AH41="","",法术数据!AJ35) | AG41: =IFERROR(VLOOKUP(AH41,法术数据!B:P,15,FALSE),"") | AI41: =IF(AK41="","",法术数据!AT85) | AJ41: =IFERROR(VLOOKUP(AK41,法术数据!B:P,15,FALSE),"")
T42: =IF(V42="","",法术数据!AJ36) | U42: =IFERROR(VLOOKUP(V42,法术数据!B:P,15,FALSE),"") | W42: =IF(Y42="","",法术数据!AJ86) | X42: =IFERROR(VLOOKUP(Y42,法术数据!B:P,15,FALSE),"") | Z42: =IF(AB42="","",法术数据!AJ36) | AA42: =IFERROR(VLOOKUP(AB42,法术数据!B:P,15,FALSE),"") | AC42: =IF(AE42="","",法术数据!AJ86) | AD42: =IFERROR(VLOOKUP(AE42,法术数据!B:P,15,FALSE),"") | AF42: =IF(AH42="","",法术数据!AJ36) | AG42: =IFERROR(VLOOKUP(AH42,法术数据!B:P,15,FALSE),"") | AI42: =IF(AK42="","",法术数据!AJ86) | AJ42: =IFERROR(VLOOKUP(AK42,法术数据!B:P,15,FALSE),"")
T43: =IF(V43="","",法术数据!AJ37) | U43: =IFERROR(VLOOKUP(V43,法术数据!B:P,15,FALSE),"") | W43: =IF(Y43="","",法术数据!AJ87) | X43: =IFERROR(VLOOKUP(Y43,法术数据!B:P,15,FALSE),"") | Z43: =IF(AB43="","",法术数据!AJ37) | AA43: =IFERROR(VLOOKUP(AB43,法术数据!B:P,15,FALSE),"") | AC43: =IF(AE43="","",法术数据!AV87) | AD43: =IFERROR(VLOOKUP(AE43,法术数据!B:P,15,FALSE),"") | AF43: =IF(AH43="","",法术数据!AJ37) | AG43: =IFERROR(VLOOKUP(AH43,法术数据!B:P,15,FALSE),"") | AI43: =IF(AK43="","",法术数据!AT87) | AJ43: =IFERROR(VLOOKUP(AK43,法术数据!B:P,15,FALSE),"")
T44: =IF(V44="","",法术数据!AJ38) | U44: =IFERROR(VLOOKUP(V44,法术数据!B:P,15,FALSE),"") | W44: =IF(Y44="","",法术数据!AJ88) | X44: =IFERROR(VLOOKUP(Y44,法术数据!B:P,15,FALSE),"") | Z44: =IF(AB44="","",法术数据!AJ38) | AA44: =IFERROR(VLOOKUP(AB44,法术数据!B:P,15,FALSE),"") | AC44: =IF(AE44="","",法术数据!AJ88) | AD44: =IFERROR(VLOOKUP(AE44,法术数据!B:P,15,FALSE),"") | AF44: =IF(AH44="","",法术数据!AJ38) | AG44: =IFERROR(VLOOKUP(AH44,法术数据!B:P,15,FALSE),"") | AI44: =IF(AK44="","",法术数据!AJ88) | AJ44: =IFERROR(VLOOKUP(AK44,法术数据!B:P,15,FALSE),"")
T45: =IF(V45="","",法术数据!AJ39) | U45: =IFERROR(VLOOKUP(V45,法术数据!B:P,15,FALSE),"") | W45: =IF(Y45="","",法术数据!AJ89) | X45: =IFERROR(VLOOKUP(Y45,法术数据!B:P,15,FALSE),"") | Z45: =IF(AB45="","",法术数据!AJ39) | AA45: =IFERROR(VLOOKUP(AB45,法术数据!B:P,15,FALSE),"") | AC45: =IF(AE45="","",法术数据!AV89) | AD45: =IFERROR(VLOOKUP(AE45,法术数据!B:P,15,FALSE),"") | AF45: =IF(AH45="","",法术数据!AJ39) | AG45: =IFERROR(VLOOKUP(AH45,法术数据!B:P,15,FALSE),"") | AI45: =IF(AK45="","",法术数据!AT89) | AJ45: =IFERROR(VLOOKUP(AK45,法术数据!B:P,15,FALSE),"")
T46: =IF(V46="","",法术数据!AJ40) | U46: =IFERROR(VLOOKUP(V46,法术数据!B:P,15,FALSE),"") | W46: =IF(Y46="","",法术数据!AJ90) | X46: =IFERROR(VLOOKUP(Y46,法术数据!B:P,15,FALSE),"") | Z46: =IF(AB46="","",法术数据!AJ40) | AA46: =IFERROR(VLOOKUP(AB46,法术数据!B:P,15,FALSE),"") | AC46: =IF(AE46="","",法术数据!AJ90) | AD46: =IFERROR(VLOOKUP(AE46,法术数据!B:P,15,FALSE),"") | AF46: =IF(AH46="","",法术数据!AJ40) | AG46: =IFERROR(VLOOKUP(AH46,法术数据!B:P,15,FALSE),"") | AI46: =IF(AK46="","",法术数据!AJ90) | AJ46: =IFERROR(VLOOKUP(AK46,法术数据!B:P,15,FALSE),"")
T47: =IF(V47="","",法术数据!AJ41) | U47: =IFERROR(VLOOKUP(V47,法术数据!B:P,15,FALSE),"") | W47: =IF(Y47="","",法术数据!AJ91) | X47: =IFERROR(VLOOKUP(Y47,法术数据!B:P,15,FALSE),"") | Z47: =IF(AB47="","",法术数据!AJ41) | AA47: =IFERROR(VLOOKUP(AB47,法术数据!B:P,15,FALSE),"") | AC47: =IF(AE47="","",法术数据!AV91) | AD47: =IFERROR(VLOOKUP(AE47,法术数据!B:P,15,FALSE),"") | AF47: =IF(AH47="","",法术数据!AJ41) | AG47: =IFERROR(VLOOKUP(AH47,法术数据!B:P,15,FALSE),"") | AI47: =IF(AK47="","",法术数据!AT91) | AJ47: =IFERROR(VLOOKUP(AK47,法术数据!B:P,15,FALSE),"")
T48: =IF(V48="","",法术数据!AJ42) | U48: =IFERROR(VLOOKUP(V48,法术数据!B:P,15,FALSE),"") | W48: =IF(Y48="","",法术数据!AJ92) | X48: =IFERROR(VLOOKUP(Y48,法术数据!B:P,15,FALSE),"") | Z48: =IF(AB48="","",法术数据!AJ42) | AA48: =IFERROR(VLOOKUP(AB48,法术数据!B:P,15,FALSE),"") | AC48: =IF(AE48="","",法术数据!AJ92) | AD48: =IFERROR(VLOOKUP(AE48,法术数据!B:P,15,FALSE),"") | AF48: =IF(AH48="","",法术数据!AJ42) | AG48: =IFERROR(VLOOKUP(AH48,法术数据!B:P,15,FALSE),"") | AI48: =IF(AK48="","",法术数据!AJ92) | AJ48: =IFERROR(VLOOKUP(AK48,法术数据!B:P,15,FALSE),"")
T49: =IF(V49="","",法术数据!AJ43) | U49: =IFERROR(VLOOKUP(V49,法术数据!B:P,15,FALSE),"") | W49: =IF(Y49="","",法术数据!AJ93) | X49: =IFERROR(VLOOKUP(Y49,法术数据!B:P,15,FALSE),"") | Z49: =IF(AB49="","",法术数据!AJ43) | AA49: =IFERROR(VLOOKUP(AB49,法术数据!B:P,15,FALSE),"") | AC49: =IF(AE49="","",法术数据!AV93) | AD49: =IFERROR(VLOOKUP(AE49,法术数据!B:P,15,FALSE),"") | AF49: =IF(AH49="","",法术数据!AJ43) | AG49: =IFERROR(VLOOKUP(AH49,法术数据!B:P,15,FALSE),"") | AI49: =IF(AK49="","",法术数据!AT93) | AJ49: =IFERROR(VLOOKUP(AK49,法术数据!B:P,15,FALSE),"")
T50: =IF(V50="","",法术数据!AJ44) | U50: =IFERROR(VLOOKUP(V50,法术数据!B:P,15,FALSE),"") | W50: =IF(Y50="","",法术数据!AJ94) | X50: =IFERROR(VLOOKUP(Y50,法术数据!B:P,15,FALSE),"") | Z50: =IF(AB50="","",法术数据!AJ44) | AA50: =IFERROR(VLOOKUP(AB50,法术数据!B:P,15,FALSE),"") | AC50: =IF(AE50="","",法术数据!AJ94) | AD50: =IFERROR(VLOOKUP(AE50,法术数据!B:P,15,FALSE),"") | AF50: =IF(AH50="","",法术数据!AJ44) | AG50: =IFERROR(VLOOKUP(AH50,法术数据!B:P,15,FALSE),"") | AI50: =IF(AK50="","",法术数据!AJ94) | AJ50: =IFERROR(VLOOKUP(AK50,法术数据!B:P,15,FALSE),"")
T51: =IF(V51="","",法术数据!AJ45) | U51: =IFERROR(VLOOKUP(V51,法术数据!B:P,15,FALSE),"") | W51: =IF(Y51="","",法术数据!AJ95) | X51: =IFERROR(VLOOKUP(Y51,法术数据!B:P,15,FALSE),"") | Z51: =IF(AB51="","",法术数据!AJ45) | AA51: =IFERROR(VLOOKUP(AB51,法术数据!B:P,15,FALSE),"") | AC51: =IF(AE51="","",法术数据!AV95) | AD51: =IFERROR(VLOOKUP(AE51,法术数据!B:P,15,FALSE),"") | AF51: =IF(AH51="","",法术数据!AJ45) | AG51: =IFERROR(VLOOKUP(AH51,法术数据!B:P,15,FALSE),"") | AI51: =IF(AK51="","",法术数据!AT95) | AJ51: =IFERROR(VLOOKUP(AK51,法术数据!B:P,15,FALSE),"")
T52: =IF(V52="","",法术数据!AJ46) | U52: =IFERROR(VLOOKUP(V52,法术数据!B:P,15,FALSE),"") | W52: =IF(Y52="","",法术数据!AJ96) | X52: =IFERROR(VLOOKUP(Y52,法术数据!B:P,15,FALSE),"") | Z52: =IF(AB52="","",法术数据!AJ46) | AA52: =IFERROR(VLOOKUP(AB52,法术数据!B:P,15,FALSE),"") | AC52: =IF(AE52="","",法术数据!AJ96) | AD52: =IFERROR(VLOOKUP(AE52,法术数据!B:P,15,FALSE),"") | AF52: =IF(AH52="","",法术数据!AJ46) | AG52: =IFERROR(VLOOKUP(AH52,法术数据!B:P,15,FALSE),"") | AI52: =IF(AK52="","",法术数据!AJ96) | AJ52: =IFERROR(VLOOKUP(AK52,法术数据!B:P,15,FALSE),"")
T53: =IF(V53="","",法术数据!AJ47) | U53: =IFERROR(VLOOKUP(V53,法术数据!B:P,15,FALSE),"") | W53: =IF(Y53="","",法术数据!AJ97) | X53: =IFERROR(VLOOKUP(Y53,法术数据!B:P,15,FALSE),"") | Z53: =IF(AB53="","",法术数据!AJ47) | AA53: =IFERROR(VLOOKUP(AB53,法术数据!B:P,15,FALSE),"") | AC53: =IF(AE53="","",法术数据!AV97) | AD53: =IFERROR(VLOOKUP(AE53,法术数据!B:P,15,FALSE),"") | AF53: =IF(AH53="","",法术数据!AJ47) | AG53: =IFERROR(VLOOKUP(AH53,法术数据!B:P,15,FALSE),"") | AI53: =IF(AK53="","",法术数据!AT97) | AJ53: =IFERROR(VLOOKUP(AK53,法术数据!B:P,15,FALSE),"")
T54: =IF(V54="","",法术数据!AJ48) | U54: =IFERROR(VLOOKUP(V54,法术数据!B:P,15,FALSE),"") | W54: =IF(Y54="","",法术数据!AJ98) | X54: =IFERROR(VLOOKUP(Y54,法术数据!B:P,15,FALSE),"") | Z54: =IF(AB54="","",法术数据!AJ48) | AA54: =IFERROR(VLOOKUP(AB54,法术数据!B:P,15,FALSE),"") | AC54: =IF(AE54="","",法术数据!AJ98) | AD54: =IFERROR(VLOOKUP(AE54,法术数据!B:P,15,FALSE),"") | AF54: =IF(AH54="","",法术数据!AJ48) | AG54: =IFERROR(VLOOKUP(AH54,法术数据!B:P,15,FALSE),"") | AI54: =IF(AK54="","",法术数据!AJ98) | AJ54: =IFERROR(VLOOKUP(AK54,法术数据!B:P,15,FALSE),"")
T55: =IF(V55="","",法术数据!AJ49) | U55: =IFERROR(VLOOKUP(V55,法术数据!B:P,15,FALSE),"") | W55: =IF(Y55="","",法术数据!AJ99) | X55: =IFERROR(VLOOKUP(Y55,法术数据!B:P,15,FALSE),"") | Z55: =IF(AB55="","",法术数据!AJ49) | AA55: =IFERROR(VLOOKUP(AB55,法术数据!B:P,15,FALSE),"") | AC55: =IF(AE55="","",法术数据!AV99) | AD55: =IFERROR(VLOOKUP(AE55,法术数据!B:P,15,FALSE),"") | AF55: =IF(AH55="","",法术数据!AJ49) | AG55: =IFERROR(VLOOKUP(AH55,法术数据!B:P,15,FALSE),"") | AI55: =IF(AK55="","",法术数据!AT99) | AJ55: =IFERROR(VLOOKUP(AK55,法术数据!B:P,15,FALSE),"")
T56: =IF(V56="","",法术数据!AJ50) | U56: =IFERROR(VLOOKUP(V56,法术数据!B:P,15,FALSE),"") | W56: =IF(Y56="","",法术数据!AJ100) | X56: =IFERROR(VLOOKUP(Y56,法术数据!B:P,15,FALSE),"") | Z56: =IF(AB56="","",法术数据!AJ50) | AA56: =IFERROR(VLOOKUP(AB56,法术数据!B:P,15,FALSE),"") | AC56: =IF(AE56="","",法术数据!AJ100) | AD56: =IFERROR(VLOOKUP(AE56,法术数据!B:P,15,FALSE),"") | AF56: =IF(AH56="","",法术数据!AJ50) | AG56: =IFERROR(VLOOKUP(AH56,法术数据!B:P,15,FALSE),"") | AI56: =IF(AK56="","",法术数据!AJ100) | AJ56: =IFERROR(VLOOKUP(AK56,法术数据!B:P,15,FALSE),"")
T57: =IF(V57="","",法术数据!AJ51) | U57: =IFERROR(VLOOKUP(V57,法术数据!B:P,15,FALSE),"") | W57: =IF(Y57="","",法术数据!AJ101) | X57: =IFERROR(VLOOKUP(Y57,法术数据!B:P,15,FALSE),"") | Z57: =IF(AB57="","",法术数据!AJ51) | AA57: =IFERROR(VLOOKUP(AB57,法术数据!B:P,15,FALSE),"") | AC57: =IF(AE57="","",法术数据!AV101) | AD57: =IFERROR(VLOOKUP(AE57,法术数据!B:P,15,FALSE),"") | AF57: =IF(AH57="","",法术数据!AJ51) | AG57: =IFERROR(VLOOKUP(AH57,法术数据!B:P,15,FALSE),"") | AI57: =IF(AK57="","",法术数据!AT101) | AJ57: =IFERROR(VLOOKUP(AK57,法术数据!B:P,15,FALSE),"")

Sheet 综合数据
A1: 版本控制 | C1: 等级 | F1: 生命值计算 | G1: 经验条 | H1: =主要!Y3 -> 1 | I1: 属性 | J1: FALSE | K1: FALSE | L1: FALSE | M1: FALSE | N1: FALSE | O1: FALSE | P1: 技能 | S1: 种类 | T1: 购点计算
A2: PHB | B2: TRUE | C2: 等级 | D2: 经验 | E2: 熟练 | F2: =IF(种族数据!V4=种族数据!B2,1,0)+IF(种族数据!V4=种族数据!K5,2,0)+IF(COUNTIF(专长数据!E2:E7,专长数据!A36),2,0) -> 0 | G2: =主要!R3 -> 0 | H2: =IFERROR(IF(H1=20,IF(H1=20,MOD((G2-D22),30000)/30000),(G2-VLOOKUP(H1,C3:D21,2,0))/((VLOOKUP(H1+1,C3:D21,2,0)-VLOOKUP(H1,C3:D21,2,0)))),0) -> 0 | I2: 1 | J2: 你还有呼吸的力气 | K2: 一动不动 | L2: 应该还算活着 | M2: 蚂蚁的智力都不可能是1 | N2: 你是怎么活到现在的 | O2: 用脸就能恐惧敌人 | P2: 运动 | Q2: =主要!I39 -> -1 | R2: FALSE | S2: 异怪 | T2: 8 | U2: 0
A3: DMG | B3: TRUE | C3: 1 | D3: 0 | E3: 2 | F3: =IF(主要!AW4="",0,主要!AW4+主要!$R$16+F2) -> 9 | G3: 0 | H3: =D4-G3 -> 300 | I3: 2 | J3: 连一枚金币都拿不起来 | K3: 残疾人士 | L3: 固有Buff：病弱 | M3: 连说话都困难 | N3: 迷惘的人啊 | O3: 你出生的时候居然没被掐死 | P3: 体操 | Q3: =主要!I41 -> 4 | R3: FALSE | S3: 野兽 | T3: 9 | U3: 1
A4: MM | B4: TRUE | C4: 2 | D4: 300 | E4: 2 | F4: =IF(主要!AY4="",0,MAX(主要!AY4+主要!$R$16,1)+F2) -> 0 | G4: =D4+1 -> 301 | H4: =D5-G4 -> 599 | I4: 3 | J4: 鸡的力量都比你强 | K4: 无法行动自如 | L4: 突然挂掉都不是奇怪的事情 | M4: 目不识丁 | N4: 上错过厕所 | O4: 路边的狗可能会冲过来咬你 | P4: 巧手 | Q4: =主要!I42 -> 4 | R4: FALSE | S4: 天界生物 | T4: 10 | U4: 2
A5: SCAG | B5: TRUE | C5: 3 | D5: 900 | E5: 2 | F5: =IF(主要!BA4="",0,MAX(主要!BA4+主要!$R$16,1)+F2) -> 0 | G5: =D5+1 -> 901 | H5: =D6-G5 -> 1799 | I5: 4 | J5: 手无抓鸡之力 | K5: 腿脚不灵活 | L5: 您的每一天都是上天的恩赐 | M5: 你能看得懂这行字？ | N5: 经常迷路 | O5: 容易被排斥 | P5: 隐匿 | Q5: =主要!I43 -> 6 | R5: FALSE | S5: 构装生物 | T5: 11 | U5: 3
A6: VGM | B6: TRUE | C6: 4 | D6: 2700 | E6: 2 | F6: =IF(主要!BC4="",0,MAX(主要!BC4+主要!$R$16,1)+F2) -> 0 | G6: =D6+1 -> 2701 | H6: =D7-G6 -> 3799 | I6: 5 | J6: 恭喜你超越了鸡的力量 | K6: 平地摔是你的家常便饭 | L6: 常年病痛缠身 | M6: 阿库娅与你同在 | N6: 在楼房里面找不到房间 | O6: 可能会被人刁难 | P6: 奥秘 | Q6: =主要!I45 -> 4 | R6: FALSE | S6: 龙类 | T6: 12 | U6: 4
A7: XGE | B7: TRUE | C7: 5 | D7: 6500 | E7: 3 | F7: =IF(主要!BE4="",0,MAX(主要!BE4+主要!$R$16,1)+F2) -> 0 | G7: =D7+1 -> 6501 | H7: =D8-G7 -> 7499 | I7: 6 | J7: 拿多点东西都气喘吁吁 | K7: 经常莫名其妙的撞上什么 | L7: 经常需要躺下休息 | M7: 学不下什么东西 | N7: 东西放在眼前就是找不到 | O7: 可能会受到种种审视 | P7: 历史 | Q7: =主要!I46 -> 2 | R7: FALSE | S7: 元素生物 | T7: 13 | U7: 5
A8: MTF | B8: TRUE | C8: 6 | D8: 14000 | E8: 3 | F8: =IF(主要!BG4="",0,MAX(主要!BG4+主要!$R$16,1)+F2) -> 0 | G8: =D8+1 -> 14001 | H8: =D9-G8 -> 8999 | I8: 7 | J8: 穿脱衣服都有些吃力 | K8: 走在平地上都会摔倒 | L8: 可能有贫血什么的 | M8: 没有受过太多的教育 | N8: 偶尔会犯迷糊 | O8: 所有的人都觉得可以轻而易举地说服你 | P8: 调查 | Q8: =主要!I47 -> 6 | R8: FALSE | S8: 精类 | T8: 14 | U8: 7
A9: GTR | B9: TRUE | C9: 7 | D9: 23000 | E9: 3 | F9: =IF(主要!BI4="",0,MAX(主要!BI4+主要!$R$16,1)+F2) -> 0 | G9: =D9+1 -> 23001 | H9: =D10-G9 -> 10999 | I9: 8 | J9: 你揍人就像在给对方按摩 | K9: 不上不下真尴尬 | L9: 健康状况堪忧 | M9: 你可能会怀疑你是不是健忘 | N9: 关键时刻掉链子 | O9: 你的说服力还是可以的 | P9: 自然 | Q9: =主要!I48 -> 4 | R9: FALSE | S9: 邪魔 | T9: 15 | U9: 9
A10: ERLW | B10: TRUE | C10: 8 | D10: 34000 | E10: 3 | F10: =IF(主要!BK4="",0,MAX(主要!BK4+主要!$R$16,1)+F2) -> 0 | G10: =D10+1 -> 34001 | H10: =D11-G10 -> 13999 | I10: 9 | J10: 比正常人稍微差一点 | K10: 比正常人稍微差一点 | L10: 比正常人稍微差一点 | M10: 思维比别人慢一拍 | N10: 比正常人稍微差一点 | O10: 比正常人稍微差一点 | P10: 宗教 | Q10: =主要!I49 -> 4 | R10: FALSE | S10: 巨人
A11: EGtW | B11: TRUE | C11: 9 | D11: 48000 | E11: 4 | F11: =IF(主要!BM4="",0,MAX(主要!BM4+主要!$R$16,1)+F2) -> 0 | G11: =D11+1 -> 48001 | H11: =D12-G11 -> 15999 | I11: 10 | J11: 有正常人的力量 | K11: 普通人的水准 | L11: 正常人的体质 | M11: 正常人的智力 | N11: 你醒啦，你很正常 | O11: 讨价还价的能力不错 | P11: 驯兽 | Q11: =主要!I51 -> 4 | R11: FALSE | S11: 类人生物
A12: Acq Inc. | B12: TRUE | C12: 10 | D12: 64000 | E12: 4 | F12: =IF(主要!BO4="",0,MAX(主要!BO4+主要!$R$16,1)+F2) -> 0 | G12: =D12+1 -> 64001 | H12: =D13-G12 -> 20999 | I12: 11 | J12: 在这个档次，做到欺软怕硬是没有问题的 | K12: 可以徒手抓住苍蝇 | L12: 疾病对于您来说，应该是偶发事故 | M12: 可以耍耍小聪明 | N12: 找东西的时候方便一些 | O12: 可以很容易地虎躯一震 | P12: 洞悉 | Q12: =主要!I52 -> 6 | R12: FALSE | S12: 怪兽
A13: MOT | B13: TRUE | C13: 11 | D13: 85000 | E13: 4 | F13: =IF(主要!AW7="",0,MAX(主要!AW7+主要!$R$16,1)+F2) -> 0 | G13: =D13+1 -> 85001 | H13: =D14-G13 -> 14999 | I13: 12 | J13: 经常锻炼的人能够达到的水平，可以很轻松地连续做上50个俯卧撑 | K13: 可以用筷子夹住苍蝇 | L13: 基本上没有吃过什么药，不是说不得病，但基本上抗一抗就过去了 | M13: 人才啊 | N13: 可以注意到别人注意不到的细节 | O13: 勉勉强强可以放出一丝王霸之气 | P13: 医药 | Q13: =主要!I53 -> 6 | R13: FALSE | S13: 泥怪
A14: TCE | B14: TRUE | C14: 12 | D14: 100000 | E14: 4 | F14: =IF(主要!AY7="",0,MAX(主要!AY7+主要!$R$16,1)+F2) -> 0 | G14: =D14+1 -> 100001 | H14: =D15-G14 -> 19999 | I14: 13 | J14: 一拳一个小朋友 | K14: 很不错的反应能力，可以在旋转的硬币落下的一瞬间看出是哪面落地 | L14: 一般的磕磕碰碰都不放在眼里 | M14: 可以很轻松地取得别人要刻苦努力才能得到的成绩 | N14: 可以推断出一些别人不知道的东西 | O14: 人们更容易接受你的意见 | P14: 察觉 | Q14: =主要!I54 -> 6 | R14: FALSE | S14: 植物
A15: VRGR | B15: TRUE | C15: 13 | D15: 120000 | E15: 5 | F15: =IF(主要!BA7="",0,MAX(主要!BA7+主要!$R$16,1)+F2) -> 0 | G15: =D15+1 -> 120001 | H15: =D16-G15 -> 19999 | I15: 14 | J15: =J14 -> 一拳一个小朋友 | K15: =K14 -> 很不错的反应能力，可以在旋转的硬币落下的一瞬间看出是哪面落地 | L15: =L14 -> 一般的磕磕碰碰都不放在眼里 | M15: =M14 -> 可以很轻松地取得别人要刻苦努力才能得到的成绩 | N15: =N14 -> 可以推断出一些别人不知道的东西 | O15: =O14 -> 人们更容易接受你的意见 | P15: 求生 | Q15: =主要!I55 -> 4 | R15: FALSE | S15: 不死生物
A16: FTD | B16: TRUE | C16: 14 | D16: 140000 | E16: 5 | F16: =IF(主要!BC7="",0,MAX(主要!BC7+主要!$R$16,1)+F2) -> 0 | G16: =D16+1 -> 140001 | H16: =D17-G16 -> 24999 | I16: 15 | J16: =J17 -> 超乎常人的力度 | K16: =K17 -> 左右横跳 | L16: =L17 -> 你从来就不知道什么叫生病 | M16: =M17 -> 就是个天才 | N16: =N17 -> 身边的一切风吹草动都逃不出您的敏锐的目光 | O16: =O17 -> 您不经意间的一举一动都有可能吸引着其他人 | P16: 欺瞒 | Q16: =主要!I57 -> 0 | R16: FALSE
A17: SCC | B17: TRUE | C17: 15 | D17: 165000 | E17: 5 | F17: =IF(主要!BE7="",0,MAX(主要!BE7+主要!$R$16,1)+F2) -> 0 | G17: =D17+1 -> 165001 | H17: =D18-G17 -> 29999 | I17: 16 | J17: 超乎常人的力度 | K17: 左右横跳 | L17: 你从来就不知道什么叫生病 | M17: 就是个天才 | N17: 身边的一切风吹草动都逃不出您的敏锐的目光 | O17: 您不经意间的一举一动都有可能吸引着其他人 | P17: 威吓 | Q17: =主要!I58 -> 0 | R17: FALSE
A18: MotM | B18: TRUE | C18: 16 | D18: 195000 | E18: 5 | F18: =IF(主要!BG7="",0,MAX(主要!BG7+主要!$R$16,1)+F2) -> 0 | G18: =D18+1 -> 195001 | H18: =D19-G18 -> 29999 | I18: 17 | J18: =J17 -> 超乎常人的力度 | K18: =K17 -> 左右横跳 | L18: =L17 -> 你从来就不知道什么叫生病 | M18: =M17 -> 就是个天才 | N18: =N17 -> 身边的一切风吹草动都逃不出您的敏锐的目光 | O18: =O17 -> 您不经意间的一举一动都有可能吸引着其他人 | P18: 表演 | Q18: =主要!I59 -> 0 | R18: FALSE
A19: MOD | B19: FALSE | C19: 17 | D19: 225000 | E19: 6 | F19: =IF(主要!BI7="",0,MAX(主要!BI7+主要!$R$16,1)+F2) -> 0 | G19: =D19+1 -> 225001 | H19: =D20-G19 -> 39999 | I19: 18 | J19: 达到人类极限力量 | K19: 超越人类的敏捷 | L19: 生命力旺盛，被人打趴数次还可以站起来继续的那种 | M19: 睿智的目光 | N19: 这个世界上的一切联系都可以被您所感知 | O19: 请注意你的其他属性，因为你很容易被犯罪 | P19: 游说 | Q19: =主要!I60 -> 0 | R19: FALSE
C20: 18 | D20: 265000 | E20: 6 | F20: =IF(主要!BK7="",0,MAX(主要!BK7+主要!$R$16,1)+F2) -> 0 | G20: =D20+1 -> 265001 | H20: =D21-G20 -> 39999 | I20: 19 | J20: 超越人类极限的力量 | K20: 你跑步的样子像香港记者 | L20: 天生的肉盾 | M20: 超凡的智慧 | N20: 你开始注意到一些本来不该是人类所注意的东西了 | O20: 红颜祸水指的就是你 | P20: 货币换算 | Q20: 弹药计重 | R20: TRUE
C21: 19 | D21: 305000 | E21: 6 | F21: =IF(主要!BM7="",0,MAX(主要!BM7+主要!$R$16,1)+F2) -> 0 | G21: =D21+1 -> 305001 | H21: =D22-G21 -> 49999 | I21: 20 | J21: 熊的力量！ | K21: 无与伦比的运动神经 | L21: 或许有复数血条 | M21: 你可以改变世界 | N21: 所有的谎言在你面前无所遁形 | O21: 沉鱼落雁，闭月羞花 | P21: =IFERROR(IF(主要!H62=P22,主要!B62/100,IF(主要!H62=P23,主要!B62/10,IF(主要!H62=P24,主要!B62/2,IF(主要!H62=P25,主要!B62,IF(主要!H62=P26,主要!B62*10,""))))),"") -> 0 | Q21: 货币计重 | R21: TRUE
C22: 20 | D22: 355000 | E22: 6 | F22: =IF(主要!BO7="",0,MAX(主要!BO7+主要!$R$16,1)+F2) -> 0 | I22: 21 | J22: 怪物之力 | K22: 跑得比香港记者还快 | L22: 大概只有天灾才杀死这种人 | M22: 或许是参透法则之人 | N22: 路过坟墓你就能看见鬼魂，经过战场你就能听见哀号 | O22: 您的敌人也可能会倾向于你 | P22: 铜币CP
I23: 22 | J23: 吃饭的时候经常不小心捏碎十几个盘子 | K23: 只要你想要，世界上没什么你弄不到东西 | L23: 被杀不一定会死 | M23: 用睿智这个词来形容你都已经是一种侮辱了 | N23: 敌人的隐形和变形对你来说毫无意义 | O23: 你很少动刀动枪，因为只要有你的存在就能化解绝大多数的纷争 | P23: 银币SP
I24: 23 | J24: 经常不小心将别人摸成骨折，当地的骨科医生都很喜欢你 | K24: 几乎没有东西有足够的速度能伤害到你 | L24: 最受欢迎的肉盾 | M24: 你一眼就能看清事物的本质，再没有任何事物能够引起你的好奇 | N24: 任何生物在你眼中他的一生命运都历历在目，任何非生物的历史你也一目了然 | O24: 只有意志最坚定的人才能直视你 | P24: 银金币EP
I25: 24 | J25: 你付账的时候从口袋里掏出来的，往往不是金币而是被巨大的力量捏成一坨的金块 | K25: 战斗的时候，敌人最头痛的就是你，因为他根本砍不到你 | L25: 强壮的体质使你在冒险团队中所向无敌 | M25: 世间的一切在你眼中都索然无味 | N25: 世界上所有的神祗都在要求你做他们的使徒 | O25: 你的一个眼神、一个动作，都可能轻易的左右其他人的思想，决定国家的存亡 | P25: 金币GP
I26: 25 | J26: 因为你的存在，你所居住的小镇已经很多年没有买过起重机了 | K26: 你从别人身边走过，别人会以为只是一阵风吹过 | L26: 传奇肉盾 | M26: 完全可以去客串半神巫妖 | N26: 你能够直接倾听神祗的话语与神交流，你就是真正的神使 | O26: 天上的众神为了争夺你打的不可开交，深渊中的恶魔因为你的存在而不愿破坏世界 | P26: 铂金币PP

Sheet 种族数据
B1: 亚种 | C1: PHB | D1: SCAG | E1: VGM | F1: MTF | G1: GTR | H1: ERLW | I1: EGtW | J1: AcqInc. | K1: MOT | L1: VRGR | M1: FTD | N1: SCC | O1: MotM | P1: MOD | R1: 体型 | S1: 种族备选 | T1: 亚种选项 | V1: 种族特性 | Z1: 待选特性 | AB1: 已选特性 | AE1: 种族 | AF1: 行 | AG1: 最小列 | AH1: 最大列 | AI1: 通用特性 | AJ1: 属性值加成 | AK1: 体型 | AL1: 速度 | AM1: 语言 | AN1: 阿斯莫向导特质 | AO1: 阿斯莫天界特性 | AP1: 蜥蜴人怪癖 | AQ1: 斑猫人追求 | AR1: 斑猫人怪癖 | AS1: 梭螺鱼人怪癖 | AT1: 精灵饰品 | AU1: 精灵冒险动机 | AV1: 卓尔冒险动机 | AW1: 卓尔家族专业 | AX1: 雅灵联系季节 | AY1: 秋季人格特点 | AZ1: 秋季缺陷 | BA1: 冬季人格特点 | BB1: 冬季缺陷 | BC1: 春季人格特点 | BD1: 春季缺陷 | BE1: 夏季人格特点 | BF1: 夏季缺陷 | BG1: 离梦人癖好 | BH1: 兽人外出理由 | BI1: 机关人怪癖 | BJ1: 矮人离开原因 | BK1: 侏儒的计画 | BL1: 半精灵起源 | BM1: 半身人怪癖 | BN1: 人类起源 | BO1: 半血裔饥渴 | BP1: 半血裔起源 | BQ1: 巫咒之子起源 | BR1: 重生者遗失的记忆 | BS1: 仙灵精类特征 | BT1: 化兽者兽化人先祖
A2: 矮人 | B2: 丘陵矮人 | C2: 山地矮人 | D2: =IF(OR(综合数据!B8=TRUE,综合数据!B18=TRUE),"灰矮人","") -> 灰矮人 | E2: =IF(综合数据!B10=TRUE,"警戒龙纹","") -> 警戒龙纹 | F2: ="" | G2: ="" | H2: ="" | I2: ="" | J2: ="" | K2: ="" | L2: ="" | M2: ="" | ... O2: ="" | R2: 微型 | S2: {=INDEX(A:A,SMALL(IF($A$2:$A$45<>"",ROW($2:$45),46),ROW(A1)))&""} -> 矮人 | T2: =VLOOKUP(V3,AE2:AF125,2,0) -> #N/A | U2: {=INDEX(T:T,SMALL(IF($T$3:$T$15<>"",ROW($3:$15),16),ROW(T1)))&""} -> #N/A | V2: =IF(主要!Y3="",0,主要!Y3) -> 1 | W2: 行 | X2: 最小列 | Y2: 最大列 | Z2: =IFERROR(IF(COUNTIF($AB$2:$AB$15,$W6),"",W6),"") | AA2: {=INDEX(Z:Z,SMALL(IF($Z$2:$Z$16<>"",ROW($2:$16),17),ROW(Z1)))&""} -> 语言 | AB2: =IF(主要!$Z84="",0,主要!$Z84) -> 属性值加成 | AC2: =IFERROR(VLOOKUP($AB2,$W$6:$X$27,2,0),"") | AD2: =IF($AB2=0,"",COUNTIF($AB$2:$AB$15,$AB2)) -> 1 | AE2: 矮人 | AF2: 1 | AG2: 1 | AH2: 5 | AI2: 丘陵矮人 | AJ2: 体质+2，感知+1 | AK2: 中型 | AL2: 基础步行速度为25尺，你的速度不会因穿着重甲而减慢 | AM2: 和矮人语 | AN2: 书生气的，教条主义的 | AO2: 锈蚀金属色、白色或木炭色的雀斑 | AP2: 你讨厌浪费，而且没有理由不清理吃光死掉的敌人。手指美味又方便！ | AQ2: 一位神祇或者位面存在 | AR2: 你想念你的热带家乡，对寒冷的天气抱怨不休，哪怕是在夏天。 | AS2: 你所说的话即是需要服从的命令。 | AT2: 一个小笔记本，任何写在上面的东西都会在一小时内消失。 | AU2: 你相信让精灵与科瑞隆重新团聚的秘密在世界上的某处而不在精灵社区之中，而你下定决心要找到这个秘密。 | AV2: 你打听到了你的家族中一位成员试图毒杀你，因而你从幽暗地域逃脱以保命。你在闯出足以让你身边有着一群忠诚的佣兵护卫前不会回去。 | AW2: 精金武器 | AX2: 秋是和平与善意的季节，众生分享着夏季的丰收。 | AY2: 如果有人需要你的帮助，你会毫无保留地伸出援手。 | AZ2: 你不暇思索地相信别人。 | BA2: 最坏的情况总是最可能发生的。 | BB2: 万物终有一死。为何还要麻烦地建造那些长存的事物呢？ | BC2: 每一天都是你生命中最美好的一天。 | BD2: 你常常酗酒。 | BE2: 你相信单刀直入是解决问题的最佳方式。 | BF2: 你很顽固。“改变”这种事让别人去做吧。 | BG2: 你试图了解敌人的动机和感受 | BH2: 你和护门者有联系，而你正要执行在阴影湿地外对抗一个与恶魔有关的威胁的委托。 | BI2: 你大声分析遇见的每个人可能会带来的潜在威胁。 | BJ2: 与敌对氏族之间的宿怨已经失控，最好是在事情平静下来的时候离开几十年。 | BK2: 你的家人正在研究一种新的元素绑定形式，但是他们需要很多凯博尔龙晶。 | BL2: 你是一个主要城市的科拉瓦社区的关键人物，主持团结餐会，并与城市中每一个半精灵保持联系。 | BM2: 你常常惊讶於五国人民认为理所当然的事情。 | BN2: 来自安黛尔的贫穷法师，努力证明你和其他安黛尔法师一样聪明 | BO2: 饥渴 | BP2: 你是吸血鬼暴君祖先的转世。 | BQ2: 想要有个孩子，你的父母和鬼婆进行了交易，而你就是那场交易的产物。 | BR2: 你回想起身体承受的巨大痛苦，你身上与之相关的伤痕或印记是什么样的？ | BS2: 你的翅膀如同鸟类的翅膀。 | BT2: 熊人
A3: 精灵 | B3: 高等精灵 | C3: 木精灵 | D3: 黑暗精灵 | E3: =IF(OR(综合数据!B8=TRUE,综合数据!B18=TRUE),"雅灵","") -> 雅灵 | F3: =IF(OR(综合数据!B8=TRUE,综合数据!B18=TRUE),"海精灵","") -> 海精灵 | G3: =IF(OR(综合数据!B8=TRUE,综合数据!B18=TRUE),"影灵","") -> 影灵 | H3: =IF(综合数据!B10=TRUE,"阴影龙纹","") -> 阴影龙纹 | I3: =IF(综合数据!B11=TRUE,"苍白精灵","") -> 苍白精灵 | J3: ="" | K3: ="" | L3: ="" | M3: ="" | N3: ="" | O3: ="" | R3: 小型 | S3: {=INDEX(A:A,SMALL(IF($A$2:$A$45<>"",ROW($2:$45),46),ROW(A2)))&""} -> 精灵 | T3: =INDEX($B$2:$K$45,$T$2,1) -> #N/A | U3: {=INDEX(T:T,SMALL(IF($T$3:$T$15<>"",ROW($3:$15),16),ROW(T2)))&""} -> #N/A | V3: =IF(主要!$D6="",0,主要!$D6) -> 拉文克劳 | W3: =IF(COUNTIF(T13:T15,V4)=0,VLOOKUP(V3,AE:AF,2,0)*2,VLOOKUP(V4,AE:AF,2,0)*2) -> #N/A | Y3: =IF(COUNTIF(T13:T15,V4)=0,VLOOKUP(V3,AE:AH,4,0),VLOOKUP(V4,AE:AH,4,0)) -> #N/A | Z3: =IFERROR(IF(COUNTIF($AB$2:$AB$15,$W7),"",W7),"") | AA3: {=INDEX(Z:Z,SMALL(IF($Z$2:$Z$16<>"",ROW($2:$16),17),ROW(Z2)))&""} | AB3: =IF(主要!$Z85="",0,主要!$Z85) -> 速度 | AC3: =IFERROR(VLOOKUP($AB3,$W$6:$X$27,2,0),"") | AD3: =IF($AB3=0,"",COUNTIF($AB$2:$AB$15,$AB3)) -> 1 | AE3: 丘陵矮人 | AG3: 6 | AH3: 6 | AI3: 山地矮人 | AJ3: 体质+2，力量+2 | AK3: =AK$2 -> 中型 | AL3: =AL$2 -> 基础步行速度为25尺，你的速度不会因穿着重甲而减慢 | AM3: =AM$2 -> 和矮人语 | AN3: 富有同情心的，给人以希望的 | AO3: 金属般的、发光的或黑暗的眼睛 | AP3: 你把大部分身体泡在水里的时候睡得最香。 | AQ3: 一只怪物 | AR3: 除非绝对必要，你从不穿同样的衣服两次。 | AS3: 你动不动就夸耀你的文明的伟大。 | AT3: 一个用象牙与黄金制成的水晶透镜，透过它，任何东西看起来都会变得色彩缤纷 | AU3: 你的同胞血亲被一个疯狂的怪物杀死了，你在击败它、杀死它前绝不停息。 | AV3: 你因为试图毒杀你有权有势的竞争对手而被奴役作为惩罚，但你逃脱了奴役并逃至地表。若你回归，你将被再次奴役。 | AW3: 暗杀 | AX3: 冬是冥想与悲伤的季节，生机勃勃的世界蛰伏了。 | AY3: 你会分享你的所有，而不考虑你自己的需求。 | AZ3: 你倾尽所有给予别人，却连必要的补给都不留给自己。 | BA3: 你会把你的所有都保存起来。今天挨饿明天饱餐总比反过来的情况好。 | BB3: 你不看重任何事，所以你允许让人引导你的行动。 | BC3: 你做任何事都饱含热情，即使是最乏味的家务事。 | BD3: 苦工是苦力的活。安逸是你的生活。 | BE3: 压倒性的力量可以解决任何事。问题越困难，就该用更大的力量。 | BF3: 最好的选择是一个人出手迅速、出人意料并且势不可挡。 | BG3: 你喜欢通过心灵感应而不是大声说话来交流 | BH3: 萨拉释克家族从沼泽中中招募你，在终末之战中充当雇佣军。 | BI3: 你经常误解情绪表现。 | BJ3: 你来自一个大家庭，没有位置让你展露光芒，所以你希望让自己在更广阔的世界出名。 | BK3: 你有一个匿名联系人通过短讯术给你发送任务。如果你按照要求去做，你会得到丰厚的回报。 | BL3: 你在一个由人类主宰的小镇上长大。你不认识任何其他半精灵，你尽了最大努力去融入他们。 | BM3: 你模仿一种恐龙的行为。 | BN3: 一个来自布鲁兰的街头盗贼，只想永远逃离萨恩的喧嚣 | BO3: 血液 | BP3: 你与一位具有掠夺性的神祇，邪魔，精类或灵魂缔结了契约，共享它们的饥渴。 | BQ3: 精类绑架者把你和你父母的孩子进行了替换。 | BR3: 回忆使你热泪盈眶。是苦涩的回忆还是甜美的回忆？现在回想起来你的感受是否还如当初一样？ | BS3: 你的皮肤闪闪发光，五彩缤纷。 | BT3: 野猪人
A4: 半身人 | B4: 轻足半身人 | C4: 敦实半身人 | D4: =IF(综合数据!B5=TRUE,"鬼智半身人","") -> 鬼智半身人 | E4: =IF(综合数据!B10=TRUE,"医疗龙纹","") -> 医疗龙纹 | F4: =IF(综合数据!B10=TRUE,"招待龙纹","") -> 招待龙纹 | G4: =IF(综合数据!B11=TRUE,"莲源半身人","") -> 莲源半身人 | H4: ="" | I4: ="" | J4: ="" | K4: ="" | L4: ="" | M4: ="" | N4: ="" | O4: ="" | R4: 中型 | S4: {=INDEX(A:A,SMALL(IF($A$2:$A$45<>"",ROW($2:$45),46),ROW(A3)))&""} -> 半身人 | T4: =INDEX($B$2:$K$45,$T$2,2) -> #N/A | U4: {=INDEX(T:T,SMALL(IF($T$3:$T$15<>"",ROW($3:$15),16),ROW(T3)))&""} -> #N/A | V4: =IF(主要!$D7="",0,主要!$D7) -> 0 | W4: =W3-1 -> #N/A | X4: =IF(COUNTIF(T13:T15,V4)=0,VLOOKUP(V4,AE:AG,3,0),0/0) -> #N/A | Y4: =VLOOKUP(V4,AE:AH,4,0) -> #N/A | Z4: =IFERROR(IF(COUNTIF($AB$2:$AB$15,$W8),"",W8),"") | AA4: {=INDEX(Z:Z,SMALL(IF($Z$2:$Z$16<>"",ROW($2:$16),17),ROW(Z3)))&""} | AB4: =IF(主要!$Z86="",0,主要!$Z86) -> 体型 | AC4: =IFERROR(VLOOKUP($AB4,$W$6:$X$27,2,0),"") | AD4: =IF($AB4=0,"",COUNTIF($AB$2:$AB$15,$AB4)) -> 1 | AE4: 山地矮人 | AG4: 7 | AH4: 7 | AI4: 灰矮人 | AJ4: 自选两项属性分别+2/+1或自选三项属性+1 | AK4: =AK$2 -> 中型 | AL4: 基础步行速度为30尺 | AM4: ，以及任意一门自选语言 | AN4: 实际主义的，使人轻松的 | AO4: 多种颜色层叠的头发 | AP4: 金钱对你来说毫无意义。 | AQ4: 一个失落的文明 | AR4: 你有轻微的恐水症，讨厌被水弄湿。 | AS4: 你习得了过时版本的通用语，并将“汝”用在你的话中。 | AT4: 一个核桃大小的金色金字塔，其上刻有精灵符文 | AU4: 一只渡鸦带来了你的一位需要援助的老友的密信，但密信中关于你这位老友的位置信息相当模糊。你正尝试花上数年时间来追踪、拯救你的老友。 | AV4: 你是一位罗丝高阶女祭司的情人，你以此作为你地位的保证。当她厌倦了你时，失去地位对你而言是个耻辱，所以你离开了。 | AW4: 基于魔法控制的巨蜘蛛养殖 | AX4: 春是快乐与庆祝的季节，欢喜随冬之悲伤的离去而来。 | AY4: 这里没有饱腹的简餐，只有奢华的盛宴。 | AZ4: 每个人都是你的朋友或者潜在的朋友。 | BA4: 生活充满了危险，但你已做好准备。 | BB4: 你的需求是第一位。在寒冬，每个人都必须照顾好自己。 | BC4: 你热爱音乐与歌唱。如果没人能为你写歌，你会为自己谱曲。 | BD4: 美人能将你轻易俘虏，但你的热情来得快去得也快。 | BE4: 你站得强健而挺拔，以便让他人能依靠你。 | BF4: 比起动口，你会先动手。 | BG4: 你有一种保护无辜者的强烈冲动 | BH4: 你是一个孤狼猎手，但你已经决定寻找进一步的机会或是湿地外世界的真正挑战。 | BI4: 你极力保护自己的朋友。 | BJ4: 你的氏族已经为你的婚姻和未来做了安排，你已经决定在安定下来之前进行一些冒险活动。 | BK4: 你继承了夸巴拉的一块地。如果你在一年内不访问，你将失去所有权。 | BL4: 你住在埃鲁登原野的一个小科拉瓦社区，你试图成为东部人类农民和西部德鲁伊教和野人之间的桥梁。 | BM4: 你非常好奇，总是在寻找新的经历。 | BN4: 一名流离失所的赛尔战士，哀伤咏叹期间在赛尔外参与了战争，现在被困在了没有家的地方 | BO4: 生肉 | BP4: 你从一位吸血鬼的攻击中幸存了下来，但是也被永远的改变了。 | BQ4: 一个鬼婆集会失去了一名成员。你被创造出来填补缺失的空位。 | BR4: 你回想起孩童时期的事情。那时候的什么事件或人物至今仍在影响着你？ | BS4: 你有着特别大的耳朵。 | BT4: 鼠人
A5: 人类 | B5: 人类变体 | C5: =IF(综合数据!B10=TRUE,"探索龙纹","") -> 探索龙纹 | D5: =IF(综合数据!B10=TRUE,"畜牧龙纹","") -> 畜牧龙纹 | E5: =IF(综合数据!B10=TRUE,"创造龙纹","") -> 创造龙纹 | F5: =IF(综合数据!B10=TRUE,"通行龙纹","") -> 通行龙纹 | G5: =IF(综合数据!B10=TRUE,"守护龙纹","") -> 守护龙纹 | H5: =IF(综合数据!B19=TRUE,"加渥尼","") | I5: =IF(综合数据!B19=TRUE,"凯锡革","") | J5: =IF(综合数据!B19=TRUE,"涅非利亚","") | K5: =IF(综合数据!B19=TRUE,"史顿襄","") | L5: ="" | M5: ="" | N5: ="" | O5: ="" | R5: 大型 | S5: {=INDEX(A:A,SMALL(IF($A$2:$A$45<>"",ROW($2:$45),46),ROW(A4)))&""} -> 人类 | T5: =INDEX($B$2:$K$45,$T$2,3) -> #N/A | U5: {=INDEX(T:T,SMALL(IF($T$3:$T$15<>"",ROW($3:$15),16),ROW(T4)))&""} -> #N/A | V5: 序号 | W5: 名称 | X5: 描述 | Y5: 增值 | Z5: =IFERROR(IF(COUNTIF($AB$2:$AB$15,$W9),"",W9),"") -> 语言 | AA5: {=INDEX(Z:Z,SMALL(IF($Z$2:$Z$16<>"",ROW($2:$16),17),ROW(Z4)))&""} | AB5: =IF(主要!$Z87="",0,主要!$Z87) -> 深厚学识 | AC5: =IFERROR(VLOOKUP($AB5,$W$6:$X$27,2,0),"") | AD5: =IF($AB5=0,"",COUNTIF($AB$2:$AB$15,$AB5)) -> 1 | AE5: 灰矮人 | AG5: 8 | AH5: =IF(V2<3,9,10) -> 9 | AI5: 警戒龙纹 | AJ5: 体质+2，智力+1 | AK5: =AK$2 -> 中型 | AL5: =AL$2 -> 基础步行速度为25尺，你的速度不会因穿着重甲而减慢 | AM5: =AM$2 -> 和矮人语 | AN5: 狂热的，报复心猛烈的 | AO5: 你的影子有不寻常的色调 | AP5: 你认为世界上只有两种人：蜥蜴人和食用肉。 | AQ5: 一名法师的秘密 | AR5: 你的尾巴总是背叛你内心的想法。 | AS5: 你认为人们都在告诉你当地风俗习惯和期望的真相。 | AT5: 一个蝴蝶形的，用搪瓷制成的斗篷针；当你取下它时，它会变成一只真正的蝴蝶，在你准备把它戴回去前又会再变成针。 | AU5: 一个美丽的精灵赢得了，又打碎了你的心。如果你通过冒险挣得了足够的金钱与荣誉，你或许可以让你的爱人回心转意。 | AV5: 你在一场出于公开侮辱你的决斗中杀死了更有权势的家族的卓尔。死者的家族发誓要摧毁你的家族，除非你人头落地。你的血亲们强迫你离开他们。你想着他们为什么会变成这样。 | AW5: 致幻物质 | AX5: 夏是大胆与进犯的季节，为无拘无束的精力所填满。 | AY5: 你将上好的食物存储起来。因为你不喜欢连这点舒适的用品都失去。 | AZ5: 你在物质享受上穷奢极欲。 | BA5: 花了一便士就是永远弄丢了一便士。 | BB5: 你只会指出他人计划中的瑕疵。 | BC5: 你总是心浮气躁、坐立不安。 | BD5: 任何值得做的事情都值得不断地重复之。 | BE5: 你往往会先加以恐吓，因为你觉得通过展示力量来避免战斗总好过伤害别人。 | BF5: 你的怒火载着你披荆斩棘。 | BG5: 你会把梦中的逻辑应用到日常生活中 | BH5: 你的村庄被来自卓姆的怪物摧毁了，因而你开始在世界中找寻一个新的落脚点。 | BI5: 你试图将战时纪律运用到每一种情况中。 | BJ5: 你在与一个私人对手进行仇杀，试图在战斗或商业中击败他们。 | BK5: 由於不寻常的三团议会法律的扭曲，你与许多其他的孩子共享相同的名字，你在法律上被认为是同一个人。 | BL5: 你们的小科拉瓦社区只有在萨恩的贫民窟里才得以生存，你们互相给予了亲密的、像家人一样的支持。 | BM5: 你喜欢自吹自擂，你总是夸大自己的奇遇。 | BN5: 一个来自恶魔荒原的野蛮人从残酷的生活中忏悔，并希望为过去的罪恶赎罪 | BO5: 脑脊液 | BP5: 一条寄生虫寄生在你体内，你听任于它的饥渴。 | BQ5: 孩童时期你遭受了诅咒。与森林中的精魂们打交道导致你被转变为巫咒之子，并且这种诅咒无法被解除。 | BR5: 回忆中传来过去一位亲近你的人的声音。他们是怎么指导你的？ | BS5: 一层闪闪发光的雾一直环绕着你。 | BT5: 虎人
A6: 龙裔 | B6: =IF(综合数据!B11=TRUE,"龙国血统","") -> 龙国血统 | C6: =IF(综合数据!B11=TRUE,"瑞雯奈特","") -> 瑞雯奈特 | D6: =IF(综合数据!B16=TRUE,"色彩龙血统","") -> 色彩龙血统 | E6: =IF(综合数据!B16=TRUE,"宝石龙血统","") -> 宝石龙血统 | F6: =IF(综合数据!B16=TRUE,"金属龙血统","") -> 金属龙血统 | G6: ="" | H6: ="" | I6: ="" | J6: ="" | K6: ="" | L6: ="" | M6: ="" | N6: ="" | O6: ="" | R6: 巨型 | S6: {=INDEX(A:A,SMALL(IF($A$2:$A$45<>"",ROW($2:$45),46),ROW(A5)))&""} -> 龙裔 | T6: =INDEX($B$2:$K$45,$T$2,4) -> #N/A | U6: {=INDEX(T:T,SMALL(IF($T$3:$T$15<>"",ROW($3:$15),16),ROW(T5)))&""} -> #N/A | W6: 属性值加成 | X6: =IF(T18=0,"",IF(V4=0,VLOOKUP($V$3,$AI:$AJ,2,0),VLOOKUP($V$4,$AI:$AJ,2,0))) -> #N/A | Z6: =IFERROR(IF(OR($W10="",COUNTIF($AB$2:$AB$15,$W10)),"",W10),"") | AA6: {=INDEX(Z:Z,SMALL(IF($Z$2:$Z$16<>"",ROW($2:$16),17),ROW(Z5)))&""} | AB6: =IF(主要!$Z88="",0,主要!$Z88) -> 罗伊纳的图书馆 | AC6: =IFERROR(VLOOKUP($AB6,$W$6:$X$27,2,0),"") | AD6: =IF($AB6=0,"",COUNTIF($AB$2:$AB$15,$AB6)) -> 1 | AE6: 警戒龙纹 | AG6: 11 | AH6: 13 | AI6: 高等精灵 | AJ6: 敏捷+2，智力+1 | AK6: 中型 | AL6: 基础步行速度为30尺 | AM6: 和精灵语 | AN6: 严厉的，主观判断的 | AO6: 你的头部环绕着鬼魂般的光环 | AP6: 你学会了笑。你用这个天赋来回应所有的情绪状况，以更好地适应你的同伴。 | AQ6: 一件平凡的东西 | AR6: 当你高兴时会发出响亮的咕噜声。 | AS6: 陆上世界是个奇妙的地方，你把它的所有细节都记在了一本日记里。 | AT6: 一个金色的罗盘，它会指向10里内最近的通往妖精荒原的传送点 | AU6: 你的父亲认为你太弱小了，没有办法作为一个冒险者生存下来，但是他错了，而你会证明这一点。 | AV6: 你的一位密友被怀疑为伊莉丝翠的信徒。她圈子里的所有人都被怀疑。逃跑便是默认了指控，尽管你对此一无所知，但若你留在此处，你会被献祭给罗丝。 | AW6: 高品质奴隶与活祭 | BG6: 你在与梦族商量事情时会不自觉地大声说出 | BH6: 作为黄泉巨龙会的信徒，你相信，杀死强大的敌人是唯一的通往深藏在地底空心世界中的天堂的道路。为了寻找有价值的敌人，你冒险越过了湿地。 | BI6: 你不知道怎么控制自己的情绪，容易产生急剧的情绪爆发。 | BJ6: 你在寻找一个传说中的矮人神器，几个世纪前被一个坎纳斯贵族偷走了。 | BK6: 你已经获得了一个包含大量奇怪代码文本的法术碎片。 | BL6: 你是瑟雷恩社区的一员，他们对银焰教会的热爱使你将团结餐会扩展到非科拉瓦。 | BM6: 你戴着一个面具，你相信它保存着你以前恐龙坐骑的灵魂。你喜欢和它说话。 | BN6: 一个来自埃鲁登原野的善良德鲁伊他想了解科瓦雷地区的植物和动物 | BO6: 心灵能量 | BP6: 一场惨剧中止了你转变为不朽者的进程。 | BQ6: 你原本是一位精类生物，一场事故改变了你，并迫使你离开了家乡。 | BR6: 你回想起一件你过去曾享受，但现在却无法忍受的事物。它是什么？为什么你现在不喜欢了？ | BS6: 你的额头上有一根灵体角，就像小型的独角兽角。 | BT6: 狼人（类似狼）
A7: 侏儒 | B7: 森林侏儒 | C7: 岩侏儒 | D7: =IF(OR(综合数据!B8=TRUE,综合数据!B18=TRUE),"地底侏儒","") -> 地底侏儒 | E7: =IF(综合数据!B10=TRUE,"抄录龙纹","") -> 抄录龙纹 | F7: ="" | G7: ="" | H7: ="" | I7: ="" | J7: ="" | K7: ="" | L7: ="" | M7: ="" | ... O7: ="" | R7: 超巨型 | S7: {=INDEX(A:A,SMALL(IF($A$2:$A$45<>"",ROW($2:$45),46),ROW(A6)))&""} -> 侏儒 | T7: =INDEX($B$2:$K$45,$T$2,5) -> #N/A | U7: {=INDEX(T:T,SMALL(IF($T$3:$T$15<>"",ROW($3:$15),16),ROW(T6)))&""} -> #N/A | W7: 体型 | X7: =IF(T18=0,"",IF(V4=0,VLOOKUP($V$3,$AI:$AK,3,0),VLOOKUP($V$4,$AI:$AK,3,0))) -> #N/A | Z7: =IFERROR(IF(OR($W11="",COUNTIF($AB$2:$AB$15,$W11)),"",W11),"") | AA7: {=INDEX(Z:Z,SMALL(IF($Z$2:$Z$16<>"",ROW($2:$16),17),ROW(Z6)))&""} | AB7: =IF(主要!$Z89="",0,主要!$Z89) -> 额外专长 | AC7: =IFERROR(VLOOKUP($AB7,$W$6:$X$27,2,0),"") | AD7: =IF($AB7=0,"",COUNTIF($AB$2:$AB$15,$AB7)) -> 1 | AE7: 精灵 | AF7: =AF2+1 -> 2 | AG7: 1 | AH7: 4 | AI7: 木精灵 | AJ7: 敏捷+2，感知+1 | AK7: =AK$6 -> 中型 | AL7: =AL$6 -> 基础步行速度为30尺 | AM7: =AM$6 -> 和精灵语 | AN7: 仁慈的，父母般的 | AO7: 你的皮肤上闪烁着彩虹 | AP7: 你还是不懂隐喻是怎么起作用的。不过这并不妨碍你在每一个机会上使用它们。 | AQ7: 一件魔法物品 | AR7: 你让一个小毛线球缠在手上并不断地摆弄着。 | AS7: 你误以为陆上住民都知道你的种族的历史并且印象深刻。 | AT7: 一个银色的小陀螺，一旦它开始转动，那么在被人为打断前就会一直转下去 | AU7: 只有那些成就伟业者才会在他们死后被长久铭记。诗人们将会为你的丰功伟绩而喝彩。 | AV7: 你是一组被埋伏了的地表突击队的队员之一，然后你被抓住了。在被监禁的几年里，你知道了罗丝的祭司告诉你的关于地表世界的一切都是谎言，现在你要自己体验这里的真相。 | AW7: 从对地表突袭中获得的物品 | BG7: 你压抑自己的情绪，依靠逻辑办事 | BH7: 你的家族与萨拉释克家族合作，你被招募为赏金猎人或调查员，即使你并非家族成员。 | BI7: 你无法理解衣服除了实用性质以外的意义，并认为一个生物的穿着代表着他的功能。 | BJ7: 你想聚集可以帮助你探索古老废墟下祖先家园的勇士们。 | BK7: 你知道一个被通缉的战犯的位置，你一直在决定是把他们交出来，还是用你的沉默来换取什麽。 | BL7: 你的科拉瓦社区是一艘拉扎尔船的船员。 | BM7: 你不了解“事实”的概念。对你来说，每件事都是一个故事，而真相就在你如何讲述它。 | BN7: 一个来自坎纳斯的牧师，他渴望学习死灵术--当然是为了最崇高的目标 | BO7: 梦 | BP7: 你是一位被削弱的异界存在，满足你的饥饿感能加快你的恢复。 | BQ7: 一个被侮慢的德鲁伊转变了你，并将你与一棵神圣的树绑定，只要这棵树还结果，你就只能以这样的姿态活下去。 | BR7: 回忆起生动的气味和感觉。你要做些什么事情来重现这一经历呢？ | BS7: 你有着昆虫的腿。 | BT7: 狼人（类似犬）
A8: 半精灵 | B8: =IF(综合数据!B5=TRUE,"半木精灵","") -> 半木精灵 | C8: =IF(综合数据!B5=TRUE,"半月精灵","") -> 半月精灵 | D8: =IF(综合数据!B5=TRUE,"半日精灵","") -> 半日精灵 | E8: =IF(综合数据!B5=TRUE,"半卓尔精灵","") -> 半卓尔精灵 | F8: =IF(综合数据!B5=TRUE,"半水生精灵","") -> 半水生精灵 | G8: =IF(综合数据!B10=TRUE,"侦测龙纹","") -> 侦测龙纹 | H8: =IF(综合数据!B10=TRUE,"暴风龙纹","") -> 暴风龙纹 | I8: ="" | J8: ="" | K8: ="" | L8: ="" | M8: ="" | N8: ="" | O8: ="" | S8: {=INDEX(A:A,SMALL(IF($A$2:$A$45<>"",ROW($2:$45),46),ROW(A7)))&""} -> 半精灵 | T8: =INDEX($B$2:$K$45,$T$2,6) -> #N/A | U8: {=INDEX(T:T,SMALL(IF($T$3:$T$15<>"",ROW($3:$15),16),ROW(T7)))&""} -> #N/A | W8: 速度 | X8: =IF(T18=0,"",IF(V4=0,VLOOKUP($V$3,$AI:$AL,4,0),VLOOKUP($V$4,$AI:$AL,4,0))) -> #N/A | Z8: =IFERROR(IF(OR($W12="",COUNTIF($AB$2:$AB$15,$W12)),"",W12),"") | AA8: {=INDEX(Z:Z,SMALL(IF($Z$2:$Z$16<>"",ROW($2:$16),17),ROW(Z7)))&""} | AB8: =IF(主要!$Z90="",0,主要!$Z90) -> 0 | AC8: =IFERROR(VLOOKUP($AB8,$W$6:$X$27,2,0),"") | AD8: =IF($AB8=0,"",COUNTIF($AB$2:$AB$15,$AB8)) | AE8: 高等精灵 | AG8: 5 | AH8: 7 | AI8: 黑暗精灵 | AJ8: 敏捷+2，魅力+1 | AK8: =AK$6 -> 中型 | AL8: =AL$6 -> 基础步行速度为30尺 | AM8: =AM$6 -> 和精灵语 | AP8: 你欣赏软弱的类人生物意识到需要用链甲和剑才配得上你与生俱来的礼物。 | AQ8: 一处场所 | AR8: 你总是在负债，因为你把你的黄金都花在豪华的聚会上和送给朋友了。 | AT8: 一只用搪瓷，金丝与奇石制成的鸣鸟，当你用精灵语说出这只鸣鸟的名字时，它会开始歌唱。 | AU8: 你私底下爱上了队伍中的一位成员，你不能忍受哪怕只是想到那个人会受伤。 | AV8: 你在一生中都对你同胞的残忍行径感到陌生与害怕。你得到的第一个机会是自愿参加一次对地表的突袭，然后你抛弃了队伍并留在了后面。现在你不管到哪里去都被憎恨着、厌恶着，但至少你找到了一小组信任并支持彼此的冒险同伴。 | AW8: 低价类人奴隶 | BG8: 你周围的情绪会强烈地影响到你 | BH8: 你们家族的首领对另一个家族犯了大错，这个家族现在发誓要消灭你们家族的每一个成员。还有什么比现在更好的看外面世界的时机呢？ | BI8: 你对自己的外表很在意，总是在擦亮自己的装甲和向他人吹嘘。 | BJ8: 你拒绝了你的氏族对异变魔魔法的态度，招致了强大矮人的敌意。 | BK8: 你一直在卖假的藏宝图，但现在你可能找到了一张真的。 | BL8: 你是位於坎纳斯的一个小科拉瓦社区的一员，这个社区对死亡和你艾伦诺祖先的做法很着迷，把你的团结餐会变成了对死亡的残酷庆祝。 | BM8: 你会为那些为小型人们设计的建筑和工具而烦恼。 | BN8: 一个来自拉扎尔邦联的海盗吟游诗人，他热爱海中的棚屋，但也想让歌曲中伟大英雄的事蹟永垂不朽 | BO8: 生命精华 | BP8: 你双亲中的一位是吸血鬼。 | BS8: 你闻起来像是刚出炉的布朗尼。
A9: 半兽人 | B9: =IF(综合数据!B10=TRUE,"探索龙纹","") -> 探索龙纹 | C9: =IF(综合数据!B19=TRUE,"阿芒凯牛头怪","") | D9: ="" | E9: ="" | F9: ="" | G9: ="" | H9: ="" | I9: ="" | J9: ="" | K9: ="" | ... O9: ="" | S9: {=INDEX(A:A,SMALL(IF($A$2:$A$45<>"",ROW($2:$45),46),ROW(A8)))&""} -> 半兽人 | T9: =INDEX($B$2:$K$45,$T$2,7) -> #N/A | U9: {=INDEX(T:T,SMALL(IF($T$3:$T$15<>"",ROW($3:$15),16),ROW(T8)))&""} -> #N/A | W9: 语言 | X9: =IF(T18=0,"","能说、读、写通用语"&IF(V4=0,VLOOKUP($V$3,$AI:$AM,5,0),VLOOKUP($V$4,$AI:$AM,5,0))) -> #N/A | Z9: =IFERROR(IF(OR($W13="",COUNTIF($AB$2:$AB$15,$W13)),"",W13),"") | AA9: {=INDEX(Z:Z,SMALL(IF($Z$2:$Z$16<>"",ROW($2:$16),17),ROW(Z8)))&""} | AB9: =IF(主要!$Z91="",0,主要!$Z91) -> 0 | AC9: =IFERROR(VLOOKUP($AB9,$W$6:$X$27,2,0),"") | AD9: =IF($AB9=0,"",COUNTIF($AB$2:$AB$15,$AB9)) | AE9: 木精灵 | AG9: 8 | AH9: 10 | AI9: 雅灵 | AJ9: 自选两项属性分别+2/+1或自选三项属性+1 | AK9: =AK$6 -> 中型 | AL9: =AL$6 -> 基础步行速度为30尺 | AM9: ，以及任意一门自选语言 | AP9: 你喜欢在你的食物还在蠕动的时候吃了它。 | AQ9: 一个传说或者故事 | AR9: 当谈论你追求的东西时，你说话飞快，从不停顿，让别人没法明白你。 | AT9: 一只用搪瓷制作的花朵，当它被放进一个人的头发里时，它会变成活的花并用一支真的花藤系住穿戴者的头发。摘下这支藤蔓上的花会让它再次变成非活物。 | AU9: 当你出生之时，你的祖母预言你会统治一个人类王国。你正在追寻这个命运。 | AV9: 在灰矮人为奴隶与财宝袭击队伍时，你是那支往其它卓尔城市传递外交信息的使节团的一员。只有你和另一个守卫逃脱了。如果你回家，你会被毒死或因失败遭到更可怕的处罚，成为一名佣兵是你最好的选择。 | AW9: 幽暗地域的地图 | BG9: 只要有可能，你更倾向于通过非暴力手段解决问题 | BH9: 作为一名调查员，你的工作让你踏上了一条远离湿地的神秘之路。 | BI9: 战争是对你来说唯一有意义的事，所以你一直都在追求战斗。 | BJ9: 你想知道其他科瓦雷人--尤其是哥布林和兽人--是如何与异变魔作战的。 | BK9: 你获得了一个龙晶矿坑的控股权，这个矿坑很久以前就被废弃了。但是为什麽呢?狗头人吗?异怪?真相只有一个! | BL9: 你是一个微型科拉瓦社区的一部分，生活在一个意想不到的地方，比如卓姆、达贡，甚至是恶魔荒原。你的人民努力寻找与当地人的共同点。 | BM9: 你要为你百姓所受的恶报仇。 | BN9: 一个被训练在夸巴拉丛林狩猎的游侠，对龙怀恨在心。 | BP9: 一场极端的实验改变了你的身体，让你以他人的生命体液维生。 | BS9: 一种明显的、无害的寒意环绕着你。
A10: 提夫林 | B10: =IF(综合数据!B5=TRUE,"提夫林变体","") -> 提夫林变体 | C10: =IF(综合数据!B8=TRUE,"巴尔泽布","") -> 巴尔泽布 | D10: =IF(综合数据!B8=TRUE,"迪斯帕特","") -> 迪斯帕特 | E10: =IF(综合数据!B8=TRUE,"菲尔娜","") -> 菲尔娜 | F10: =IF(综合数据!B8=TRUE,"格莱西雅","") -> 格莱西雅 | G10: =IF(综合数据!B8=TRUE,"莱维斯图斯","") -> 莱维斯图斯 | H10: =IF(综合数据!B8=TRUE,"马曼","") -> 马曼 | I10: =IF(综合数据!B8=TRUE,"墨菲斯托菲利斯","") -> 墨菲斯托菲利斯 | J10: =IF(综合数据!B8=TRUE,"扎瑞尔","") -> 扎瑞尔 | K10: ="" | L10: ="" | M10: ="" | N10: ="" | O10: ="" | S10: {=INDEX(A:A,SMALL(IF($A$2:$A$45<>"",ROW($2:$45),46),ROW(A9)))&""} -> 提夫林 | T10: =INDEX($B$2:$K$45,$T$2,8) -> #N/A | U10: {=INDEX(T:T,SMALL(IF($T$3:$T$15<>"",ROW($3:$15),16),ROW(T9)))&""} -> #N/A | V10: =IF($V9+1>$Y$3,IF($X$4+$Y9>$Y$4,"",$X$4+$Y9),$V9+1) -> #N/A | W10: =INDEX($B$52:$AD$147,W$4,$V10) -> #N/A | X10: =INDEX($B$52:$AD$147,W$3,$V10) -> #N/A | Y10: =IF($V9+1>$Y$3,$Y9+1,0) -> #N/A | Z10: =IFERROR(IF(OR($W14="",COUNTIF($AB$2:$AB$15,$W14)),"",W14),"") | AA10: {=INDEX(Z:Z,SMALL(IF($Z$2:$Z$16<>"",ROW($2:$16),17),ROW(Z9)))&""} | AB10: =IF(主要!$Z92="",0,主要!$Z92) -> 0 | AC10: =IFERROR(VLOOKUP($AB10,$W$6:$X$27,2,0),"") | AD10: =IF($AB10=0,"",COUNTIF($AB$2:$AB$15,$AB10)) | AE10: 黑暗精灵 | AG10: 11 | AH10: 14 | AI10: 海精灵 | AJ10: =AJ9 -> 自选两项属性分别+2/+1或自选三项属性+1 | AK10: =AK$6 -> 中型 | AL10: =AL$6 -> 基础步行速度为30尺 | AM10: =AM9 -> ，以及任意一门自选语言 | AR10: 你按耐不住地想要独吞你感兴趣的东西。 | AW10: 毒药 | BG10: 你被勇士的精神体所影响，会为了任何高尚的事业而奋斗 | BK10: 你的家庭正面临经济崩溃，他们给你买了保险。只有在你非自然死亡时才能理赔，他们鼓励你去寻找更危险的冒险。 | BL10: 你与林兰德家族或梅丹尼家族有联系，但你更感兴趣的是家族在支持科拉瓦社区方面所扮演的角色，而不是其公会的工作。 | BM10: 你永远不会忘记一个侮辱或伤害。 | BN10: 一个来自阴影湿地的契术师走了过来，在神智清醒的边缘摇摇欲坠，同时凝视着异变魔
A11: =IF(OR(综合数据!B6=TRUE,综合数据!B11=TRUE,综合数据!B18=TRUE),"阿斯莫","") -> 阿斯莫 | B11: ="" | C11: ="" | D11: ="" | E11: ="" | F11: ="" | G11: ="" | H11: ="" | I11: ="" | ... O11: ="" | S11: {=INDEX(A:A,SMALL(IF($A$2:$A$45<>"",ROW($2:$45),46),ROW(A10)))&""} -> 阿斯莫 | T11: =INDEX($B$2:$K$45,$T$2,9) -> #N/A | U11: {=INDEX(T:T,SMALL(IF($T$3:$T$15<>"",ROW($3:$15),16),ROW(T10)))&""} -> #N/A | V11: =IF($V10+1>$Y$3,IF($X$4+$Y10>$Y$4,"",$X$4+$Y10),$V10+1) -> #N/A | W11: =INDEX($B$52:$AD$147,W$4,$V11) -> #N/A | X11: =INDEX($B$52:$AD$147,W$3,$V11) -> #N/A | Y11: =IF($V10+1>$Y$3,$Y10+1,0) -> #N/A | Z11: =IFERROR(IF(OR($W15="",COUNTIF($AB$2:$AB$15,$W15)),"",W15),"") | AA11: {=INDEX(Z:Z,SMALL(IF($Z$2:$Z$16<>"",ROW($2:$16),17),ROW(Z10)))&""} | AB11: =IF(主要!$Z93="",0,主要!$Z93) -> 0 | AC11: =IFERROR(VLOOKUP($AB11,$W$6:$X$27,2,0),"") | AD11: =IF($AB11=0,"",COUNTIF($AB$2:$AB$15,$AB11)) | AE11: 雅灵 | AG11: 15 | AH11: 15 | AI11: 影灵 | AJ11: =AJ9 -> 自选两项属性分别+2/+1或自选三项属性+1 | AK11: =AK$6 -> 中型 | AL11: =AL$6 -> 基础步行速度为30尺 | AM11: =AM9 -> ，以及任意一门自选语言 | AR11: 你说话的时候会将你发现过的传说与故事当梗用到你的话里。 | AW11: 运输用爬行动物 | BG11: 你被梦境之暗的阴谋纠缠 | BK11: 你在兜售一个延长寿命的计划，让客户被梅杜莎石化，然後再恢复。 | BL11: 你在维伦那旅行，希望有一天能证明你配得上一个守护灵祖先。 | BM11: 你把一切都归因於灵魂的工作。 | BN11: 一个瑟雷恩的银焰教会圣骑士，他在寻找一些东西来证明支撑信仰的真理。
A12: =IF(OR(综合数据!B6=TRUE,综合数据!B11=TRUE,综合数据!B18=TRUE),"费尔伯格人","") -> 费尔伯格人 | B12: ="" | C12: ="" | D12: ="" | E12: ="" | F12: ="" | G12: ="" | H12: ="" | I12: ="" | ... O12: ="" | S12: {=INDEX(A:A,SMALL(IF($A$2:$A$45<>"",ROW($2:$45),46),ROW(A11)))&""} -> 费尔伯格人 | T12: =INDEX($B$2:$K$45,$T$2,10) -> #N/A | U12: {=INDEX(T:T,SMALL(IF($T$3:$T$15<>"",ROW($3:$15),16),ROW(T11)))&""} -> #N/A | V12: =IF($V11+1>$Y$3,IF($X$4+$Y11>$Y$4,"",$X$4+$Y11),$V11+1) -> #N/A | W12: =INDEX($B$52:$AD$147,W$4,$V12) -> #N/A | X12: =INDEX($B$52:$AD$147,W$3,$V12) -> #N/A | Y12: =IF($V11+1>$Y$3,$Y11+1,0) -> #N/A | Z12: =IFERROR(IF(OR($W16="",COUNTIF($AB$2:$AB$15,$W16)),"",W16),"") | AA12: {=INDEX(Z:Z,SMALL(IF($Z$2:$Z$16<>"",ROW($2:$16),17),ROW(Z11)))&""} | AB12: =IF(主要!$Z94="",0,主要!$Z94) -> 0 | AC12: =IFERROR(VLOOKUP($AB12,$W$6:$X$27,2,0),"") | AD12: =IF($AB12=0,"",COUNTIF($AB$2:$AB$15,$AB12)) | AE12: 海精灵 | AG12: 16 | AH12: 18 | AI12: 阴影龙纹 | AJ12: 敏捷+2，魅力+1 | AK12: =AK$6 -> 中型 | AL12: =AL$6 -> 基础步行速度为30尺 | AM12: =AM$6 -> 和精灵语
A13: =IF(OR(综合数据!B6=TRUE,综合数据!B11=TRUE,综合数据!B18=TRUE),"歌利亚","") -> 歌利亚 | B13: ="" | C13: ="" | D13: ="" | E13: ="" | F13: ="" | G13: ="" | H13: ="" | I13: ="" | ... O13: ="" | S13: {=INDEX(A:A,SMALL(IF($A$2:$A$45<>"",ROW($2:$45),46),ROW(A12)))&""} -> 歌利亚 | T13: =IF(综合数据!B15=TRUE,"半血裔","") -> 半血裔 | U13: {=INDEX(T:T,SMALL(IF($T$3:$T$15<>"",ROW($3:$15),16),ROW(T12)))&""} -> #N/A | V13: =IF($V12+1>$Y$3,IF($X$4+$Y12>$Y$4,"",$X$4+$Y12),$V12+1) -> #N/A | W13: =INDEX($B$52:$AD$147,W$4,$V13) -> #N/A | X13: =INDEX($B$52:$AD$147,W$3,$V13) -> #N/A | Y13: =IF($V12+1>$Y$3,$Y12+1,0) -> #N/A | Z13: =IFERROR(IF(OR($W17="",COUNTIF($AB$2:$AB$15,$W17)),"",W17),"") | AA13: {=INDEX(Z:Z,SMALL(IF($Z$2:$Z$16<>"",ROW($2:$16),17),ROW(Z12)))&""} | AB13: =IF(主要!$Z95="",0,主要!$Z95) -> 0 | AC13: =IFERROR(VLOOKUP($AB13,$W$6:$X$27,2,0),"") | AD13: =IF($AB13=0,"",COUNTIF($AB$2:$AB$15,$AB13)) | AE13: 影灵 | AG13: 19 | AH13: 20 | AI13: 苍白精灵 | AJ13: 敏捷+2，感知+1 | AK13: =AK$6 -> 中型 | AL13: =AL$6 -> 基础步行速度为30尺 | AM13: =AM$6 -> 和精灵语
A14: =IF(OR(综合数据!B6=TRUE,综合数据!B11=TRUE,综合数据!B18=TRUE),"天狗","") -> 天狗 | B14: ="" | C14: ="" | D14: ="" | E14: ="" | F14: ="" | G14: ="" | H14: ="" | I14: ="" | ... O14: ="" | S14: {=INDEX(A:A,SMALL(IF($A$2:$A$45<>"",ROW($2:$45),46),ROW(A13)))&""} -> 天狗 | T14: =IF(综合数据!B15=TRUE,"巫咒之子","") -> 巫咒之子 | U14: {=INDEX(T:T,SMALL(IF($T$3:$T$15<>"",ROW($3:$15),16),ROW(T13)))&""} -> #N/A | V14: =IF($V13+1>$Y$3,IF($X$4+$Y13>$Y$4,"",$X$4+$Y13),$V13+1) -> #N/A | W14: =INDEX($B$52:$AD$147,W$4,$V14) -> #N/A | X14: =INDEX($B$52:$AD$147,W$3,$V14) -> #N/A | Y14: =IF($V13+1>$Y$3,$Y13+1,0) -> #N/A | Z14: =IFERROR(IF(OR($W18="",COUNTIF($AB$2:$AB$15,$W18)),"",W18),"") | AA14: {=INDEX(Z:Z,SMALL(IF($Z$2:$Z$16<>"",ROW($2:$16),17),ROW(Z13)))&""} | AB14: =IF(主要!$Z96="",0,主要!$Z96) -> 0 | AC14: =IFERROR(VLOOKUP($AB14,$W$6:$X$27,2,0),"") | AD14: =IF($AB14=0,"",COUNTIF($AB$2:$AB$15,$AB14)) | AE14: 阴影龙纹 | AG14: 21 | AH14: 23 | AI14: 轻足半身人 | AJ14: 敏捷+2，魅力+1 | AK14: 小型 | AL14: 基础步行速度为25尺 | AM14: 和半身人语
A15: =IF(OR(综合数据!B6=TRUE,综合数据!B18=TRUE),"蜥蜴人","") -> 蜥蜴人 | B15: ="" | C15: ="" | D15: ="" | E15: ="" | F15: ="" | G15: ="" | H15: ="" | I15: ="" | ... O15: ="" | S15: {=INDEX(A:A,SMALL(IF($A$2:$A$45<>"",ROW($2:$45),46),ROW(A14)))&""} -> 蜥蜴人 | T15: =IF(综合数据!B15=TRUE,"重生者","") -> 重生者 | V15: =IF($V14+1>$Y$3,IF($X$4+$Y14>$Y$4,"",$X$4+$Y14),$V14+1) -> #N/A | W15: =INDEX($B$52:$AD$147,W$4,$V15) -> #N/A | X15: =INDEX($B$52:$AD$147,W$3,$V15) -> #N/A | Y15: =IF($V14+1>$Y$3,$Y14+1,0) -> #N/A | Z15: =IFERROR(IF(OR($W19="",COUNTIF($AB$2:$AB$15,$W19)),"",W19),"") | AA15: {=INDEX(Z:Z,SMALL(IF($Z$2:$Z$16<>"",ROW($2:$16),17),ROW(Z14)))&""} | AB15: =IF(主要!$Z97="",0,主要!$Z97) -> 0 | AC15: =IFERROR(VLOOKUP($AB15,$W$6:$X$27,2,0),"") | AD15: =IF($AB15=0,"",COUNTIF($AB$2:$AB$15,$AB15)) | AE15: 苍白精灵 | AG15: 24 | AH15: 25 | AI15: 敦实半身人 | AJ15: 敏捷+2，体质+1 | AK15: =AK$14 -> 小型 | AL15: =AL$14 -> 基础步行速度为25尺 | AM15: =AM$14 -> 和半身人语
A16: =IF(OR(综合数据!B6=TRUE,综合数据!B11=TRUE,综合数据!B18=TRUE),"斑猫人","") -> 斑猫人 | B16: ="" | C16: ="" | D16: ="" | E16: ="" | F16: ="" | G16: ="" | H16: ="" | I16: ="" | ... O16: ="" | S16: {=INDEX(A:A,SMALL(IF($A$2:$A$45<>"",ROW($2:$45),46),ROW(A15)))&""} -> 斑猫人 | V16: =IF($V15+1>$Y$3,IF($X$4+$Y15>$Y$4,"",$X$4+$Y15),$V15+1) -> #N/A | W16: =INDEX($B$52:$AD$147,W$4,$V16) -> #N/A | X16: =INDEX($B$52:$AD$147,W$3,$V16) -> #N/A | Y16: =IF($V15+1>$Y$3,$Y15+1,0) -> #N/A | Z16: =IFERROR(IF(OR($W20="",COUNTIF($AB$2:$AB$15,$W20)),"",W20),"") | AA16: {=INDEX(Z:Z,SMALL(IF($Z$2:$Z$16<>"",ROW($2:$16),17),ROW(Z15)))&""} | AB16: 重复特性 | AC16: =COUNTIF(AD2:AD15,">1") -> 0 | AD16: 动物强化 | AE16: 半身人 | AF16: =AF7+1 -> 3 | AG16: 1 | AH16: 3 | AI16: 鬼智半身人 | AJ16: 敏捷+2，感知+1 | AK16: =AK$14 -> 小型 | AL16: =AL$14 -> 基础步行速度为25尺 | AM16: =AM$14 -> 和半身人语
A17: =IF(OR(综合数据!B6=TRUE,综合数据!B18=TRUE),"梭螺鱼人","") -> 梭螺鱼人 | B17: ="" | C17: ="" | D17: ="" | E17: ="" | F17: ="" | G17: ="" | H17: ="" | I17: ="" | ... O17: ="" | S17: {=INDEX(A:A,SMALL(IF($A$2:$A$45<>"",ROW($2:$45),46),ROW(A16)))&""} -> 梭螺鱼人 | T17: 亚种错误 | U17: 未选亚种 | V17: =IF($V16+1>$Y$3,IF($X$4+$Y16>$Y$4,"",$X$4+$Y16),$V16+1) -> #N/A | W17: =INDEX($B$52:$AD$147,W$4,$V17) -> #N/A | X17: =INDEX($B$52:$AD$147,W$3,$V17) -> #N/A | Y17: =IF($V16+1>$Y$3,$Y16+1,0) -> #N/A | AB17: 互斥特性 | AC17: =COUNTIF(AC18:AC25,">1") -> 0 | AD17: =IF(AND(V2<5,AD21>0),2,IF(AD19+AD21>2,2,IF(AD21>1,2,0))) -> 0 | AE17: 轻足半身人 | AG17: 4 | AH17: 4 | AI17: 医疗龙纹 | AJ17: 敏捷+2，感知+1 | AK17: =AK$14 -> 小型 | AL17: =AL$14 -> 基础步行速度为25尺 | AM17: =AM$14 -> 和半身人语
A18: =IF(OR(综合数据!B6=TRUE,综合数据!B11=TRUE,综合数据!B18=TRUE),"地精","") -> 地精 | B18: 熊地精 | C18: 大地精 | D18: =IF(综合数据!B19=TRUE,"依夏兰","") | E18: =IF(综合数据!B19=TRUE,"赞迪卡","") | F18: ="" | G18: ="" | H18: ="" | I18: ="" | J18: ="" | K18: ="" | L18: ="" | M18: ="" | ... O18: ="" | S18: {=INDEX(A:A,SMALL(IF($A$2:$A$45<>"",ROW($2:$45),46),ROW(A17)))&""} -> 地精 | T18: =IF($V4=0,"",COUNTIF($T$3:$T$15,$V4)) | U18: =IF(AND(V4=0,OR(V3=A2,V3=A3,V3=A4,V3=A7,V3=A22,V3=A33,V3=A44,V3=A45)),1,"") | V18: =IF($V17+1>$Y$3,IF($X$4+$Y17>$Y$4,"",$X$4+$Y17),$V17+1) -> #N/A | W18: =INDEX($B$52:$AD$147,W$4,$V18) -> #N/A | X18: =INDEX($B$52:$AD$147,W$3,$V18) -> #N/A | Y18: =IF($V17+1>$Y$3,$Y17+1,0) -> #N/A | AB18: 半木精灵 | AC18: =IF(V3=A8,COUNTIF($AB$2:$AB$15,"多才多艺")+COUNTIF($AB$2:$AB$15,"敏锐感官")+COUNTIF($AB$2:$AB$15,"木精灵武器训练")+COUNTIF($AB$2:$AB$15,"轻捷步伐")+COUNTIF($AB$2:$AB$15,"野性面具"),0) -> 0 | AD18: 初级 | AE18: 敦实半身人 | AG18: 5 | AH18: 5 | AI18: 招待龙纹 | AJ18: 敏捷+2，魅力+1 | AK18: =AK$14 -> 小型 | AL18: =AL$14 -> 基础步行速度为25尺 | AM18: =AM$14 -> 和半身人语
A19: =IF(OR(综合数据!B6=TRUE,综合数据!B18=TRUE),"狗头人","") -> 狗头人 | B19: ="" | C19: ="" | D19: ="" | E19: ="" | F19: ="" | G19: ="" | H19: ="" | I19: ="" | ... O19: ="" | S19: {=INDEX(A:A,SMALL(IF($A$2:$A$45<>"",ROW($2:$45),46),ROW(A18)))&""} -> 狗头人 | V19: =IF($V18+1>$Y$3,IF($X$4+$Y18>$Y$4,"",$X$4+$Y18),$V18+1) -> #N/A | W19: =INDEX($B$52:$AD$147,W$4,$V19) -> #N/A | X19: =INDEX($B$52:$AD$147,W$3,$V19) -> #N/A | Y19: =IF($V18+1>$Y$3,$Y18+1,0) -> #N/A | AB19: 半日月精灵 | AC19: =IF(V3=A8,COUNTIF($AB$2:$AB$15,"多才多艺")+COUNTIF($AB$2:$AB$15,"敏锐感官")+COUNTIF($AB$2:$AB$15,"高等精灵武器训练")+COUNTIF($AB$2:$AB$15,"戏法"),0) -> 0 | AD19: =IF(V3=A26,COUNTIF($AB$2:$AB$15,"蝠鲼滑翔")+COUNTIF($AB$2:$AB$15,"灵活攀登")+COUNTIF($AB$2:$AB$15,"水下适应"),0) -> 0 | AE19: 鬼智半身人 | AG19: 6 | AH19: 6 | AI19: 莲源半身人 | AJ19: 敏捷+2，感知+1 | AK19: =AK$14 -> 小型 | AL19: =AL$14 -> 基础步行速度为25尺 | AM19: =AM$14 -> 和半身人语
A20: =IF(OR(综合数据!B6=TRUE,综合数据!B10=TRUE,综合数据!B11=TRUE,综合数据!B18=TRUE),"兽人","") -> 兽人 | B20: ="" | C20: ="" | D20: ="" | E20: ="" | F20: ="" | G20: ="" | H20: ="" | I20: ="" | ... O20: ="" | S20: {=INDEX(A:A,SMALL(IF($A$2:$A$45<>"",ROW($2:$45),46),ROW(A19)))&""} -> 兽人 | V20: =IF($V19+1>$Y$3,IF($X$4+$Y19>$Y$4,"",$X$4+$Y19),$V19+1) -> #N/A | W20: =INDEX($B$52:$AD$147,W$4,$V20) -> #N/A | X20: =INDEX($B$52:$AD$147,W$3,$V20) -> #N/A | Y20: =IF($V19+1>$Y$3,$Y19+1,0) -> #N/A | AB20: 半卓尔精灵 | AC20: =IF(V3=A8,COUNTIF($AB$2:$AB$15,"多才多艺")+COUNTIF($AB$2:$AB$15,"敏锐感官")+COUNTIF($AB$2:$AB$15,"卓尔魔法"),0) -> 0 | AD20: 高级 | AE20: 医疗龙纹 | AG20: 7 | AH20: 9 | AI20: 人类 | AJ20: 全部属性+1 | AK20: 中型 | AL20: 基础步行速度为30尺 | AM20: ，以及任意一门自选语言
A21: =IF(OR(综合数据!B6=TRUE,综合数据!B18=TRUE),"原体蛇人","") -> 原体蛇人 | B21: ="" | C21: ="" | D21: ="" | E21: ="" | F21: ="" | G21: ="" | H21: ="" | I21: ="" | ... O21: ="" | S21: {=INDEX(A:A,SMALL(IF($A$2:$A$45<>"",ROW($2:$45),46),ROW(A20)))&""} -> 原体蛇人 | AB21: 半水生精灵 | AC21: =IF(V3=A8,COUNTIF($AB$2:$AB$15,"多才多艺")+COUNTIF($AB$2:$AB$15,"敏锐感官")+COUNTIF($AB$2:$AB$15,"游泳速度"),0) -> 0 | AD21: =IF(V3=A26,COUNTIF($AB$2:$AB$15,"斗殴附件")+COUNTIF($AB$2:$AB$15,"甲壳")+COUNTIF($AB$2:$AB$15,"酸液喷吐"),0) -> 0 | AE21: 招待龙纹 | AG21: 10 | AH21: 12 | AI21: 人类变体 | AJ21: 自选两项不同属性各+1 | AK21: =AK$20 -> 中型 | AL21: =AL$20 -> 基础步行速度为30尺 | AM21: =AM$20 -> ，以及任意一门自选语言
A22: =IF(OR(综合数据!B8=TRUE,综合数据!B18=TRUE),"吉斯人","") -> 吉斯人 | B22: 吉斯洋基人 | C22: 吉斯泽莱人 | D22: ="" | E22: ="" | F22: ="" | G22: ="" | H22: ="" | I22: ="" | J22: ="" | K22: ="" | ... O22: ="" | S22: {=INDEX(A:A,SMALL(IF($A$2:$A$45<>"",ROW($2:$45),46),ROW(A21)))&""} -> 吉斯人 | AB22: 提夫林变体 | AC22: =IF(V3=A10,COUNTIF($AB$2:$AB$15,"地狱遗赠")+COUNTIF($AB$2:$AB$15,"魔鬼之舌")+COUNTIF($AB$2:$AB$15,"地狱之火")+COUNTIF($AB$2:$AB$15,"飞翼"),0) -> 0 | AE22: 莲源半身人 | AG22: 13 | AH22: 14 | AI22: 探索龙纹 | AJ22: 感知+2，体质+1 | AK22: =AK$20 -> 中型 | AL22: =AL$20 -> 基础步行速度为30尺 | AM22: =IF(V3=A9,"、兽人语和地精语","和地精语，以及任意一门自选语言") -> 和地精语，以及任意一门自选语言
A23: =IF(OR(综合数据!B9=TRUE,综合数据!B18=TRUE),"人马","") -> 人马 | B23: ="" | C23: ="" | D23: ="" | E23: ="" | F23: ="" | G23: ="" | H23: ="" | I23: ="" | ... O23: ="" | S23: {=INDEX(A:A,SMALL(IF($A$2:$A$45<>"",ROW($2:$45),46),ROW(A22)))&""} -> 人马 | AB23: 阿斯莫 | AC23: =IF(V3=A11,COUNTIF($AB$2:$AB$15,"死灵环绕")+COUNTIF($AB$2:$AB$15,"光辉焚化")+COUNTIF($AB$2:$AB$15,"光辉灵魂"),0) -> 0 | AE23: 人类 | AF23: =AF16+1 -> 4 | AG23: 1 | AH23: 0 | AI23: 畜牧龙纹 | AJ23: 感知+2，自选一项其他属性+1 | AK23: =AK$20 -> 中型 | AL23: =AL$20 -> 基础步行速度为30尺 | AM23: =AM$20 -> ，以及任意一门自选语言
A24: =IF(OR(综合数据!B9=TRUE,综合数据!B18=TRUE),"牛头人","") -> 牛头人 | B24: ="" | C24: ="" | D24: ="" | E24: ="" | F24: ="" | G24: ="" | H24: ="" | I24: ="" | ... O24: ="" | S24: {=INDEX(A:A,SMALL(IF($A$2:$A$45<>"",ROW($2:$45),46),ROW(A23)))&""} -> 牛头人 | AB24: 狗头人 | AC24: =IF(V3=A19,COUNTIF($AB$2:$AB$15,"狡猾")+COUNTIF($AB$2:$AB$15,"反抗")+COUNTIF($AB$2:$AB$15,"龙族术法"),0) -> 0 | AE24: 人类变体 | AG24: 1 | AH24: 2 | AI24: 创造龙纹 | AJ24: 智力+2，自选一项其他属性+1 | AK24: =AK$20 -> 中型 | AL24: =AL$20 -> 基础步行速度为30尺 | AM24: =AM$20 -> ，以及任意一门自选语言
A25: =IF(综合数据!B9=TRUE,"象族","") -> 象族 | B25: ="" | C25: ="" | D25: ="" | E25: ="" | F25: ="" | G25: ="" | H25: ="" | I25: ="" | ... O25: ="" | S25: {=INDEX(A:A,SMALL(IF($A$2:$A$45<>"",ROW($2:$45),46),ROW(A24)))&""} -> 象族 | AB25: 化兽者 | AC25: =IF(V3=A30,COUNTIF($AB$2:$AB$15,"兽皮")+COUNTIF($AB$2:$AB$15,"长牙")+COUNTIF($AB$2:$AB$15,"迅捷")+COUNTIF($AB$2:$AB$15,"猎食"),0) -> 0 | AE25: 探索龙纹 | AG25: =IF(V3=A9,5,3) -> 3 | AH25: =IF(V3=A9,8,6) -> 6 | AI25: 通行龙纹 | AJ25: 敏捷+2，自选一项其他属性+1 | AK25: =AK$20 -> 中型 | AL25: =AL$20 -> 基础步行速度为30尺 | AM25: =AM$20 -> ，以及任意一门自选语言
A26: =IF(综合数据!B9=TRUE,"析米克混生体","") -> 析米克混生体 | B26: ="" | C26: ="" | D26: ="" | E26: ="" | F26: ="" | G26: ="" | H26: ="" | I26: ="" | ... O26: ="" | S26: {=INDEX(A:A,SMALL(IF($A$2:$A$45<>"",ROW($2:$45),46),ROW(A25)))&""} -> 析米克混生体 | AE26: 畜牧龙纹 | AG26: 7 | AH26: 11 | AI26: 守护龙纹 | AJ26: 体质+2，感知+1 | AK26: =AK$20 -> 中型 | AL26: =AL$20 -> 基础步行速度为30尺 | AM26: =AM$20 -> ，以及任意一门自选语言
A27: =IF(综合数据!B9=TRUE,"维多肯","") -> 维多肯 | B27: ="" | C27: ="" | D27: ="" | E27: ="" | F27: ="" | G27: ="" | H27: ="" | I27: ="" | ... O27: ="" | S27: {=INDEX(A:A,SMALL(IF($A$2:$A$45<>"",ROW($2:$45),46),ROW(A26)))&""} -> 维多肯 | AE27: 创造龙纹 | AG27: 12 | AH27: 15 | AI27: 加渥尼 | AJ27: =$AJ20 -> 全部属性+1 | AK27: =AK$20 -> 中型 | AL27: =AL$20 -> 基础步行速度为30尺 | AM27: =AM$20 -> ，以及任意一门自选语言
A28: =IF(OR(综合数据!B10=TRUE,综合数据!B18=TRUE),"幻身灵","") -> 幻身灵 | B28: ="" | C28: ="" | D28: ="" | E28: ="" | F28: ="" | G28: ="" | H28: ="" | I28: ="" | ... O28: ="" | S28: {=INDEX(A:A,SMALL(IF($A$2:$A$45<>"",ROW($2:$45),46),ROW(A27)))&""} -> 幻身灵 | AE28: 通行龙纹 | AG28: 16 | AH28: 19 | AI28: 凯锡革 | AJ28: 敏捷+1，感知+1 | AK28: =AK$20 -> 中型 | AL28: =AL$20 -> 基础步行速度为30尺 | AM28: =AM$20 -> ，以及任意一门自选语言
A29: =IF(综合数据!B10=TRUE,"离梦人","") -> 离梦人 | B29: ="" | C29: ="" | D29: ="" | E29: ="" | F29: ="" | G29: ="" | H29: ="" | I29: ="" | ... O29: ="" | S29: {=INDEX(A:A,SMALL(IF($A$2:$A$45<>"",ROW($2:$45),46),ROW(A28)))&""} -> 离梦人 | AE29: 守护龙纹 | AG29: 20 | AH29: 23 | AI29: 涅非利亚 | AJ29: 智力+1，魅力+1 | AK29: =AK$20 -> 中型 | AL29: =AL$20 -> 基础步行速度为30尺 | AM29: =AM$20 -> ，以及任意一门自选语言
A30: =IF(OR(综合数据!B10=TRUE,综合数据!B18=TRUE),"化兽者","") -> 化兽者 | B30: ="" | C30: ="" | D30: ="" | E30: ="" | F30: ="" | G30: ="" | H30: ="" | I30: ="" | ... O30: ="" | S30: {=INDEX(A:A,SMALL(IF($A$2:$A$45<>"",ROW($2:$45),46),ROW(A29)))&""} -> 化兽者 | AE30: 加渥尼 | AG30: 24 | AH30: 0 | AI30: 史顿襄 | AJ30: 力量+1，体质+1 | AK30: =AK$20 -> 中型 | AL30: =AL$20 -> 基础步行速度为30尺 | AM30: =AM$20 -> ，以及任意一门自选语言
A31: =IF(综合数据!B10=TRUE,"机关人","") -> 机关人 | B31: ="" | C31: ="" | D31: ="" | E31: ="" | F31: ="" | G31: ="" | H31: ="" | I31: ="" | ... O31: ="" | S31: {=INDEX(A:A,SMALL(IF($A$2:$A$45<>"",ROW($2:$45),46),ROW(A30)))&""} -> 机关人 | AE31: 凯锡革 | AG31: 24 | AH31: 27 | AI31: 龙裔 | AJ31: 力量+2，魅力+1 | AK31: 中型 | AL31: 基础步行速度为30尺 | AM31: 和龙语
A32: =IF(OR(综合数据!B11=TRUE,综合数据!B18=TRUE),"阿兰寇拉鹰人","") -> 阿兰寇拉鹰人 | B32: ="" | C32: ="" | D32: ="" | E32: ="" | F32: ="" | G32: ="" | H32: ="" | I32: ="" | ... O32: ="" | S32: {=INDEX(A:A,SMALL(IF($A$2:$A$45<>"",ROW($2:$45),46),ROW(A31)))&""} -> 阿兰寇拉鹰人 | AE32: 涅非利亚 | AG32: 28 | AH32: 28 | AI32: 龙国血统 | AJ32: 智力+2，魅力+1 | AK32: =AK$31 -> 中型 | AL32: =AL$31 -> 基础步行速度为30尺 | AM32: =AM$31 -> 和龙语
A33: =IF(OR(综合数据!B11=TRUE,综合数据!B18=TRUE),"元素裔","") -> 元素裔 | B33: 气元素裔 | C33: 土元素裔 | D33: 火元素裔 | E33: 水元素裔 | F33: ="" | G33: ="" | H33: ="" | I33: ="" | J33: ="" | K33: ="" | L33: ="" | M33: ="" | ... O33: ="" | S33: {=INDEX(A:A,SMALL(IF($A$2:$A$45<>"",ROW($2:$45),46),ROW(A32)))&""} -> 元素裔 | AE33: 史顿襄 | AG33: 29 | AH33: 30 | AI33: 瑞雯奈特 | AJ33: 力量+2，体质+1 | AK33: =AK$31 -> 中型 | AL33: =AL$31 -> 基础步行速度为30尺 | AM33: =AM$31 -> 和龙语
A34: =IF(OR(综合数据!B11=TRUE,综合数据!B18=TRUE),"龟人","") -> 龟人 | B34: ="" | C34: ="" | D34: ="" | E34: ="" | F34: ="" | G34: ="" | H34: ="" | I34: ="" | ... O34: ="" | S34: {=INDEX(A:A,SMALL(IF($A$2:$A$45<>"",ROW($2:$45),46),ROW(A33)))&""} -> 龟人 | AE34: 龙裔 | AF34: =AF23+1 -> 5 | AG34: 1 | AH34: =IF(COUNTIF(D6:F6,V4),1,IF(COUNTIF(B6:C6,V4),2,3)) -> 3 | AI34: 色彩龙血统 | AJ34: 自选两项属性分别+2/+1或自选三项属性+1 | AK34: =AK$31 -> 中型 | AL34: =AL$31 -> 基础步行速度为30尺 | AM34: =AM$20 -> ，以及任意一门自选语言
A35: =IF(综合数据!B12=TRUE,"佛丹人","") -> 佛丹人 | B35: ="" | C35: ="" | D35: ="" | E35: ="" | F35: ="" | G35: ="" | H35: ="" | I35: ="" | ... O35: ="" | S35: {=INDEX(A:A,SMALL(IF($A$2:$A$45<>"",ROW($2:$45),46),ROW(A34)))&""} -> 佛丹人 | AE35: 龙国血统 | AG35: 4 | AH35: 5 | AI35: 宝石龙血统 | AJ35: =AJ34 -> 自选两项属性分别+2/+1或自选三项属性+1 | AK35: =AK$31 -> 中型 | AL35: =AL$31 -> 基础步行速度为30尺 | AM35: =AM$20 -> ，以及任意一门自选语言
A36: =IF(综合数据!B13=TRUE,"狮族","") -> 狮族 | B36: ="" | C36: ="" | D36: ="" | E36: ="" | F36: ="" | G36: ="" | H36: ="" | I36: ="" | ... O36: ="" | S36: {=INDEX(A:A,SMALL(IF($A$2:$A$45<>"",ROW($2:$45),46),ROW(A35)))&""} -> 狮族 | AE36: 瑞雯奈特 | AG36: 6 | AH36: 7 | AI36: 金属龙血统 | AJ36: =AJ34 -> 自选两项属性分别+2/+1或自选三项属性+1 | AK36: =AK$31 -> 中型 | AL36: =AL$31 -> 基础步行速度为30尺 | AM36: =AM$20 -> ，以及任意一门自选语言
A37: =IF(OR(综合数据!B13=TRUE,综合数据!B18=TRUE),"半羊人","") -> 半羊人 | B37: ="" | C37: ="" | D37: ="" | E37: ="" | F37: ="" | G37: ="" | H37: ="" | I37: ="" | ... O37: ="" | S37: {=INDEX(A:A,SMALL(IF($A$2:$A$45<>"",ROW($2:$45),46),ROW(A36)))&""} -> 半羊人 | AE37: 色彩龙血统 | AG37: 8 | AH37: =IF(V2<5,9,10) -> 9 | AI37: 森林侏儒 | AJ37: 智力+2，敏捷+1 | AK37: 小型 | AL37: 基础步行速度为25尺 | AM37: 和侏儒语
A38: =IF(综合数据!B17=TRUE,"枭人","") -> 枭人 | B38: ="" | C38: ="" | D38: ="" | E38: ="" | F38: ="" | G38: ="" | H38: ="" | I38: ="" | ... O38: ="" | S38: {=INDEX(A:A,SMALL(IF($A$2:$A$45<>"",ROW($2:$45),46),ROW(A37)))&""} -> 枭人 | AE38: 宝石龙血统 | AG38: 11 | AH38: =IF(V2<5,13,14) -> 13 | AI38: 岩侏儒 | AJ38: 智力+2，体质+1 | AK38: =AK$37 -> 小型 | AL38: =AL$37 -> 基础步行速度为25尺 | AM38: =AM$37 -> 和侏儒语
A39: =IF(综合数据!B18=TRUE,"仙灵","") -> 仙灵 | B39: ="" | C39: ="" | D39: ="" | E39: ="" | F39: ="" | G39: ="" | H39: ="" | I39: ="" | ... O39: ="" | S39: {=INDEX(A:A,SMALL(IF($A$2:$A$45<>"",ROW($2:$45),46),ROW(A38)))&""} -> 仙灵 | AE39: 金属龙血统 | AG39: 15 | AH39: =IF(V2<5,16,19) -> 16 | AI39: 地底侏儒 | AJ39: 自选两项属性分别+2/+1或自选三项属性+1 | AK39: =AK$37 -> 小型 | AL39: 基础步行速度为30尺 | AM39: ，以及任意一门自选语言
A40: =IF(综合数据!B18=TRUE,"兔人","") -> 兔人 | B40: ="" | C40: ="" | D40: ="" | E40: ="" | F40: ="" | G40: ="" | H40: ="" | I40: ="" | ... O40: ="" | S40: {=INDEX(A:A,SMALL(IF($A$2:$A$45<>"",ROW($2:$45),46),ROW(A39)))&""} -> 兔人 | AE40: 侏儒 | AF40: =AF34+1 -> 6 | AG40: 1 | AH40: 2 | AI40: 抄录龙纹 | AJ40: 智力+2，魅力+1 | AK40: =AK$37 -> 小型 | AL40: =AL$37 -> 基础步行速度为25尺 | AM40: =AM$37 -> 和侏儒语
A41: =IF(综合数据!B19=TRUE,"洛卡鱼人","") | B41: ="" | C41: ="" | D41: ="" | E41: ="" | F41: ="" | G41: ="" | H41: ="" | I41: ="" | ... O41: ="" | S41: {=INDEX(A:A,SMALL(IF($A$2:$A$45<>"",ROW($2:$45),46),ROW(A40)))&""} | AE41: 森林侏儒 | AG41: 3 | AH41: 4 | AI41: 半精灵 | AJ41: 魅力+2，自选两项其他属性各+1 | AK41: 中型 | AL41: 基础步行速度为30尺 | AM41: 和精灵语，以及任意一门自选语言
A42: =IF(综合数据!B19=TRUE,"阿芒凯那伽","") | B42: ="" | C42: ="" | D42: ="" | E42: ="" | F42: ="" | G42: ="" | H42: ="" | I42: ="" | ... O42: ="" | S42: {=INDEX(A:A,SMALL(IF($A$2:$A$45<>"",ROW($2:$45),46),ROW(A41)))&""} | AE42: 岩侏儒 | AG42: 5 | AH42: 9 | AI42: 半木精灵 | AJ42: =AJ$41 -> 魅力+2，自选两项其他属性各+1 | AK42: =AK$41 -> 中型 | AL42: =AL$41 -> 基础步行速度为30尺 | AM42: =AM$41 -> 和精灵语，以及任意一门自选语言
A43: =IF(综合数据!B19=TRUE,"人鱼","") | B43: 绿色人鱼 | C43: 蓝色人鱼 | D43: ="" | E43: ="" | F43: ="" | G43: ="" | H43: ="" | I43: ="" | J43: ="" | K43: ="" | ... O43: ="" | S43: {=INDEX(A:A,SMALL(IF($A$2:$A$45<>"",ROW($2:$45),46),ROW(A42)))&""} | AE43: 地底侏儒 | AG43: 10 | AH43: =IF(V2<3,11,12) -> 11 | AI43: 半月精灵 | AJ43: =AJ$41 -> 魅力+2，自选两项其他属性各+1 | AK43: =AK$41 -> 中型 | AL43: =AL$41 -> 基础步行速度为30尺 | AM43: =AM$41 -> 和精灵语，以及任意一门自选语言
A44: =IF(综合数据!B19=TRUE,"吸血鬼","") | B44: 依夏兰 | C44: 赞迪卡 | D44: ="" | E44: ="" | F44: ="" | G44: ="" | H44: ="" | I44: ="" | J44: ="" | K44: ="" | ... O44: ="" | S44: {=INDEX(A:A,SMALL(IF($A$2:$A$45<>"",ROW($2:$45),46),ROW(A43)))&""} | AE44: 抄录龙纹 | AG44: 13 | AH44: 15 | AI44: 半日精灵 | AJ44: =AJ$43 -> 魅力+2，自选两项其他属性各+1 | AK44: =AK$43 -> 中型 | AL44: =AL$43 -> 基础步行速度为30尺 | AM44: =AM$43 -> 和精灵语，以及任意一门自选语言
A45: =IF(综合数据!B19=TRUE,"塞连","") | B45: ="" | C45: ="" | D45: ="" | E45: ="" | F45: ="" | G45: ="" | H45: ="" | I45: ="" | ... O45: ="" | S45: {=INDEX(A:A,SMALL(IF($A$2:$A$45<>"",ROW($2:$45),46),ROW(A44)))&""} | AE45: 半精灵 | AF45: =AF40+1 -> 7 | AG45: 1 | AH45: =IF(COUNTIF(G8:H8,V4),2,3) -> 3 | AI45: 半卓尔精灵 | AJ45: =AJ$41 -> 魅力+2，自选两项其他属性各+1 | AK45: =AK$41 -> 中型 | AL45: =AL$41 -> 基础步行速度为30尺 | AM45: =AM$41 -> 和精灵语，以及任意一门自选语言
AE46: 半木精灵 | AG46: 4 | AH46: 7 | AI46: 半水生精灵 | AJ46: =AJ$41 -> 魅力+2，自选两项其他属性各+1 | AK46: =AK$41 -> 中型 | AL46: =AL$41 -> 基础步行速度为30尺 | AM46: =AM$41 -> 和精灵语，以及任意一门自选语言
AE47: 半月精灵 | AG47: 8 | AH47: 10 | AI47: 侦测龙纹 | AJ47: 感知+2，自选一项其他属性+1 | AK47: =AK$41 -> 中型 | AL47: =AL$41 -> 基础步行速度为30尺 | AM47: =AM$41 -> 和精灵语，以及任意一门自选语言
AE48: 半日精灵 | AG48: 8 | AH48: 10 | AI48: 暴风龙纹 | AJ48: 魅力+2，敏捷+1 | AK48: =AK$41 -> 中型 | AL48: =AL$41 -> 基础步行速度为30尺 | AM48: =AM$41 -> 和精灵语，以及任意一门自选语言
AE49: 半卓尔精灵 | AG49: 11 | AH49: 12 | AI49: 半兽人 | AJ49: 力量+2，体质+1 | AK49: 中型 | AL49: 基础步行速度为30尺 | AM49: 和兽人语
AE50: 半水生精灵 | AG50: 13 | AH50: 14 | AI50: 探索龙纹 | AJ50: =AJ$22 -> 感知+2，体质+1 | AK50: =AK$49 -> 中型 | AL50: =AL$49 -> 基础步行速度为30尺 | AM50: =IF(V3=A5,"、兽人语和地精语","和地精语，以及任意一门自选语言") -> 和地精语，以及任意一门自选语言
B51: 1 | C51: 2 | D51: 3 | E51: 4 | F51: 5 | G51: 6 | H51: 7 | I51: 8 | J51: 9 | K51: 10 | L51: 11 | M51: 12 | N51: 13 | O51: 14 | P51: 15 | Q51: 16 | R51: 17 | S51: 18 | T51: 19 | U51: 20 | V51: 21 | W51: 22 | X51: 23 | Y51: 24 | Z51: 25 | AA51: 26 | AB51: 27 | AC51: 28 | AD51: 29 | AE51: 侦测龙纹 | AG51: 15 | AH51: 17 | AI51: 阿芒凯牛头怪 | AJ51: 力量+2，体质+1 | AK51: =AK$49 -> 中型 | AL51: =AL$49 -> 基础步行速度为30尺 | AM51: 和牛头人语
A52: 矮人 | B52: 黑暗视觉 | C52: 矮人体魄 | D52: 矮人战斗训练 | E52: 工具熟练项 | F52: 石中精妙 | G52: 矮人刚毅 | H52: 矮人护甲训练 | I52: 增强黑暗视觉 | J52: 灵能坚韧 | K52: 灰矮人魔法 | L52: 龙纹法术 | M52: 守卫直觉 | N52: 保护与封锁 | AE52: 暴风龙纹 | AG52: 18 | AH52: 21 | AI52: 提夫林 | AJ52: 智力+1，魅力+2 | AK52: 中型 | AL52: 基础步行速度为30尺 | AM52: 和炼狱语
B53: 在微光光照下，你身边60尺内可以视为等同于明亮光照。而在黑暗中，该范围内可视为等同于微光光照。你无法在黑暗中分辨颜色，只能看到有灰度的黑白画面 | C53: 你进行对抗中毒的豁免时具有优势，你对毒素伤害具有抗性 | D53: 你具有战斧，手斧，轻锤和战锤的武器熟练项 | E53: 你从以下工具中选择一项获得熟练项：铁匠工具、酿酒工具或石匠工具 | F53: 每当你对一件石制品的起源做智力（历史）检定时，你视为具有历史技能的熟练项，并可以在检定中加上双倍的熟练加值 | G53: 你的生命值最大值加1，且此后每次升级时再加1 | H53: 你具有轻甲和中甲的护甲熟练项 | I53: 你的黑暗视觉感官范围提升至120尺 | J53: 你进行对抗魅惑和震慑的豁免时具有优势 | K53: 第3级起，你可以用此特质对自己施展一次变巨/缩小术 第5级起，你可以用此特质施展一次变巨/缩小术或隐形术 你必须完成一次长休后才能再次启用该能力。你也可以通过法术位正常施展该特性中的法术，该法术的施法关键属性为智力、感知或魅力并在最初选择种族时决定 当你使用该特质施展这些法术时，无需法术成分 | L53: 如果你拥有施法或契约魔法职业能力，将以下龙纹法术加入施法职业法术列表中： 1环：警报术，艾嘉西斯之铠 2环：秘法锁，敲击术 3环：守卫刻文，防护法阵 4环：李欧蒙秘藏箱，摩登肯忠犬 5环：防活物护罩 | M53: 当你进行智力（调查）检定或使用盗贼工具进行属性检定时，你能掷一个d4，并把结果加到属性检定的结果上 | N53: 你能够施展警报术和法师护甲法术，从3级起，你还能施展秘法锁。一旦你使用此特性施展了前述法术，你将无法再次使用此特性，直到完成一次长休。智力是你在施展这些法术时的关键属性，你无需为这些法术提供材料成分 | AE53: 半兽人 | AF53: =AF45+1 -> 8 | AG53: 1 | AH53: =IF(COUNTIF(B9:C9,V4),0,4) -> 4 | AI53: 提夫林变体 | AJ53: 智力+1，敏捷+2 | AK53: =AK$52 -> 中型 | AL53: =AL$52 -> 基础步行速度为30尺 | AM53: =AM$52 -> 和炼狱语
A54: 精灵 | B54: 黑暗视觉 | C54: 敏锐感官 | D54: 精类血统 | E54: 出神 | F54: 精灵武器训练 | G54: 戏法 | H54: 额外语言 | I54: 精灵武器训练 | J54: 轻捷步伐 | K54: 野性面具 | L54: 增强黑暗视觉 | M54: 日照敏感 | N54: 卓尔魔法 | O54: 卓尔武器训练 | P54: 精类步 | Q54: 游泳 | R54: 海之子 | S54: 海之友 | T54: 黯蚀抗性 | U54: 鸦后的祝福 | V54: 龙纹法术 | W54: 狡诈直觉 | X54: 阴影塑形 | Y54: 增强敏锐感官 | Z54: 月织者的祝福 | AE54: 探索龙纹 | AG54: =IF(V3=A5,3,5) -> 5 | AH54: =IF(V3=A5,6,8) -> 8 | AI54: 巴尔泽布 | AJ54: 魅力+2，智力+1 | AK54: =AK$52 -> 中型 | AL54: =AL$52 -> 基础步行速度为30尺 | AM54: =AM$52 -> 和炼狱语
B55: =B53 -> 在微光光照下，你身边60尺内可以视为等同于明亮光照。而在黑暗中，该范围内可视为等同于微光光照。你无法在黑暗中分辨颜色，只能看到有灰度的黑白画面 | C55: 你拥有察觉的技能熟练项 | D55: 你进行对抗魅惑的豁免时具有优势，并且不会因魔法效应而陷入睡眠 | E55: ="你在需要休息时陷入持续4个小时的半清醒深度冥想中。冥想时精灵也会做梦。以这种方式休息后，你获得人类睡眠8小时的全部益处"&IF(OR(V4=E3,V4=F3,V4=G3),"。当你结束这段冥想时，你可以改变你的季节，并且你能够获得两项你未拥有的武器或工具熟练项直到你完成下次长休","") -> 你在需要休息时陷入持续4个小时的半清醒深度冥想中。冥想时精灵也会做梦。以这种方式休息后，你获得人类睡眠8小时的全部益处 | F55: 你具有长剑、短剑、短弓和长弓的武器熟练项 | G55: 你掌握一个法师法术列表中自选戏法 | H55: 你能额外说、读、写一门额外的自选语言 | I55: =F55 -> 你具有长剑、短剑、短弓和长弓的武器熟练项 | J55: 基础步行速度提升至35尺 | K55: 你从树丛，大雨，落雪，雾气或其他自然现象中获得轻度遮蔽时，就可以尝试执行躲藏 | L55: =I53 -> 你的黑暗视觉感官范围提升至120尺 | M55: 你进行攻击检定和依赖视觉的感知（察觉）检定时，如果你本人、你的攻击目标或你尝试察觉的东西位于阳光直射下，则你所进行的相应检定具有劣势 | N55: 你习得戏法舞光术。达到3级后，你可以每日使用一次法术妖火。达到5级后，你可以每日使用一次法术黑暗术。这些每日施展一次的法术其施法关键属性是魅力。你必须完成一次长休才能再次以该特质施展这些法术 | O55: 你具有刺剑、短剑和手弩的武器熟练项 | P55: 以一个附赠动作，你能使用魔法传送到30尺内你可见的一处未被占据的空间。你可以使用该特质的次数等于你的熟练加值，当你完成一次长休后，你重新获得所有消耗的次数 从3级开始，你的精类步得到了基于你季节的额外效果。如果该效果需要进行一次豁免，则难度等级为8+你的熟练加值+你的智力、感知或魅力调整值并在最初选择种族时决定： 秋。你使用精类步后，可以立刻选择10尺内你可见的至多两个生物，其必须通过一次感知豁免，否则被你魅惑1分钟，直到你或你的伙伴对其造成任何伤害 冬。你使用精类步时，你指定的一只传送前于你5尺内的生物必须通过一次感知豁免，否则将在你下回合结束之前对你恐慌 春。你使用精类步时，可以触摸5尺内一只自愿的生物，他将取代你进行传送，出现于30尺内你选择的对你可见的一处未被占据的空间 夏。你使用精类步后，5尺内你选择的每一只你可见的生物将受到等同于你熟练加值的火焰伤害（至少1点） | Q55: 你拥有等于步行速度的游泳速度 | R55: 你对冷冻伤害具有抗性，并且你可以在空气和水中呼吸 | S55: 你可以向任何拥有游泳速度的野兽传达简单的想法。它们可以理解你的话的意思，虽然你没有特殊的能力来明白它们的回应 | T55: 你对黯蚀伤害具有抗性 | U55: 以一个附赠动作，你能使用魔法传送到30尺内你可见的一处未被占据的空间。你可以使用该特质的次数等于你的熟练加值，当你完成一次长休后，你重新获得所有消耗的次数 从3级开始，你将在你以此能力传送之后得到对于所有伤害的抗性。该抗性将持续到你你的下回合开始。在此期间，你的身体呈现出如幽魂般的半透明 | V55: 如果你拥有施法或契约魔法职业能力，将以下龙纹法术加入施法职业法术列表中： 1环：易容术，无声幻影 2环：黑暗术，行动无踪 3环：鹰眼术，高等幻影 4环：高等隐形术，幻景 5环：假象术 | W55: 当你进行魅力（表演）或敏捷（隐匿）检定时，你能掷一个d4，并把结果加到属性检定的结果上 | X55: 你习得戏法次级幻影。从第3级起，你能够通过此特性施展隐形术。一旦你使用此特性施展了前述法术，你将无法再次使用此特性，直到完成一次长休。魅力是你在施展这些法术时的关键属性 | Y55: 你在智力（调查）和感知（洞悉）检定上具有优势 | Z55: 你习得戏法光亮术。当你抵达3级时，你能通过本特质释放一次睡眠术，当你完成一次长休后可重获释放次数。当你抵达5级时，你能释放一次隐形术（只能对自身释放），当你完成一次长休后可重获释放次数。通过本特质释放的这些法术不需要材料成分。感知是你释放这些法术的施法属性 | AE55: 阿芒凯牛头怪 | AG55: 9 | AH55: 12 | AI55: 迪斯帕特 | AJ55: 魅力+2，敏捷+1 | AK55: =AK$52 -> 中型 | AL55: =AL$52 -> 基础步行速度为30尺 | AM55: =AM$52 -> 和炼狱语
A56: 半身人 | B56: 幸运 | C56: 勇气 | D56: 半身人灵巧 | E56: 天生善匿 | F56: 敦实体魄 | G56: 鬼灵言语 | H56: 龙纹法术 | I56: 医疗直觉 | J56: 医疗之触 | K56: 龙纹法术 | L56: 永远热情好客 | M56: 旅店老板的魔法 | N56: 树林之子 | O56: 木行 | AE56: 提夫林 | AF56: =AF53+1 -> 9 | AG56: 1 | AH56: =IF(COUNTIF(C10:J10,V4),2,3) -> 3 | AI56: 菲尔娜 | AJ56: 魅力+2，感知+1 | AK56: =AK$52 -> 中型 | AL56: =AL$52 -> 基础步行速度为30尺 | AM56: =AM$52 -> 和炼狱语
B57: 当攻击检定、属性检定以及豁免检定掷出1时，你可以再重掷一次，但必须使用重掷的结果 | C57: 你进行对抗恐慌的豁免时具有优势 | D57: 你可以穿越任何体形比你大的生物所在空间 | E57: 当你从体型比自己大的生物获得遮蔽时，可以尝试执行躲藏动作 | F57: =C53 -> 你进行对抗中毒的豁免时具有优势，你对毒素伤害具有抗性 | G57: 你可以向你30尺内的任何生物如同心灵感应般进行沟通。生物必须与你共同知晓一种语言才能理解你的发言。你通过这个方式每次只能和一名生物进行心灵沟通 | H57: 如果你拥有施法或契约魔法职业能力，将以下龙纹法术加入施法职业法术列表中： 1环：疗伤术，治愈真言 2环：次级复原术，治疗祷言 3环：活力灵光，群体治愈真言 4环：净化灵光，生命灵光 5环：高等复原术 | I57: 当你进行感知（医药）检定时，你能掷一个d4，并把结果加到属性检定的结果上 | J57: 你能够通过此特性施展疗伤术，从第3级起，你还能施展次级复原术。一旦你使用此特性施展了前述法术，你将无法再次使用此特性，直到完成一次长休。感知是你在施展这些法术时的关键属性 | K57: 如果你拥有施法或契约魔法职业能力，将以下龙纹法术加入施法职业法术列表中： 1环：神莓术，睡眠术 2环：援助术，安定心神 3环：造粮术，李欧蒙小屋 4环：净化灵光，摩登肯私人密室 5环：圣居 | L57: 当你进行魅力（游说）检定或者使用酿酒工具或厨师工具进行属性检定时，你能掷一个d4，并把结果加到属性检定的结果上 | M57: 你习得戏法魔法伎俩。同时，你能够通过此特性施展净化食粮和隐形仆役。一旦你使用此特性施展了前述法术，你将无法再次使用此特性，直到完成一次长休。魅力是你在施展这些法术时的关键属性 | N57: 你习得戏法德鲁伊伎俩。当你抵达3级时，你能通过本特质释放一次纠缠术，当你完成一次长休后可重获释放次数。当你抵达5级时，你能释放一次荆棘丛生，当你完成一次长休后可重获释放次数。通过本特质释放的这些法术不需要材料成分。感知是你释放这些法术的施法属性 | O57: 对你进行追踪的属性检定具有劣势，并且你在通过由非魔法的植物和灌木丛形成的困难地形时，不需要花费额外移动力 | AE57: 提夫林变体 | AG57: 4 | AH57: 6 | AI57: 格莱西雅 | AJ57: 魅力+2，敏捷+1 | AK57: =AK$52 -> 中型 | AL57: =AL$52 -> 基础步行速度为30尺 | AM57: =AM$52 -> 和炼狱语
A58: 人类 | B58: 技能 | C58: 专长 | D58: 龙纹法术 | E58: 黑暗视觉 | F58: 猎人直觉 | G58: 寻者魔法 | H58: 龙纹法术 | I58: 野性直觉 | J58: 调教能手 | K58: 原始链接 | L58: 它们不过是大了点 | M58: 龙纹法术 | N58: 工匠直觉 | O58: 匠师天赋 | P58: 魔力制造 | Q58: 龙纹法术 | R58: 快递员之速 | S58: 运动直觉 | T58: 魔法通道 | U58: 龙纹法术 | V58: 哨兵直觉 | W58: 哨兵之盾 | X58: 警觉的护卫 | Y58: 森之住民 | Z58: 健步如飞 | AA58: 脚踏实地 | AB58: 跳跃攻击 | AC58: 知识呼吸 | AD58: 威风堂堂 | AE58: 巴尔泽布 | AG58: 7 | AH58: 7 | AI58: 莱维斯图斯 | AJ58: 魅力+2，体质+1 | AK58: =AK$52 -> 中型 | AL58: =AL$52 -> 基础步行速度为30尺 | AM58: =AM$52 -> 和炼狱语
B59: 你获得一项自选的技能作为熟练项 | C59: 你获得一项自选的专长 | D59: 如果你拥有施法或契约魔法职业能力，将以下龙纹法术加入施法职业法术列表中： 1环：妖火，大步奔行 2环：动植物定位术，物件定位术 3环：鹰眼术，植物交谈 4环：预言术，生物定位术 5环：问道自然 | E59: =B53 -> 在微光光照下，你身边60尺内可以视为等同于明亮光照。而在黑暗中，该范围内可视为等同于微光光照。你无法在黑暗中分辨颜色，只能看到有灰度的黑白画面 | F59: 当你进行感知（察觉）或感知（求生）检定时，你能掷一个d4，并把结果加到属性检定的结果上 | G59: 你能通过此特性施展猎人印记法术。从第3级起，你还能施展物件定位术。一旦你使用此特性施展了前述法术，你将无法再次使用此特性，直到完成一次长休。感知是你在施展这些法术时的关键属性 | H59: 如果你拥有施法或契约魔法职业能力，将以下龙纹法术加入施法职业法术列表中： 1环：化兽为友，动物交谈 2环：野兽知觉，安定心神 3环：希望信标，召唤动物 4环：生命灵光，支配野兽 5环：启蒙术 | I59: 当你进行感知（驯兽）或智力（自然）检定时，你能掷一个d4，并把结果加到属性检定的结果上 | J59: 你能够对30英尺（取代通常的5英尺）内的友方动物伙伴或坐骑使用协助动作 | K59: 你能够通过此特性施展化兽为友和动物交谈，且无需材料成分。一旦你使用此特性施展了前述法术，你将无法再次使用此特性，直到完成一次长休。感知是你在施展这些法术时的关键属性 | L59: 当你施展只对动物有效的法术时，该法术同时也能对智力3或以下的怪物生效 | M59: 如果你拥有施法或契约魔法职业能力，将以下龙纹法术加入施法职业法术列表中： 1环：鉴定术，谭森浮碟术 2环：不灭明焰，魔化武器 3环：召唤箭雨，元素武器 4环：鬼斧神工，塑石术 5环：造物术 | N59: 当你用工匠工具进行属性检定时，你能掷一个d4，并把结果加到属性检定的结果上 | O59: 你选择一种工匠工具，获得其熟练项 | P59: 你习得戏法修复术。同时，你能够通过此特性施展魔化武器，当你这么做时，该法术持续1小时，无需专注。一旦你使用此特性施展了前述法术，你将无法再次使用此特性，直到完成一次长休。智力是你在施展这些法术时的关键属性 | Q59: 如果你拥有施法或契约魔法职业能力，将以下龙纹法术加入施法职业法术列表中： 1环：脚底抹油，跳跃术 2环：迷踪步，行动无踪 3环：闪现术，魅影驹 4环：任意门，行动自如 5环：传送法阵 | R59: =J55 -> 基础步行速度提升至35尺 | S59: 当你进行力量（运动）检定或者为了操作或维护陆运载具而进行属性检定时，你能掷一个d4，并把结果加到属性检定的结果上 | T59: 你能够通过此特性施展迷踪步。一旦你使用此特性施展了前述法术，你将无法再次使用此特性，直到完成一次长休。敏捷是你在施展这些法术时的关键属性 | U59: 如果你拥有施法或契约魔法职业能力，将以下龙纹法术加入施法职业法术列表中： 1环：强令对决，虔诚护盾 2环：守护之链，诚实之域 3环：法术反制，防护能量伤害 4环：防死结界，信仰守卫 5环：毕格比之手 | V59: 当你进行感知（洞悉）或感知（察觉）检定时，你能掷一个d4，并把结果加到属性检定的结果上 | W59: 你能够通过此特性施展护盾术，在完成一次长休后，你能再次施展此法术。感知是你在施展这些法术时的关键属性 | X59: 当距离你5尺内的可见生物被攻击命中时，你能以一个反应动作与该生物交换位置，同时你代替该生物被击中。这么做后，你将无法再次使用此特性，直到完成一次长休 | Y59: 你拥有求生的技能熟练项 | Z59: 基础步行速度提升至40尺 | AA59: 当你进行疾冲动作的时候，困难地形不会使用你本回合的额外移动力 | AB59: 如果你本回合对一个生物发动了近战攻击，不论你是否命中，在本回合剩下的行动中你不会引发借机攻击 | AC59: 你获得任意四种技能或者四种工具的熟练 | AD59: 你拥有威吓的技能熟练项 | AE59: 迪斯帕特 | AG59: 8 | AH59: 8 | AI59: 马曼 | AJ59: 魅力+2，智力+1 | AK59: =AK$52 -> 中型 | AL59: =AL$52 -> 基础步行速度为30尺 | AM59: =AM$52 -> 和炼狱语
A60: 龙裔 | B60: 龙族血统 | C60: 吐息武器 | D60: 伤害抗性 | E60: 黑暗视觉 | F60: 盛气凌人 | G60: 黑暗视觉 | H60: 复仇突击 | I60: 吐息武器 | J60: 龙族抗性 | K60: 繁彩防护 | L60: 吐息武器 | M60: 龙族抗性 | N60: 灵能心智 | O60: 宝石之翼 | P60: 吐息武器 | Q60: 龙族抗性 | R60: 金属龙吐息 | S60: 衰弱吐息 | T60: 排斥吐息 | AE60: 菲尔娜 | AG60: 9 | AH60: 9 | AI60: 墨菲斯托菲利斯 | AJ60: 魅力+2，智力+1 | AK60: =AK$52 -> 中型 | AL60: =AL$52 -> 基础步行速度为30尺 | AM60: =AM$52 -> 和炼狱语
B61: 你拥有巨龙的血统。并基于所选龙种，决定你吐息的形式及其他优势特征 | C61: 你可以使用动作呼出破坏性的能量。你的龙族血统决定了吐息的范围、形状以及其伤害类型 使用吐息时，你吐息范围内的每个生物都必须进行一次豁免，其豁免类型取决于你的龙族血统。该豁免的DC等于8+你的体质调整值+你的熟练加值。豁免失败者将受到2d6点伤害。豁免成功则伤害减半。其伤害值在6级时增加到3d6，11级增加到4d6，16级增加到5d6 使用吐息后，你必须完成一次长休或短休后才能再次使用 黑龙血统：你的吐息的范围为30尺长5尺宽、形状为线状，伤害类型为强酸，豁免类型为敏捷 蓝龙血统：你的吐息的范围为30尺长5尺宽、形状为线状，伤害类型为闪电，豁免类型为敏捷 黄铜龙血统：你的吐息的范围为30尺长5尺宽、形状为线状，伤害类型为火焰，豁免类型为敏捷 青铜龙血统：你的吐息的范围为30尺长5尺宽、形状为线状，伤害类型为闪电，豁免类型为敏捷 赤铜龙血统：你的吐息的范围为30尺长5尺宽、形状为线状，伤害类型为强酸，豁免类型为敏捷 金龙血统：你的吐息的范围为15尺、形状为锥状，伤害类型为火焰，豁免类型为敏捷 绿龙血统：你的吐息的范围为15尺、形状为锥状，伤害类型为毒素，豁免类型为体质 红龙血统：你的吐息的范围为15尺、形状为锥状，伤害类型为火焰，豁免类型为敏捷 银龙血统：你的吐息的范围为15尺、形状为锥状，伤害类型为冷冻，豁免类型为体质 白龙血统：你的吐息的范围为15尺、形状为锥状，伤害类型为冷冻，豁免类型为体质 | D61: 你的龙族血统为你带来对某类伤害类型的伤害抗性 黑龙/赤铜龙血统：强酸 蓝龙/青铜龙血统：闪电 黄铜龙/金龙/红龙血统：火焰 绿龙血统：毒素 银龙/白龙血统：冷冻 | E61: =B53 -> 在微光光照下，你身边60尺内可以视为等同于明亮光照。而在黑暗中，该范围内可视为等同于微光光照。你无法在黑暗中分辨颜色，只能看到有灰度的黑白画面 | F61: 当你进行一次魅力（威吓或游说）检定时，你可以获得优势。一旦使用了本特质，直到完成一次短休或长休后你才能再次使用 | G61: =B53 -> 在微光光照下，你身边60尺内可以视为等同于明亮光照。而在黑暗中，该范围内可视为等同于微光光照。你无法在黑暗中分辨颜色，只能看到有灰度的黑白画面 | H61: 当一个生物对你造出伤害时，如果它在你所持用的武器的射程之内，你能用你的反应动作使用该武器对那个生物进行一次攻击。一旦使用了本特质，直到完成一次短休或长休后你才能再次使用 | I61: 你可以使用动作呼出一道30尺长、5尺宽矩形的魔法能量。你的龙族血统决定了吐息的伤害类型 使用吐息时，你吐息范围内的每个生物都必须进行一次敏捷豁免，该豁免的DC等于8+你的体质调整值+你的熟练加值。豁免失败者将受到1D10点伤害。豁免成功则伤害减半。其伤害值在5级时增加到2D10，11级增加到3D10，17级增加到4D10 你可以使用该特性的次数等同于你的熟练加值，你在完成一次长休后重获所有已使用的次数 黑龙血统：强酸 蓝龙血统：闪电 绿龙血统：毒素 红龙血统：火焰 白龙血统：冷冻 | J61: 你的龙族血统为你带来对某类伤害类型的伤害抗性 黑龙血统：强酸 蓝龙血统：闪电 红龙血统：火焰 绿龙血统：毒素 白龙血统：冷冻 | K61: 第5级起，以一个动作你可以引导自己的龙族能量，1分钟内，你对某类伤害类型免疫。在你使用此特性后，你在完成一次长休之前不能再次使用 黑龙血统：强酸 蓝龙血统：闪电 红龙血统：火焰 绿龙血统：毒素 白龙血统：冷冻 | L61: 你可以使用动作呼出一道15尺锥状的魔法能量。你的龙族血统决定了吐息的伤害类型 使用吐息时，你吐息范围内的每个生物都必须进行一次敏捷豁免，该豁免的DC等于8+你的体质调整值+你的熟练加值。豁免失败者将受到1D10点伤害。豁免成功则伤害减半。其伤害值在5级时增加到2D10，11级增加到3D10，17级增加到4D10 你可以使用该特性的次数等同于你的熟练加值，你在完成一次长休后重获所有已使用的次数 紫水晶龙血统：力场 水晶龙血统：光耀 翡翠龙血统：心灵 蓝宝石龙血统：雷鸣 黄玉龙血统：暗蚀 | M61: 你的龙族血统为你带来对某类伤害类型的伤害抗性 紫水晶龙血统：力场 水晶龙血统：光耀 翡翠龙血统：心灵 蓝宝石龙血统：雷鸣 黄玉龙血统：暗蚀 | N61: 你可以与身边30尺内任意你能看见的生物通过心灵感应方式进行交流。你无须懂得该生物的语言也能使其理解你通过心灵感应所传达的话语，但它必须至少会一种语言来理解你传达的信息 | O61: 第5级起，你可以用附赠动作在身上显形一对幽光翅膀，持续1分钟。你在持续时间内获得等同你步行速度的飞行速度，并且可以悬浮。使用此特性后，你在完成一次长休前不能再次使用 | P61: 你可以使用动作呼出一道15尺锥状的魔法能量。你的龙族血统决定了吐息的伤害类型 使用吐息时，你吐息范围内的每个生物都必须进行一次敏捷豁免，该豁免的DC等于8+你的体质调整值+你的熟练加值。豁免失败者将受到1D10点伤害。豁免成功则伤害减半。其伤害值在5级时增加到2D10，11级增加到3D10，17级增加到4D10 你可以使用该特性的次数等同于你的熟练加值，你在完成一次长休后重获所有已使用的次数 黄铜龙血统：火焰 青铜龙血统：闪电 赤铜龙血统：强酸 金龙血统：火焰 银龙血统：冷冻 | Q61: 你的龙族血统为你带来对某类伤害类型的伤害抗性 黄铜龙血统：火焰 青铜龙血统：闪电 赤铜龙血统：强酸 金龙血统：火焰 银龙血统：冷冻 | R61: 第5级起，你可以使用衰弱吐息或排斥吐息，一旦使用了其中一种，直到完成一次长休后你才能再次使用 | S61: 第5级起，你可以使用动作呼出一道15尺锥状的魔法气体。使用吐息时，你吐息范围内的每个生物都必须进行一次体制豁免，该豁免的DC等于8+你的体质调整值+你的熟练加值。豁免失败者将陷入失能，直到你的下个回合开始 | T61: 第5级起，你可以使用动作呼出一道15尺锥状的魔法气体。使用吐息时，你吐息范围内的每个生物都必须进行一次力量豁免，该豁免的DC等于8+你的体质调整值+你的熟练加值。豁免失败者将被推离20尺并倒地 | AE61: 格莱西雅 | AG61: 10 | AH61: 10 | AI61: 扎瑞尔 | AJ61: 魅力+2，力量+1 | AK61: =AK$52 -> 中型 | AL61: =AL$52 -> 基础步行速度为30尺 | AM61: =AM$52 -> 和炼狱语
A62: 侏儒 | B62: 黑暗视觉 | C62: 侏儒狡黠 | D62: 自然幻术师 | E62: 小型野兽交谈 | F62: 工匠学识 | G62: 修补匠 | H62: 发条玩具 | I62: 打火机 | J62: 音乐盒 | K62: 增强黑暗视觉 | L62: 斯涅布力伪装 | M62: 斯涅布力赠礼 | N62: 龙纹法术 | O62: 天才抄写员 | P62: 抄写员的领悟 | AE62: 莱维斯图斯 | AG62: 11 | AH62: 11 | AI62: 阿斯莫 | AJ62: 自选两项属性分别+2/+1或自选三项属性+1 | AK62: 中型或小型。在你选择种族时选择体型 | AL62: 基础步行速度为30尺 | AM62: ，以及任意一门自选语言
B63: =B53 -> 在微光光照下，你身边60尺内可以视为等同于明亮光照。而在黑暗中，该范围内可视为等同于微光光照。你无法在黑暗中分辨颜色，只能看到有灰度的黑白画面 | C63: 你进行对抗魔法的智力、感知和魅力的豁免时具有优势 | D63: 你习得戏法次级幻影。其施法关键属性为智力 | E63: 你可以通过声音和手势与小型或更小的野兽进行简单沟通 | F63: 当你进行关于魔法物品、炼金物品或是工艺元件的智力（历史）检定时，你可以在检定中加上双倍的熟练加值 | G63: 你拥有工匠工具（修理工具）的熟练项。使用这些工具时，你可以花费1小时时间和10gp材料制作一个超小型的发条机械装置（AC5，HP1）。该装置在24小时后将自动停止运作（除非你再花费1小时来修理它让它保持运作），你也可以使用你的动作主动使其停止运作。它停止运作后，你将收回用来制造它的材料。你最多可以同时激活三个这样的装置 | H63: 该玩具是个机械的动物、怪物或人，例如青蛙、老鼠、鸟、龙或者士兵。当被放在地上时，该玩具能在你的回合里随机向一个方向移动5尺。此外该玩具还会模范所模拟生物发出声响 | I63: 该装置可以产生微小的火焰。你可以用它来点蜡烛，火把或营火。使用该装置需要花费动作 | J63: 音乐盒打开时，将以适中的音量奏响固定的一首的歌曲。音乐播放完毕，或音乐盒被关闭时，音乐盒将停止发声 | K63: =I53 -> 你的黑暗视觉感官范围提升至120尺 | L63: 当你进行隐匿检定时，你可以使该次检定具有优势。你可以使用此特质的次数等于你的熟练加值，当你完成一次长休后，你重新获得所有消耗的次数 | M63: 第3级起，你可以用此特质施展一次易容术 第5级起，你可以用此特质施展一次易容术或回避侦测 你必须完成一次长休后才能再次启用该能力。你也可以通过法术位正常施展该特性中的法术，该法术的施法关键属性为智力、感知或魅力并在最初选择种族时决定 当你使用该特质施展这些法术时，无需法术成分 | N63: 如果你拥有施法或契约魔法职业能力，将以下龙纹法术加入施法职业法术列表中： 1环：通晓语言，迷幻手稿 2环：动物信使，沉默术 3环：短讯术，巧言术 4环：秘法眼，困惑术 5环：托梦术 | O63: 你当你进行智力（历史）检定或使用书法工具进行属性检定时，你能掷一个d4，并把结果加到属性检定的结果上 | P63: 你习得戏法传讯术。同时，你能够通过此特性施展通晓语言，在完成一次短休或长休后，你能再次施展此法术。从第3级起，你还能通过此特性施展魔嘴术，在完成一次长休后，你能再次施展此法术。智力是你在施展这些法术时的关键属性 | AE63: 马曼 | AG63: 12 | AH63: 12 | AI63: 费尔伯格人 | AJ63: 自选两项属性分别+2/+1或自选三项属性+1 | AK63: 中型 | AL63: 基础步行速度为30尺 | AM63: ，以及任意一门自选语言
A64: 半精灵 | B64: 黑暗视觉 | C64: 精类血统 | D64: =IF(AND(COUNTIF(AC18:AC21,">=1"),COUNTIF($AB$2:$AB$15,"多才多艺")=0),"","多才多艺") -> 多才多艺 | E64: =IF(OR(AC18<1,COUNTIF($AB$2:$AB$15,"敏锐感官")),"敏锐感官","") -> 敏锐感官 | F64: =IF(OR(AC18<1,COUNTIF($AB$2:$AB$15,"木精灵武器训练")),"木精灵武器训练","") -> 木精灵武器训练 | G64: =IF(OR(AC18<1,COUNTIF($AB$2:$AB$15,"轻捷步伐")),"轻捷步伐","") -> 轻捷步伐 | H64: =IF(OR(AC18<1,COUNTIF($AB$2:$AB$15,"野性面具")),"野性面具","") -> 野性面具 | I64: =IF(OR(AC19<1,COUNTIF($AB$2:$AB$15,"敏锐感官")),"敏锐感官","") -> 敏锐感官 | J64: =IF(OR(AC19<1,COUNTIF($AB$2:$AB$15,"高等精灵武器训练")),"高等精灵武器训练","") -> 高等精灵武器训练 | K64: =IF(OR(AC19<1,COUNTIF($AB$2:$AB$15,"戏法")),"戏法","") -> 戏法 | L64: =IF(OR(AC20<1,COUNTIF($AB$2:$AB$15,"敏锐感官")),"敏锐感官","") -> 敏锐感官 | M64: =IF(OR(AC20<1,COUNTIF($AB$2:$AB$15,"卓尔魔法")),"卓尔魔法","") -> 卓尔魔法 | N64: =IF(OR(AC20<1,COUNTIF($AB$2:$AB$15,"敏锐感官")),"敏锐感官","") -> 敏锐感官 | O64: =IF(OR(AC20<1,COUNTIF($AB$2:$AB$15,"游泳速度")),"游泳速度","") -> 游泳速度 | P64: 龙纹法术 | Q64: 推理直觉 | R64: 魔法侦测 | S64: 龙纹法术 | T64: 驭风者直觉 | U64: 暴风之祝福 | V64: 逆风行事 | AE64: 墨菲斯托菲利斯 | AG64: 13 | AH64: 13 | AI64: 歌利亚 | AJ64: 自选两项属性分别+2/+1或自选三项属性+1 | AK64: 中型 | AL64: 基础步行速度为30尺 | AM64: ，以及任意一门自选语言
B65: =B53 -> 在微光光照下，你身边60尺内可以视为等同于明亮光照。而在黑暗中，该范围内可视为等同于微光光照。你无法在黑暗中分辨颜色，只能看到有灰度的黑白画面 | C65: =D55 -> 你进行对抗魅惑的豁免时具有优势，并且不会因魔法效应而陷入睡眠 | D65: 你获得两项自选技能的熟练项 | E65: =C55 -> 你拥有察觉的技能熟练项 | F65: =F55 -> 你具有长剑、短剑、短弓和长弓的武器熟练项 | G65: =J55 -> 基础步行速度提升至35尺 | H65: =K55 -> 你从树丛，大雨，落雪，雾气或其他自然现象中获得轻度遮蔽时，就可以尝试执行躲藏 | I65: =C55 -> 你拥有察觉的技能熟练项 | J65: =F55 -> 你具有长剑、短剑、短弓和长弓的武器熟练项 | K65: =G55 -> 你掌握一个法师法术列表中自选戏法 | L65: =C55 -> 你拥有察觉的技能熟练项 | M65: =N55 -> 你习得戏法舞光术。达到3级后，你可以每日使用一次法术妖火。达到5级后，你可以每日使用一次法术黑暗术。这些每日施展一次的法术其施法关键属性是魅力。你必须完成一次长休才能再次以该特质施展这些法术 | N65: =C55 -> 你拥有察觉的技能熟练项 | O65: 基础游泳速度为30尺 | P65: 如果你拥有施法或契约魔法职业能力，将以下龙纹法术加入施法职业法术列表中： 1环：侦测善恶，侦测毒性和疾病 2环：侦测思想，寻找陷阱 3环：鹰眼术，回避侦测 4环：秘法眼，预言术 5环：通晓传奇 | Q65: 当你进行智力（调查）或感知（洞悉）检定时，你能够掷一个d4，将结果加到你的属性检定结果中 | R65: 你能够施展侦测魔法与侦测毒性和疾病法术，从3级起，你还能施展识破隐形。一旦你使用此特性施展了前述法术，你将无法再次使用此特性，直到完成一次长休。智力是你在施展这些法术时的关键属性，你无需为这些法术提供材料成分 | S65: 如果你拥有施法或契约魔法职业能力，将以下龙纹法术加入施法职业法术列表中： 1环：羽落术，云雾术 2环：造风术，浮空术 3环：雪雨暴，风墙术 4环：召唤次级元素生物，操控水体 5环：召唤元素生物 | T65: 当你进行敏捷（体操）检定或任何使用领航工具的属性检定时，你能掷一个d4，并把结果加到属性检定的结果上 | U65: 你对闪电伤害具有抗性 | V65: 你习得戏法舞风术。从第3级起，你能够通过此特性施展造风术。一旦你使用此特性施展了前述法术，你将无法再次使用此特性，直到完成一次长休。魅力是你在施展这些法术时的关键属性 | AE65: 扎瑞尔 | AG65: 14 | AH65: 14 | AI65: 天狗 | AJ65: 自选两项属性分别+2/+1或自选三项属性+1 | AK65: 中型 | AL65: 基础步行速度为30尺 | AM65: ，以及任意一门自选语言
A66: 半兽人 | B66: 黑暗视觉 | C66: 凶恶 | D66: 坚韧不屈 | E66: 凶蛮攻击 | F66: 龙纹法术 | G66: 黑暗视觉 | H66: 猎人直觉 | I66: 寻者魔法 | J66: 天生武器 | K66: 凶恶 | L66: 坚韧不屈 | M66: 凶蛮攻击 | AE66: 阿斯莫 | AF66: =AF56+1 -> 10 | AG66: 1 | AH66: =IF(V2<3,4,7) -> 4 | AI66: 蜥蜴人 | AJ66: 自选两项属性分别+2/+1或自选三项属性+1 | AK66: 中型 | AL66: 基础步行速度为30尺 | AM66: ，以及任意一门自选语言
B67: =B53 -> 在微光光照下，你身边60尺内可以视为等同于明亮光照。而在黑暗中，该范围内可视为等同于微光光照。你无法在黑暗中分辨颜色，只能看到有灰度的黑白画面 | C67: 你拥有威吓的技能熟练项 | D67: 当你生命值降至0而没有立即死亡时，可以改为使生命值降至1。此特质生效后必须完成一次长休后才能再次生效 | E67: 使用近战武器攻击造成重击时，你可以额外掷一个该武器的伤害骰，并将其数值加入到重击的额外伤害中 | F67: =D59 -> 如果你拥有施法或契约魔法职业能力，将以下龙纹法术加入施法职业法术列表中： 1环：妖火，大步奔行 2环：动植物定位术，物件定位术 3环：鹰眼术，植物交谈 4环：预言术，生物定位术 5环：问道自然 | G67: =B53 -> 在微光光照下，你身边60尺内可以视为等同于明亮光照。而在黑暗中，该范围内可视为等同于微光光照。你无法在黑暗中分辨颜色，只能看到有灰度的黑白画面 | H67: =F59 -> 当你进行感知（察觉）或感知（求生）检定时，你能掷一个d4，并把结果加到属性检定的结果上 | I67: =G59 -> 你能通过此特性施展猎人印记法术。从第3级起，你还能施展物件定位术。一旦你使用此特性施展了前述法术，你将无法再次使用此特性，直到完成一次长休。感知是你在施展这些法术时的关键属性 | J67: 你头上的弯羊角是一件天生武器，可以用来进行徒手攻击。如果你击中了目标，你造成1d6+你的力量调整值的钝击伤害 | K67: =C67 -> 你拥有威吓的技能熟练项 | L67: =D67 -> 当你生命值降至0而没有立即死亡时，可以改为使生命值降至1。此特质生效后必须完成一次长休后才能再次生效 | M67: =E67 -> 使用近战武器攻击造成重击时，你可以额外掷一个该武器的伤害骰，并将其数值加入到重击的额外伤害中 | AE67: 费尔伯格人 | AF67: =AF66+1 -> 11 | AG67: 1 | AH67: 4 | AI67: 斑猫人 | AJ67: 自选两项属性分别+2/+1或自选三项属性+1 | AK67: 中型或小型。在你选择种族时选择体型 | AL67: 基础步行速度为30尺 | AM67: ，以及任意一门自选语言
A68: 提夫林 | B68: 黑暗视觉 | C68: 炎狱抗性 | D68: =IF(OR(AC22<1,COUNTIF($AB$2:$AB$15,"地狱遗赠")),"地狱遗赠","") -> 地狱遗赠 | E68: =IF(OR(AC22<1,COUNTIF($AB$2:$AB$15,"魔鬼之舌")),"魔鬼之舌","") -> 魔鬼之舌 | F68: =IF(OR(AC22<1,COUNTIF($AB$2:$AB$15,"地狱之火")),"地狱之火","") -> 地狱之火 | G68: =IF(OR(AC22<1,COUNTIF($AB$2:$AB$15,"飞翼")),"飞翼","") -> 飞翼 | H68: 马拉多米尼之遗赠 | I68: 迪斯遗赠 | J68: 福莱格索斯的遗赠 | K68: 马尔伯吉之遗赠 | L68: 斯泰吉亚之遗赠 | M68: 弥瑙洛斯之遗赠 | N68: 卡尼亚遗赠 | O68: 阿弗纳斯之遗赠 | AE68: 歌利亚 | AF68: =AF67+1 -> 12 | AG68: 1 | AH68: 3 | AI68: 梭螺鱼人 | AJ68: 自选两项属性分别+2/+1或自选三项属性+1 | AK68: 中型 | AL68: 基础步行速度为30尺 | AM68: ，以及任意一门自选语言
B69: =B53 -> 在微光光照下，你身边60尺内可以视为等同于明亮光照。而在黑暗中，该范围内可视为等同于微光光照。你无法在黑暗中分辨颜色，只能看到有灰度的黑白画面 | C69: 你对火焰伤害具有抗性 | D69: 你习得戏法奇术。第3级时，你可以每日施展一次二环的炼狱叱喝。第5级时，你可以每日施展一次黑暗术。花费掉的法术次数将在完成一次长休后恢复。与该特质相关的施法关键属性为魅力 | E69: 你习得戏法恶言相加。当你到达3级时，你可以施展一次魅惑人类作为一个二环法术。当你到达5级时，你可以施展一次注目术。你必须完成一次长休息才能再次从这个特性中施展这些法术。魅力是你的施法主属性 | F69: 你习得戏法奇术。第3级时，你可以每日施展一次二环的燃烧之手。第5级时，你可以每日施展一次黑暗术。花费掉的法术次数将在完成一次长休后恢复。与该特质相关的施法关键属性为魅力 | G69: 当你不着装重甲时，你得到30尺飞行速度 | H69: 你习得戏法奇术。第3级时，你可以每日施展一次2环的致病射线。第5级，你可以每日施展一次疯狂冠冕。花费掉的法术次数将在一次长休后恢复。与该特质相关的施法关键属性为魅力 | I69: 你习得戏法奇术。第3级时，你可以每日施展一次易容术。第5级，你可以每日施展一次侦测思想。花费掉的法术次数将在一次长休后恢复。与该特质相关的施法关键属性为魅力 | J69: 你习得戏法交友术。第3级时，你可以每日施展一次2环的魅惑人类。第5级，你可以每日施展一次暗示术。花费掉的法术次数将在一次长休后恢复。与该特质相关的施法关键属性为魅力 | K69: 你习得戏法次级幻影。第3级时，你可以每日施展一次2环的易容术。第5级，你可以每日施展一次隐形术。花费掉的法术次数将在一次长休后恢复。与该特质相关的施法关键属性为魅力 | L69: 你习得戏法冷冻射线。第3级时，你可以每日施展一次2环的艾嘉西斯之铠。第5级，你可以每日施展一次黑暗术。花费掉的法术次数将在一次长休后恢复。与该特质相关的施法关键属性为魅力 | M69: 你习得戏法法师之手。第3级时，你可以施展一次谭森浮碟术，你在一次短休或长休后可以重新施展此法术。第5级，你可以施展一次秘法锁而不需要材料成分，你在一次长休后可以重新施展此法术。与该特质相关的施法关键属性为魅力 | N69: 你习得戏法法师之手。第3级时，你可以每日施展一次2环的燃烧之手。第5级，你可以每日施展一次火焰刀。花费掉的法术次数将在一次长休后恢复。与该特质相关的施法关键属性为魅力 | O69: 你习得戏法奇术。第3级时，你可以每日施展一次2环的炽焰斩。第5级，你可以每日施展一次印记斩。花费掉的法术次数将在一次长休后恢复。与该特质相关的施法关键属性为魅力 | AE69: 天狗 | AF69: =AF68+1 -> 13 | AG69: 1 | AH69: 3 | AI69: 地精 | AJ69: 自选两项属性分别+2/+1或自选三项属性+1 | AK69: 小型 | AL69: 基础步行速度为30尺 | AM69: ，以及任意一门自选语言
A70: 阿斯莫 | B70: 黑暗视觉 | C70: 天界抗力 | D70: 治愈之手 | E70: 光辉掌者 | F70: =IF(OR(AC23<1,COUNTIF($AB$2:$AB$15,"光辉灵魂")),"光辉灵魂","") -> 光辉灵魂 | G70: =IF(OR(AC23<1,COUNTIF($AB$2:$AB$15,"光辉焚化")),"光辉焚化","") -> 光辉焚化 | H70: =IF(OR(AC23<1,COUNTIF($AB$2:$AB$15,"死灵环绕")),"死灵环绕","") -> 死灵环绕 | AE70: 蜥蜴人 | AF70: =AF69+1 -> 14 | AG70: 1 | AH70: 6 | AI70: 熊地精 | AJ70: =AJ69 -> 自选两项属性分别+2/+1或自选三项属性+1 | AK70: 中型 | AL70: =AL$69 -> 基础步行速度为30尺 | AM70: =AM69 -> ，以及任意一门自选语言
B71: =B53 -> 在微光光照下，你身边60尺内可以视为等同于明亮光照。而在黑暗中，该范围内可视为等同于微光光照。你无法在黑暗中分辨颜色，只能看到有灰度的黑白画面 | C71: 你对光耀和黯蚀伤害具有抗性 | D71: 以一个动作，你可以触碰一个生物并使他恢复等同于你熟练加值数量的D4骰的生命值。一旦你使用了这个特性，在下次长休息完成之前你不能再次使用 | E71: 你习得戏法光亮术。其施法关键属性为魅力 | F71: 从3级起，你可以使用一个附赠动作来释放你内在的神圣能量 你的转变持续一分钟或直到你以一个附赠动作中止。在这期间，你得到等同于步行速度的飞行速度，并且每个你的回合中一次，当你的攻击或法术成功造成伤害，你将对一个目标造成等于你熟练加值的额外的光耀伤害 一旦你使用这个特性，在下次长休息完成之前你不能再次使用 | G71: 从3级起，你可以使用一个附赠动作使你体内的神圣能量解除拘束 你的转变持续一分钟或直到你以一个附赠动作中止。在这期间，明亮的光辉会照亮你周围10尺并给予额外10尺的微光照明。并且，每个你的回合结束，你和你周围10尺内的每个生物都将受到等同于你熟练加值的光耀伤害。此外，每个你的回合中一次，当你的攻击或法术成功造成伤害，你将对一个目标造成等于你熟练加值的额外光耀伤害 一旦你使用这个特性，在下次长休息完成之前你不能再次使用 | H71: 从3级起，你可以使用一个动作来解放你内在的腐败力量 在你进行转变的同时，你所指定周围10尺内能看见你的生物必须通过魅力豁免检定（DC=8+你的熟练值+你的魅力调整值），否则直到你的下回合结束之前他们将对你恐惧 你的转变持续一分钟或直到你以一个附赠动作中止。在这期间，每个你的回合中一次，当你的攻击或法术成功造成伤害，你将对一个目标造成等于你熟练加值的额外的黯蚀伤害 一旦你使用这个特性，在下次长休息完成之前你不能再次使用 | AE71: 斑猫人 | AF71: =AF70+1 -> 15 | AG71: 1 | AH71: 5 | AI71: 大地精 | AJ71: =AJ69 -> 自选两项属性分别+2/+1或自选三项属性+1 | AK71: =AK$70 -> 中型 | AL71: =AL$69 -> 基础步行速度为30尺 | AM71: =AM69 -> ，以及任意一门自选语言
A72: 费尔伯格人 | B72: 费尔伯格人魔法 | C72: 神隐步 | D72: 强健体格 | E72: 兽与叶之语 | AE72: 梭螺鱼人 | AF72: =AF71+1 -> 16 | AG72: 1 | AH72: 6 | AI72: 依夏兰 | AJ72: =IF(V3=A44,"魅力+2，感知+1","敏捷+2") -> 敏捷+2 | AK72: =IF(V3=A44,"中型","小型") -> 小型 | AL72: =IF(V3=A44,"基础步行速度为30尺","基础步行速度为25尺") -> 基础步行速度为25尺 | AM72: =IF(V3=A44,"和吸血鬼语","和地精语") -> 和地精语
B73: 你可以用此特质施展一次侦测魔法或易容术 你必须完成一次长休后才能再次启用该能力。你也可以通过法术位正常施展该特性中的法术，该法术的施法关键属性为智力、感知或魅力并在最初选择种族时决定 当你施展这个版本的易容术时，你可以看起来比平时高或矮3尺 | C73: 以一个附赠动作，你能如魔法般变为隐形，直到你的下一回合开始，或者直到你攻击，进行一次伤害骰，或者强迫某人进行一次豁免检定。你可以使用该特质的次数等于你的熟练加值，当你完成一次长休后，你重新获得所有消耗的次数 | D73: 你的负重、推动、拉动及抬起物品的能力视同为体型大一级的生物 | E73: 你有能力以有限的方式与野兽以及植物交流。它们可以理解你的话的意思，虽然你没有特殊的能力来明白它们的回应。你在所有试图影响它们的魅力检定上有优势 | AE73: 地精 | AF73: =AF72+1 -> 17 | AG73: 1 | AH73: =IF(COUNTIF(B18:C18,V4),2,4) -> 4 | AI73: 赞迪卡 | AJ73: =IF(V3=A44,"魅力+2，智力+1","体质+2") -> 体质+2 | AK73: =AK72 -> 小型 | AL73: =AL72 -> 基础步行速度为25尺 | AM73: =AM72 -> 和地精语
A74: 歌利亚 | B74: 小型巨人 | C74: 石之坚韧 | D74: 生于高山 | AE74: 熊地精 | AG74: 5 | AH74: 8 | AI74: 狗头人 | AJ74: 自选两项属性分别+2/+1或自选三项属性+1 | AK74: 小型 | AL74: 基础步行速度为30尺 | AM74: ，以及任意一门自选语言
B75: 你拥有运动的技能熟练项，并且你的负重、推动、拉动及抬起物品的能力视同为体型大一级的生物 | C75: 受到伤害时，你可以用自己的反应骰一次d12，再将骰值加上你的体质调整。你所受的实际伤害将减去该总值 你可以使用此特质的次数等于你的熟练加值，当你完成一次长休后，你重新获得所有消耗的次数 | D75: 你对冷冻伤害具有抗性 | AE75: 大地精 | AG75: 9 | AH75: 10 | AI75: 兽人 | AJ75: 自选两项属性分别+2/+1或自选三项属性+1 | AK75: 中型 | AL75: 基础步行速度为30尺 | AM75: ，以及任意一门自选语言
A76: 天狗 | B76: 复制专家 | C76: 天狗回想 | D76: 拟声 | AE76: 依夏兰 | AG76: =IF(V3=A44,4,11) -> 11 | AH76: =IF(V3=A44,4,11) -> 11 | AI76: 原体蛇人 | AJ76: 自选两项属性分别+2/+1或自选三项属性+1 | AK76: 中型或小型。在你选择种族时选择体型 | AL76: 基础步行速度为30尺 | AM76: ，以及任意一门自选语言
B77: 你可以仿造其他生物的笔迹和工艺。你在为伪造文书和复制现存物体进行的任何检定中获得优势 | C77: 你任选两项技能获得熟练项 此外，当你使用任何你具有熟练的技能进行一次属性检定时，在你投掷d20前，你可以让该检定具有优势。你可以使用这种方式给予自身优势的次数等于你的熟练加值，当你完成一次长休后，你重新获得所有消耗的次数 | D77: 你可以模仿你听到的声音，包括人的嗓音。听到声音的生物需要通过DC为8+你的熟练加值+你的魅力调整值的洞悉检定，若成功将发现是模仿的 | AE77: 赞迪卡 | AG77: =IF(V3=A44,5,12) -> 12 | AH77: =IF(V3=A44,5,12) -> 12 | AI77: 吉斯洋基人 | AJ77: 自选两项属性分别+2/+1或自选三项属性+1 | AK77: 中型 | AL77: 基础步行速度为30尺 | AM77: ，以及任意一门自选语言
A78: 蜥蜴人 | B78: 游泳 | C78: 啃咬 | D78: 屏息 | E78: 天生护甲 | F78: 自然直觉 | G78: 饥渴之喉 | AE78: 狗头人 | AF78: =AF73+1 -> 18 | AG78: 1 | AH78: 5 | AI78: 吉斯泽莱人 | AJ78: 自选两项属性分别+2/+1或自选三项属性+1 | AK78: =AK$77 -> 中型 | AL78: =AL$77 -> 基础步行速度为30尺 | AM78: =AM77 -> ，以及任意一门自选语言
B79: =Q55 -> 你拥有等于步行速度的游泳速度 | C79: 你的尖牙是一件天生武器，可以用来进行徒手攻击。如果你击中了目标，你造成1d6+你的力量调整值的挥砍伤害 | D79: 你能屏住你的呼吸15分钟 | E79: 当你没有穿戴盔甲或穿戴的盔甲给予你的AC较低时，你的AC是13+你的敏捷调整值。你在使用你的天生护甲时，仍能获得盾牌的好处 | F79: 你从以下技能中选择两项获得熟练项：医药、自然、察觉、隐匿或求生 | G79: 在战斗中，你能以一个附赠动作，用你的啃咬攻击做一次特殊攻击，如果攻击命中，造成正常的伤害，同时你获得等同于你熟练加值的临生命值。你可以使用此特质的次数等于你的熟练加值，当你完成一次长休后，你重新获得所有消耗的次数 | AE79: 兽人 | AF79: =AF78+1 -> 19 | AG79: 1 | AH79: 4 | AI79: 人马 | AJ79: 自选两项属性分别+2/+1或自选三项属性+1 | AK79: 中型 | AL79: 基础步行速度为40尺 | AM79: ，以及任意一门自选语言
A80: 斑猫人 | B80: 黑暗视觉 | C80: 攀爬 | D80: 猫之利爪 | E80: 猫之天性 | F80: 猫之迅捷 | AE80: 原体蛇人 | AF80: =AF79+1 -> 20 | AG80: 1 | AH80: 4 | AI80: 牛头人 | AJ80: 自选两项属性分别+2/+1或自选三项属性+1 | AK80: 中型 | AL80: 基础步行速度为30尺 | AM80: ，以及任意一门自选语言
B81: =B53 -> 在微光光照下，你身边60尺内可以视为等同于明亮光照。而在黑暗中，该范围内可视为等同于微光光照。你无法在黑暗中分辨颜色，只能看到有灰度的黑白画面 | C81: 你获得等于你步行速度的攀爬速度 | D81: 你能够以爪子进行徒手攻击。如果你击中了目标，你造成1d6+你的力量调整值的挥砍伤害 | E81: 你拥有察觉和隐匿的技能熟练项 | F81: 当你在战斗中移动时，你可以让你的速度增加一倍，直到回合结束。一旦你使用了这个特性，除非你在你的一个回合移动了0尺，否则你不能再使用它 | AE81: 吉斯人 | AF81: =AF80+1 -> 21 | AG81: 1 | AH81: 1 | AI81: 象族 | AJ81: 体质+2，感知+1 | AK81: 中型 | AL81: 基础步行速度为30尺 | AM81: 和象族语
A82: 梭螺鱼人 | B82: 黑暗视觉 | C82: 游泳 | D82: 两栖 | E82: 控风操水 | F82: 海之使者 | G82: 海渊守卫 | AE82: 吉斯洋基人 | AG82: 2 | AH82: 3 | AI82: 析米克混生体 | AJ82: 体质+2，自选一项其他属性+1 | AK82: 中型 | AL82: 基础步行速度为30尺 | AM82: 和维多肯语或精灵语
B83: =B53 -> 在微光光照下，你身边60尺内可以视为等同于明亮光照。而在黑暗中，该范围内可视为等同于微光光照。你无法在黑暗中分辨颜色，只能看到有灰度的黑白画面 | C83: =Q55 -> 你拥有等于步行速度的游泳速度 | D83: 你能在空气中或水中呼吸 | E83: 你可以用此特质施展一次云雾术 第3级起，你可以用此特质施展一次云雾术或造风术 第5级起，你可以用此特质施展一次云雾术或造风术或水上行走 你必须完成一次长休后才能再次启用该能力。你也可以通过法术位正常施展该特性中的法术，该法术的施法关键属性为智力、感知或魅力并在最初选择种族时决定 | F83: 你可以与具有游泳速度的野兽、元素或怪兽沟通。它们能够理解你的话的意思，虽然你没有特殊的能力来明白它们的回应 | G83: 你对冷冻伤害具有抗性 | AE83: 吉斯泽莱人 | AG83: 4 | AH83: 5 | AI83: 维多肯 | AJ83: 智力+2，感知+1 | AK83: 中型 | AL83: 基础步行速度为30尺 | AM83: 和维多肯语，以及任意一门自选语言
A84: 地精 | B84: 黑暗视觉 | C84: 精类血统 | D84: 小型生物的怒火 | E84: 迅捷逃生 | F84: 长肢 | G84: 强力体格 | H84: 隐秘 | I84: 突袭攻击 | J84: 精类赠礼 | K84: 集众之运 | L84: 灵巧攀爬者 | M84: 砂砾 | AE84: 人马 | AF84: =AF81+1 -> 22 | AG84: 1 | AH84: 5 | AI84: 幻身灵 | AJ84: 自选两项属性分别+2/+1或自选三项属性+1 | AK84: 中型 | AL84: 基础步行速度为30尺 | AM84: ，以及任意一门自选语言
B85: =B53 -> 在微光光照下，你身边60尺内可以视为等同于明亮光照。而在黑暗中，该范围内可视为等同于微光光照。你无法在黑暗中分辨颜色，只能看到有灰度的黑白画面 | C85: 你进行对抗魅惑的豁免时具有优势 | D85: 当你对比你大型的生物使用攻击或魔法，并造成伤害时，你可以对它造成等于你熟练加值的额外伤害 你可以使用此特质的次数等于你的熟练加值，当你完成一次长休后，你重新获得所有消耗的次数。并且你一回合不能使用该特质超过一次 | E85: 你可在自己的回合，以一个附赠动作进行撤离或者躲藏动作 | F85: 当你在你的回合使用近战攻击时，你的触及范围增加5尺 | G85: =D73 -> 你的负重、推动、拉动及抬起物品的能力视同为体型大一级的生物 | H85: 你拥有隐匿的技能熟练项。此外，当你通过或停留在仅供容纳小型生物的空间时不需要挤身 | I85: 如果你的攻击检定命中了一个战斗开始后还没开始过自己回合的生物，这次攻击额外造成2d6伤害 | J85: 你可以使用该特质以一个附赠动作进行协助动作，而你可以使用此特质的次数等于你的熟练加值。当你完成一次长休后，你重新获得所有消耗的次数 第3级起，每当你使用该特质进行协助动作时，从下列选项中选择一项： 好客：你与受你协助的生物都获得等于1d6加你的熟练加值的临时生命值 通行：你与受你协助的生物的步行速度都增加10尺，直到你下一个的回合开始 恶意：直到你下一个的回合开始，当受你协助的生物首次使用攻击检定命中目标，该目标在下一分钟内的下一次攻击检定具有劣势 | K85: 如果你在一次攻击检定没有命中，或是在一次属性检定或豁免检定中失败，你将会获得骰值加值，此次加值的数目等同于你30尺内能见的友方数目（最多+3）。你可以使用此特质的次数等于你的熟练加值，当你完成一次长休后，你重新获得所有消耗的次数 | L85: 你的攀爬速度为25尺，当你身穿中型或重型护甲时你无法使用自己的攀爬速度。（如果你的游戏中使用规则变体：负重，如果你处于重载，你不能使用攀爬速度 | M85: 你对强酸和火焰伤害具有抗性，另外在你不穿护甲时，你的AC为11+你的敏捷加值 | AE85: 牛头人 | AF85: =AF84+1 -> 23 | AG85: 1 | AH85: 4 | AI85: 离梦人 | AJ85: 感知+2，魅力+1 | AK85: 中型 | AL85: 基础步行速度为30尺 | AM85: 和梦族语，以及任意一门自选语言
A86: 狗头人 | B86: 黑暗视觉 | C86: 龙吼 | D86: =IF(OR(AC24<1,COUNTIF($AB$2:$AB$15,"狡猾")),"狡猾","") -> 狡猾 | E86: =IF(OR(AC24<1,COUNTIF($AB$2:$AB$15,"反抗")),"反抗","") -> 反抗 | F86: =IF(OR(AC24<1,COUNTIF($AB$2:$AB$15,"龙族术法")),"龙族术法","") -> 龙族术法 | AE86: 象族 | AF86: =AF85+1 -> 24 | AG86: 1 | AH86: 5 | AI86: 化兽者 | AJ86: 自选两项属性分别+2/+1或自选三项属性+1 | AK86: 中型 | AL86: 基础步行速度为30尺 | AM86: ，以及任意一门自选语言
B87: =B53 -> 在微光光照下，你身边60尺内可以视为等同于明亮光照。而在黑暗中，该范围内可视为等同于微光光照。你无法在黑暗中分辨颜色，只能看到有灰度的黑白画面 | C87: 用一个附赠动作，你向在你周围10尺内的敌人发出吼叫。直到你的下一个回合开始前，你和你的盟友对所有能听见你的敌人进行的攻击检定具有优势。你可以使用此特质的次数等于你的熟练加值，当你完成一次长休后，你重新获得所有消耗的次数 | D87: 你从以下技能中选择一项获得熟练项：奥秘、调查、医药、巧手或求生 | E87: 你进行对抗恐慌的豁免时具有优势 | F87: 你学会一项术士法术列表中的戏法。该法术的施法关键属性为智力、感知或魅力并在最初选择种族时决定 | AE87: 析米克混生体 | AF87: =AF86+1 -> 25 | AG87: 1 | AH87: =IF(V2<5,5,8) -> 5 | AI87: 机关人 | AJ87: 体质+2，自选一项其他属性+1 | AK87: =AK$86 -> 中型 | AL87: =AL$86 -> 基础步行速度为30尺 | AM87: ，以及任意一门自选语言
A88: 兽人 | B88: 黑暗视觉 | C88: 应激冲刺 | D88: 强健体格 | E88: 坚韧不屈 | AE88: 维多肯 | AF88: =AF87+1 -> 26 | AG88: 1 | AH88: 3 | AI88: 阿兰寇拉鹰人 | AJ88: 自选两项属性分别+2/+1或自选三项属性+1 | AK88: 中型 | AL88: 基础步行速度为30尺 | AM88: ，以及任意一门自选语言
B89: =B53 -> 在微光光照下，你身边60尺内可以视为等同于明亮光照。而在黑暗中，该范围内可视为等同于微光光照。你无法在黑暗中分辨颜色，只能看到有灰度的黑白画面 | C89: 你可以用附赠动作进行疾走动作。你可以使用此特质的次数等于你的熟练加值，当你完成一次长休后，你重新获得所有消耗的次数。并且你一回合不能使用该特质超过一次 每当你使用该特质时，你获得等于你熟练加值的临时生命值 | D89: =D73 -> 你的负重、推动、拉动及抬起物品的能力视同为体型大一级的生物 | E89: 当你生命值降至0而没有立即死亡时，可以改为使生命值降至1。此特质生效后必须完成一次长休后才能再次生效 | AE89: 幻身灵 | AF89: =AF88+1 -> 27 | AG89: 1 | AH89: 3 | AI89: 气元素裔 | AJ89: 自选两项属性分别+2/+1或自选三项属性+1 | AK89: 中型或小型。在你选择种族时选择体型 | AL89: 基础步行速度为35尺 | AM89: ，以及任意一门自选语言
A90: 原体蛇人 | B90: 黑暗视觉 | C90: 魔法抗性 | D90: 毒素抗性 | E90: 毒蛇魔法 | AE90: 离梦人 | AF90: =AF89+1 -> 28 | AG90: 1 | AH90: 4 | AI90: 土元素裔 | AJ90: =AJ89 -> 自选两项属性分别+2/+1或自选三项属性+1 | AK90: =AK89 -> 中型或小型。在你选择种族时选择体型 | AL90: 基础步行速度为30尺 | AM90: =AM89 -> ，以及任意一门自选语言
B91: =B53 -> 在微光光照下，你身边60尺内可以视为等同于明亮光照。而在黑暗中，该范围内可视为等同于微光光照。你无法在黑暗中分辨颜色，只能看到有灰度的黑白画面 | C91: 你进行对抗法术的豁免时具有优势 | D91: =C53 -> 你进行对抗中毒的豁免时具有优势，你对毒素伤害具有抗性 | E91: 你学会毒气喷溅 你能无限次施展化兽为友，不过目标只能是蛇 第3级起，你可以用此特质施展一次暗示术 你必须完成一次长休后才能再次启用该能力。你也可以通过法术位正常施展该特性中的法术，该法术的施法关键属性为智力、感知或魅力并在最初选择种族时决定 | AE91: 化兽者 | AF91: =AF90+1 -> 29 | AG91: 1 | AH91: 7 | AI91: 火元素裔 | AJ91: =AJ89 -> 自选两项属性分别+2/+1或自选三项属性+1 | AK91: =AK89 -> 中型或小型。在你选择种族时选择体型 | AL91: =AL$90 -> 基础步行速度为30尺 | AM91: =AM89 -> ，以及任意一门自选语言
A92: 吉斯人 | B92: 心灵抗性 | C92: 星界知识 | D92: 吉斯洋基灵能 | E92: 精神灵术 | F92: 吉斯泽莱灵能 | AE92: 机关人 | AF92: =AF91+1 -> 30 | AG92: 1 | AH92: 4 | AI92: 水元素裔 | AJ92: =AJ89 -> 自选两项属性分别+2/+1或自选三项属性+1 | AK92: =AK89 -> 中型或小型。在你选择种族时选择体型 | AL92: =AL$90 -> 基础步行速度为30尺 | AM92: =AM89 -> ，以及任意一门自选语言
B93: 你对心灵伤害具有抗性 | C93: 当你结束长休时，你能够获得一项你未拥有的技能熟练项及一项武器或工具熟练项，直到你完成下次长休 | D93: 你学会法师之手，当你使用该特质施展该戏法时，这只手是隐形的 第3级起，你可以用此特质施展一次跳跃术 第5级起，你可以用此特质施展一次跳跃术或迷踪步 你必须完成一次长休后才能再次启用该能力。你也可以通过法术位正常施展该特性中的法术，该法术的施法关键属性为智力、感知或魅力并在最初选择种族时决定 当你使用该特质施展这些法术时，无需法术成分 | E93: 你进行对抗魅惑和恐慌的豁免时具有优势 | F93: 你学会法师之手，当你使用该特质施展该戏法时，这只手是隐形的 第3级起，你可以用此特质施展一次护盾术 第5级起，你可以用此特质施展一次护盾术或侦测思想 你必须完成一次长休后才能再次启用该能力。你也可以通过法术位正常施展该特性中的法术，该法术的施法关键属性为智力、感知或魅力并在最初选择种族时决定 当你使用该特质施展这些法术时，无需法术成分 | AE93: 阿兰寇拉鹰人 | AF93: =AF92+1 -> 31 | AG93: 1 | AH93: =IF(V2<3,2,3) -> 2 | AI93: 龟人 | AJ93: 自选两项属性分别+2/+1或自选三项属性+1 | AK93: 中型 | AL93: 基础步行速度为30尺 | AM93: ，以及任意一门自选语言
A94: 人马 | B94: 精类生物 | C94: 冲锋 | D94: 蹄击 | E94: 马体构造 | F94: 自然亲和 | AE94: 元素裔 | AF94: =AF93+1 -> 32 | AG94: 1 | AH94: 1 | AI94: 佛丹人 | AJ94: 体质+1，魅力+2 | AK94: 1-4级为小型，5级后为中型 | AL94: 基础步行速度为30尺 | AM94: 和地精语，以及任意一门自选语言
B95: 你的生物类型是精类，而非类人 | C95: 如果你向着目标直线移动了至少30尺，并在同一轮内以近战武器攻击命中了目标，你可以紧跟着此次攻击使用附赠动作，使用你的马蹄攻击此目标 | D95: 你的马蹄视作天生近战武器，你可以用来做徒手攻击。如果你以蹄击中目标，将造成1d6+力量调整值的钝击伤害 | E95: 在决定你的载重与推拉抬极限时，视你为大一级的体型。另外，因为你的马腿，任何需要手脚并用的攀爬对你而言尤其困难。当你进行这样的攀爬时，每移动1尺需要花费额外4尺移动力，而非额外1尺 | F95: 你从以下技能中选择一项获得熟练项：驯兽、医药、自然或求生 | AE95: 气元素裔 | AG95: 2 | AH95: 4 | AI95: 狮族 | AJ95: 体质+2，力量+1 | AK95: 中型 | AL95: 基础步行速度为35尺 | AM95: 和狮族语
A96: 牛头人 | B96: 角击 | C96: 猛抵冲撞 | D96: 角锤 | E96: 迷宫追忆 | AE96: 土元素裔 | AG96: 5 | AH96: 6 | AI96: 半羊人 | AJ96: 自选两项属性分别+2/+1或自选三项属性+1 | AK96: 中型 | AL96: 基础步行速度为35尺 | AM96: ，以及任意一门自选语言
B97: 你的角是天生近战武器，你可以用它进行徒手攻击。当你以角击中目标时，将造成1d6+力量调整值的穿刺伤害 | C97: 在你于你的回合中使用疾走动作，并至少移动了20尺之后，你可以立即以附赠动作用你的角击进行一次近战攻击 | D97: 在你于你的回合中以近战武器攻击作为攻击动作的一部分击中一个生物后，你可以使用一个附赠动作尝试以角推撞之。目标生物不能比你大超过一级体型，并且需要在你5尺之内。目标必须进行一次难度等级为8+你的熟练加值+你的力量调整值的力量豁免检定，若其失败，你将其推离你10尺 | E97: 你总是能知道哪个方向是北方， 同时你在任何为导航和追踪所进行的求生检定具有优势 | AE97: 火元素裔 | AG97: 7 | AH97: 8 | AI97: 半血裔 | AJ97: 自选两项属性分别+2/+1或自选三项属性+1 | AK97: 中型或小型。在你获得该族系时选择体型 | AL97: 基础步行速度为35尺 | AM97: ，以及任意一门自选语言
A98: 象族 | B98: 身强体壮 | C98: 象之宁静 | D98: 天生护甲 | E98: 象鼻 | F98: 敏锐嗅觉 | AE98: 水元素裔 | AG98: 9 | AH98: 12 | AI98: 巫咒之子 | AJ98: 自选两项属性分别+2/+1或自选三项属性+1 | AK98: 中型或小型。在你获得该族系时选择体型 | AL98: 基础步行速度为30尺 | AM98: ，以及任意一门自选语言
B99: =D73 -> 你的负重、推动、拉动及抬起物品的能力视同为体型大一级的生物 | C99: 你进行对抗恐慌和魅惑的豁免时具有优势 | D99: 当你没有穿戴盔甲或穿戴的盔甲给予你的AC较低时，你的AC是12+你的体质调整值。你在使用你的天生护甲时，仍能获得盾牌的好处 | E99: 你可以用你的象鼻抓取物品，你也可以把它作为通气孔，它具有五尺的触及并可以举起等同你力量值5倍磅数的物品。你可以用它来完成以下简单的任务：抬起，放下，握住，推一个物品或一个生物；打开或关上一扇门或一个容器，擒抱某人或进行徒手击打 你的象鼻不能使用武器或盾牌或任何需要手动操作的事情，比如使用工具或魔法物品或作为一个法术的姿势成分 | F99: 仰仗你敏感的鼻子，你在依赖嗅觉进行的感知（察觉），感知（求生）和智力（调查）检定上具有优势 | AE99: 龟人 | AF99: =AF94+1 -> 33 | AG99: 1 | AH99: 5 | AI99: 重生者 | AJ99: 自选两项属性分别+2/+1或自选三项属性+1 | AK99: 中型或小型。在你获得该族系时选择体型 | AL99: 基础步行速度为30尺 | AM99: ，以及任意一门自选语言
A100: 析米克混生体 | B100: 黑暗视觉 | C100: 动物强化 | D100: =IF(OR(AD19+AD21<IF(V2>=5,2,1),COUNTIF($AB$2:$AB$15,"蝠鲼滑翔")),"蝠鲼滑翔","") -> 蝠鲼滑翔 | E100: =IF(OR(AD19+AD21<IF(V2>=5,2,1),COUNTIF($AB$2:$AB$15,"灵活攀登")),"灵活攀登","") -> 灵活攀登 | F100: =IF(OR(AD19+AD21<IF(V2>=5,2,1),COUNTIF($AB$2:$AB$15,"水下适应")),"水下适应","") -> 水下适应 | G100: =IF(OR(AND(AD21<1,AD19+AD21<2),COUNTIF($AB$2:$AB$15,"斗殴附件")),"斗殴附件","") -> 斗殴附件 | H100: =IF(OR(AND(AD21<1,AD19+AD21<2),COUNTIF($AB$2:$AB$15,"甲壳")),"甲壳","") -> 甲壳 | I100: =IF(OR(AND(AD21<1,AD19+AD21<2),COUNTIF($AB$2:$AB$15,"酸液喷吐")),"酸液喷吐","") -> 酸液喷吐 | AE100: 佛丹人 | AF100: =AF99+1 -> 34 | AG100: 1 | AH100: 4 | AI100: 枭人 | AJ100: 自选两项属性分别+2/+1或自选三项属性+1 | AK100: 中型或小型。在你选择种族时选择体型 | AL100: 基础步行速度为30尺 | AM100: =AM$20 -> ，以及任意一门自选语言
...

Sheet 职业数据
B1: 流派 | C1: PHB | D1: DMG | E1: SCAG | F1: XGE | G1: GTR | H1: EGtW | I1: MOT | J1: TCE | K1: VRGR | L1: FTD | N1: MOD | U1: 通用特性 | V1: 生命骰 | W1: 护甲熟练项 | X1: 武器熟练项 | Y1: 工具熟练项 | Z1: 豁免熟练项 | AA1: 技能熟练项 | AB1: 属性值提升 | AC1: 兼职护甲熟练项 | AD1: 兼职武器熟练项 | AE1: 兼职工具熟练项 | AF1: 兼职技能熟练项 | AG1: 职业等级 | AH1: 施法等级 | AI1: 兼职1条件 | AJ1: 兼职2条件 | AK1: 子职标记 | AL1: 备选 | AM1: 职业 | AN1: 列 | AO1: 最小行 | AP1: 最大行 | AQ1: 职业1特性 | AU1: 职业2特性 | AY1: 职业3特性 | BC1: 职业特性 | BE1: 待选特性 | BG1: 已选特性 | BJ1: 野兽道途起源 | BK1: 遗物 | BL1: 圣域 | BM1: 星辰结社星图样式 | BN1: 花招 | BO1: 姿态 | BP1: 命流宗命流面具 | BQ1: 圣武士克星 | BR1: 物品（临时武器） | BS1: 集群守卫集群外观 | BT1: 妖精漫游者精野之赐 | BU1: 术士反应 | BV1: 幽影术士异闻 | BW1: 畸变心智异常起源 | BX1: 时械之魂秩序显迹 | BY1: 巨灵宗主巨灵器皿 | BZ1: 炼金师实验性灵药 | CA1: 龙兽守卫起源 | CB1: 神龙宗起源
A2: 野蛮人 | B2: 狂战士道途 | C2: 图腾武者道途 | D2: =IF(综合数据!B5=TRUE,"战狂道途","") -> 战狂道途 | E2: =IF(综合数据!B7=TRUE,"先祖守卫道途","") -> 先祖守卫道途 | F2: =IF(综合数据!B7=TRUE,"风暴先驱道途","") -> 风暴先驱道途 | G2: =IF(综合数据!B7=TRUE,"狂热者道途","") -> 狂热者道途 | H2: =IF(综合数据!B14=TRUE,"狂野魔法道途","") -> 狂野魔法道途 | I2: =IF(综合数据!B14=TRUE,"野兽道途","") -> 野兽道途 | U2: 野蛮人 | V2: D12 | W2: 轻甲、中甲、盾牌 | X2: 简易武器、军用武器 | Z2: 力量、体质 | AA2: 从驯兽、运动、威吓、自然、察觉和求生中选择两项 | AB2: 4、8、12、16、19 | AC2: 盾牌 | AD2: 简易武器、军用武器 | AG2: =IFERROR(VLOOKUP(U2,$AC$16:$AE$18,3,0),0) -> 0 | AI2: =IF(AND(SUM(主要!I14:M14)>=13,$AC$16<>0,$AC$16<>$A2,主要!Y3-主要!Y4>=1),$A2,"") | AJ2: =IF(AND($AC$17<>0,$AC$17<>$A2,AI2<>"",主要!Y3-主要!Y4-主要!Y6>=1),$A2,"") | AK2: =IF(AG2>=3,1,"") | AL2: 子职1 | AM2: 野蛮人 | AN2: 1 | AO2: 1 | AP2: =IF($AG$2=20,15,IF($AG$2>=18,14,IF($AG$2>=15,13,IF($AG$2>=11,12,IF($AG$2>=9,11,IF($AG$2>=7,10,IF($AG$2>=5,8,IF($AG$2>=3,6,IF($AG$2>=2,4,IF($AG$2>=1,2,0)))))))))) -> 0 | AR2: 列 | AS2: 最小行 | AT2: 最大行 | AV2: 列 | AW2: 最小行 | AX2: 最大行 | AZ2: 列 | BA2: 最小行 | BB2: 最大行 | BC2: =VLOOKUP(主要!$B$82,$AC$16:$AF$18,4,0)*4-2 -> #N/A | BD2: =VLOOKUP(主要!$B$82,$AC$16:$AF$18,4,0)*4-1 -> #N/A | BE2: =IFERROR(IF(COUNTIF($BG$2:$BG$46,BC4),"",BC4),"") | BF2: {=INDEX(BE:BE,SMALL(IF($BE$2:$BE$143<>"",ROW($2:$143),144),ROW(BE1)))&""} | BG2: =IF(主要!C84="",0,主要!C84) -> 生命骰 | BH2: =IFERROR(VLOOKUP($BG2,$BC$4:$BD$143,2,0),"") -> 1× | BI2: =IF($BG2=0,"",COUNTIF($BG$2:$BG$46,$BG2)) -> 1 | BJ2: 你的生父或生母患有兽化症，你也遗传了这方面的一些诅咒。 | BK2: 圣人腿骨制成的手杖。（50GP） | BL2: 一块充当公园的墓地。 | BM2: 一幅布满星座图列的卷轴 | BN2: 你是一位假摔大师，通过假装已经因为伤势丧失作战能力挑逗敌人来补刀，你不但可以保护队友，还可以让敌人见识你其实还剩下多少战斗力。 | BO2: 失禁老人式：站直，双膝并拢。（极为适宜在排长队时保命） | BP2: 渡鸦 | BQ2: 一个强大的兽人酋长，威胁要超越并摧毁你的一切。 | BR2: 一个烤巨鸟腿。（巨棒，如有断骨则为长剑） | BS2: 群聚的昆虫 | BT2: 在你进行长休或短休时，缥缈的蝴蝶在你周身振翅。 | BU2: 的力量被你周围的人视为一种巨大的祝福，你也被期望用它们来为身边人服务。 | BV2: 你摸起来一直是冰冷的。 | BW2: 你曾暴露在遥远国度扭曲的影响之下。你坚信着有触须在你身上生长，但其他人都看不到。 | BX2: 幽灵般的虚幻齿轮在你身后旋转。 | BY2: 油灯 | BZ2: 治疗。饮用者恢复2d4+你智力调整值的生命值。 | CA2: 你通过研究龙的鳞片或爪子，或一件从龙的宝库里找到的饰品，从这些徽记物上获取了残留的龙族魔法，构成了联结 | CB2: 你通过观察巨龙并将自己的气与它们改天换地的力量相调谐来磨练自己的技艺。
A3: 吟游诗人 | B3: 逸闻学院 | C3: 勇气学院 | D3: =IF(综合数据!B7=TRUE,"迷惑学院","") -> 迷惑学院 | E3: =IF(综合数据!B7=TRUE,"剑舞学院","") -> 剑舞学院 | F3: =IF(综合数据!B7=TRUE,"低语学院","") -> 低语学院 | G3: =IF(综合数据!B13=TRUE,"雄辩学院","") -> 雄辩学院 | H3: =IF(综合数据!B14=TRUE,"创造学院","") -> 创造学院 | I3: =IF(综合数据!B15=TRUE,"精魂学院","") -> 精魂学院 | U3: 吟游诗人 | V3: D8 | W3: 轻甲 | X3: 简易武器、手弩、长剑、刺剑、短剑 | Y3: 自选三种乐器 | Z3: 敏捷、魅力 | AA3: 自选三项技能 | AB3: =AB2 -> 4、8、12、16、19 | AC3: 轻甲 | AE3: 自选一种乐器 | AF3: ，再自选一项技能 | AG3: =IFERROR(VLOOKUP(U3,$AC$16:$AE$18,3,0),0) -> 0 | AH3: =AG3 -> 0 | AI3: =IF(AND(SUM(主要!I19:M19)>=13,$AC$16<>0,$AC$16<>$A3,主要!Y3-主要!Y4>=1),$A3,"") | AJ3: =IF(AND($AC$17<>0,$AC$17<>$A3,AI3<>"",主要!Y3-主要!Y4-主要!Y6>=1),$A3,"") | AK3: =IF(AG3>=2,2,"") | AL3: {=INDEX(AI:AI,SMALL(IF($AI$18:$AI$35<>"",ROW($18:$35),36),ROW(AI1)))&""} -> #N/A | AM3: 狂战士道途 | AO3: 16 | AP3: =IF($AG$2>=14,19,IF($AG$2>=10,18,IF($AG$2>=6,17,IF($AG$2>=3,16,0)))) -> 0 | AQ3: =VLOOKUP(AC16,AM:AN,2,0) -> #N/A | AR3: =AQ3*2 -> #N/A | AS3: 1 | AT3: =VLOOKUP(AC16,AM:AP,4,0) -> #N/A | AU3: =VLOOKUP(AC17,AM:AN,2,0) -> #N/A | AV3: =AU3*2 -> #N/A | AW3: 1 | AX3: =VLOOKUP(AC17,AM:AP,4,0) -> #N/A | AY3: =VLOOKUP(AC18,AM:AN,2,0) -> #N/A | AZ3: =AY3*2 -> #N/A | BA3: 1 | BB3: =VLOOKUP(AC18,AM:AP,4,0) -> #N/A | BC3: 名称 | BD3: 描述 | BE3: =IFERROR(IF(COUNTIF($BG$2:$BG$46,BC5),"",BC5),"") | BF3: {=INDEX(BE:BE,SMALL(IF($BE$2:$BE$143<>"",ROW($2:$143),144),ROW(BE2)))&""} | BG3: =IF(主要!C85="",0,主要!C85) -> 护甲熟练项 | BH3: =IFERROR(VLOOKUP($BG3,$BC$4:$BD$143,2,0),"") | BI3: =IF($BG3=0,"",COUNTIF($BG$2:$BG$46,$BG3)) -> 1 | BJ3: 你是一位大德鲁伊的后人并且继承了变形部分躯体的能力。 | BK3: 自助放纵工具包。（10GP） | BL3: 一座用来展示进口珍惜动植物的博物馆。 | BM3: 一块钻有细孔的石板 | BN3: 你腰包里随身会装一小袋盐或沙子，只要能让你的对手目盲，哪怕一瞬间，你也基本就要赢了。 | BO3: 腐臭蝰蛇式：平躺在地上。（试图躲藏时堪称完美） | BP3: 黑白 | BQ3: 一个恶魔或天族，外层位面力量的代理人，你被指名受其腐败或救赎，视情况而定。 | BR3: 一长条放干的面包。（硬头锤） | BS3: 微小的枯枝怪 | BT3: 每天黎明，新鲜的、当季的花朵将在你的头发中生长。 | BU3: 你的力量在他们变得明显的时候造成了毁灭，甚至死亡，你被当作罪犯对待。 | BV3: 当你熟睡时看上去没有呼吸。（尽管你需要呼吸来维生。） | BW3: 一阵来自星界的灵能之风将心灵异能灌入你的体内。现在，当你使用这股力量时，你的身边会有微弱的光点闪烁。 | BX3: 时钟的指针出现在你的眼中。 | BY3: 瓮 | BZ3: 疾速。饮用者在1小时内速度增加10尺。 | CA3: 一个专门收集和保护龙族学问的游侠会社向你传授了他们的道途。 | CB3: 一位巨龙主动地帮助你修炼自身的能量。
A4: 牧师 | B4: 知识领域 | C4: 生命领域 | D4: 光明领域 | E4: 自然领域 | F4: 风暴领域 | G4: 诡术领域 | H4: 战争领域 | I4: =IF(综合数据!B3=TRUE,"死亡领域","") -> 死亡领域 | J4: =IF(综合数据!B5=TRUE,"奥秘领域","") -> 奥秘领域 | K4: =IF(综合数据!B7=TRUE,"锻造领域","") -> 锻造领域 | L4: =IF(综合数据!B7=TRUE,"坟墓领域","") -> 坟墓领域 | M4: =IF(综合数据!B9=TRUE,"秩序领域","") -> 秩序领域 | N4: =IF(综合数据!B14=TRUE,"和平领域","") -> 和平领域 | O4: =IF(综合数据!B14=TRUE,"暮光领域","") -> 暮光领域 | P4: =IF(综合数据!B19=TRUE,"团结领域","") | Q4: =IF(综合数据!B19=TRUE,"力量领域","") | R4: =IF(综合数据!B19=TRUE,"野心领域","") | S4: =IF(综合数据!B19=TRUE,"热忱领域","") | U4: 牧师 | V4: D8 | W4: 轻甲、中甲、盾牌 | X4: 简易武器 | Z4: 感知、魅力 | AA4: 从历史、洞悉、医药、游说和宗教中选择两项 | AB4: =AB2 -> 4、8、12、16、19 | AC4: 轻甲、中甲、盾牌 | AG4: =IFERROR(VLOOKUP(U4,$AC$16:$AE$18,3,0),0) -> 0 | AH4: =AG4 -> 0 | AI4: =IF(AND(SUM(主要!I18:M18)>=13,$AC$16<>0,$AC$16<>$A4,主要!Y3-主要!Y4>=1),$A4,"") | AJ4: =IF(AND($AC$17<>0,$AC$17<>$A4,AI4<>"",主要!Y3-主要!Y4-主要!Y6>=1),$A4,"") | AK4: 3 | AL4: {=INDEX(AI:AI,SMALL(IF($AI$18:$AI$35<>"",ROW($18:$35),36),ROW(AI2)))&""} -> #N/A | AM4: 图腾武者道途 | AO4: 20 | AP4: =IF($AG$2>=14,39,IF($AG$2>=10,33,IF($AG$2>=6,32,IF($AG$2>=3,26,0)))) -> 0 | AR4: =AR3-1 -> #N/A | AS4: =VLOOKUP(AD16,AM:AO,3,0) -> #N/A | AT4: =IF(AD19=0,0,VLOOKUP(AD16,AM:AP,4,0)) -> 0 | AV4: =AV3-1 -> #N/A | AW4: =VLOOKUP(AD17,AM:AO,3,0) -> #N/A | AX4: =IF(AD20=0,0,VLOOKUP(AD17,AM:AP,4,0)) -> #N/A | AZ4: =AZ3-1 -> #N/A | BA4: =VLOOKUP(AD18,AM:AO,3,0) -> #N/A | BB4: =IF(AD21=0,0,VLOOKUP(AD18,AM:AP,4,0)) -> #N/A | BC4: 生命骰 | BD4: =IF(AC16>0,AE16&"×"&AS6,"")&IF(AC17>0,"＋"&AE17&"×"&AW6,"")&IF(AC18>0,"＋"&AE18&"×"&BA6,"") -> 1× | BE4: =IFERROR(IF(COUNTIF($BG$2:$BG$46,BC6),"",BC6),"") | BF4: {=INDEX(BE:BE,SMALL(IF($BE$2:$BE$143<>"",ROW($2:$143),144),ROW(BE3)))&""} | BG4: =IF(主要!C86="",0,主要!C86) -> 武器熟练项 | BH4: =IFERROR(VLOOKUP($BG4,$BC$4:$BD$143,2,0),"") | BI4: =IF($BG4=0,"",COUNTIF($BG$2:$BG$46,$BG4)) -> 1 | BJ4: 一只精类的精魂赐予你变换不同野兽形态的能力。 | BK4: 圣水酿造啤酒。（20GP） | BL4: 一块不适合建设的沼泽地，充斥着沼泽生物群落。 | BM4: 一张斑点枭熊皮，标有凸痕记号 | BN4: 你在战斗开始时会先用副手攻击，诱骗你的对手将攻击和防御都放在那边，然后瞅准时机迅速换成主手，让你的敌人猝不及防。 | BO4: 沉重补丁式：摊成烂泥。（当你想假装喝多了时很有用） | BP4: 哭脸 | BQ4: 一条龙，它的仆人缠住了你，阻碍你的步伐。 | BR4: 一件只剩一根弦的乐器。（短弓） | BS4: 飞舞的群鸟 | BT4: 你身上有淡淡的肉桂、薰衣草或肉豆蔻，或另一种令人舒适的药草或香料的香味。 | BU4: 你的邻居憎恨你，害怕你的力量，他们离你躲得远远的。 | BV4: 你很少流血，即使受了重伤。 | BW4: 你曾受到底栖魔鱼的支配，它的力量在你的脑海中留下了一个精神碎片。 | BX4: 你的皮肤发出如黄铜般的金属光泽。 | BY4: 可装东西的戒指 | BZ4: 韧性。饮用者在10分钟内AC+1。 | CA4: 一条龙给了你一枚晶球或宝石，并让你进行照看，你没想到的是，龙兽从这块石头里孵化了出来。 | CB4: 你所在修道院的教义可追溯到百年甚至数百年前一只巨龙的指导，或某位献身于龙神的存在。
A5: 德鲁伊 | B5: 大地结社 | C5: 月亮结社 | D5: =IF(综合数据!B7=TRUE,"梦境结社","") -> 梦境结社 | E5: =IF(综合数据!B7=TRUE,"牧人结社","") -> 牧人结社 | F5: =IF(综合数据!B9=TRUE,"孢子结社","") -> 孢子结社 | G5: 星辰结社 | H5: 野火结社 | U5: 德鲁伊 | V5: D8 | W5: 轻甲、中甲、盾牌（不能装备或使用金属质的护甲和盾） | X5: 短棒、匕首、飞镖、标枪、硬头锤、长棍、弯刀、镰刀、投石索、矛 | Y5: 草药工具 | Z5: 智力、感知 | AA5: 从奥秘、驯兽、洞悉、医药、自然、察觉、宗教和求生中选择两项 | AB5: =AB2 -> 4、8、12、16、19 | AC5: 轻甲、中甲、盾牌（不使用铁质护甲或盾牌） | AG5: =IFERROR(VLOOKUP(U5,$AC$16:$AE$18,3,0),0) -> 0 | AH5: =AG5 -> 0 | AI5: =IF(AND(SUM(主要!I18:M18)>=13,$AC$16<>0,$AC$16<>$A5,主要!Y3-主要!Y4>=1),$A5,"") | AJ5: =IF(AND($AC$17<>0,$AC$17<>$A5,AI5<>"",主要!Y3-主要!Y4-主要!Y6>=1),$A5,"") | AK5: =IF(AG5>=2,4,"") | AL5: {=INDEX(AI:AI,SMALL(IF($AI$18:$AI$35<>"",ROW($18:$35),36),ROW(AI3)))&""} -> #N/A | AM5: 战狂道途 | AO5: 40 | AP5: =IF($AG$2>=14,43,IF($AG$2>=10,42,IF($AG$2>=6,41,IF($AG$2>=3,40,0)))) -> 0 | AQ5: 序号 | AR5: 名称 | AS5: 描述 | AT5: 增值 | AU5: 序号 | AV5: 名称 | AW5: 描述 | AX5: 增值 | AY5: 序号 | AZ5: 名称 | BA5: 描述 | BB5: 增值 | BC5: 护甲熟练项 | BD5: =IF(COUNTIF(AS7,"全部*"),"全部护甲",IF(COUNTIF(AS7:BA7,"*中甲*"),"轻甲、中甲",IF(COUNTIF(AS7:BA7,"*轻甲*"),"轻甲","")))&IF(COUNTIF(AS7:BA7,"*盾牌*"),IF(COUNTIF(AS7:BA7,"*甲*"),"、","")&"盾牌","")&IF(COUNTIF(AS7:BA7,"*金属*"),"（不能装备或使用金属质的护甲和盾）","") | BE5: =IFERROR(IF(COUNTIF($BG$2:$BG$46,BC7),"",BC7),"") | BF5: {=INDEX(BE:BE,SMALL(IF($BE$2:$BE$143<>"",ROW($2:$143),144),ROW(BE4)))&""} | BG5: =IF(主要!C87="",0,主要!C87) -> 工具熟练项 | BH5: =IFERROR(VLOOKUP($BG5,$BC$4:$BD$143,2,0),"") | BI5: =IF($BG5=0,"",COUNTIF($BG$2:$BG$46,$BG5)) -> 1 | BJ5: 一只上古野兽的精魂住在你的体内，为你打开选择此道途的大门。 | BK5: 梵天神侍羽翼制作的书签。（10GP） | BL5: 一片居住着树栖动物的大树林。 | BM5: 一套黑檀木封皮地图集 | BN5: 诅咒、谩骂、侮辱，你是一样不落，你喷向对手的那堆下流脏话，即使让食人魔蛮子都觉得尴尬。 | BO5: 受惊侏儒式：蜷缩成胎儿的样子。（非常适合用于遭到巨大伤害之前） | BP5: 笑脸 | BQ5: 大祭司将你看作误入歧途的愚昧之徒，想要你放弃你的信仰。 | BR5: 一只流行运动中用到的球拍。（手斧或战斧） | BS5: 好动的皮克精 | BT5: 你的影子会在没人直视它时起舞。 | BU5: 你开始注意到有一个邪恶的邪教组织，他们计划着利用你的能力。 | BV5: 你的心脏一分钟才脉动一下，有时候你自己都感到吃惊。 | BW5: 你被植入了一只夺心魔蝌蚪，但蜕变一直没能完成。现在，其灵能力已经被你占为已有。当你使用灵能时，你的身体里会冒出奇怪的粘液。 | BX5: 你的体表浮动着方程式和几何图形。 | BY5: 被塞住的瓶子 | BZ5: 勇气。饮用者在1分钟内，能够在每个攻击检定和豁免检定中增加一个d4。 | CA5: 你吞下了几滴龙血，永远给你的自然魔法注入了龙的力量。 | CB5: 你在一个远古巨龙巢穴的影响范围内冥想良久，并凭此吸收了环境中的魔力。
A6: 战士 | B6: 勇士 | C6: 战斗大师 | D6: 奥法骑士 | E6: =IF(综合数据!B5=TRUE,"紫龙骑士","") -> 紫龙骑士 | F6: =IF(综合数据!B7=TRUE,"魔射手","") -> 魔射手 | G6: =IF(综合数据!B7=TRUE,"骑兵","") -> 骑兵 | H6: =IF(综合数据!B7=TRUE,"武士","") -> 武士 | I6: =IF(综合数据!B11=TRUE,"回音骑士","") -> 回音骑士 | J6: =IF(综合数据!B14=TRUE,"符文骑士","") -> 符文骑士 | K6: =IF(综合数据!B14=TRUE,"灵能武士","") -> 灵能武士 | U6: 战士 | V6: D10 | W6: 全部护甲、盾牌 | X6: 简易武器、军用武器 | Z6: 力量、体质 | AA6: 从体操、驯兽、运动、历史、洞悉、威吓、察觉和求生中选择两项 | AB6: 4、6、8、12、14、16、19 | AC6: 轻甲、中甲、盾牌 | AD6: 简易武器、军用武器 | AG6: =IFERROR(VLOOKUP(U6,$AC$16:$AE$18,3,0),0) -> 0 | AH6: =IF(AND(COUNTIF(AD16:AD18,D6),AG6>=3),IF(SUM(AG3:AG5)+ROUNDDOWN(AG8/2, )+ROUNDDOWN(AG9/2, )+COUNTIF(AD16:AD18,D10)+AG11+SUM(AG13:AG14)=0,ROUNDUP(AG6/3, ),ROUNDDOWN(AG6/3, )),0) -> 0 | AI6: =IF(AND(OR(SUM(主要!I14:M14)>=13,SUM(主要!I15:M15)>=13),$AC$16<>0,$AC$16<>$A6,主要!Y3-主要!Y4>=1),$A6,"") | AJ6: =IF(AND($AC$17<>0,$AC$17<>$A6,AI6<>"",主要!Y3-主要!Y4-主要!Y6>=1),$A6,"") | AK6: =IF(AG6>=3,5,"") | AL6: {=INDEX(AI:AI,SMALL(IF($AI$18:$AI$35<>"",ROW($18:$35),36),ROW(AI4)))&""} -> #N/A | AM6: 先祖守卫道途 | AO6: 44 | AP6: =IF($AG$2>=14,47,IF($AG$2>=10,46,IF($AG$2>=6,45,IF($AG$2>=3,44,0)))) -> 0 | AQ6: 豁免熟练项 | AR6: 生命骰 | AS6: =IFERROR(INDEX(V2:AB14,$AQ$3,1),"") | AV6: 生命骰 | AW6: =IFERROR(INDEX(V2:AB14,$AU$3,1),"") | AZ6: 生命骰 | BA6: =IFERROR(INDEX(V2:AB14,$AY$3,1),"") | BC6: 武器熟练项 | BD6: =IF(COUNTIF(AS8:BA8,"简易*"),"简易武器",IF(COUNTIF(AS8,"*短棒*"),"短棒、匕首、飞镖、标枪、硬头锤、长棍、镰刀、投石索、矛",IF(COUNTIF(AS8,"*轻弩"),"匕首、飞镖、投石索、长棍、轻弩","")))&IF(COUNTIF(AS8:BA8,"*军用*"),"、军用武器",IF(COUNTIF(AS8,"*手弩*"),"、手弩、长剑、刺剑",IF(COUNTIF(AS8,"*弯刀*"),"、弯刀",""))&IF(COUNTIF(AS8:BA8,"*短剑"),"、短剑",""))&IF(COUNTIF(AS8:BA8,"*火器"),"、火器","") | BE6: =IFERROR(IF(COUNTIF($BG$2:$BG$46,BC8),"",BC8),"") | BF6: {=INDEX(BE:BE,SMALL(IF($BE$2:$BE$143<>"",ROW($2:$143),144),ROW(BE5)))&""} | BG6: =IF(主要!C88="",0,主要!C88) -> 豁免熟练项 | BH6: =IFERROR(VLOOKUP($BG6,$BC$4:$BD$143,2,0),"") | BI6: =IF($BG6=0,"",COUNTIF($BG$2:$BG$46,$BG6)) -> 1 | BK6: 神灵亲笔签名的圣徽。（100GP） | BL6: 一个当地居民集资建立的社区花园。 | BM6: 一块遇光会投射出星辰轨迹的水晶 | BN6: 你在战斗中一直和对面没完没了的唠叨，尽你所能的去分散他们的注意力或给他们洗脑，你猜有多少人在战斗中搞不清自己的鞋带开没开。 | BO6: 积极学生式：高举一只手站立。（当你想被人看到时好用） | BP6: 骷髅 | BQ6: 一个曾与你一同训练的圣武士，如今背弃了誓言，与你对立。 | BR6: 一根金属尖的拐杖。（巨剑或矛） | BT6: 你的头发中长出纤细的触角或鹿角。 | BU6: 你周围的人都认为你的力量是对你的家庭的一种诅咒，因为过去的罪行。 | BV6: 你难以记住生物和尸体应该被区别对待。 | BW6: 小时候，你有一个想象中的朋友，它看上去像是呋噜或是一只奇怪的鸭嘴兽形生物。某天，它赠与你灵能的力量，但它最终不再止步于想象。 | BX6: 你的法器短暂地变化成小巧的机械装置。 | BY6: 空心小雕像 | BZ6: 飞行。饮用者在10分钟内获得10尺飞行速度。 | CA6: 当你大声朗读巨石柱上的古代龙纹铭文后，你被赋予了力量。 | CB6: 你找到了一张龙语卷轴，里面包含了令人顿悟的崭新技巧。
A7: 武僧 | B7: 散打宗 | C7: 暗影宗 | D7: 四象宗 | E7: =IF(综合数据!B5=TRUE,"永亡宗","") -> 永亡宗 | F7: =IF(综合数据!B7=TRUE,"醉拳宗","") -> 醉拳宗 | G7: =IF(综合数据!B7=TRUE,"剑圣宗","") -> 剑圣宗 | H7: =IF(综合数据!B7=TRUE,"日魂宗","") -> 日魂宗 | I7: =IF(综合数据!B14=TRUE,"命流宗","") -> 命流宗 | J7: =IF(综合数据!B14=TRUE,"星我宗","") -> 星我宗 | K7: =IF(综合数据!B16=TRUE,"神龙宗","") -> 神龙宗 | U7: 武僧 | V7: D8 | X7: 简易武器、短剑 | Y7: 自选一种工匠工具或一种乐器 | Z7: 力量、敏捷 | AA7: 从体操、运动、历史、洞悉、宗教、隐匿中选择两项 | AB7: =AB2 -> 4、8、12、16、19 | AD7: 简易武器、短剑 | AG7: =IFERROR(VLOOKUP(U7,$AC$16:$AE$18,3,0),0) -> 0 | AI7: =IF(AND(SUM(主要!I15:M15)>=13,SUM(主要!I18:M18)>=13,$AC$16<>0,$AC$16<>$A7,主要!Y3-主要!Y4>=1),$A7,"") | AJ7: =IF(AND($AC$17<>0,$AC$17<>$A7,AI7<>"",主要!Y3-主要!Y4-主要!Y6>=1),$A7,"") | AK7: =IF(AG7>=3,6,"") | AL7: {=INDEX(AI:AI,SMALL(IF($AI$18:$AI$35<>"",ROW($18:$35),36),ROW(AI5)))&""} -> #N/A | AM7: 风暴先驱道途 | AO7: 48 | AP7: =IF($AG$2>=14,60,IF($AG$2>=10,56,IF($AG$2>=6,55,IF($AG$2>=3,51,0)))) -> 0 | AQ7: =IFERROR(INDEX(V2:AA14,$AQ$3,5),"") | AR7: 护甲熟练项 | AS7: =IFERROR(INDEX(V2:AB14,$AQ$3,2),0) -> 0 | AV7: 护盾熟练 | AW7: =IFERROR(INDEX(AC2:AF14,$AU$3,1),0) -> 0 | AZ7: 护盾熟练 | BA7: =IFERROR(INDEX(AC2:AF14,$AY$3,1),0) -> 0 | BC7: 工具熟练项 | BD7: =IF(AS9=0,"",AS9)&IF(AW9=0,"",IF(AS9=0,"","、")&AW9)&IF(BA9=0,"",IF(AND(AS9=0,AW9=0),"","、")&BA9) | BE7: =IFERROR(IF(COUNTIF($BG$2:$BG$46,BC9),"",BC9),"") | BF7: {=INDEX(BE:BE,SMALL(IF($BE$2:$BE$143<>"",ROW($2:$143),144),ROW(BE6)))&""} | BG7: =IF(主要!C89="",0,主要!C89) -> 技能熟练项 | BH7: =IFERROR(VLOOKUP($BG7,$BC$4:$BD$143,2,0),"") | BI7: =IF($BG7=0,"",COUNTIF($BG$2:$BG$46,$BG7)) -> 1 | BK7: 摩擦生香的圣象。（5GP） | BL7: 一片被自然侵蚀的废弃街区。 | BM7: 描绘星座排列的玻璃圆盘 | BN7: 你有一个特制的腰包，专门用来在战斗最激烈时释放滚珠或铁蒺藜，迫使你的敌人同时躲避你的攻击和这些东西。 | BO7: 吵闹酒仙式：伸直一只手做出敬酒的动作。（对于防止被掌掴特别实用） | BP7: 蝴蝶 | BQ7: 被某人打败的吸血鬼，发誓要对所有圣武士复仇。 | BR7: 一大瓶葡萄酒。（硬头锤，如被敲碎则为短剑） | BU7: 据传，你的力量与一个古老的疯王、在一个世纪前的血腥起义中有某些关联。 | BV7: 你上周只眨了一次眼。 | BW7: 你的噩梦向你透露了真相：你的灵能不是来源于自身，而是从你未能成功出世的孪生兄弟/姐妹处抽取来的！ | BX7: 你和那些受到你法术影响的生物都会听到齿轮的滴答声或是钟表的响铃。 | BY7: 华丽提灯 | BZ7: 变形。饮用者的身体产生如同变身术的变化。具体怎样变化由饮用者决定，持续时间10分钟 | CA7: 你做了一个逼真的梦，你梦见一个神秘的人物，有七只黄色的金丝雀伴随其左右，警告你即将到来的浩劫。当你醒来时，你的龙兽就在你的身边盯着你。 | CB7: 你梦到了一名五首龙裔，而你醒来时，体内的气就已不同以往，宛如巨龙之息。
A8: 圣武士 | B8: 奉献之誓 | C8: 古贤之誓 | D8: 复仇之誓 | E8: =IF(综合数据!B3=TRUE,"破誓者","") -> 破誓者 | F8: =IF(综合数据!B5=TRUE,"王冠之誓","") -> 王冠之誓 | G8: =IF(综合数据!B7=TRUE,"征服之誓","") -> 征服之誓 | H8: =IF(综合数据!B7=TRUE,"救赎之誓","") -> 救赎之誓 | I8: =IF(综合数据!B13=TRUE,"荣耀之誓","") -> 荣耀之誓 | J8: =IF(综合数据!B14=TRUE,"守望之誓","") -> 守望之誓 | U8: 圣武士 | V8: D10 | W8: 全部护甲、盾牌 | X8: 简易武器、军用武器 | Z8: 感知、魅力 | AA8: 从运动、洞悉、威吓、医药、说服、宗教中选择两项 | AB8: =AB2 -> 4、8、12、16、19 | AC8: 轻甲、中甲、盾牌 | AD8: 简易武器、军用武器 | AG8: =IFERROR(VLOOKUP(U8,$AC$16:$AE$18,3,0),0) -> 0 | AH8: =IF(AG8>=2,IF(SUM(AG3:AG5)+COUNTIF(AD16:AD18,D6)+ROUNDDOWN(AG9/2, )+COUNTIF(AD16:AD18,D10)+AG11+SUM(AG13:AG14)=0,ROUNDUP(AG8/2, ),ROUNDDOWN(AG8/2, )),0) -> 0 | AI8: =IF(AND(SUM(主要!I14:M14)>=13,SUM(主要!I19:M19)>=13,$AC$16<>0,$AC$16<>$A8,主要!Y3-主要!Y4>=1),$A8,"") | AJ8: =IF(AND($AC$17<>0,$AC$17<>$A8,AI8<>"",主要!Y3-主要!Y4-主要!Y6>=1),$A8,"") | AK8: =IF(AG8>=3,7,"") | AL8: {=INDEX(AI:AI,SMALL(IF($AI$18:$AI$35<>"",ROW($18:$35),36),ROW(AI6)))&""} -> #N/A | AM8: 狂热者道途 | AO8: 61 | AP8: =IF($AG$2>=14,65,IF($AG$2>=10,64,IF($AG$2>=6,63,IF($AG$2>=3,62,0)))) -> 0 | AR8: 武器熟练项 | AS8: =IFERROR(INDEX(V2:AB14,$AQ$3,3),0) -> 0 | AV8: 武器熟练项 | AW8: =IFERROR(INDEX(AC2:AF14,$AU$3,2),0) -> 0 | AZ8: 武器熟练项 | BA8: =IFERROR(INDEX(AC2:AF14,$AY$3,2),0) -> 0 | BC8: 豁免熟练项 | BD8: =AQ7 | BE8: =IFERROR(IF(COUNTIF($BG$2:$BG$46,BC10),"",BC10),"") | BF8: {=INDEX(BE:BE,SMALL(IF($BE$2:$BE$143<>"",ROW($2:$143),144),ROW(BE7)))&""} | BG8: =IF(主要!C90="",0,主要!C90) -> 属性值提升 | BH8: =IFERROR(VLOOKUP($BG8,$BC$4:$BD$143,2,0),"") -> 当达到第级时，你可以选择一项属性值提升2点，或是选择两项属性各提升1点。不过你不能通过此特性让属性值超过20 | BI8: =IF($BG8=0,"",COUNTIF($BG$2:$BG$46,$BG8)) -> 1 | BK8: 异界神侍剃须刀。（15GP） | BL8: 一间由奇怪而强大的德鲁伊同袍照料的动物园。 | BO8: 强壮鸟妖式：边唱歌边疯狂扇动双臂。（鼓励人们远离你，同时也可以在夏天用来降温）
A9: 游侠 | B9: 猎人 | C9: 驯兽师 | D9: =IF(综合数据!B7=TRUE,"幽域追踪者","") -> 幽域追踪者 | E9: =IF(综合数据!B7=TRUE,"边界行者","") -> 边界行者 | F9: =IF(综合数据!B7=TRUE,"怪物杀手","") -> 怪物杀手 | G9: =IF(综合数据!B14=TRUE,"集群守卫","") -> 集群守卫 | H9: =IF(综合数据!B14=TRUE,"妖精漫游者","") -> 妖精漫游者 | I9: =IF(综合数据!B16=TRUE,"龙兽守卫","") -> 龙兽守卫 | U9: 游侠 | V9: D10 | W9: 轻甲、中甲、盾牌 | X9: 简易武器、军用武器 | Z9: 力量、敏捷 | AA9: 从驯兽、运动、洞悉、调查、自然、察觉、隐匿和求生中选择三项 | AB9: =AB2 -> 4、8、12、16、19 | AC9: 轻甲、中甲、盾牌 | AD9: 简易武器、军用武器 | AF9: ，再从驯兽、运动、洞悉、调查、自然、察觉、隐匿和求生中选择一项 | AG9: =IFERROR(VLOOKUP(U9,$AC$16:$AE$18,3,0),0) -> 0 | AH9: =IF(AG9>=2,IF(SUM(AG3:AG5)+COUNTIF(AD16:AD18,D6)+ROUNDDOWN(AG8/2, )+COUNTIF(AD16:AD18,D10)+AG11+SUM(AG13:AG14)=0,ROUNDUP(AG9/2, ),ROUNDDOWN(AG9/2, )),0) -> 0 | AI9: =IF(AND(SUM(主要!I15:M15)>=13,SUM(主要!I18:M18)>=13,$AC$16<>0,$AC$16<>$A9,主要!Y3-主要!Y4>=1),$A9,"") | AJ9: =IF(AND($AC$17<>0,$AC$17<>$A9,AI9<>"",主要!Y3-主要!Y4-主要!Y6>=1),$A9,"") | AK9: =IF(AG9>=3,8,"") | AL9: {=INDEX(AI:AI,SMALL(IF($AI$18:$AI$35<>"",ROW($18:$35),36),ROW(AI7)))&""} -> #N/A | AM9: 狂野魔法道途 | AO9: 66 | AP9: =IF($AG$2>=14,70,IF($AG$2>=10,69,IF($AG$2>=6,68,IF($AG$2>=3,67,0)))) -> 0 | AR9: 工具熟练项 | AS9: =IFERROR(INDEX(V2:AB14,$AQ$3,4),0) -> 0 | AV9: 工具熟练项 | AW9: =IFERROR(INDEX(AC2:AF14,$AU$3,3),0) -> 0 | AZ9: 工具熟练项 | BA9: =IFERROR(INDEX(AC2:AF14,$AY$3,3),0) -> 0 | BC9: 技能熟练项 | BD9: =AS10&IF(AW10=0,"",AW10)&IF(BA10=0,"",BA10) | BE9: =IFERROR(IF(OR(BC11="",COUNTIF($BG$2:$BG$46,BC11)),"",BC11),"") | BF9: {=INDEX(BE:BE,SMALL(IF($BE$2:$BE$143<>"",ROW($2:$143),144),ROW(BE8)))&""} | BG9: =IF(主要!C91="",0,主要!C91) -> 0 | BH9: =IFERROR(VLOOKUP($BG9,$BC$4:$BD$143,2,0),"") | BI9: =IF($BG9=0,"",COUNTIF($BG$2:$BG$46,$BG9)) | BK9: 下流话未经删减的原版圣经（10GP） | BL9: 一座仅供有钱人享受的收费私人公园。 | BO9: 断裂桥面式：脸和膝盖贴地并撅起臀部。（降低正面的敌人能见度，并为盟友提供一个实用的滑梯）
A10: 游荡者 | B10: 盗贼 | C10: 刺客 | D10: 诡术师 | E10: =IF(综合数据!B7=TRUE,"审判官","") -> 审判官 | F10: =IF(综合数据!B7=TRUE,"策士","") -> 策士 | G10: =IF(综合数据!B7=TRUE,"斥候","") -> 斥候 | H10: =IF(综合数据!B7=TRUE,"游荡剑客","") -> 游荡剑客 | I10: =IF(综合数据!B14=TRUE,"鬼魅","") -> 鬼魅 | J10: =IF(综合数据!B14=TRUE,"魂刃","") -> 魂刃 | U10: 游荡者 | V10: D8 | W10: 轻甲 | X10: 简易武器、手弩、长剑、刺剑、短剑 | Y10: =IF(COUNTIF(AC16:AC18,A14),0,"盗贼工具") -> 盗贼工具 | Z10: 敏捷、智力 | AA10: 从体操、运动、欺瞒、洞悉、威吓、调查、察觉、表演、游说、巧手、隐匿中选择四项 | AB10: 4、8、10、12、16、19 | AC10: 轻甲 | AE10: =IF(COUNTIF(AC16:AC18,A14),0,"盗贼工具") -> 盗贼工具 | AF10: ，再从体操、运动、欺瞒、洞悉、威吓、调查、察觉、表演、游说、巧手、隐匿中选择一项 | AG10: =IFERROR(VLOOKUP(U10,$AC$16:$AE$18,3,0),0) -> 0 | AH10: =IF(AND(COUNTIF(AD16:AD18,D10),AG10>=3),IF(SUM(AG3:AG5)+COUNTIF(AD16:AD18,D6)+ROUNDDOWN(AG8/2, )+ROUNDDOWN(AG9/2, )+AG11+SUM(AG13:AG14)=0,ROUNDUP(AG10/3, ),ROUNDDOWN(AG10/3, )),0) -> 0 | AI10: =IF(AND(SUM(主要!I15:M15)>=13,$AC$16<>0,$AC$16<>$A10,主要!Y3-主要!Y4>=1),$A10,"") | AJ10: =IF(AND($AC$17<>0,$AC$17<>$A10,AI10<>"",主要!Y3-主要!Y4-主要!Y6>=1),$A10,"") | AK10: =IF(AG10>=3,9,"") | AL10: {=INDEX(AI:AI,SMALL(IF($AI$18:$AI$35<>"",ROW($18:$35),36),ROW(AI8)))&""} -> #N/A | AM10: 野兽道途 | AO10: 71 | AP10: =IF($AG$2>=14,77,IF($AG$2>=10,76,IF($AG$2>=6,55,IF($AG$2>=3,71,0)))) -> 0 | AR10: 技能熟练项 | AS10: =IFERROR(INDEX(V2:AB14,$AQ$3,6),"") | AV10: 技能熟练项 | AW10: =IFERROR(INDEX(AC2:AF14,$AU$3,4),0) -> 0 | AZ10: 技能熟练项 | BA10: =IFERROR(INDEX(AC2:AF14,$AY$3,4),0) -> 0 | BC10: 属性值提升 | BD10: =IF(AC16>0,"当达到第"&IFERROR(INDEX(AQ11:BB11,1,$BD$2),"")&"级时，你可以选择一项属性值提升2点，或是选择两项属性各提升1点。不过你不能通过此特性让属性值超过20","") -> 当达到第级时，你可以选择一项属性值提升2点，或是选择两项属性各提升1点。不过你不能通过此特性让属性值超过20 | BE10: =IFERROR(IF(OR(BC12="",COUNTIF($BG$2:$BG$46,BC12)),"",BC12),"") | BF10: {=INDEX(BE:BE,SMALL(IF($BE$2:$BE$143<>"",ROW($2:$143),144),ROW(BE9)))&""} | BG10: =IF(主要!C92="",0,主要!C92) -> 0 | BH10: =IFERROR(VLOOKUP($BG10,$BC$4:$BD$143,2,0),"") | BI10: =IF($BG10=0,"",COUNTIF($BG$2:$BG$46,$BG10)) | BL10: 一片收容因被捕猎而惊恐的动物的自然保护区。
A11: 术士 | B11: 龙族血脉 | C11: 狂野魔法 | D11: =IF(综合数据!B7=TRUE,"神性之魂","") -> 神性之魂 | E11: =IF(综合数据!B7=TRUE,"幽影魔法","") -> 幽影魔法 | F11: =IF(综合数据!B7=TRUE,"风暴术法","") -> 风暴术法 | G11: =IF(综合数据!B14=TRUE,"畸变心智","") -> 畸变心智 | H11: =IF(综合数据!B14=TRUE,"时械之魂","") -> 时械之魂 | U11: 术士 | V11: D6 | X11: 匕首、飞镖、投石索、长棍、轻弩 | Z11: 体质、魅力 | AA11: 从奥秘、欺瞒、洞悉、威吓、游说、宗教中选择两项 | AB11: =AB2 -> 4、8、12、16、19 | AG11: =IFERROR(VLOOKUP(U11,$AC$16:$AE$18,3,0),0) -> 0 | AH11: =AG11 -> 0 | AI11: =IF(AND(SUM(主要!I19:M19)>=13,$AC$16<>0,$AC$16<>$A11,主要!Y3-主要!Y4>=1),$A11,"") | AJ11: =IF(AND($AC$17<>0,$AC$17<>$A11,AI11<>"",主要!Y3-主要!Y4-主要!Y6>=1),$A11,"") | AK11: 10 | AL11: {=INDEX(AI:AI,SMALL(IF($AI$18:$AI$35<>"",ROW($18:$35),36),ROW(AI9)))&""} -> #N/A | AM11: 吟游诗人 | AN11: 2 | AO11: 1 | AP11: =IF($AG$3=20,18,IF($AG$3>=10,17,IF($AG$3>=6,16,IF($AG$3>=5,15,IF($AG$3>=4,14,IF($AG$3>=3,13,IF($AG$3>=2,11,IF($AG$3>=1,8,0)))))))) -> 0 | AR11: 属性值提升 | AS11: =IFERROR(INDEX(V2:AB14,$AQ$3,7),0) -> 0 | AV11: 属性值提升 | AW11: =IFERROR(INDEX(V2:AB14,$AU$3,7),0) -> 0 | AZ11: 属性值提升 | BA11: =IFERROR(INDEX(V2:AB14,$AY$3,7),0) -> 0 | BC11: =IFERROR(INDEX($AQ$12:$BF$87,1,$BC$2),"") | BD11: =IFERROR(INDEX($AQ$12:$BF$87,1,$BD$2),"") | BE11: =IFERROR(IF(OR(BC13="",COUNTIF($BG$2:$BG$46,BC13)),"",BC13),"") | BF11: {=INDEX(BE:BE,SMALL(IF($BE$2:$BE$143<>"",ROW($2:$143),144),ROW(BE10)))&""} | BG11: =IF(主要!C93="",0,主要!C93) -> 0 | BH11: =IFERROR(VLOOKUP($BG11,$BC$4:$BD$143,2,0),"") | BI11: =IF($BG11=0,"",COUNTIF($BG$2:$BG$46,$BG11)) | BL11: 一间培育稀有的异国动植物并用其制作各种商品的商铺。
A12: 邪术师 | B12: 至高妖精 | C12: 邪魔 | D12: 旧日支配者 | E12: =IF(综合数据!B5=TRUE,"不朽者","") -> 不朽者 | F12: =IF(综合数据!B7=TRUE,"天界宗主","") -> 天界宗主 | G12: =IF(综合数据!B7=TRUE,"咒剑士","") -> 咒剑士 | H12: =IF(综合数据!B14=TRUE,"巨灵宗主","") -> 巨灵宗主 | I12: =IF(综合数据!B14=TRUE,"深海意志","") -> 深海意志 | J12: =IF(综合数据!B15=TRUE,"死灵宗主","") -> 死灵宗主 | U12: 邪术师 | V12: D8 | W12: 轻甲 | X12: 简易武器 | Z12: 感知，魅力 | AA12: 从奥秘、欺瞒、威吓、洞悉、历史、自然、宗教中选择两项 | AB12: =AB2 -> 4、8、12、16、19 | AC12: 轻甲 | AD12: 简易武器 | AG12: =IFERROR(VLOOKUP(U12,$AC$16:$AE$18,3,0),0) -> 0 | AI12: =IF(AND(SUM(主要!I19:M19)>=13,$AC$16<>0,$AC$16<>$A12,主要!Y3-主要!Y4>=1),$A12,"") | AJ12: =IF(AND($AC$17<>0,$AC$17<>$A12,AI12<>"",主要!Y3-主要!Y4-主要!Y6>=1),$A12,"") | AK12: 11 | AL12: {=INDEX(AI:AI,SMALL(IF($AI$18:$AI$35<>"",ROW($18:$35),36),ROW(AI10)))&""} -> #N/A | AM12: 逸闻学院 | AO12: 19 | AP12: =IF($AG$3>=14,22,IF($AG$3>=6,21,IF($AG$3>=3,20,0))) -> 0 | AQ12: =IF(AQ11+1>$AT$3,IF(AQ11+1>$AT$3,IF($AS$4+AT11>$AT$4,"",$AS$4+AT11)),AQ11+1) -> #N/A | AR12: =INDEX($B$17:$AA$154,AQ12,$AR$4) -> #N/A | AS12: =INDEX($B$17:$AA$154,AQ12,$AR$3) -> #N/A | AT12: =IF(AQ11+1>$AT$3,AT11+1,0) -> #N/A | AU12: =IF($AU11+1>$AX$3,IF($AU11+1>$AX$3,IF($AW$4+AX11>$AX$4,"",$AW$4+AX11)),$AU11+1) -> #N/A | AV12: =INDEX($B$17:$AA$154,AU12,$AV$4) -> #N/A | AW12: =INDEX($B$17:$AA$154,AU12,$AV$3) -> #N/A | AX12: =IF($AU11+1>$AX$3,$AX11+1,0) -> #N/A | AY12: =IF($AY11+1>$BB$3,IF($AY11+1>$BB$3,IF($BA$4+BB11>$BB$4,"",$BA$4+BB11)),$AY11+1) -> #N/A | AZ12: =INDEX($B$17:$AA$154,AY12,$AZ$4) -> #N/A | BA12: =INDEX($B$17:$AA$154,AY12,$AZ$3) -> #N/A | BB12: =IF($AY11+1>$BB$3,$BB11+1,0) -> #N/A | BC12: =IFERROR(INDEX($AQ$12:$BF$87,2,$BC$2),"") | BD12: =IFERROR(INDEX($AQ$12:$BF$87,2,$BD$2),"") | BE12: =IFERROR(IF(OR(BC14="",COUNTIF($BG$2:$BG$46,BC14)),"",BC14),"") | BF12: {=INDEX(BE:BE,SMALL(IF($BE$2:$BE$143<>"",ROW($2:$143),144),ROW(BE11)))&""} | BG12: =IF(主要!C94="",0,主要!C94) -> 0 | BH12: =IFERROR(VLOOKUP($BG12,$BC$4:$BD$143,2,0),"") | BI12: =IF($BG12=0,"",COUNTIF($BG$2:$BG$46,$BG12))
A13: 法师 | B13: 防护学派 | C13: 咒法学派 | D13: 预言学派 | E13: 附魔学派 | F13: 塑能学派 | G13: 幻术学派 | H13: 死灵学派 | I13: 变化学派 | J13: =IF(综合数据!B5=TRUE,"剑咏者","") -> 剑咏者 | K13: =IF(综合数据!B7=TRUE,"战法师","") -> 战法师 | L13: =IF(综合数据!B11=TRUE,"时间魔法","") -> 时间魔法 | M13: =IF(综合数据!B11=TRUE,"重力魔法","") -> 重力魔法 | N13: =IF(综合数据!B14=TRUE,"书士会","") -> 书士会 | U13: 法师 | V13: D6 | X13: 匕首、飞镖、投石索、长棍、轻弩 | Z13: 智力、感知 | AA13: 在奥秘、历史、洞悉、调查、医药、宗教中选择两项 | AB13: =AB2 -> 4、8、12、16、19 | AG13: =IFERROR(VLOOKUP(U13,$AC$16:$AE$18,3,0),0) -> 0 | AH13: =AG13 -> 0 | AI13: =IF(AND(SUM(主要!I17:M17)>=13,$AC$16<>0,$AC$16<>$A13,主要!Y3-主要!Y4>=1),$A13,"") | AJ13: =IF(AND($AC$17<>0,$AC$17<>$A13,AI13<>"",主要!Y3-主要!Y4-主要!Y6>=1),$A13,"") | AK13: =IF(AG13>=2,12,"") | AL13: {=INDEX(AI:AI,SMALL(IF($AI$18:$AI$35<>"",ROW($18:$35),36),ROW(AI11)))&""} -> #N/A | AM13: 勇气学院 | AO13: 23 | AP13: =IF($AG$3>=14,26,IF($AG$3>=6,25,IF($AG$3>=3,24,0))) -> 0 | AQ13: =IF(AQ12+1>$AT$3,IF(AQ12+1>$AT$3,IF($AS$4+AT12>$AT$4,"",$AS$4+AT12)),AQ12+1) -> #N/A | AR13: =INDEX($B$17:$AA$154,AQ13,$AR$4) -> #N/A | AS13: =INDEX($B$17:$AA$154,AQ13,$AR$3) -> #N/A | AT13: =IF(AQ12+1>$AT$3,AT12+1,0) -> #N/A | AU13: =IF($AU12+1>$AX$3,IF($AU12+1>$AX$3,IF($AW$4+AX12>$AX$4,"",$AW$4+AX12)),$AU12+1) -> #N/A | AV13: =INDEX($B$17:$AA$154,AU13,$AV$4) -> #N/A | AW13: =INDEX($B$17:$AA$154,AU13,$AV$3) -> #N/A | AX13: =IF($AU12+1>$AX$3,$AX12+1,0) -> #N/A | AY13: =IF($AY12+1>$BB$3,IF($AY12+1>$BB$3,IF($BA$4+BB12>$BB$4,"",$BA$4+BB12)),$AY12+1) -> #N/A | AZ13: =INDEX($B$17:$AA$154,AY13,$AZ$4) -> #N/A | BA13: =INDEX($B$17:$AA$154,AY13,$AZ$3) -> #N/A | BB13: =IF($AY12+1>$BB$3,$BB12+1,0) -> #N/A | BC13: =IFERROR(INDEX($AQ$12:$BF$87,3,$BC$2),"") | BD13: =IFERROR(INDEX($AQ$12:$BF$87,3,$BD$2),"") | BE13: =IFERROR(IF(OR(BC15="",COUNTIF($BG$2:$BG$46,BC15)),"",BC15),"") | BF13: {=INDEX(BE:BE,SMALL(IF($BE$2:$BE$143<>"",ROW($2:$143),144),ROW(BE12)))&""} | BG13: =IF(主要!C95="",0,主要!C95) -> 施法关键属性 | BH13: =IFERROR(VLOOKUP($BG13,$BC$4:$BD$143,2,0),"") | BI13: =IF($BG13=0,"",COUNTIF($BG$2:$BG$46,$BG13)) -> 1
A14: =IF(OR(综合数据!B10=TRUE,综合数据!B14=TRUE),"奇械师","") -> 奇械师 | B14: 炼金师 | C14: 魔炮师 | D14: 战地匠师 | E14: =IF(综合数据!B14=TRUE,"装甲师","") -> 装甲师 | U14: 奇械师 | V14: D8 | W14: 轻甲、中甲、盾牌 | X14: ="简易武器"&IF(综合数据!B3=TRUE,"、火器","") -> 简易武器、火器 | Y14: 盗贼工具、修补工具、另外自选一种工匠工具 | Z14: 体质、智力 | AA14: 从奥秘、历史、调查、医药、自然、察觉、巧手中选择两项 | AB14: =AB2 -> 4、8、12、16、19 | AC14: 轻甲，中甲，盾牌 | AD14: =IF(综合数据!B3=TRUE,"火器","") -> 火器 | AE14: 盗贼工具、修补工具 | AG14: =IFERROR(VLOOKUP(U14,$AC$16:$AE$18,3,0),0) -> 0 | AH14: =ROUNDUP(AG14/2, ) -> 0 | AI14: =IF(AND(SUM(主要!I17:M17)>=13,$AC$16<>0,$AC$16<>$A14,主要!Y3-主要!Y4>=1),$A14,"") | AJ14: =IF(AND($AC$17<>0,$AC$17<>$A14,AI14<>"",主要!Y3-主要!Y4-主要!Y6>=1),$A14,"") | AK14: =IF(AG14>=3,13,"") | AL14: {=INDEX(AI:AI,SMALL(IF($AI$18:$AI$35<>"",ROW($18:$35),36),ROW(AI12)))&""} -> #N/A | AM14: 迷惑学院 | AO14: 27 | AP14: =IF($AG$3>=14,30,IF($AG$3>=6,29,IF($AG$3>=3,28,0))) -> 0 | AQ14: =IF(AQ13+1>$AT$3,IF(AQ13+1>$AT$3,IF($AS$4+AT13>$AT$4,"",$AS$4+AT13)),AQ13+1) -> #N/A | AR14: =INDEX($B$17:$AA$154,AQ14,$AR$4) -> #N/A | AS14: =INDEX($B$17:$AA$154,AQ14,$AR$3) -> #N/A | AT14: =IF(AQ13+1>$AT$3,AT13+1,0) -> #N/A | AU14: =IF($AU13+1>$AX$3,IF($AU13+1>$AX$3,IF($AW$4+AX13>$AX$4,"",$AW$4+AX13)),$AU13+1) -> #N/A | AV14: =INDEX($B$17:$AA$154,AU14,$AV$4) -> #N/A | AW14: =INDEX($B$17:$AA$154,AU14,$AV$3) -> #N/A | AX14: =IF($AU13+1>$AX$3,$AX13+1,0) -> #N/A | AY14: =IF($AY13+1>$BB$3,IF($AY13+1>$BB$3,IF($BA$4+BB13>$BB$4,"",$BA$4+BB13)),$AY13+1) -> #N/A | AZ14: =INDEX($B$17:$AA$154,AY14,$AZ$4) -> #N/A | BA14: =INDEX($B$17:$AA$154,AY14,$AZ$3) -> #N/A | BB14: =IF($AY13+1>$BB$3,$BB13+1,0) -> #N/A | BC14: =IFERROR(INDEX($AQ$12:$BF$87,4,$BC$2),"") | BD14: =IFERROR(INDEX($AQ$12:$BF$87,4,$BD$2),"") | BE14: =IFERROR(IF(OR(BC16="",COUNTIF($BG$2:$BG$46,BC16)),"",BC16),"") | BF14: {=INDEX(BE:BE,SMALL(IF($BE$2:$BE$143<>"",ROW($2:$143),144),ROW(BE13)))&""} | BG14: =IF(主要!C96="",0,主要!C96) -> 0 | BH14: =IFERROR(VLOOKUP($BG14,$BC$4:$BD$143,2,0),"") | BI14: =IF($BG14=0,"",COUNTIF($BG$2:$BG$46,$BG14))
AL15: {=INDEX(AI:AI,SMALL(IF($AI$18:$AI$35<>"",ROW($18:$35),36),ROW(AI13)))&""} -> #N/A | AM15: 剑舞学院 | AO15: 31 | AP15: =IF($AG$3>=14,37,IF($AG$3>=6,36,IF($AG$3>=3,35,0))) -> 0 | AQ15: =IF(AQ14+1>$AT$3,IF(AQ14+1>$AT$3,IF($AS$4+AT14>$AT$4,"",$AS$4+AT14)),AQ14+1) -> #N/A | AR15: =INDEX($B$17:$AA$154,AQ15,$AR$4) -> #N/A | AS15: =INDEX($B$17:$AA$154,AQ15,$AR$3) -> #N/A | AT15: =IF(AQ14+1>$AT$3,AT14+1,0) -> #N/A | AU15: =IF($AU14+1>$AX$3,IF($AU14+1>$AX$3,IF($AW$4+AX14>$AX$4,"",$AW$4+AX14)),$AU14+1) -> #N/A | AV15: =INDEX($B$17:$AA$154,AU15,$AV$4) -> #N/A | AW15: =INDEX($B$17:$AA$154,AU15,$AV$3) -> #N/A | AX15: =IF($AU14+1>$AX$3,$AX14+1,0) -> #N/A | AY15: =IF($AY14+1>$BB$3,IF($AY14+1>$BB$3,IF($BA$4+BB14>$BB$4,"",$BA$4+BB14)),$AY14+1) -> #N/A | AZ15: =INDEX($B$17:$AA$154,AY15,$AZ$4) -> #N/A | BA15: =INDEX($B$17:$AA$154,AY15,$AZ$3) -> #N/A | BB15: =IF($AY14+1>$BB$3,$BB14+1,0) -> #N/A | BC15: =IFERROR(INDEX($AQ$12:$BF$87,5,$BC$2),"") | BD15: =IFERROR(INDEX($AQ$12:$BF$87,5,$BD$2),"") | BE15: =IFERROR(IF(OR(BC17="",COUNTIF($BG$2:$BG$46,BC17)),"",BC17),"") | BF15: {=INDEX(BE:BE,SMALL(IF($BE$2:$BE$143<>"",ROW($2:$143),144),ROW(BE14)))&""} | BG15: =IF(主要!C97="",0,主要!C97) -> 0 | BH15: =IFERROR(VLOOKUP($BG15,$BC$4:$BD$143,2,0),"") | BI15: =IF($BG15=0,"",COUNTIF($BG$2:$BG$46,$BG15))
B16: 野蛮人 | D16: 吟游诗人 | F16: 牧师 | H16: 德鲁伊 | J16: 战士 | L16: 武僧 | N16: 圣武士 | P16: 游侠 | R16: 游荡者 | T16: 术士 | V16: 邪术师 | X16: 法师 | Z16: 奇械师 | AC16: =IF(主要!R4="",0,主要!R4) -> 秘学士 | AD16: =IF(主要!V4="",0,主要!V4) -> 神奇动物 | AE16: =主要!Y4 -> 1 | AF16: 1 | AG16: 备选兼职 | AI16: 子职1 | AJ16: 子职2 | AK16: 子职3 | AL16: {=INDEX(AI:AI,SMALL(IF($AI$18:$AI$35<>"",ROW($18:$35),36),ROW(AI14)))&""} -> #N/A | AM16: 低语学院 | AO16: 38 | AP16: =IF($AG$3>=14,41,IF($AG$3>=6,40,IF($AG$3>=3,39,0))) -> 0 | AQ16: =IF(AQ15+1>$AT$3,IF(AQ15+1>$AT$3,IF($AS$4+AT15>$AT$4,"",$AS$4+AT15)),AQ15+1) -> #N/A | AR16: =INDEX($B$17:$AA$154,AQ16,$AR$4) -> #N/A | AS16: =INDEX($B$17:$AA$154,AQ16,$AR$3) -> #N/A | AT16: =IF(AQ15+1>$AT$3,AT15+1,0) -> #N/A | AU16: =IF($AU15+1>$AX$3,IF($AU15+1>$AX$3,IF($AW$4+AX15>$AX$4,"",$AW$4+AX15)),$AU15+1) -> #N/A | AV16: =INDEX($B$17:$AA$154,AU16,$AV$4) -> #N/A | AW16: =INDEX($B$17:$AA$154,AU16,$AV$3) -> #N/A | AX16: =IF($AU15+1>$AX$3,$AX15+1,0) -> #N/A | AY16: =IF($AY15+1>$BB$3,IF($AY15+1>$BB$3,IF($BA$4+BB15>$BB$4,"",$BA$4+BB15)),$AY15+1) -> #N/A | AZ16: =INDEX($B$17:$AA$154,AY16,$AZ$4) -> #N/A | BA16: =INDEX($B$17:$AA$154,AY16,$AZ$3) -> #N/A | BB16: =IF($AY15+1>$BB$3,$BB15+1,0) -> #N/A | BC16: =IFERROR(INDEX($AQ$12:$BF$87,6,$BC$2),"") | BD16: =IFERROR(INDEX($AQ$12:$BF$87,6,$BD$2),"") | BE16: =IFERROR(IF(OR(BC18="",COUNTIF($BG$2:$BG$46,BC18)),"",BC18),"") | BF16: {=INDEX(BE:BE,SMALL(IF($BE$2:$BE$143<>"",ROW($2:$143),144),ROW(BE15)))&""} | BG16: =IF(主要!C98="",0,主要!C98) -> 0 | BH16: =IFERROR(VLOOKUP($BG16,$BC$4:$BD$143,2,0),"") | BI16: =IF($BG16=0,"",COUNTIF($BG$2:$BG$46,$BG16))
A17: 1 | B17: 狂暴 | C17: 第1级起，你可以在自己回合内以一个附赠动作进入狂暴 狂暴持续期间，只要你未着装重甲就获得以下增益： 你进行力量检定和力量豁免时具有优势 你用力量值发动近战武器攻击时的伤害掷骰获得加值。此加值随你的野蛮人等级提升而增加，具体见“野蛮人职业表”中“狂暴伤害”一栏 你拥有钝击，穿刺和挥砍伤害的抗性 拥有施法能力的角色无法在狂暴持续期间施展法术或进行法术专注 你的狂暴状态维持1分钟。如果你在狂暴其间陷入昏迷，或者，如果你在上一个自己回合之后到本回合结束时都未攻击任何敌对生物也未受到伤害，则狂暴提前结束。你也可以在自己回合里以一个附赠动作主动结束狂暴状态 “野蛮人职业表”中根据你的野蛮人等级给出了相应的狂暴次数。如果你用光了这些次数，则必须完成一次长休才能再次使用狂暴 | D17: 施法-吟游诗人 | E17: 你习得以音乐为媒介随意解构、分解，再重新构造现实的方法。你的法术是融入你纷繁奏乐中的音符，也是你以各种形式谱奏的魔法乐章 | F17: 施法-牧师 | G17: 你作为神圣力量的导体得以施展牧师法术 | H17: 德鲁伊语 | I17: 第1级时，你习得德鲁伊语——即一种德鲁伊间的秘密语言。你可以说这门语言并用它留下隐藏的信息。懂得这门语言的人（包括你自己）会自动注意到此信息，而不懂此语言的人通过一次DC15的感知（察觉）检定后可以注意到其存在，不过不能用非魔法手段读懂 | J17: 战斗风格-战士 | K17: 第1级时，你可以选择一种战斗风格作为你的专精。同一种战斗风格不可重复选择 | L17: =IF(AND(COUNTIF(AC17:AC18,A7),COUNTIF(AC16:AC17,A2)),"","无甲防御") -> 无甲防御 | M17: 第1级起，未着装任何护甲也没持用盾牌时，你的AC等于10+你的敏捷调整值+你的感知调整值 | N17: 神圣感知 | O17: 第1级起，你可以使用一个动作扩展你的意识，直到你下回合结束前，你可以对身边60尺范围内进行感测，任何未对你处在全身掩护状态的天界生物、邪魔或不死生物都将被你定位。你感应到范围内生物的种类，不过并不能精确指明。在同样的范围内，你也可以侦测任何受到圣居一类的法术祝福或亵渎的地点或物件 该特性的可用次数等于1＋你的魅力调整值。而已消耗的特性使用次数，则可以通过完成一次长休进行恢复 | P17: =IF(OR(BH57<1,COUNTIF($BG$2:$BG$46,"宿敌")),"宿敌","") -> 宿敌 | Q17: 第1级起，从下列种类中选择其一作为宿敌：异怪、野兽、天界生物、构装生物、龙、元素生物、精类生物、邪魔、巨人、怪兽、泥怪、植物、不死生物。或者作为另一种方案，你也可以选择两个类人生物种族作为宿敌 追踪宿敌时，你的感知（求生）检定，以及回想关于宿敌信息时进行的智力检定具有优势 获得该特性时，如果你选择的宿敌具有语言能力，则你还可以学会宿敌所知晓的一门语言 第6和第14级时，你将分别获得一个额外的宿敌以及相关语言。另外，随着等级的提升，你所选择的宿敌应该与你在冒险中所遭遇怪物的种类层次相符 | R17: 专精-游荡者 | S17: 第1级起，你选择两个已有技能熟练项，或者一个技能熟练项和盗贼工具熟练项。此后你进行该项目的检定时，可以使用双倍的熟练加值 第6级时，你可以再选择另外两个已有的技能熟练项（或盗贼工具熟练项）从该特性中获益 | T17: 施法-术士 | U17: 过去的一个事件激发了你体内先辈的血脉，为你烙上了奥法力量的坚固印记。这股起源于某种存在的魔力驱动着你的法术能力 | V17: 异界宗主 | W17: 第1级时，你就跟某个异界的存在订下契约。随后，你将在第1、第6、第10和第14级获得所选契约的相应特性 | X17: 施法-法师 | Y17: 作为一名奥术魔法的研习者，你拥有一本自己的法术书。书中所包含的法术隐约透露着你真正的力量 | Z17: 魔法工艺 | AA17: 第1级起，当你手持修补工具，或其他工匠工具。然后花费一个动作触摸一个微小的非魔法物体，从以下魔法属性中选择一个赋予它： 该物体提供5尺半径的明亮照明，以及该范围外5尺范围的微光照明 无论何时，只要该物品被生物触碰，就会发出可在10尺外听到的录音信息。录入的信息在你将此属性赋予对象时决定，且时长不可超过6秒 物品不断地发出一种气味或一种非语言的声音。这一现象最多能传播10尺远 一个静态的视觉效果出现在物体的表面上。这个效果可以是一幅图片，最多25个单词的文本，线条和形状，或者这些元素的混合，如你所愿 所选的魔法属性持续时间无限。你能够以一个动作触摸对象来消除这一魔法属性 你能够通过此特性将魔力赋予多个物品，每次使用该特性时都需要触摸一个物品，并且单个物品一次只能承载一种魔法属性。你能够使用该特性影响的物品的最大数量等于你的智力调整值（最少一个物品）。如果你试图超过最大值，最老的魔法属性将立即结束，然后新的魔法属性生效 | AB17: =IF(AC17=0,"",COUNTIF(AC16:AC18,AC17)) | AC17: =IF(主要!R6="",0,主要!R6) -> 0 | AD17: =IF(主要!V6="",0,主要!V6) -> 0 | AE17: =主要!Y6 -> 0 | AF17: 2 | AG17: {=INDEX(AI:AI,SMALL(IF($AI$2:$AI$14<>"",ROW($2:$14),15),ROW(AI1)))&""} | AH17: {=INDEX(AJ:AJ,SMALL(IF($AJ$2:$AJ$14<>"",ROW($2:$14),15),ROW(AJ1)))&""} | AI17: =VLOOKUP(AC16,U2:AK14,17,0) -> #N/A | AJ17: =VLOOKUP(AC17,U2:AK14,17,0) -> #N/A | AK17: =VLOOKUP(AC18,U2:AK14,17,0) -> #N/A | AL17: {=INDEX(AI:AI,SMALL(IF($AI$18:$AI$35<>"",ROW($18:$35),36),ROW(AI15)))&""} -> #N/A | AM17: 雄辩学院 | AO17: 42 | AP17: =IF($AG$3>=14,46,IF($AG$3>=6,45,IF($AG$3>=3,46,0))) -> 0 | AQ17: =IF(AQ16+1>$AT$3,IF(AQ16+1>$AT$3,IF($AS$4+AT16>$AT$4,"",$AS$4+AT16)),AQ16+1) -> #N/A | AR17: =INDEX($B$17:$AA$154,AQ17,$AR$4) -> #N/A | AS17: =INDEX($B$17:$AA$154,AQ17,$AR$3) -> #N/A | AT17: =IF(AQ16+1>$AT$3,AT16+1,0) -> #N/A | AU17: =IF($AU16+1>$AX$3,IF($AU16+1>$AX$3,IF($AW$4+AX16>$AX$4,"",$AW$4+AX16)),$AU16+1) -> #N/A | AV17: =INDEX($B$17:$AA$154,AU17,$AV$4) -> #N/A | AW17: =INDEX($B$17:$AA$154,AU17,$AV$3) -> #N/A | AX17: =IF($AU16+1>$AX$3,$AX16+1,0) -> #N/A | AY17: =IF($AY16+1>$BB$3,IF($AY16+1>$BB$3,IF($BA$4+BB16>$BB$4,"",$BA$4+BB16)),$AY16+1) -> #N/A | AZ17: =INDEX($B$17:$AA$154,AY17,$AZ$4) -> #N/A | BA17: =INDEX($B$17:$AA$154,AY17,$AZ$3) -> #N/A | BB17: =IF($AY16+1>$BB$3,$BB16+1,0) -> #N/A | BC17: =IFERROR(INDEX($AQ$12:$BF$87,7,$BC$2),"") | BD17: =IFERROR(INDEX($AQ$12:$BF$87,7,$BD$2),"") | BE17: =IFERROR(IF(OR(BC19="",COUNTIF($BG$2:$BG$46,BC19)),"",BC19),"") | BF17: {=INDEX(BE:BE,SMALL(IF($BE$2:$BE$143<>"",ROW($2:$143),144),ROW(BE16)))&""} | BG17: =IF(主要!C99="",0,主要!C99) -> 0 | BH17: =IFERROR(VLOOKUP($BG17,$BC$4:$BD$143,2,0),"") | BI17: =IF($BG17=0,"",COUNTIF($BG$2:$BG$46,$BG17))
A18: 2 | B18: =IF(AND(COUNTIF(AC17:AC18,A2),COUNTIF(AC16:AC17,A7)),"","无甲防御") -> 无甲防御 | C18: 第1级起，未着装任何护甲时，你的AC等于10＋你的敏捷调整值＋你的体质调整值。使用盾牌不会影响你从此特性获益 | D18: 戏法-吟游诗人 | E18: 第1级时，你从诗人法术列表中选择两个戏法作为已知法术。在获得更高诗人等级后你还可以习得其它的戏法，具体数量见“吟游诗人职业表”中“已知戏法”一栏 | F18: 戏法-牧师 | G18: 第1级时，你选择三个牧师法术列表中的戏法作为已知法术。在获得更高的牧师等级后你还可以习得其它的戏法，具体数据参见“牧师职业表”中“已知戏法”一栏 | H18: 施法-德鲁伊 | I18: 你掌握自然世界的神圣本质，并依你的意志施展法术对其进行重塑 | J18: =IF(OR(BI53>0,COUNTIF($BG$2:$BG$46,"战斗风格-箭术")),"战斗风格-箭术","") | K18: 你使用远程武器进行攻击检定时具有+2加值 | L18: 武艺 | M18: 第1级起，你获得徒手打击和武僧武器的武器熟练。武僧武器包括短剑和所有不含双手与重型属性的简易近战武器 未着装任何护甲也没持用盾牌时，如果你徒手或只持用武僧武器，则你发动的攻击拥有下列增益： 你使用徒手打击或武僧武器进行攻击时，可以用敏捷值代替力量值进行攻击检定和伤害掷骰 你使用徒手打击或武僧武器进行攻击时，可以选择用武艺骰代替原本的伤害掷骰，该骰子将随武僧职业等级的提升而增大，具体数据见“武僧职业表”中“武艺”一栏 你使用徒手打击或武僧武器执行攻击动作时，可以在自己回合内以附赠动作发动一次徒手打击 某些宗派的武僧会使用一些奇异的武僧武器，无论你使用什么武器，其属性数据都参考与其相似的常规武器属性数据 | N18: 圣疗 | O18: 第1级起，你获得一个治疗能量池，其内的治疗能量在每次完成长休后自动补满。治疗能量池储备的可恢复生命值总值等于你的圣武士职业等级×5 你可以用一个动作触碰一个生物，并抽取治疗能量池中的能量恢复该生物的生命值，其恢复量最多等于你治疗能量池中剩余的治疗量 此外，你也可以使用5点治疗量治愈目标生物身上的一种疾病，或者祛除一种中毒效应。你可以在一次圣疗中治愈复数的疾病并祛除复数的毒素，但你需要为每一种疾病和毒素分别支付治疗量 该职业特性对不死生物和构装生物无效 | P18: =IF(AND(综合数据!B14=TRUE,OR(BH57<1,COUNTIF($BG$2:$BG$46,"夙敌"))),"夙敌","") -> 夙敌 | Q18: 第1级起，当你以一次攻击掷骰命中一个生物时，你可以呼唤你与自然的神秘羁连以将目标标记为你的夙敌，持续一分钟或直到你失去专注(如同你在专注一道法术) 你在你的回合内第一次命中你的夙敌并对其造成伤害，且你正在标记它时，你可以造成额外的1d4点伤害。你可以使用同等于你的熟练加值次该特性来标记你的夙敌，你在完成一次长休后恢复所有已使用的次数。 6级起，额外1d6伤害；14级起，额外1d8伤害 夙敌可以触发屠灭众敌特性 | R18: 偷袭 | S18: 第1级起，每当你的攻击命中一个生物时，如果该攻击的攻击检定带有优势，则可以造成额外1d6的伤害。该伤害每回合可以产生一次，且造成伤害的攻击必须使用带灵巧属性的武器或远程武器 如果目标生物身边5尺内还有其他与之对敌者，且该对敌者并未处于失能状态，则只要你的攻击检定没有劣势，就可以发动偷袭 你的偷袭伤害也将会随游荡者职业等级的提升而提高，其具体数值见“游荡者职业表” | T18: 戏法-术士 | U18: 第1级时，你从术士法术列表中选择四个戏法作为已知法术。在获得更高术士等级后你还可以习得其它的戏法，具体数量见“术士职业表”中“已知戏法”一栏 | V18: 契约魔法 | W18: 你的法术力量源于你的奥秘研究和宗主的魔法馈赠 | X18: 戏法-法师 | Y18: 第1级时，你从法师法术列表中选择三个戏法作为已知法术。在获得更高法师等级后你还可以习得其它的戏法，具体数量见“法师职业表”中“已知戏法”一栏 | Z18: 施法-奇械师 | AA18: 你已经学习了魔法的工作原理，知道如何引导魔法进入物体，以及如何唤醒魔法 | AB18: =IF(AC18=0,"",COUNTIF(AC16:AC18,AC18)) | AC18: =IF(主要!R7="",0,主要!R7) -> 0 | AD18: =IF(主要!V7="",0,主要!V7) -> 0 | AE18: =主要!Y7 -> 0 | AF18: 3 | AG18: {=INDEX(AI:AI,SMALL(IF($AI$2:$AI$14<>"",ROW($2:$14),15),ROW(AI2)))&""} | AH18: {=INDEX(AJ:AJ,SMALL(IF($AJ$2:$AJ$14<>"",ROW($2:$14),15),ROW(AJ2)))&""} | AI18: =INDEX($B$2:$S$14,AI$17,1) -> #N/A | AJ18: =INDEX($B$2:$S$14,AJ$17,1) -> #N/A | AK18: =INDEX($B$2:$S$14,AK$17,1) -> #N/A | AL18: {=INDEX(AI:AI,SMALL(IF($AI$18:$AI$35<>"",ROW($18:$35),36),ROW(AI16)))&""} -> #N/A | AM18: 创造学院 | AO18: 47 | AP18: =IF($AG$3>=14,50,IF($AG$3>=6,49,IF($AG$3>=3,48,0))) -> 0 | AQ18: =IF(AQ17+1>$AT$3,IF(AQ17+1>$AT$3,IF($AS$4+AT17>$AT$4,"",$AS$4+AT17)),AQ17+1) -> #N/A | AR18: =INDEX($B$17:$AA$154,AQ18,$AR$4) -> #N/A | AS18: =INDEX($B$17:$AA$154,AQ18,$AR$3) -> #N/A | AT18: =IF(AQ17+1>$AT$3,AT17+1,0) -> #N/A | AU18: =IF($AU17+1>$AX$3,IF($AU17+1>$AX$3,IF($AW$4+AX17>$AX$4,"",$AW$4+AX17)),$AU17+1) -> #N/A | AV18: =INDEX($B$17:$AA$154,AU18,$AV$4) -> #N/A | AW18: =INDEX($B$17:$AA$154,AU18,$AV$3) -> #N/A | AX18: =IF($AU17+1>$AX$3,$AX17+1,0) -> #N/A | AY18: =IF($AY17+1>$BB$3,IF($AY17+1>$BB$3,IF($BA$4+BB17>$BB$4,"",$BA$4+BB17)),$AY17+1) -> #N/A | AZ18: =INDEX($B$17:$AA$154,AY18,$AZ$4) -> #N/A | BA18: =INDEX($B$17:$AA$154,AY18,$AZ$3) -> #N/A | BB18: =IF($AY17+1>$BB$3,$BB17+1,0) -> #N/A | BC18: =IFERROR(INDEX($AQ$12:$BF$87,8,$BC$2),"") | BD18: =IFERROR(INDEX($AQ$12:$BF$87,8,$BD$2),"") | BE18: =IFERROR(IF(OR(BC20="",COUNTIF($BG$2:$BG$46,BC20)),"",BC20),"") | BF18: {=INDEX(BE:BE,SMALL(IF($BE$2:$BE$143<>"",ROW($2:$143),144),ROW(BE17)))&""} | BG18: =IF(主要!C100="",0,主要!C100) -> 0 | BH18: =IFERROR(VLOOKUP($BG18,$BC$4:$BD$143,2,0),"") | BI18: =IF($BG18=0,"",COUNTIF($BG$2:$BG$46,$BG18))
A19: 3 | B19: 鲁莽攻击 | C19: 第2级起，你在自己回合内发动第一次攻击时，可以选择发动鲁莽攻击。使用此特性后，你本回合内所有使用力量值发动的近战武器攻击具有优势。此后，所有对你发动的攻击检定也将具有优势，且该优势持续存在至你的下个回合 | D19: 法术位-吟游诗人 | E19: “吟游诗人职业表”中记录了你可用以施展诗人法术的1环及更高环阶法术位数量。施展诗人法术时，你必须同时消耗其对应环阶的法术位。已消耗的法术位可在完成长休后恢复 | F19: 法术的准备与施展-牧师 | G19: “牧师职业表”里记录了你用以施展牧师法术的1环及更高环阶法术位数量。施展某个牧师法术时，你必须同时消耗其对应环阶的法术位。已消耗的法术位可在完成长休后恢复 你可以准备牧师法术列表中所有符合当前施展条件的法术。准备法术时，你所准备法术的总数等于你的感知调整值＋你的牧师职业等级（最少可以准备一个）。另外，你只能准备已经获得相应环阶法术位的法术 你可以在完成长休后改变你的准备法术列表。准备新的牧师法术列表时，你要再花时间进行祈祷和冥想。准备时，你要为你列表上每个法术的每个环阶都花费至少1分钟时间 | H19: 戏法-德鲁伊 | I19: 第1级时，你选择两项德鲁伊法术列表中的戏法作为已知法术。在获得更高的德鲁伊等级后你还可以习得其它的戏法，具体数据参见“德鲁伊职业表”中“已知戏法”一栏 | J19: =IF(OR(BI53>0,COUNTIF($BG$2:$BG$46,"战斗风格-防御")),"战斗风格-防御","") | K19: 着装护甲时，你的AC获得+1加值 | L19: 气 | M19: 第2级起，你将拥有一定数量的气作为储备。而气的储备量由你的武僧等级决定，具体数值见“武僧职业表”中“气”一栏 你可以消耗气以行使各种特性 消耗掉的气必须在你短休或长休时完成至少30分钟的冥想，才能重获所有消耗掉的气值 | N19: 战斗风格-圣武士 | O19: 第2级时，你可以选择一种战斗风格作为你的专精。同一种战斗风格不可重复选择 | P19: =IF(OR(BH58<1,COUNTIF($BG$2:$BG$46,"自然探索者")),"自然探索者","") -> 自然探索者 | Q19: 第1级起，从下列类别中选择一种偏爱地形：极地、海岸、荒漠、丛林、草原、山地、沼泽或幽暗地域。当你进行与偏好地形相关的智力或感知检定时，如果你拥有该技能的熟练项，则在检定时加入双倍熟练加值 当你在偏好地形上移动一小时或更长时间时，你获得以下增益： 你的队伍旅行时不会因困难地形而变慢 除非受魔法效应影响，否则你的队伍不会迷路 旅行时，即使你进行另一项活动，仍能对危险保持警觉 独自旅行时，你能够保持隐匿状态以正常步调移动 觅食时，你会发现两倍的食物 追踪其他生物时，你还能了解他们的确切数量、体型以及离开踪迹的时间 你在第6级和第10级时将分别获得一个额外的偏好地形 | R19: 盗贼黑话 | S19: 第1级时，你掌握了盗贼黑话——一门混合了土话、术语和密语的秘密语言，掌握这门语言后，你可以在平时对话中不落痕迹的加入隐藏信息。而只有另一个懂盗贼黑话的生物才能看懂这些隐藏信息。不过这种交流方式需要花费四倍于直接交流所需要的时间 另外，你还习得一套用以传达简单短小信息的秘密符文和标识。它能发布的内容诸如某地区是否危险，是否受盗贼公会管辖，附近是否有战利品，附近的人是否好主顾或者路上是否有安全的房屋以供庇护 | T19: 法术位-术士 | U19: “术士职业表”中记录了你可用以施展术士法术的1环及更高环阶法术位数量。施展术士法术时，你必须同时消耗其对应环阶的法术位。已消耗的法术位可在完成长休后恢复 | V19: 戏法-邪术师 | W19: 第1级时，你从邪术师法术列表中选择两个戏法作为已知法术。在获得更高邪术师等级后你还可以习得其它的戏法，具体数量见“邪术师职业表”中“已知戏法”一栏 | X19: 法术位-法师 | Y19: “法师职业表”中记录了你可用以施展法师法术的1环及更高环阶法术位数量。施展法师法术时，你必须同时消耗其对应环阶的法术位。已消耗的法术位可在完成长休后恢复 | Z19: 必备工具 | AA19: 当你使用施法特性来施展法术时，必须手持盗贼工具或工匠工具作为法器。你必须熟练这一工具才能将它作为法器使用 第2级起，你也能使用任何你进行过物品注法的物品来作为法器使用 | AB19: 职业重复 | AC19: 错误子职 | AD19: =IF($AD16=0,"",(COUNTIF($AI$18:$AI$35,$AD16))) -> 0 | AE19: =IF(AND(AD16=0,AI17<>""),1,0) -> #N/A | AF19: =IF(AND(AC16<>0,AE16=0),1,0) -> 0 | AG19: {=INDEX(AI:AI,SMALL(IF($AI$2:$AI$14<>"",ROW($2:$14),15),ROW(AI3)))&""} | AH19: {=INDEX(AJ:AJ,SMALL(IF($AJ$2:$AJ$14<>"",ROW($2:$14),15),ROW(AJ3)))&""} | AI19: =INDEX($B$2:$S$14,AI$17,2) -> #N/A | AJ19: =INDEX($B$2:$S$14,AJ$17,2) -> #N/A | AK19: =INDEX($B$2:$S$14,AK$17,2) -> #N/A | AL19: {=INDEX(AI:AI,SMALL(IF($AI$18:$AI$35<>"",ROW($18:$35),36),ROW(AI17)))&""} -> #N/A | AM19: 精魂学院 | AO19: 51 | AP19: =IF($AG$3>=14,55,IF($AG$3>=6,54,IF($AG$3>=3,53,0))) -> 0 | AQ19: =IF(AQ18+1>$AT$3,IF(AQ18+1>$AT$3,IF($AS$4+AT18>$AT$4,"",$AS$4+AT18)),AQ18+1) -> #N/A | AR19: =INDEX($B$17:$AA$154,AQ19,$AR$4) -> #N/A | AS19: =INDEX($B$17:$AA$154,AQ19,$AR$3) -> #N/A | AT19: =IF(AQ18+1>$AT$3,AT18+1,0) -> #N/A | AU19: =IF($AU18+1>$AX$3,IF($AU18+1>$AX$3,IF($AW$4+AX18>$AX$4,"",$AW$4+AX18)),$AU18+1) -> #N/A | AV19: =INDEX($B$17:$AA$154,AU19,$AV$4) -> #N/A | AW19: =INDEX($B$17:$AA$154,AU19,$AV$3) -> #N/A | AX19: =IF($AU18+1>$AX$3,$AX18+1,0) -> #N/A | AY19: =IF($AY18+1>$BB$3,IF($AY18+1>$BB$3,IF($BA$4+BB18>$BB$4,"",$BA$4+BB18)),$AY18+1) -> #N/A | AZ19: =INDEX($B$17:$AA$154,AY19,$AZ$4) -> #N/A | BA19: =INDEX($B$17:$AA$154,AY19,$AZ$3) -> #N/A | BB19: =IF($AY18+1>$BB$3,$BB18+1,0) -> #N/A | BC19: =IFERROR(INDEX($AQ$12:$BF$87,9,$BC$2),"") | BD19: =IFERROR(INDEX($AQ$12:$BF$87,9,$BD$2),"") | BE19: =IFERROR(IF(OR(BC21="",COUNTIF($BG$2:$BG$46,BC21)),"",BC21),"") | BF19: {=INDEX(BE:BE,SMALL(IF($BE$2:$BE$143<>"",ROW($2:$143),144),ROW(BE18)))&""} | BG19: =IF(主要!C101="",0,主要!C101) -> 0 | BH19: =IFERROR(VLOOKUP($BG19,$BC$4:$BD$143,2,0),"") | BI19: =IF($BG19=0,"",COUNTIF($BG$2:$BG$46,$BG19))
A20: 4 | B20: 险境感知 | C20: 第2级起，在受到你能看见的效应（诸如陷阱和法术）影响时，你对其进行的敏捷豁免具有优势。你无法在目盲、耳聋或是失能的状态下从此特性获益 | D20: 已知法术-吟游诗人 | E20: 你从诗人法术列表中选择四个1环法术作为已知法术 “吟游诗人职业表”中“已知法术”一栏记录了你获得更多已知法术时的相应等级。但是，你只能获取已有相应环阶法术位的法术 另外，你每提升一个诗人等级，可以从诗人法术列表中选择一个新法术来代替一个已知法术列表中的旧法术，不过你必须已有新法术的相应环阶法术位 | F20: 施法关键属性-牧师 | G20: 当你的牧师法术需要施法关键属性时均指向你的感知值。而你牧师法术的豁免DC和攻击检定，则使用你的感知调整值 法术豁免DC＝8＋你的熟练加值＋你的感知调整值 法术攻击调整值＝你的熟练加值＋你的感知调整值 | H20: 法术的准备与施展-德鲁伊 | I20: “德鲁伊职业表”里记录了你用以施展德鲁伊法术的一环及更高环阶法术位数量。施展某个德鲁伊法术时，你必须同时消耗其对应环阶的法术位。已消耗的法术位可在完成长休后恢复 你可以准备德鲁伊法术列表中所有符合当前施展条件的法术。准备法术时，你所准备法术的总数等于你的感知调整值＋你的德鲁伊职业等级（最少可以准备一个）。另外，你只能准备已经获得相应环阶法术位的法术 你可以在完成长休后改变你的准备法术列表。如需准备新的德鲁伊法术，则需要你再花时间进行祈祷和冥想。准备法术时，法术的每个环阶平均要花费至少1分钟的准备时间 | J20: =IF(OR(BI53>0,COUNTIF($BG$2:$BG$46,"战斗风格-对决")),"战斗风格-对决","") | K20: 单手持用一把近战武器，且并未同时持用其他武器时，你用该武器攻击的伤害掷骰获得+2加值 | L20: 疾风连击 | M20: 第2级起，你在自己回合内执行攻击动作后，可立即消耗1点气并以一个附赠动作发动两次徒手打击 | N20: =IF(OR(BI53>0,COUNTIF($BG$2:$BG$46,"战斗风格-防御")),"战斗风格-防御","") | O20: 着装护甲时，你的AC获得+1加值 | P20: =IF(AND(综合数据!B14=TRUE,OR(BH58<1,COUNTIF($BG$2:$BG$46,"熟练探险家"))),"熟练探险家","") -> 熟练探险家 | Q20: 第1级起，你获得以下增益： 第1级时，你选择一项你拥有熟练的技能，你在使用该技能时的任何属性检定的使用两倍的熟练加值。此外，你可以额外说，读，写两门你选择的语言 第6级起，你的步行速度增加5，同时你获得等于你步行速度的攀爬速度和游泳速度 第10级起，以一个动作，你能够给予自己1d8+你的感知调整值的临时生命值。你能够使用此特性的次数等于你的熟练加值次（最少1次），已消费的次数可以通过完成一次长休进行恢复。此外，当你完成一次短休时，你的力竭等级减少1（若有） | R20: 灵巧动作 | S20: 第2级起，你在战斗中每回合可执行一次附赠动作，该附赠动作可用以执行撤离、疾走或躲藏三种动作项其中之一 | T20: 已知法术-术士 | U20: 你从术士法术列表中选择两个1环法术作为已知法术 “术士职业表”中“已知法术”一栏记录了你获得更多已知法术时的相应等级。但是，你只能获取已有相应环阶法术位的法术 另外，你每提升一个术士等级，可以从术士法术列表中选择一个新法术来代替一个已知法术列表中的旧法术，不过你必须已有新法术的相应环阶法术位 | V20: 法术位-邪术师 | W20: “邪术师职业表”中记录了你可用以施展邪术师法术的1环及更高环阶法术位数量。施展邪术师法术时，你必须同时消耗其对应环阶的法术位。已消耗的法术位可在完成长休或短休后恢复 | X20: 法术书 | Y20: 第1级时，你从法师法术列表中选择六个1环法术作为已知法术。你的法术书储存着你除戏法外的所有已知法术，而你的戏法则直接铭记在你脑海中 你在等级提升时加入法术书中的法师法术，体现了你的奥术研究成果，同时也代表你对多元宇宙本质的认知的新突破。你也许会在冒险过程中发现其他的法术 你的法术书是一本独特的法术合集，其上有着独特的使用痕迹和空白页 | Z20: 戏法-奇械师 | AA20: 第1级时，你从奇械师法术列表中选择两个戏法作为已知法术。在获得更高奇械师等级后你还可以习得其它的戏法，具体数量见“奇械师职业表”中“已知戏法”一栏 当你提升一个奇械师等级时，可以从奇械师戏法列表表中选择一个你未习得的戏法，替换一个你已经习得的戏法 | AB20: =COUNTIF(AB17:AB18,">1") -> 0 | AC20: =COUNTIF(AD19:AD21,"=0") -> 1 | AD20: =IF($AD17=0,"",COUNTIF($AJ$18:$AJ$35,$AD17)) | AE20: =IF(AND(AD17=0,AJ17<>""),1,0) -> #N/A | AF20: =IF(AND(AC17<>0,AE17=0),1,0) -> 0 | AG20: {=INDEX(AI:AI,SMALL(IF($AI$2:$AI$14<>"",ROW($2:$14),15),ROW(AI4)))&""} | AH20: {=INDEX(AJ:AJ,SMALL(IF($AJ$2:$AJ$14<>"",ROW($2:$14),15),ROW(AJ4)))&""} | AI20: =INDEX($B$2:$S$14,AI$17,3) -> #N/A | AJ20: =INDEX($B$2:$S$14,AJ$17,3) -> #N/A | AK20: =INDEX($B$2:$S$14,AK$17,3) -> #N/A | AL20: {=INDEX(AI:AI,SMALL(IF($AI$18:$AI$35<>"",ROW($18:$35),36),ROW(AI18)))&""} -> #N/A | AM20: 牧师 | AN20: 3 | AO20: 1 | AP20: =IF($AG$4>=10,15,IF($AG$4>=8,14,IF($AG$4>=5,13,IF($AG$4>=4,12,IF($AG$4>=2,11,IF($AG$4>=1,8,0)))))) -> 0 | AQ20: =IF(AQ19+1>$AT$3,IF(AQ19+1>$AT$3,IF($AS$4+AT19>$AT$4,"",$AS$4+AT19)),AQ19+1) -> #N/A | AR20: =INDEX($B$17:$AA$154,AQ20,$AR$4) -> #N/A | AS20: =INDEX($B$17:$AA$154,AQ20,$AR$3) -> #N/A | AT20: =IF(AQ19+1>$AT$3,AT19+1,0) -> #N/A | AU20: =IF($AU19+1>$AX$3,IF($AU19+1>$AX$3,IF($AW$4+AX19>$AX$4,"",$AW$4+AX19)),$AU19+1) -> #N/A | AV20: =INDEX($B$17:$AA$154,AU20,$AV$4) -> #N/A | AW20: =INDEX($B$17:$AA$154,AU20,$AV$3) -> #N/A | AX20: =IF($AU19+1>$AX$3,$AX19+1,0) -> #N/A | AY20: =IF($AY19+1>$BB$3,IF($AY19+1>$BB$3,IF($BA$4+BB19>$BB$4,"",$BA$4+BB19)),$AY19+1) -> #N/A | AZ20: =INDEX($B$17:$AA$154,AY20,$AZ$4) -> #N/A | BA20: =INDEX($B$17:$AA$154,AY20,$AZ$3) -> #N/A | BB20: =IF($AY19+1>$BB$3,$BB19+1,0) -> #N/A | BC20: =IFERROR(INDEX($AQ$12:$BF$87,10,$BC$2),"") | BD20: =IFERROR(INDEX($AQ$12:$BF$87,10,$BD$2),"") | BE20: =IFERROR(IF(OR(BC22="",COUNTIF($BG$2:$BG$46,BC22)),"",BC22),"") | BF20: {=INDEX(BE:BE,SMALL(IF($BE$2:$BE$143<>"",ROW($2:$143),144),ROW(BE19)))&""} | BG20: =IF(主要!C102="",0,主要!C102) -> 0 | BH20: =IFERROR(VLOOKUP($BG20,$BC$4:$BD$143,2,0),"") | BI20: =IF($BG20=0,"",COUNTIF($BG$2:$BG$46,$BG20))
A21: 5 | B21: 原初道途 | C21: 第3级时，你选择一种道途来塑造你狂怒时的特质。随后，你将在第3、第6、第10、第14级时获得所选道途的相应特性 | D21: 施法关键属性-吟游诗人 | E21: 当你的诗人法术需要施法关键属性时均指向你的魅力值。而你诗人法术的豁免DC和攻击检定，则使用你的魅力调整值 法术豁免DC＝8＋你的熟练加值＋你的魅力调整值 法术攻击调整值＝你的熟练加值＋你的魅力调整值 | F21: 仪式施法-牧师 | G21: 如果你所准备牧师法术中的某法术有带仪式标签，则你可以用这些法术进行仪式施法 | H21: 施法关键属性-德鲁伊 | I21: 当你的德鲁伊法术需要施法关键属性时均指向你的感知值。而你德鲁伊法术的豁免DC和攻击检定，则使用你的感知调整值 法术豁免DC＝8＋你的熟练加值＋你的感知调整值 法术攻击调整值＝你的熟练加值＋你的感知调整值 | J21: =IF(OR(BI53>0,COUNTIF($BG$2:$BG$46,"战斗风格-巨武器战斗")),"战斗风格-巨武器战斗","") | K21: 双手持用一把近战武器发动攻击时，如果你的伤害掷骰掷出1或2，则可以选择重掷。你必须接受重掷的数值。此外，该武器必须具有双手或两用属性 | L21: 坚强防御 | M21: 第2级起，你在自己回合内，可以消耗1点气，并以一个附赠动作的形式来执行回避动作 | N21: =IF(OR(BI53>0,COUNTIF($BG$2:$BG$46,"战斗风格-对决")),"战斗风格-对决","") | O21: 单手持用一把近战武器，且并未同时持用其他武器时，你使用该武器进行攻击的伤害掷骰获得+2加值 | P21: 战斗风格‐游侠 | Q21: 第2级时，你可以选择一种战斗风格作为你的专精。同一种战斗风格不可重复选择 | R21: 游荡者范型 | S21: 第3级时，你选择学习一种特定的战斗范型。随后，你将在第3、第9、第13和第17级获得所选范型的相应特性 | T21: 施法关键属性-术士 | U21: 当你的术士法术需要施法关键属性时均指向你的魅力值。而你术士法术的豁免DC和攻击检定，则使用你的魅力调整值 法术豁免DC＝8＋你的熟练加值＋你的魅力调整值 法术攻击调整值＝你的熟练加值＋你的魅力调整值 | V21: 已知法术-邪术师 | W21: 你从邪术师法术列表中选择两个1环法术作为已知法术 “邪术师职业表”中“已知法术”一栏记录了你获得更多已知法术时的相应等级。但是，你只能获取已有相应环阶法术位的法术 另外，你每提升一个邪术师等级，可以从邪术师法术列表中选择一个新法术来代替一个已知法术列表中的旧法术，不过你必须已有新法术的相应环阶法术位 | X21: 将法术抄入法术书 | Y21: 当你发现一道1环或更高环阶的法师法术时，你可以将其抄入你的法术书中，前提是，你必须能够准备该法术，且也有时间去解读和复制它 抄写法术时，你必须先重构该法术的基础式，然后解读抄写该法术的法师所使用的独特符号系统。你必须反复练习这个法术，直至完全理解其所需的咒语和手势，最后用再用你自己的符号系统将之抄入法术书 这个过程将消耗每法术环阶2小时的时间和每法术环阶50gp的资金。这笔开销代表你在练习这个法术的过程中消耗的材料成分，还有抄录法术所需的上好的墨水。当你花费了这一笔时间和金钱后，你就可以如同准备其他法术一般准备这个法术了 | Z21: 法术的准备和施展 | AA21: “奇械师职业表”里记录了你用以施展法师法术的一环及更高环阶法术位数量。施展某个奇械师法术时，你必须同时消耗其对应环阶的法术位。已消耗的法术位可在完成长休后恢复 你可以准备奇械师法术列表中所有符合当前施展条件的法术。准备法术时，你所准备法术的总数等于你的智力调整值＋你的奇械师职业等级的一半（最少可以准备一个）。另外，你只能准备已经获得相应环阶法术位的法术 你可以在完成长休后改变你的准备法术列表。如需准备新的奇械师法术，你需要花时间来调整你的法器。准备法术时，法术的每个环阶平均要花费至少1分钟的准备时间 | AB21: 未选子职 | AC21: =COUNTIF(AE19:AE21,"=1") -> 0 | AD21: =IF($AD18=0,"",COUNTIF($AK$18:$AK$35,$AD18)) | AE21: =IF(AND(AD18=0,AK17<>""),1,0) -> #N/A | AF21: =IF(AND(AC18<>0,AE18=0),1,0) -> 0 | AG21: {=INDEX(AI:AI,SMALL(IF($AI$2:$AI$14<>"",ROW($2:$14),15),ROW(AI5)))&""} | AH21: {=INDEX(AJ:AJ,SMALL(IF($AJ$2:$AJ$14<>"",ROW($2:$14),15),ROW(AJ5)))&""} | AI21: =INDEX($B$2:$S$14,AI$17,4) -> #N/A | AJ21: =INDEX($B$2:$S$14,AJ$17,4) -> #N/A | AK21: =INDEX($B$2:$S$14,AK$17,4) -> #N/A | AL21: 子职2 | AM21: 知识领域 | AO21: 16 | AP21: =IF($AG$4>=17,21,IF($AG$4>=8,20,IF($AG$4>=6,19,IF($AG$4>=2,18,IF($AG$4>=1,17,0))))) -> 0 | AQ21: =IF(AQ20+1>$AT$3,IF(AQ20+1>$AT$3,IF($AS$4+AT20>$AT$4,"",$AS$4+AT20)),AQ20+1) -> #N/A | AR21: =INDEX($B$17:$AA$154,AQ21,$AR$4) -> #N/A | AS21: =INDEX($B$17:$AA$154,AQ21,$AR$3) -> #N/A | AT21: =IF(AQ20+1>$AT$3,AT20+1,0) -> #N/A | AU21: =IF($AU20+1>$AX$3,IF($AU20+1>$AX$3,IF($AW$4+AX20>$AX$4,"",$AW$4+AX20)),$AU20+1) -> #N/A | AV21: =INDEX($B$17:$AA$154,AU21,$AV$4) -> #N/A | AW21: =INDEX($B$17:$AA$154,AU21,$AV$3) -> #N/A | AX21: =IF($AU20+1>$AX$3,$AX20+1,0) -> #N/A | AY21: =IF($AY20+1>$BB$3,IF($AY20+1>$BB$3,IF($BA$4+BB20>$BB$4,"",$BA$4+BB20)),$AY20+1) -> #N/A | AZ21: =INDEX($B$17:$AA$154,AY21,$AZ$4) -> #N/A | BA21: =INDEX($B$17:$AA$154,AY21,$AZ$3) -> #N/A | BB21: =IF($AY20+1>$BB$3,$BB20+1,0) -> #N/A | BC21: =IFERROR(INDEX($AQ$12:$BF$87,11,$BC$2),"") | BD21: =IFERROR(INDEX($AQ$12:$BF$87,11,$BD$2),"") | BE21: =IFERROR(IF(OR(BC23="",COUNTIF($BG$2:$BG$46,BC23)),"",BC23),"") | BF21: {=INDEX(BE:BE,SMALL(IF($BE$2:$BE$143<>"",ROW($2:$143),144),ROW(BE20)))&""} | BG21: =IF(主要!C103="",0,主要!C103) -> 0 | BH21: =IFERROR(VLOOKUP($BG21,$BC$4:$BD$143,2,0),"") | BI21: =IF($BG21=0,"",COUNTIF($BG$2:$BG$46,$BG21))
A22: 6 | B22: =IF(综合数据!B14=TRUE,"原初学识","") -> 原初学识 | C22: 第3级时，你可以从野蛮人技能熟练项列表中选择一个技能，获得该技能的熟练 第10级时，你可以再选择一个技能获得熟练项 | D22: 仪式施法-吟游诗人 | E22: 如果你已知法术列表中的某法术带有仪式标签，则你可以用这些法术进行仪式施法 | F22: 法器-牧师 | G22: 你可以使用圣徽作为施展牧师法术的法器 | H22: 仪式施法-德鲁伊 | I22: 如果你所准备德鲁伊法术中的某法术有带仪式标签，则你可以用这些法术进行仪式施法 | J22: =IF(OR(BI53>0,COUNTIF($BG$2:$BG$46,"战斗风格-守护")),"战斗风格-守护","") | K22: 当某个你能看见的生物攻击你身边5尺内除你之外的目标时，你可以用反应迫使该攻击的攻击检定具有劣势。此时你必须持用盾牌 | L22: 飞檐走壁 | M22: 第2级起，你在自己回合内，可以消耗1点气，并以一个附赠动作的形式来执行撤离动作或疾走动作，同时使你该回合内的跳跃距离翻倍 | N22: =IF(OR(BI53>0,COUNTIF($BG$2:$BG$46,"战斗风格-巨武器战斗")),"战斗风格-巨武器战斗","") | O22: 双手持用一把近战武器发动攻击时，若你的伤害掷骰掷出1或2，则可以选择重掷。你必须接受重掷的数值。此外，该武器必须具有双手或两用属性 | P22: =IF(OR(BI53>0,COUNTIF($BG$2:$BG$46,"战斗风格-箭术")),"战斗风格-箭术","") | Q22: 使用远程武器进行攻击检定时具有+2加值 | R22: =IF(综合数据!B14=TRUE,"手稳就准","") -> 手稳就准 | S22: 第3级起，以一个附赠动作，你在当前回合为你的下一次攻击提供优势。你只能在你本回合还没有移动的时候使用这个附赠动作，而且在你使用这个附赠动作后，你的速度在当前回合里降为0 | T22: 法器-术士 | U22: 你可以使用奥术法器作为施展术士法术的法器 | V22: 施法关键属性-邪术师 | W22: 当你的邪术师法术需要施法关键属性时均指向你的魅力值。而你邪术师法术的豁免DC和攻击检定，则使用你的魅力调整值 法术豁免DC＝8＋你的熟练加值＋你的魅力调整值 法术攻击调整值＝你的熟练加值＋你的魅力调整值 | X22: 替换法术书 | Y22: 你可以把法术从你的法术书抄到另一本书上——例如，你打算为你的法术书做一个备份时，就可以这么做。这个进程和将新法术抄入法术书相似，但更快也更简单，因为你早已理解了你自己的符号系统，也知道如何施展这个法术。这时，你只需要花费每环阶1小时和每环阶10gp的花费 如果你弄丢了法术书，你也可以用相同的流程将你准备的法术抄入一本新法术书中。而要填满法术书的其余部分就需要你自己去寻找新的法术了。所以，很多法师都喜欢在安全的地方保存好备份的法术书 | Z22: 施法关键属性-奇械师 | AA22: 当你的奇械师法术需要施法关键属性时均指向你的智力值。而你奇械师法术的豁免DC和攻击检定，则使用你的智力调整值 法术豁免DC＝8＋你的熟练加值＋你的智力调整值 法术攻击调整值＝你的熟练加值＋你的智力调整值 | AB22: 职业0级 | AC22: =COUNTIF(AF19:AF21,">=1") -> 0 | AD22: 施法等级 | AE22: =SUM(AH2:AH14) -> 0 | AG22: {=INDEX(AI:AI,SMALL(IF($AI$2:$AI$14<>"",ROW($2:$14),15),ROW(AI6)))&""} | AH22: {=INDEX(AJ:AJ,SMALL(IF($AJ$2:$AJ$14<>"",ROW($2:$14),15),ROW(AJ6)))&""} | AI22: =INDEX($B$2:$S$14,AI$17,5) -> #N/A | AJ22: =INDEX($B$2:$S$14,AJ$17,5) -> #N/A | AK22: =INDEX($B$2:$S$14,AK$17,5) -> #N/A | AL22: {=INDEX(AJ:AJ,SMALL(IF($AJ$18:$AJ$35<>"",ROW($18:$35),36),ROW(AJ1)))&""} -> #N/A | AM22: 生命领域 | AO22: 22 | AP22: =IF($AG$4>=17,28,IF($AG$4>=8,27,IF($AG$4>=6,26,IF($AG$4>=2,25,IF($AG$4>=1,24,0))))) -> 0 | AQ22: =IF(AQ21+1>$AT$3,IF(AQ21+1>$AT$3,IF($AS$4+AT21>$AT$4,"",$AS$4+AT21)),AQ21+1) -> #N/A | AR22: =INDEX($B$17:$AA$154,AQ22,$AR$4) -> #N/A | AS22: =INDEX($B$17:$AA$154,AQ22,$AR$3) -> #N/A | AT22: =IF(AQ21+1>$AT$3,AT21+1,0) -> #N/A | AU22: =IF($AU21+1>$AX$3,IF($AU21+1>$AX$3,IF($AW$4+AX21>$AX$4,"",$AW$4+AX21)),$AU21+1) -> #N/A | AV22: =INDEX($B$17:$AA$154,AU22,$AV$4) -> #N/A | AW22: =INDEX($B$17:$AA$154,AU22,$AV$3) -> #N/A | AX22: =IF($AU21+1>$AX$3,$AX21+1,0) -> #N/A | AY22: =IF($AY21+1>$BB$3,IF($AY21+1>$BB$3,IF($BA$4+BB21>$BB$4,"",$BA$4+BB21)),$AY21+1) -> #N/A | AZ22: =INDEX($B$17:$AA$154,AY22,$AZ$4) -> #N/A | BA22: =INDEX($B$17:$AA$154,AY22,$AZ$3) -> #N/A | BB22: =IF($AY21+1>$BB$3,$BB21+1,0) -> #N/A | BC22: =IFERROR(INDEX($AQ$12:$BF$87,12,$BC$2),"") | BD22: =IFERROR(INDEX($AQ$12:$BF$87,12,$BD$2),"") | BE22: =IFERROR(IF(OR(BC24="",COUNTIF($BG$2:$BG$46,BC24)),"",BC24),"") | BF22: {=INDEX(BE:BE,SMALL(IF($BE$2:$BE$143<>"",ROW($2:$143),144),ROW(BE21)))&""} | BG22: =IF(主要!C104="",0,主要!C104) -> 0 | BH22: =IFERROR(VLOOKUP($BG22,$BC$4:$BD$143,2,0),"") | BI22: =IF($BG22=0,"",COUNTIF($BG$2:$BG$46,$BG22))
A23: 7 | B23: =IF(COUNTIF($BG$2:$BG$46,"额外攻击-*"),"","额外攻击") -> 额外攻击 | C23: 第5级起，你在自己回合内执行攻击动作时可以发动两次攻击 | D23: 法器-吟游诗人 | E23: 你可以使用乐器作为施展诗人法术的法器 | F23: 神圣领域 | G23: 第1级时，你将选择一个与你所信仰神祇的神职相关的神圣领域。随后，你将在第1、第2、第6、第8、第17级时获得所选领域的相应特性 某些领域其领域法术可能并不在牧师法术列表中，此时如果你选择了该领域，则你视该领域的领域法术为你的牧师法术 | H23: 法器-德鲁伊 | I23: 你可以用德鲁伊法器作为你施展德鲁伊法术的法器 | J23: =IF(OR(BI53>0,COUNTIF($BG$2:$BG$46,"战斗风格-双武器战斗")),"战斗风格-双武器战斗","") | K23: 使用两把武器战斗时，你可以将相应属性调整值加到第二次攻击的伤害上 | L23: 无甲移动 | M23: 第2级起，当未穿着任何护甲也没持用盾牌时，你的移动速度增加10尺。该加值将随着武僧职业等级的提升而增加，具体数值见“武僧职业表”中“无甲移动”一栏 第9级起，你在自己的回合内，可以在垂直平面或水面等地形移动，但移动结束时你必须处在不会坠落的地方 | N23: =IF(OR(BI53>0,COUNTIF($BG$2:$BG$46,"战斗风格-守护")),"战斗风格-守护","") | O23: 当某个你能看见的生物攻击你身边5尺内除你之外的目标时，你可以用反应迫使该攻击的攻击检定具有劣势。此时你必须持用盾牌 | P23: =IF(OR(BI53>0,COUNTIF($BG$2:$BG$46,"战斗风格-防御")),"战斗风格-防御","") | Q23: 着装护甲时，你的AC获得+1加值 | R23: 直觉闪避 | S23: 第5级起，当一个你能看见的敌人攻击命中你时，你可以用反应让此次攻击的伤害减半 | T23: 术法起源 | U23: 第1级时，你选择一个术法起源作为你天赋魔力的源泉。随后，你将在第1、第6、第14和第18级获得所选起源的相应特性 | V23: 法器-邪术师 | W23: 你可以使用奥术法器作为施展邪术师法术的法器 | X23: 法术的准备与施展-法师 | Y23: “法师职业表”里记录了你用以施展法师法术的一环及更高环阶法术位数量。施展某个法师法术时，你必须同时消耗其对应环阶的法术位。已消耗的法术位可在完成长休后恢复 你可以准备法师法术列表中所有符合当前施展条件的法术。准备法术时，你所准备法术的总数等于你的智力调整值＋你的法师职业等级（最少可以准备一个）。另外，你只能准备已经获得相应环阶法术位的法术 你可以在完成长休后改变你的准备法术列表。如需准备新的法师法术，你要再花时间研读你的法术书，并重新记忆所准备法术的咒语和施展动作。准备法术时，法术的每个环阶平均要花费至少1分钟的准备时间 | Z23: 仪式施法-奇械师 | AA23: 如果你所准备奇械师法术中的某法术有带仪式标签，则你可以用这些法术进行仪式施法 | AB23: 职业等级 | AF23: HD | AG23: {=INDEX(AI:AI,SMALL(IF($AI$2:$AI$14<>"",ROW($2:$14),15),ROW(AI7)))&""} | AH23: {=INDEX(AJ:AJ,SMALL(IF($AJ$2:$AJ$14<>"",ROW($2:$14),15),ROW(AJ7)))&""} | AI23: =INDEX($B$2:$S$14,AI$17,6) -> #N/A | AJ23: =INDEX($B$2:$S$14,AJ$17,6) -> #N/A | AK23: =INDEX($B$2:$S$14,AK$17,6) -> #N/A | AL23: {=INDEX(AJ:AJ,SMALL(IF($AJ$18:$AJ$35<>"",ROW($18:$35),36),ROW(AJ2)))&""} -> #N/A | AM23: 光明领域 | AO23: 29 | AP23: =IF($AG$4>=17,35,IF($AG$4>=8,34,IF($AG$4>=6,33,IF($AG$4>=2,32,IF($AG$4>=1,31,0))))) -> 0 | AQ23: =IF(AQ22+1>$AT$3,IF(AQ22+1>$AT$3,IF($AS$4+AT22>$AT$4,"",$AS$4+AT22)),AQ22+1) -> #N/A | AR23: =INDEX($B$17:$AA$154,AQ23,$AR$4) -> #N/A | AS23: =INDEX($B$17:$AA$154,AQ23,$AR$3) -> #N/A | AT23: =IF(AQ22+1>$AT$3,AT22+1,0) -> #N/A | AU23: =IF($AU22+1>$AX$3,IF($AU22+1>$AX$3,IF($AW$4+AX22>$AX$4,"",$AW$4+AX22)),$AU22+1) -> #N/A | AV23: =INDEX($B$17:$AA$154,AU23,$AV$4) -> #N/A | AW23: =INDEX($B$17:$AA$154,AU23,$AV$3) -> #N/A | AX23: =IF($AU22+1>$AX$3,$AX22+1,0) -> #N/A | AY23: =IF($AY22+1>$BB$3,IF($AY22+1>$BB$3,IF($BA$4+BB22>$BB$4,"",$BA$4+BB22)),$AY22+1) -> #N/A | AZ23: =INDEX($B$17:$AA$154,AY23,$AZ$4) -> #N/A | BA23: =INDEX($B$17:$AA$154,AY23,$AZ$3) -> #N/A | BB23: =IF($AY22+1>$BB$3,$BB22+1,0) -> #N/A | BC23: =IFERROR(INDEX($AQ$12:$BF$87,13,$BC$2),"") | BD23: =IFERROR(INDEX($AQ$12:$BF$87,13,$BD$2),"") | BE23: =IFERROR(IF(OR(BC25="",COUNTIF($BG$2:$BG$46,BC25)),"",BC25),"") | BF23: {=INDEX(BE:BE,SMALL(IF($BE$2:$BE$143<>"",ROW($2:$143),144),ROW(BE22)))&""} | BG23: =IF(主要!C105="",0,主要!C105) -> 0 | BH23: =IFERROR(VLOOKUP($BG23,$BC$4:$BD$143,2,0),"") | BI23: =IF($BG23=0,"",COUNTIF($BG$2:$BG$46,$BG23))
A24: 8 | B24: 快速移动 | C24: 第5级起，你在未着装重甲时速度提升10尺 | D24: 诗人激励 | E24: 第1级起，你可以在自己回合内用一个附赠动作指定身边60尺内一个能听到你声音的生物（不能指定你自身），并使该生物获得一个诗人激励，即一个d6的激励骰 在接下来的10分钟内，该生物在进行单次属性检定、攻击检定、豁免检定时可以使用该激励骰，以将其结果加到掷骰结果中。该生物可以在d20结果掷出后，DM宣布结果前决定是否使用诗人激励。而诗人激励一旦使用即被消耗掉。一个生物同一时间里只能保有一个诗人激励 你能够使用该特性的次数等于你的魅力调整值（最低一次）。完成一次长休后，你将重获所有消耗掉的诗人激励次数 你产生的激励骰大小可以在达到本职业的特定等级时增大。第5级起为d8，第10级起为d10，而第15级起为d12 | F24: 领域法术 | G24: 第1级起，每个领域都有其相应的领域法术列表。当你获得表中所对应的牧师等级时，你将同时习得这些法术。领域法术一旦习得，将会一直在你的准备法术列表中，且不计入你的每日准备法术上限 任何领域法术对你而言都是牧师法术，而不论其是否在牧师法术列表之上 | H24: 荒野形态 | I24: 第2级起，你可以用动作以魔力变化为曾见识过的野兽形态。该特性可以使用两次，且在完成一次短休或长休后，你将重新获得所有消耗掉的荒野形态次数 你的德鲁伊职业等级决定了你可以变化的野兽种类，你可以变化成任意没有飞行或游泳速度且挑战等级为¼或更低的野兽形态。第4级起可以变化成任意没有飞行速度且挑战等级为½或更低的野兽形态。第8级起你可以变化成任意挑战等级为1或更低的野兽形态 你可以在数个小时里保持着野兽形态，其持续时间具体数值等于你的德鲁伊职业等级的一半（向下取整）。你可以在持续时间过后恢复原形，或者你也可以再次使用此特性来维持变形。另外，你也可以在你的回合内用一个附赠动作来恢复原形。在你陷入昏迷、生命值为0或者死亡的时候，变形将自动解除 你变形时必须遵从以下规则： 你的属性数据替换为新形态的数值，但你仍保持你的阵营、个性，以及智力值、感知值、魅力值。你保留技能与豁免的熟练项，并且获得新形态的技能和豁免熟练项。如果新形态的熟练项与你相同且熟练加值较高，则使用新形态的熟练加值。你不能使用新形态可能拥有的传奇动作或巢穴动作 变形后，你使用新形态的生命值和生命骰。变回原形时，你的生命值恢复变形之前的数值。而任何让你的生命值降至0的伤害，都可以使你变回原形并承受该伤害的溢出伤害量。例如，你在动物形态下受到了10点伤害而你只剩1点生命值，则你变回原形并受到9点伤害。只要超过的伤害没有将你原形的生命值降至0，你就不会因此陷入昏迷 你不能施法，并且任何说话或者需要用手的动作，在你处于野兽形态时都将受到限制。变形不会打断你正在专注的法术，也不会妨碍你执行作为已施展法术一部分的某些动作 你保持从职业、种族或其它来源特性的收益，并且可以在新形态身体能力允许下使用这些特性。不过，你无法使用任何原有的特殊感官，除非你的新形态也具有这种感官 变形时，你可以选择将你的装备丢在所处空间，或者将其融入新形态，又或者直接着装在身上。新形态直接着装的装备可以如常起作用，但DM有权基于新形态的体型和身姿作出判断，并最终决定新形态使用该装备是否合理。装备不会改变大小来适应新形态，新形态无法着装某装备时，该装备会掉落你所处空间或融入新形态中。融入新形态的装备失去其效应，且在你变回原形时才能恢复 | J24: =IF(AND(综合数据!B14=TRUE,OR(BI53>0,COUNTIF($BG$2:$BG$46,"战斗风格-盲斗"))),"战斗风格-盲斗","") | K24: 你获得10尺盲视。在10尺范围内，你可以看见除了处于全遮掩后的任何东西，哪怕你正在被目盲或是在黑暗之中。另外，你可以看见该范围内的未对你成功躲藏的隐形生物 | L24: =IF(综合数据!B14=TRUE,"专用武器","") -> 专用武器 | M24: 第2级起，每当你完成短休或长休时，可以碰触一件武器，将气集中在它之中，然后该武器就视为武僧武器，直到你再次使用这个能力 所选武器必须符合以下标准： 武器必须是简易武器或军用武器 你必须拥有其熟练项 不能拥有重型或特殊属性 | N24: =IF(AND(综合数据!B14=TRUE,OR(BI53>0,COUNTIF($BG$2:$BG$46,"战斗风格-受祝福的勇士"))),"战斗风格-受祝福的勇士","") | O24: 你从牧师法术列表中选择两种戏法习得。这些戏法对你来说是圣武士法术，这些戏法的施法关键属性是魅力。当你提升此职业的等级时，你能够将一个已知戏法替换为牧师法术列表中的另一个戏法 | P24: =IF(OR(BI53>0,COUNTIF($BG$2:$BG$46,"战斗风格-对决")),"战斗风格-对决","") | Q24: 单手持用一把近战武器，且并未同时持用其他武器时，你用该武器攻击的伤害掷骰获得+2加值 | R24: 反射闪避 | S24: 第7级起，你在成为某一范围效应影响对象时，若该效应允许你通过成功的敏捷豁免来使伤害减半，则你在该豁免成功时不受伤害，而豁免失败时只受一半伤害 | T24: 魔力泉涌 | U24: 第2级起，你体内涌现的魔力体现为你的可用术法点。你可以使用术法点创造各种魔法效应 | V24: 魔能祈唤 | W24: 第2级时，你获得两种自选的魔能祈唤。在获得更高的邪术师等级后你还可以习得其它的魔能祈唤，具体数据见“邪术师职业表”中“已知祈唤”一栏 另外，你提升邪术师职业等级时，可以用新的祈唤替换一个已学会的祈唤，但你的角色必须满足学习新祈唤的先决条件 | X24: 施法关键属性-法师 | Y24: 当你的法师法术需要施法关键属性时均指向你的智力值。而你法师法术的豁免DC和攻击检定，则使用你的智力调整值 法术豁免DC＝8＋你的熟练加值＋你的智力调整值 法术攻击调整值＝你的熟练加值＋你的智力调整值 | Z24: 物品注法 | AA24: 第2级起，每当你完成一个长休后，你可以触摸一个非魔法的物体，使用奇械师注法来把它变成一个魔法物品。注法只能作用于注法描述中写明的指定类型物品。如果该物品需要调谐，你可以在为物品进行注法的那一刻调谐到它，或者你可以放弃调谐，以便其他人能够调谐到该物品。如果你决定以后与这个物品进行调谐，你必须进行通常的调谐程序 你的注法持续时间无限，但当你死亡时，注法会在你智力调整值的天数后消失（至少1天）。如果你将某个注法从已知中替换掉，该注法的效果也将消失 你能在一次长休后为复数物品进行注法；具体数据见“奇械师职业表”中“注法数量上限”一栏。你必须触摸每一个物体，且一种注法在同一时间内只能存在于一个物品上。如果你试图超过你的最大注法量，则最旧的注法立即结束，然后新的注法适用 | AB24: =IF(AND(主要!$R$4<>"",主要!$Y$3-主要!$Y$6-主要!$Y$7>=1),1,"") -> 1 | AC24: =IF(AND(主要!$R$6<>"",主要!$Y$3-主要!$Y$4-主要!$Y$7>=1),1,"") | AD24: =IF(AND(主要!$R$7<>"",主要!$Y$3-主要!$Y$4-主要!$Y$6>=1),1,"") | AF24: D6 | AG24: {=INDEX(AI:AI,SMALL(IF($AI$2:$AI$14<>"",ROW($2:$14),15),ROW(AI8)))&""} | AH24: {=INDEX(AJ:AJ,SMALL(IF($AJ$2:$AJ$14<>"",ROW($2:$14),15),ROW(AJ8)))&""} | AI24: =INDEX($B$2:$S$14,AI$17,7) -> #N/A | AJ24: =INDEX($B$2:$S$14,AJ$17,7) -> #N/A | AK24: =INDEX($B$2:$S$14,AK$17,7) -> #N/A | AL24: {=INDEX(AJ:AJ,SMALL(IF($AJ$18:$AJ$35<>"",ROW($18:$35),36),ROW(AJ3)))&""} -> #N/A | AM24: 自然领域 | AO24: 36 | AP24: =IF($AG$4>=17,42,IF($AG$4>=8,41,IF($AG$4>=6,40,IF($AG$4>=2,39,IF($AG$4>=1,38,0))))) -> 0 | AQ24: =IF(AQ23+1>$AT$3,IF(AQ23+1>$AT$3,IF($AS$4+AT23>$AT$4,"",$AS$4+AT23)),AQ23+1) -> #N/A | AR24: =INDEX($B$17:$AA$154,AQ24,$AR$4) -> #N/A | AS24: =INDEX($B$17:$AA$154,AQ24,$AR$3) -> #N/A | AT24: =IF(AQ23+1>$AT$3,AT23+1,0) -> #N/A | AU24: =IF($AU23+1>$AX$3,IF($AU23+1>$AX$3,IF($AW$4+AX23>$AX$4,"",$AW$4+AX23)),$AU23+1) -> #N/A | AV24: =INDEX($B$17:$AA$154,AU24,$AV$4) -> #N/A | AW24: =INDEX($B$17:$AA$154,AU24,$AV$3) -> #N/A | AX24: =IF($AU23+1>$AX$3,$AX23+1,0) -> #N/A | AY24: =IF($AY23+1>$BB$3,IF($AY23+1>$BB$3,IF($BA$4+BB23>$BB$4,"",$BA$4+BB23)),$AY23+1) -> #N/A | AZ24: =INDEX($B$17:$AA$154,AY24,$AZ$4) -> #N/A | BA24: =INDEX($B$17:$AA$154,AY24,$AZ$3) -> #N/A | BB24: =IF($AY23+1>$BB$3,$BB23+1,0) -> #N/A | BC24: =IFERROR(INDEX($AQ$12:$BF$87,14,$BC$2),"") | BD24: =IFERROR(INDEX($AQ$12:$BF$87,14,$BD$2),"") | BE24: =IFERROR(IF(OR(BC26="",COUNTIF($BG$2:$BG$46,BC26)),"",BC26),"") | BF24: {=INDEX(BE:BE,SMALL(IF($BE$2:$BE$143<>"",ROW($2:$143),144),ROW(BE23)))&""} | BG24: =IF(主要!C106="",0,主要!C106) -> 0 | BH24: =IFERROR(VLOOKUP($BG24,$BC$4:$BD$143,2,0),"") | BI24: =IF($BG24=0,"",COUNTIF($BG$2:$BG$46,$BG24))
A25: 9 | B25: 野性直觉 | C25: 第7级起，你骰先攻时具有优势 此外，如果你在战斗开始时被突袭但并未陷入失能，则你仍可以在你的第一回合正常行动。不过你必须在进行任何其它行动前进入狂暴 | D25: 万事通 | E25: 第2级起，在你进行属性检定时，如果检定结果不包含你的熟练加值，则你可以将自身熟练加值的一半（向下取整）加入到检定结果中 | F25: 引导神力 | G25: 第2级时，你获得引导神祇所授予神圣能量的能力，所引导的能量将用以实现各种魔法效应。你最初将获得两种效应：驱散不死生物和另一个与你所选领域相关的效应。随着你在冒险中提升等级，某些领域会赋予更多额外的效应，具体信息可以参考相应领域的描述内容 引导神力最终产生的效应由你自行选择。引导神力后，你必须完成一次长休或短休才能再次使用该特性 第6级起，你可以在两次休息之间使用两次引导神力，第18级起可以使用三次。完成一次短休或长休后，你将重新获得所有消耗掉的引导神力次数 | H25: 德鲁伊结社 | I25: 第2级时，你将选择参与一个德鲁伊结社。随后，你将在第2、第6、第10、第14级时获得所选结社的相应特性 | J25: =IF(AND(综合数据!B14=TRUE,OR(BI53>0,COUNTIF($BG$2:$BG$46,"战斗风格-拦截"))),"战斗风格-拦截","") | K25: 当一个你可见的生物攻击距离你5尺以内你以外的目标时，你能以一个反应将目标受到的伤害减少1d10+你熟练加值（最多减到0伤害）。当你手持一面盾牌或者一把简单或军用武器时才能执行此反应 | L25: 宗派 | M25: 第3级时，你选择投入一个宗派精进你的技艺。随后，你将在第3、第6、第11、第17级时获得所选宗派的相应特性 | N25: =IF(AND(综合数据!B14=TRUE,OR(BI53>0,COUNTIF($BG$2:$BG$46,"战斗风格-盲斗"))),"战斗风格-盲斗","") | O25: 你获得10尺盲视。在此范围内，你视为能看见任何未被完全遮蔽的事物，即便你目盲或在黑暗光照下。此外，你也可以看见范围内的隐形生物，除非其针对你进行隐匿并成功 | P25: =IF(OR(BI53>0,COUNTIF($BG$2:$BG$46,"战斗风格-双武器战斗")),"战斗风格-双武器战斗","") | Q25: 使用两把武器战斗时，你可以将相应属性调整值加到第二次攻击的伤害上 | R25: 可靠才能 | S25: 第11级起，每当你进行的属性检定可以使用熟练加值时，你可以将d20骰中10以下的结果都视为10 | T25: 术法点 | U25: 第2级起，你拥有2个术法点。此后你每提升一个术士等级，都会获得更多的术法点，详见“术士职业表”中“术法点”一栏。你的术法点永远不能超过表中所列对应你当前等级的数值。而已消耗的术法点则可以通过完成一次长休进行恢复 | V25: =IF(AND(COUNTIF(法术数据!AK2:AK301,法术数据!B8)>=1,OR(BI65>0,COUNTIF($BG$2:$BG$46,"魔能祈唤-苦痛魔爆"))),"魔能祈唤-苦痛魔爆","") | W25: 施展魔能爆时，你可以将魅力调整值加到其每次命中所造成的伤害中 先决条件：习得戏法魔能爆 | X25: 仪式施法-法师 | Y25: 如果你法术书中所记录的某法术有带仪式标签，则你可以用这些法术进行仪式施法。进行仪式施法时，你不需要准备相应的法术 | Z25: 已知注法 | AA25: 第2级时，你获得四种自选的奇械师注法。在获得更高的奇械师等级后你还可以习得其它的奇械师，具体数据见“奇械师职业表”中“已知注法”一栏 另外，你提升奇械师职业等级时，可以用新的注法替换一个已学会的注法，但你的角色必须满足学习新注法的先决条件 除非注法的描述中写明，否则你无法重复学习同一个注法 | AB25: =IF(AND(主要!$R$4<>"",主要!$Y$3-主要!$Y$6-主要!$Y$7>=2),2,"") | AC25: =IF(AND(主要!$R$6<>"",主要!$Y$3-主要!$Y$4-主要!$Y$7>=2),2,"") | AD25: =IF(AND(主要!$R$7<>"",主要!$Y$3-主要!$Y$4-主要!$Y$6>=2),2,"") | AF25: D8 | AG25: {=INDEX(AI:AI,SMALL(IF($AI$2:$AI$14<>"",ROW($2:$14),15),ROW(AI9)))&""} | AH25: {=INDEX(AJ:AJ,SMALL(IF($AJ$2:$AJ$14<>"",ROW($2:$14),15),ROW(AJ9)))&""} | AI25: =INDEX($B$2:$S$14,AI$17,8) -> #N/A | AJ25: =INDEX($B$2:$S$14,AJ$17,8) -> #N/A | AK25: =INDEX($B$2:$S$14,AK$17,8) -> #N/A | AL25: {=INDEX(AJ:AJ,SMALL(IF($AJ$18:$AJ$35<>"",ROW($18:$35),36),ROW(AJ4)))&""} -> #N/A | AM25: 风暴领域 | AO25: 43 | AP25: =IF($AG$4>=17,49,IF($AG$4>=8,48,IF($AG$4>=6,47,IF($AG$4>=2,46,IF($AG$4>=1,45,0))))) -> 0 | AQ25: =IF(AQ24+1>$AT$3,IF(AQ24+1>$AT$3,IF($AS$4+AT24>$AT$4,"",$AS$4+AT24)),AQ24+1) -> #N/A | AR25: =INDEX($B$17:$AA$154,AQ25,$AR$4) -> #N/A | AS25: =INDEX($B$17:$AA$154,AQ25,$AR$3) -> #N/A | AT25: =IF(AQ24+1>$AT$3,AT24+1,0) -> #N/A | AU25: =IF($AU24+1>$AX$3,IF($AU24+1>$AX$3,IF($AW$4+AX24>$AX$4,"",$AW$4+AX24)),$AU24+1) -> #N/A | AV25: =INDEX($B$17:$AA$154,AU25,$AV$4) -> #N/A | AW25: =INDEX($B$17:$AA$154,AU25,$AV$3) -> #N/A | AX25: =IF($AU24+1>$AX$3,$AX24+1,0) -> #N/A | AY25: =IF($AY24+1>$BB$3,IF($AY24+1>$BB$3,IF($BA$4+BB24>$BB$4,"",$BA$4+BB24)),$AY24+1) -> #N/A | AZ25: =INDEX($B$17:$AA$154,AY25,$AZ$4) -> #N/A | BA25: =INDEX($B$17:$AA$154,AY25,$AZ$3) -> #N/A | BB25: =IF($AY24+1>$BB$3,$BB24+1,0) -> #N/A | BC25: =IFERROR(INDEX($AQ$12:$BF$87,15,$BC$2),"") | BD25: =IFERROR(INDEX($AQ$12:$BF$87,15,$BD$2),"") | BE25: =IFERROR(IF(AND(NOT(BC27="注法-复制魔法物品"),OR(BC27="",COUNTIF($BG$2:$BG$46,BC27))),"",BC27),"") | BF25: {=INDEX(BE:BE,SMALL(IF($BE$2:$BE$143<>"",ROW($2:$143),144),ROW(BE24)))&""} | BG25: =IF(主要!C107="",0,主要!C107) -> 0 | BH25: =IFERROR(VLOOKUP($BG25,$BC$4:$BD$143,2,0),"") | BI25: =IF($BG25=0,"",COUNTIF($BG$2:$BG$46,$BG25))
A26: 10 | B26: =IF(综合数据!B14=TRUE,"直觉猛扑","") -> 直觉猛扑 | C26: 第7级起，作为你进入狂暴状态的附赠动作的一部分，你可以移动一段距离。这段距离长度是你速度的一半 | D26: 休憩曲 | E26: 第2级起，如果你或任何友方生物可以在其短休时听到你的演奏声，且决定在此时使用生命骰恢复生命值，则其恢复量可以额外增加1d6 该额外恢复的数值在达到特定职业等级时可以再增加。第9级起增为1d8，第13级起增为1d10，第17级起增为1d12 | F26: 引导神力-驱散不死生物 | G26: 第2级起，你以一个动作展示你的圣徽，并说出一段谴责不死生物的祷言。你身边30尺范围内能够看到圣徽或听到你祷言的不死生物必须进行一次感知豁免，豁免失败则受到驱散，其效应持续1分钟或直到其受到任何伤害 一个被驱散的生物必须花费其回合内的所有速度尽力远离你，而且无法主动靠近你30尺内。被驱散的生物无法使用反应，只能使用既有的疾走动作或从任何妨碍他们移动的效应中挣脱。该生物无路可走时会使用“回避”动作 豁免DC等于你的牧师法术豁免DC | H26: =IF(综合数据!B14=TRUE,"荒野伙伴","") -> 荒野伙伴 | I26: 第2级起，以一个动作，你能够消耗一次荒野变形使用次数来施放一次无需材料的获得魔宠法术 当你以此方法施放该法术时，魔宠的类型是精类而不是野兽，魔宠会在等同于你德鲁伊等级一半的小时数后消失 | J26: =IF(AND(综合数据!B14=TRUE,OR(BI53>0,COUNTIF($BG$2:$BG$46,"战斗风格-卓越技巧"))),"战斗风格-卓越技巧","") | K26: 你从战斗大师武术范型的战技列表中习得一项战技。如果该战技需要豁免，则豁免DC为8+你的熟练加值+你的力量或敏捷调整值（由你选择）。 你获得一个d6的卓越骰（此卓越骰与任何你能够其他方式获得的卓越骰累计）。此卓越骰可用于启动你的战技。卓越骰一经使用即消耗，并在完成一次短休或长休后恢复 | L26: 拨挡飞弹 | M26: 第3级起，你可以用你的反应拨挡或抓取一个击中你的远程武器攻击。使用本特性后，该次攻击的伤害将被削弱，其减数值等于1d10+你的敏捷调整值+你的武僧职业等级 当被拨挡攻击的伤害减少至0，且实施伤害的飞弹可以被你单手抓住时，你可以用此时空闲的手去抓取该飞弹。此时你可以消耗1点气以该“飞弹”进行一次远程攻击，而该攻击将视为本次反应的一部分。无论你是否具有被拨挡武器的熟练项，本次攻击中你都视为进行具有熟练项的攻击，所使用的飞弹也视为武僧武器，其射程为20/60尺 | N26: =IF(AND(综合数据!B14=TRUE,OR(BI53>0,COUNTIF($BG$2:$BG$46,"战斗风格-拦截"))),"战斗风格-拦截","") | O26: 当一个你可见的生物攻击并击中了你5尺内一个你以外的生物时，你可以用反应减少该目标受到的伤害，减少数值为1d10+你的熟练加值。你必须正在持用一面盾牌或一把简单武器或军用武器才能使用此能力 | P26: =IF(AND(综合数据!B14=TRUE,OR(BI53>0,COUNTIF($BG$2:$BG$46,"战斗风格-盲斗"))),"战斗风格-盲斗","") | Q26: 你获得10尺盲视。在10尺范围内，你可以看见除了处于全遮掩后的任何东西，哪怕你正在被目盲或是在黑暗之中。另外，你可以看见该范围内的隐形生物，除非该生物成功地对你躲藏 | R26: 听声辨位 | S26: 第14级起，只要能听到声音，你就可以定位身边10尺内躲藏或隐形的生物 | T26: 灵活施法 | U26: 第2级起，你可以使用术法点来获得额外的法术位，或是消耗法术位来换取额外的术法点。随着术士等级的提升，你还可以学会其他术法点的使用方法 | V26: =IF(OR(BI65>0,COUNTIF($BG$2:$BG$46,"魔能祈唤-幽影护甲")),"魔能祈唤-幽影护甲","") | W26: 你可以随意以自身为目标施展法师护甲，且无需消耗法术位和材料成分 | X26: 法器-法师 | Y26: 你可以用奥术法器作为你施展法师法术的法器 | Z26: =IF(OR(BI67>0,COUNTIF($BG$2:$BG$46,"注法-增强奥术法器")),"注法-增强奥术法器","") | AA26: 物品：一根权杖、法杖或是魔杖（需调谐） 当持续此物品时，持有者的法术攻击检定获得+1加值，同时在进行法术法术攻击时无视半身掩护 10级起，该加值变成+2 | AB26: =IF(AND(主要!$R$4<>"",主要!$Y$3-主要!$Y$6-主要!$Y$7>=3),3,"") | AC26: =IF(AND(主要!$R$6<>"",主要!$Y$3-主要!$Y$4-主要!$Y$7>=3),3,"") | AD26: =IF(AND(主要!$R$7<>"",主要!$Y$3-主要!$Y$4-主要!$Y$6>=3),3,"") | AF26: D10 | AG26: {=INDEX(AI:AI,SMALL(IF($AI$2:$AI$14<>"",ROW($2:$14),15),ROW(AI10)))&""} | AH26: {=INDEX(AJ:AJ,SMALL(IF($AJ$2:$AJ$14<>"",ROW($2:$14),15),ROW(AJ10)))&""} | AI26: =INDEX($B$2:$S$14,AI$17,9) -> #N/A | AJ26: =INDEX($B$2:$S$14,AJ$17,9) -> #N/A | AK26: =INDEX($B$2:$S$14,AK$17,9) -> #N/A | AL26: {=INDEX(AJ:AJ,SMALL(IF($AJ$18:$AJ$35<>"",ROW($18:$35),36),ROW(AJ5)))&""} -> #N/A | AM26: 诡术领域 | AO26: 50 | AP26: =IF($AG$4>=17,55,IF($AG$4>=8,54,IF($AG$4>=6,53,IF($AG$4>=2,52,IF($AG$4>=1,51,0))))) -> 0 | AQ26: =IF(AQ25+1>$AT$3,IF(AQ25+1>$AT$3,IF($AS$4+AT25>$AT$4,"",$AS$4+AT25)),AQ25+1) -> #N/A | AR26: =INDEX($B$17:$AA$154,AQ26,$AR$4) -> #N/A | AS26: =INDEX($B$17:$AA$154,AQ26,$AR$3) -> #N/A | AT26: =IF(AQ25+1>$AT$3,AT25+1,0) -> #N/A | AU26: =IF($AU25+1>$AX$3,IF($AU25+1>$AX$3,IF($AW$4+AX25>$AX$4,"",$AW$4+AX25)),$AU25+1) -> #N/A | AV26: =INDEX($B$17:$AA$154,AU26,$AV$4) -> #N/A | AW26: =INDEX($B$17:$AA$154,AU26,$AV$3) -> #N/A | AX26: =IF($AU25+1>$AX$3,$AX25+1,0) -> #N/A | AY26: =IF($AY25+1>$BB$3,IF($AY25+1>$BB$3,IF($BA$4+BB25>$BB$4,"",$BA$4+BB25)),$AY25+1) -> #N/A | AZ26: =INDEX($B$17:$AA$154,AY26,$AZ$4) -> #N/A | BA26: =INDEX($B$17:$AA$154,AY26,$AZ$3) -> #N/A | BB26: =IF($AY25+1>$BB$3,$BB25+1,0) -> #N/A | BC26: =IFERROR(INDEX($AQ$12:$BF$87,16,$BC$2),"") | BD26: =IFERROR(INDEX($AQ$12:$BF$87,16,$BD$2),"") | BE26: =IFERROR(IF(OR(BC28="",COUNTIF($BG$2:$BG$46,BC28)),"",BC28),"") | BF26: {=INDEX(BE:BE,SMALL(IF($BE$2:$BE$143<>"",ROW($2:$143),144),ROW(BE25)))&""} | BG26: =IF(主要!C108="",0,主要!C108) -> 0 | BH26: =IFERROR(VLOOKUP($BG26,$BC$4:$BD$143,2,0),"") | BI26: =IF($BG26=0,"",COUNTIF($BG$2:$BG$46,$BG26))
A27: 11 | B27: 凶蛮重击 | C27: 第9级起，计算近战攻击的重击伤害时，你可以额外骰一个所用武器的伤害骰 第13级起，你可以额外骰两个；第17级时，你可以额外骰三个 | D27: =IF(综合数据!B14=TRUE,"魔法激励","") -> 魔法激励 | E27: 第2级起，如果一个生物拥有来自你的诗人激励骰子，在他释放一个恢复生命值或者造成伤害的法术时，他可以掷出激励骰子并选择法术的其中一个被法术影响的目标，在对该目标的恢复或者伤害数值上加上诗人激励骰的掷骰结果。这个诗人激励骰子随即被消耗 | F27: =IF(综合数据!B14=TRUE,"神力掌控","") -> 神力掌控 | G27: 第2级起，你可以花费一次你的引导神力次数来充能你的法术。你可以用一个附赠动作触碰你的圣徽并祈祷，你恢复一个环阶不超过你熟练加值的一半（向上取整）的法术位。你能使用此特性的次数取决于你此职业的等级：2级一次；6级两次；18级三次。完成一次长休后，你将恢复所有已消耗的次数 | H27: =IF(综合数据!B14=TRUE,"替换戏法-德鲁伊","") -> 替换戏法-德鲁伊 | I27: 第4级起，当你的德鲁伊职业等级抵达能让你获得属性值提升时，你可以将一个你通过此职业的施法特性学会的德鲁伊戏法替换为德鲁伊法术列表中的另一个戏法 | J27: =IF(AND(综合数据!B14=TRUE,OR(BI53>0,COUNTIF($BG$2:$BG$46,"战斗风格-投掷武器战斗"))),"战斗风格-投掷武器战斗","") | K27: 你可以在使用一件带有投掷属性武器进行进攻时，将那件武器作为攻击的一部分而拔出。另外，在你以一件投掷武器于远程攻击中命中对手时，你的伤害掷骰+2 | L27: =IF(综合数据!B14=TRUE,"驭气以击","") -> 驭气以击 | M27: 第3级起，如果你在你的回合中执行动作时花费了1点或更多的气，则你可以在回合结束前用1附赠动作以徒手打击或武僧武器进行一次攻击 | N27: 施法-圣武士 | O27: 你学会通过冥想与祈祷引导神圣魔法，其原理与牧师相仿 | P27: =IF(AND(综合数据!B14=TRUE,OR(BI53>0,COUNTIF($BG$2:$BG$46,"战斗风格-德鲁伊教战士"))),"战斗风格-德鲁伊教战士","") | Q27: 你学会两个来自德鲁伊法术列表的你自选的戏法。它们对你视作游侠法术，感知是你施展他们的施法关键属性。当你升级时，你可以将其中一个戏法替换为德鲁伊法术列表中的另一个戏法 | R27: 圆滑心智 | S27: 第15级起，你获得感知豁免的熟练项 | T27: 生成法术位 | U27: 第2级起，你可以在自己回合内以附赠动作将未使用的术法点转换为法术位。另外，你无法生成高于五环的法术位。以此方式生成的法术位将在完成一次长休后消散 一环法术位需要2术法点，二环法术位需要3术法点，三环法术位需要5术法点，四环法术位需要6术法点，五环法术位需要7术法点 | V27: =IF(OR(BI65>0,COUNTIF($BG$2:$BG$46,"魔能祈唤-野兽之语")),"魔能祈唤-野兽之语","") | W27: 你可以随意以自身为目标施展动物交谈，且无需消耗法术位和材料成分 | X27: 学习法术 | Y27: 你每提升一个法师等级，可以将两项自选的法师法术加入你的法术书中。但是，你只能加入已经获得相应环阶法术位的法术。你在冒险过程中所发现的法术也可以加入到法术书中 | Z27: =IF(OR(BI67>0,COUNTIF($BG$2:$BG$46,"注法-增强防御")),"注法-增强防御","") | AA27: 物品：一套盔甲或一面盾牌 穿着该盔甲或挥舞该盾牌的生物在AC上获得+1加值 10级起，该加值变成+2 | AB27: =IF(AND(主要!$R$4<>"",主要!$Y$3-主要!$Y$6-主要!$Y$7>=4),4,"") | AC27: =IF(AND(主要!$R$6<>"",主要!$Y$3-主要!$Y$4-主要!$Y$7>=4),4,"") | AD27: =IF(AND(主要!$R$7<>"",主要!$Y$3-主要!$Y$4-主要!$Y$6>=4),4,"") | AF27: D12 | AG27: {=INDEX(AI:AI,SMALL(IF($AI$2:$AI$14<>"",ROW($2:$14),15),ROW(AI11)))&""} | AH27: {=INDEX(AJ:AJ,SMALL(IF($AJ$2:$AJ$14<>"",ROW($2:$14),15),ROW(AJ11)))&""} | AI27: =INDEX($B$2:$S$14,AI$17,10) -> #N/A | AJ27: =INDEX($B$2:$S$14,AJ$17,10) -> #N/A | AK27: =INDEX($B$2:$S$14,AK$17,10) -> #N/A | AL27: {=INDEX(AJ:AJ,SMALL(IF($AJ$18:$AJ$35<>"",ROW($18:$35),36),ROW(AJ6)))&""} -> #N/A | AM27: 战争领域 | AO27: 56 | AP27: =IF($AG$4>=17,62,IF($AG$4>=8,61,IF($AG$4>=6,60,IF($AG$4>=2,59,IF($AG$4>=1,58,0))))) -> 0 | AQ27: =IF(AQ26+1>$AT$3,IF(AQ26+1>$AT$3,IF($AS$4+AT26>$AT$4,"",$AS$4+AT26)),AQ26+1) -> #N/A | AR27: =INDEX($B$17:$AA$154,AQ27,$AR$4) -> #N/A | AS27: =INDEX($B$17:$AA$154,AQ27,$AR$3) -> #N/A | AT27: =IF(AQ26+1>$AT$3,AT26+1,0) -> #N/A | AU27: =IF($AU26+1>$AX$3,IF($AU26+1>$AX$3,IF($AW$4+AX26>$AX$4,"",$AW$4+AX26)),$AU26+1) -> #N/A | AV27: =INDEX($B$17:$AA$154,AU27,$AV$4) -> #N/A | AW27: =INDEX($B$17:$AA$154,AU27,$AV$3) -> #N/A | AX27: =IF($AU26+1>$AX$3,$AX26+1,0) -> #N/A | AY27: =IF($AY26+1>$BB$3,IF($AY26+1>$BB$3,IF($BA$4+BB26>$BB$4,"",$BA$4+BB26)),$AY26+1) -> #N/A | AZ27: =INDEX($B$17:$AA$154,AY27,$AZ$4) -> #N/A | BA27: =INDEX($B$17:$AA$154,AY27,$AZ$3) -> #N/A | BB27: =IF($AY26+1>$BB$3,$BB26+1,0) -> #N/A | BC27: =IFERROR(INDEX($AQ$12:$BF$87,17,$BC$2),"") | BD27: =IFERROR(INDEX($AQ$12:$BF$87,17,$BD$2),"") | BE27: =IFERROR(IF(OR(BC29="",COUNTIF($BG$2:$BG$46,BC29)),"",BC29),"") | BF27: {=INDEX(BE:BE,SMALL(IF($BE$2:$BE$143<>"",ROW($2:$143),144),ROW(BE26)))&""} | BG27: =IF(主要!C109="",0,主要!C109) -> 0 | BH27: =IFERROR(VLOOKUP($BG27,$BC$4:$BD$143,2,0),"") | BI27: =IF($BG27=0,"",COUNTIF($BG$2:$BG$46,$BG27))
A28: 12 | B28: 坚韧狂暴 | C28: 第11级起，如果你的生命值降至0但并未立即死亡，则你可以进行一次DC10的体质豁免。豁免成功则改为你的生命值降至1 第一次使用此特性后，每当你再次使用此特性时其体质豁免DC提高5。在你完成一次短休或长休后其DC重置为10 | D28: 吟游诗人学院 | E28: 第3级时，你将选择加入一个吟游诗人的学院协会，以探寻更精深的技艺。随后，你将在第3、第6、第14级时获得所选学院的相应特性 | F28: =IF(综合数据!B14=TRUE,"替换戏法-牧师","") -> 替换戏法-牧师 | G28: 第4级起，当你的牧师职业等级抵达能让你获得属性值提升时，你可以将一个你通过此职业的施法特性学会的牧师戏法替换为牧师法术列表中的另一个戏法 | H28: 不朽身-德鲁伊 | I28: 第18级起，每经过10年的岁月，你的身体就仿佛只过了1年 | J28: =IF(AND(综合数据!B14=TRUE,OR(BI53>0,COUNTIF($BG$2:$BG$46,"战斗风格-徒手战斗"))),"战斗风格-徒手战斗","") | K28: 你的徒手打击可以造成1d6+你力量调整值的钝击伤害，如果你没有手持任何武器或盾牌进行攻击，伤害骰从d6变成d8 每个你的回合开始时，你可以对被你擒抱的生物造成1d4钝击伤害 | L28: 轻身坠 | M28: 第4级起，当你要承受坠地伤害时，你可以使用反应将伤害减少等同于五倍武僧职业等级的数值 | N28: 法术的准备与施展-圣骑士 | O28: “圣武士职业表”里记录了你用以施展圣武士法术的1环及更高环阶法术位数量。施展某个圣武士法术时，你必须同时消耗其对应环阶的法术位。已消耗的法术位可在完成长休后恢复 你可以准备圣武士法术列表中所有符合当前施展条件的法术。准备法术时，你所准备法术的总数等于你的魅力调整值＋你的圣武士职业等级的一半（最少可以准备一个）。另外，你只能准备已经获得相应环阶法术位的法术 你可以在完成长休后改变你的准备法术列表。准备新的圣武士法术列表时，你要再花时间进行祈祷和冥想。准备时，你要为你列表上每个法术的每个环阶都花费至少1分钟时间 | P28: =IF(AND(综合数据!B14=TRUE,OR(BI53>0,COUNTIF($BG$2:$BG$46,"战斗风格-投掷武器战斗"))),"战斗风格-投掷武器战斗","") | Q28: 你可以在使用一件带有投掷属性武器进行进攻时，将那件武器作为攻击的一部分而拔出。另外，在你以一件投掷武器于远程攻击中命中对手时，你的伤害掷骰+2 | R28: 飘忽不定 | S28: 第18级起，除非你处于失能状态，否则以你为目标的攻击检定无法取得优势 | T28: 法术位转换术法点 | U28: 第2级起，你可以在自己回合内使用附赠动作将未使用的法术位转化为术法点。你消耗一枚法术位并获得等于该法术位环阶的术法点 所有你以该特性生成的法术位，在你完成一次长休后也将随之消失 | V28: =IF(OR(BI65>0,COUNTIF($BG$2:$BG$46,"魔能祈唤-诱导话术")),"魔能祈唤-诱导话术","") | W28: 你获得欺瞒和游说技能的技能熟练项 | X28: 奥术回想 | Y28: 第1级起，你可以每日使用一次奥术回想，以在你完成一次短休后恢复若干已消耗的法术位，所恢复的法术位环阶总和不得大于你法师等级的一半（向上取整），且任何一枚法术位的环阶都必须小于6环 | Z28: =IF(OR(BI67>0,COUNTIF($BG$2:$BG$46,"注法-增强武器")),"注法-增强武器","") | AA28: 物品：一把简易或军用武器 该魔法武器在攻击和伤害检定中具有+1加值 10级起，该加值变成+2 | AB28: =IF(AND(主要!$R$4<>"",主要!$Y$3-主要!$Y$6-主要!$Y$7>=5),5,"") | AC28: =IF(AND(主要!$R$6<>"",主要!$Y$3-主要!$Y$4-主要!$Y$7>=5),5,"") | AD28: =IF(AND(主要!$R$7<>"",主要!$Y$3-主要!$Y$4-主要!$Y$6>=5),5,"") | AG28: {=INDEX(AI:AI,SMALL(IF($AI$2:$AI$14<>"",ROW($2:$14),15),ROW(AI12)))&""} | AH28: {=INDEX(AJ:AJ,SMALL(IF($AJ$2:$AJ$14<>"",ROW($2:$14),15),ROW(AJ12)))&""} | AI28: =INDEX($B$2:$S$14,AI$17,11) -> #N/A | AJ28: =INDEX($B$2:$S$14,AJ$17,11) -> #N/A | AK28: =INDEX($B$2:$S$14,AK$17,11) -> #N/A | AL28: {=INDEX(AJ:AJ,SMALL(IF($AJ$18:$AJ$35<>"",ROW($18:$35),36),ROW(AJ7)))&""} -> #N/A | AM28: 死亡领域 | AO28: 63 | AP28: =IF($AG$4>=17,69,IF($AG$4>=8,68,IF($AG$4>=6,67,IF($AG$4>=2,66,IF($AG$4>=1,65,0))))) -> 0 | AQ28: =IF(AQ27+1>$AT$3,IF(AQ27+1>$AT$3,IF($AS$4+AT27>$AT$4,"",$AS$4+AT27)),AQ27+1) -> #N/A | AR28: =INDEX($B$17:$AA$154,AQ28,$AR$4) -> #N/A | AS28: =INDEX($B$17:$AA$154,AQ28,$AR$3) -> #N/A | AT28: =IF(AQ27+1>$AT$3,AT27+1,0) -> #N/A | AU28: =IF($AU27+1>$AX$3,IF($AU27+1>$AX$3,IF($AW$4+AX27>$AX$4,"",$AW$4+AX27)),$AU27+1) -> #N/A | AV28: =INDEX($B$17:$AA$154,AU28,$AV$4) -> #N/A | AW28: =INDEX($B$17:$AA$154,AU28,$AV$3) -> #N/A | AX28: =IF($AU27+1>$AX$3,$AX27+1,0) -> #N/A | AY28: =IF($AY27+1>$BB$3,IF($AY27+1>$BB$3,IF($BA$4+BB27>$BB$4,"",$BA$4+BB27)),$AY27+1) -> #N/A | AZ28: =INDEX($B$17:$AA$154,AY28,$AZ$4) -> #N/A | BA28: =INDEX($B$17:$AA$154,AY28,$AZ$3) -> #N/A | BB28: =IF($AY27+1>$BB$3,$BB27+1,0) -> #N/A | BC28: =IFERROR(INDEX($AQ$12:$BF$87,18,$BC$2),"") | BD28: =IFERROR(INDEX($AQ$12:$BF$87,18,$BD$2),"") | BE28: =IFERROR(IF(OR(BC30="",COUNTIF($BG$2:$BG$46,BC30)),"",BC30),"") | BF28: {=INDEX(BE:BE,SMALL(IF($BE$2:$BE$143<>"",ROW($2:$143),144),ROW(BE27)))&""} | BG28: =IF(主要!C110="",0,主要!C110) -> 0 | BH28: =IFERROR(VLOOKUP($BG28,$BC$4:$BD$143,2,0),"") | BI28: =IF($BG28=0,"",COUNTIF($BG$2:$BG$46,$BG28))
A29: 13 | B29: 持久狂暴 | C29: 第15级起，只有当你昏迷或是主动终止狂暴时才能使之提前结束 | D29: 专精-吟游诗人 | E29: 第3级时，你选择两个已有的技能熟练项。此后你进行所选技能的属性检定时，可以使用双倍的熟练加值 第10级起，你可以再选择另外两个已有的技能熟练项从该特性中获益 | F29: 摧毁不死生物 | G29: 第5级起，当不死生物进行对抗你驱散特性的豁免失败时，如果其挑战等级等于或低于一个既定的下限，则该不死生物将被即时摧毁 第5级起：½或更低 第8级起：1或更低 第11级起：2或更低 第14级起：3或更低 第17级起：4或更低 | H29: 野兽施法 | I29: 第18级起，你在荒野变形状态下可以施展大部分的德鲁伊法术。在野兽形态时，你可以完成德鲁伊法术的姿势与语言成分，但无法完成其材料成分的使用 | J29: 回气 | K29: 第1级起，可以在自己回合内用一个附赠动作恢复生命值，其总值为1d10＋你的战士职业等级。你必须完成一次长休或短休才能再次使用该特性 | L29: =IF(综合数据!B14=TRUE,"加速愈合","") -> 加速愈合 | M29: 第4级起，以一个动作，你能消耗2点气并且投掷一粒武艺骰，你恢复等同于掷骰结果加上你的熟练加值的生命值 | N29: 施法关键属性-圣武士 | O29: 当你的圣武士法术需要施法关键属性时均指向你的魅力值。而你圣武士法术的豁免DC和攻击检定，则使用你的魅力调整值 法术豁免DC＝8＋你的熟练加值＋你的魅力调整值 法术攻击调整值＝你的熟练加值＋你的魅力调整值 | P29: 施法-游侠 | Q29: 你学会运用自然世界的魔法本源进行施法，你的施法方式与德鲁伊类似 | R29: 幸运一击 | S29: 第20级时，当你的攻击未命中时，可以直接更改判定为命中。或者，当你的属性检定失败时，可以直接将d20骰的结果视为20 你必须完成一次长休或短休才能再次使用该特性 | T29: 超魔法 | U29: 第3级起，你可以扭曲所施展的法术使其符合你的需求。从超魔法选项中选择其二。随后你将在第10和第17级分别再获得其一 除非特别说明，否则对一个法术只能应用一种超魔法项 | V29: =IF(OR(BI65>0,COUNTIF($BG$2:$BG$46,"魔能祈唤-魔鬼视界")),"魔能祈唤-魔鬼视界","") | W29: 你在黑暗中拥有120尺的可视距离，而无论其属于魔法黑暗还是非魔法黑暗 | X29: 奥术传承 | Y29: 第2级时，你选择一种奥术传承以使你的训练专注。随后，你将在第2、第6、第10和第14级获得所选传承的相应特性 | Z29: =IF(OR(BI67>0,COUNTIF($BG$2:$BG$46,"注法-人工生命仆从")),"注法-人工生命仆从","") | AA29: 物品：一颗价值至少100gp的宝石或水晶 你在注法中使用的物品变成人工生命的心脏，而它的身体会立即围绕心脏成型 你能够决定人工生命的外观 人工生命对你和你的同伴都十分友善，且服从你的命令。人工生命的游戏数据见下，它的数据中某几项会适用你的熟练加值 在战斗中，人工生命使用你的先攻，并且在你的回合后立即行动。它能自由移动和执行反应，但除非你以一个附赠动作命令它进行数据中列出的动作或其他动作，否则它在回合中只能进行闪避动作。如果你失能，人工生命可以进行任何动作，而不仅仅是闪避 如果你对人工生命施放修复术，它将恢复2d6生命值。如果你或人工生命死亡，它将消失，只有心脏会留在它之前占据的地方 人工生命仆从 微型构装体 护甲等级：13(天生护甲) 生命值：1+你的智力调整值+5×你的奇械师等级（野兽具有你奇械师等级数量的生命骰[d4]） 速度：20尺速度，30尺飞行速度 力量4（-3） 敏捷15（+2） 体质12（+1） 智力10（+0） 感知10（+0） 魅力7（-2） 豁免：敏捷：2+熟练加值 技能：察觉：2×熟练加值；隐匿：2+熟练加值 伤害免疫：毒素 状态免疫：力竭、中毒 感官能力：60尺黑暗视觉，被动察觉10+2×熟练加值 语言能力：能听懂你所说的语言 熟练加值：与你等同 反射闪避：当需要通过敏捷豁免来使伤害减半时，若豁免成功则不受伤害，豁免失败则伤害减半。此特性在失能时无效 动作： 力场冲击：远程武器攻击：使用你的法术攻击调整值，射程30尺，可以攻击你能看到的单一目标，造成1d4+熟练加值的力场伤害 反应： 传递法术：当你施展施法距离为触及的法术时，只要人工生命距离你120尺内，它就能替你传递该法术 | AB29: =IF(AND(主要!$R$4<>"",主要!$Y$3-主要!$Y$6-主要!$Y$7>=6),6,"") | AC29: =IF(AND(主要!$R$6<>"",主要!$Y$3-主要!$Y$4-主要!$Y$7>=6),6,"") | AD29: =IF(AND(主要!$R$7<>"",主要!$Y$3-主要!$Y$4-主要!$Y$6>=6),6,"") | AI29: =INDEX($B$2:$S$14,AI$17,12) -> #N/A | AJ29: =INDEX($B$2:$S$14,AJ$17,12) -> #N/A | AK29: =INDEX($B$2:$S$14,AK$17,12) -> #N/A | AL29: {=INDEX(AJ:AJ,SMALL(IF($AJ$18:$AJ$35<>"",ROW($18:$35),36),ROW(AJ8)))&""} -> #N/A | AM29: 奥秘领域 | AO29: 70 | AP29: =IF($AG$4>=17,75,IF($AG$4>=8,74,IF($AG$4>=6,73,IF($AG$4>=2,72,IF($AG$4>=1,71,0))))) -> 0 | AQ29: =IF(AQ28+1>$AT$3,IF(AQ28+1>$AT$3,IF($AS$4+AT28>$AT$4,"",$AS$4+AT28)),AQ28+1) -> #N/A | AR29: =INDEX($B$17:$AA$154,AQ29,$AR$4) -> #N/A | AS29: =INDEX($B$17:$AA$154,AQ29,$AR$3) -> #N/A | AT29: =IF(AQ28+1>$AT$3,AT28+1,0) -> #N/A | AU29: =IF($AU28+1>$AX$3,IF($AU28+1>$AX$3,IF($AW$4+AX28>$AX$4,"",$AW$4+AX28)),$AU28+1) -> #N/A | AV29: =INDEX($B$17:$AA$154,AU29,$AV$4) -> #N/A | AW29: =INDEX($B$17:$AA$154,AU29,$AV$3) -> #N/A | AX29: =IF($AU28+1>$AX$3,$AX28+1,0) -> #N/A | AY29: =IF($AY28+1>$BB$3,IF($AY28+1>$BB$3,IF($BA$4+BB28>$BB$4,"",$BA$4+BB28)),$AY28+1) -> #N/A | AZ29: =INDEX($B$17:$AA$154,AY29,$AZ$4) -> #N/A | BA29: =INDEX($B$17:$AA$154,AY29,$AZ$3) -> #N/A | BB29: =IF($AY28+1>$BB$3,$BB28+1,0) -> #N/A | BC29: =IFERROR(INDEX($AQ$12:$BF$87,19,$BC$2),"") | BD29: =IFERROR(INDEX($AQ$12:$BF$87,19,$BD$2),"") | BE29: =IFERROR(IF(OR(BC31="",COUNTIF($BG$2:$BG$46,BC31)),"",BC31),"") | BF29: {=INDEX(BE:BE,SMALL(IF($BE$2:$BE$143<>"",ROW($2:$143),144),ROW(BE28)))&""} | BG29: =IF(主要!C111="",0,主要!C111) -> 0 | BH29: =IFERROR(VLOOKUP($BG29,$BC$4:$BD$143,2,0),"") | BI29: =IF($BG29=0,"",COUNTIF($BG$2:$BG$46,$BG29))
